streamTest/streamReg_halfPipe/streamReg_halfPipe.v
// Generator : SpinalHDL v1.7.0a    git head : 150a9b9067020722818dfb17df4a23ac712a7af8
// Component : streamReg_halfPipe
// Git hash  : 3a903e741cbbe310a98c75dc1ebbd289cb1c87a4

`timescale 1ns/1ps

module streamReg_halfPipe (
  input               io_s_in_valid,
  output              io_s_in_ready,
  input      [31:0]   io_s_in_payload,
  output              io_m_out_valid,
  input               io_m_out_ready,
  output     [31:0]   io_m_out_payload,
  input               clk,
  input               reset
);

  wire                io_s_in_halfPipe_valid;
  wire                io_s_in_halfPipe_ready;
  wire       [31:0]   io_s_in_halfPipe_payload;
  reg                 io_s_in_rValid;
  wire                io_s_in_halfPipe_fire;
  reg        [31:0]   io_s_in_rData;

  assign io_s_in_halfPipe_fire = (io_s_in_halfPipe_valid && io_s_in_halfPipe_ready);
  assign io_s_in_ready = (! io_s_in_rValid);
  assign io_s_in_halfPipe_valid = io_s_in_rValid;
  assign io_s_in_halfPipe_payload = io_s_in_rData;
  assign io_m_out_valid = io_s_in_halfPipe_valid;
  assign io_s_in_halfPipe_ready = io_m_out_ready;
  assign io_m_out_payload = io_s_in_halfPipe_payload;
  always @(posedge clk or posedge reset) begin
    if(reset) begin
      io_s_in_rValid <= 1'b0;
    end else begin
      if(io_s_in_valid) begin
        io_s_in_rValid <= 1'b1;
      end
      if(io_s_in_halfPipe_fire) begin
        io_s_in_rValid <= 1'b0;
      end
    end
  end

  always @(posedge clk) begin
    if(io_s_in_ready) begin
      io_s_in_rData <= io_s_in_payload;
    end
  end


    initial begin
    $dumpfile("streamReg_halfPipe_test.vcd");
    $dumpvars(0, streamReg_halfPipe);
  end


endmodule

streamTest/streamReg_halfPipe/streamReg_halfPipe_test.vcd
$date
	Thu May 26 13:21:46 2022
$end
$version
	Icarus Verilog
$end
$timescale
	1ps
$end
$scope module streamReg_halfPipe $end
$var wire 1 ! clk $end
$var wire 32 " io_m_out_payload [31:0] $end
$var wire 1 # io_m_out_ready $end
$var wire 1 $ io_m_out_valid $end
$var wire 1 % io_s_in_halfPipe_fire $end
$var wire 1 & io_s_in_halfPipe_ready $end
$var wire 1 ' io_s_in_halfPipe_valid $end
$var wire 32 ( io_s_in_payload [31:0] $end
$var wire 1 ) io_s_in_valid $end
$var wire 1 * reset $end
$var wire 1 + io_s_in_ready $end
$var wire 32 , io_s_in_halfPipe_payload [31:0] $end
$var reg 32 - io_s_in_rData [31:0] $end
$var reg 1 . io_s_in_rValid $end
$upscope $end
$enddefinitions $end
#0
$dumpvars
0.
bx -
bx ,
1+
1*
z)
bz (
0'
z&
0%
0$
z#
bx "
0!
$end
#1000
0)
b0 (
0&
0#
0*
#1500
b0 "
b0 ,
b0 -
1!
#2000
0!
#2500
1!
#3000
0!
#3500
1&
1#
1!
#4000
0!
#4500
1)
1!
#5000
0!
#5500
1%
0+
1$
1'
1.
1!
#6000
0!
#6500
0&
0#
0%
1+
0$
0'
0.
1!
#7000
0!
#7500
1%
0)
1&
1#
0+
1$
1'
1.
1!
#8000
0!
#8500
1)
b11111100000000011111011010111100 (
0&
0#
0%
1+
0$
0'
0.
1!
#9000
0!
#9500
1%
0)
b0 (
1&
1#
b11111100000000011111011010111100 "
b11111100000000011111011010111100 ,
b11111100000000011111011010111100 -
0+
1$
1'
1.
1!
#10000
0!
#10500
1)
b11010100101000110111010101100 (
0&
0#
0%
1+
0$
0'
0.
1!
#11000
0!
#11500
0)
b0 (
b11010100101000110111010101100 "
b11010100101000110111010101100 ,
b11010100101000110111010101100 -
0+
1$
1'
1.
1!
#12000
0!
#12500
1%
1)
b11011001010101110100011001111110 (
1&
1#
1!
#13000
0!
#13500
0&
0#
0%
1+
0$
0'
0.
1!
#14000
0!
#14500
1%
0)
b0 (
1&
1#
b11011001010101110100011001111110 "
b11011001010101110100011001111110 ,
b11011001010101110100011001111110 -
0+
1$
1'
1.
1!
#15000
0!
#15500
0&
0#
0%
1+
0$
0'
0.
1!
#16000
0!
#16500
1)
b11110011101110110101011110110010 (
b0 "
b0 ,
b0 -
1!
#17000
0!
#17500
1%
0)
b0 (
1&
1#
b11110011101110110101011110110010 "
b11110011101110110101011110110010 ,
b11110011101110110101011110110010 -
0+
1$
1'
1.
1!
#18000
0!
#18500
0&
0#
0%
1+
0$
0'
0.
1!
#19000
0!
#19500
b0 "
b0 ,
b0 -
1!
#20000
0!
#20500
1!
#21000
0!
#21500
1!
#22000
0!
#22500
1)
b1101111110010010111001000110101 (
1&
1#
1!
#23000
0!
#23500
0)
b0 (
1%
b1101111110010010111001000110101 "
b1101111110010010111001000110101 ,
b1101111110010010111001000110101 -
0+
1$
1'
1.
1!
#24000
0!
#24500
1)
b11001011010000111011111001000 (
0&
0#
0%
1+
0$
0'
0.
1!
#25000
0!
#25500
1%
0)
b0 (
1&
1#
b11001011010000111011111001000 "
b11001011010000111011111001000 ,
b11001011010000111011111001000 -
0+
1$
1'
1.
1!
#26000
0!
#26500
1)
b10010110101100111000011011011 (
0&
0#
0%
1+
0$
0'
0.
1!
#27000
0!
#27500
1%
0)
b0 (
1&
1#
b10010110101100111000011011011 "
b10010110101100111000011011011 ,
b10010110101100111000011011011 -
0+
1$
1'
1.
1!
#28000
0!
#28500
0&
0#
0%
1+
0$
0'
0.
1!
#29000
0!
#29500
1&
1#
b0 "
b0 ,
b0 -
1!
#30000
0!
#30500
1)
b11011000110001011111010100111001 (
1!
#31000
0!
#31500
0)
b0 (
1%
b11011000110001011111010100111001 "
b11011000110001011111010100111001 ,
b11011000110001011111010100111001 -
0+
1$
1'
1.
1!
#32000
0!
#32500
0&
0#
0%
1+
0$
0'
0.
1!
#33000
0!
#33500
1)
b1101010101110001000111111100001 (
1&
1#
b0 "
b0 ,
b0 -
1!
#34000
0!
#34500
0)
b0 (
1%
b1101010101110001000111111100001 "
b1101010101110001000111111100001 ,
b1101010101110001000111111100001 -
0+
1$
1'
1.
1!
#35000
0!
#35500
1)
b10101110100110111101101110111000 (
0&
0#
0%
1+
0$
0'
0.
1!
#36000
0!
#36500
0)
b0 (
b10101110100110111101101110111000 "
b10101110100110111101101110111000 ,
b10101110100110111101101110111000 -
0+
1$
1'
1.
1!
#37000
0!
#37500
1)
b11010111001000001001000000111100 (
1!
#38000
0!
#38500
1!
#39000
0!
#39500
1!
#40000
0!
#40500
1!
#41000
0!
#41500
1%
1&
1#
1!
#42000
0!
#42500
0&
0#
0%
1+
0$
0'
0.
1!
#43000
0!
#43500
1%
0)
b0 (
1&
1#
b11010111001000001001000000111100 "
b11010111001000001001000000111100 ,
b11010111001000001001000000111100 -
0+
1$
1'
1.
1!
#44000
0!
#44500
0&
0#
0%
1+
0$
0'
0.
1!
#45000
0!
#45500
1)
b1010101010100111110110000110 (
1&
1#
b0 "
b0 ,
b0 -
1!
#46000
0!
#46500
0)
b0 (
1%
b1010101010100111110110000110 "
b1010101010100111110110000110 ,
b1010101010100111110110000110 -
0+
1$
1'
1.
1!
#47000
0!
#47500
1)
b1001100001100011101011110010010 (
0&
0#
0%
1+
0$
0'
0.
1!
#48000
0!
#48500
1%
0)
b0 (
1&
1#
b1001100001100011101011110010010 "
b1001100001100011101011110010010 ,
b1001100001100011101011110010010 -
0+
1$
1'
1.
1!
#49000
0!
#49500
0&
0#
0%
1+
0$
0'
0.
1!
#50000
0!
#50500
1)
b10001010100111001110010101111100 (
1&
1#
b0 "
b0 ,
b0 -
1!
#51000
0!
#51500
0)
b0 (
1%
b10001010100111001110010101111100 "
b10001010100111001110010101111100 ,
b10001010100111001110010101111100 -
0+
1$
1'
1.
1!
#52000
0!
#52500
1)
b11100100101001101110101010001100 (
0&
0#
0%
1+
0$
0'
0.
1!
#53000
0!
#53500
1%
0)
b0 (
1&
1#
b11100100101001101110101010001100 "
b11100100101001101110101010001100 ,
b11100100101001101110101010001100 -
0+
1$
1'
1.
1!
#54000
0!
#54500
1)
b1110011010001101000011010000011 (
0&
0#
0%
1+
0$
0'
0.
1!
#55000
0!
#55500
0)
b0 (
b1110011010001101000011010000011 "
b1110011010001101000011010000011 ,
b1110011010001101000011010000011 -
0+
1$
1'
1.
1!
#56000
0!
#56500
1!
#57000
0!
#57500
1%
1&
1#
1!
#58000
0!
#58500
1)
b100010001110101110111110100000 (
0&
0#
0%
1+
0$
0'
0.
1!
#59000
0!
#59500
1%
0)
b0 (
1&
1#
b100010001110101110111110100000 "
b100010001110101110111110100000 ,
b100010001110101110111110100000 -
0+
1$
1'
1.
1!
#60000
0!
#60500
0&
0#
0%
1+
0$
0'
0.
1!
#61000
0!
#61500
1&
1#
b0 "
b0 ,
b0 -
1!
#62000
0!
#62500
1!
#63000
0!
#63500
1!
#64000
0!
#64500
1)
b10011100011100100011110011000 (
1!
#65000
0!
#65500
0)
b0 (
1%
b10011100011100100011110011000 "
b10011100011100100011110011000 ,
b10011100011100100011110011000 -
0+
1$
1'
1.
1!
#66000
0!
#66500
1)
b10000100011110011111101100010010 (
0&
0#
0%
1+
0$
0'
0.
1!
#67000
0!
#67500
1%
0)
b0 (
1&
1#
b10000100011110011111101100010010 "
b10000100011110011111101100010010 ,
b10000100011110011111101100010010 -
0+
1$
1'
1.
1!
#68000
0!
#68500
1)
b1101111011001111011000101110110 (
0&
0#
0%
1+
0$
0'
0.
1!
#69000
0!
#69500
1%
0)
b0 (
1&
1#
b1101111011001111011000101110110 "
b1101111011001111011000101110110 ,
b1101111011001111011000101110110 -
0+
1$
1'
1.
1!
#70000
0!
#70500
0&
0#
0%
1+
0$
0'
0.
1!
#71000
0!
#71500
1)
b1010100101011111001100100110011 (
b0 "
b0 ,
b0 -
1!
#72000
0!
#72500
1%
0)
b0 (
1&
1#
b1010100101011111001100100110011 "
b1010100101011111001100100110011 ,
b1010100101011111001100100110011 -
0+
1$
1'
1.
1!
#73000
0!
#73500
1)
b10001011011000001001110001001001 (
0&
0#
0%
1+
0$
0'
0.
1!
#74000
0!
#74500
1%
0)
b0 (
1&
1#
b10001011011000001001110001001001 "
b10001011011000001001110001001001 ,
b10001011011000001001110001001001 -
0+
1$
1'
1.
1!
#75000
0!
#75500
0&
0#
0%
1+
0$
0'
0.
1!
#76000
0!
#76500
1)
b1001111110100110000000011110101 (
1&
1#
b0 "
b0 ,
b0 -
1!
#77000
0!
#77500
0)
b0 (
1%
b1001111110100110000000011110101 "
b1001111110100110000000011110101 ,
b1001111110100110000000011110101 -
0+
1$
1'
1.
1!
#78000
0!
#78500
1)
b110100101011001010001111111111 (
0&
0#
0%
1+
0$
0'
0.
1!
#79000
0!
#79500
1%
0)
b0 (
1&
1#
b110100101011001010001111111111 "
b110100101011001010001111111111 ,
b110100101011001010001111111111 -
0+
1$
1'
1.
1!
#80000
0!
#80500
1)
b111000100000001100011100110000 (
0&
0#
0%
1+
0$
0'
0.
1!
#81000
0!
#81500
1%
0)
b0 (
1&
1#
b111000100000001100011100110000 "
b111000100000001100011100110000 ,
b111000100000001100011100110000 -
0+
1$
1'
1.
1!
#82000
0!
#82500
1)
b1100010110001011011100000001000 (
0&
0#
0%
1+
0$
0'
0.
1!
#83000
0!
#83500
0)
b0 (
b1100010110001011011100000001000 "
b1100010110001011011100000001000 ,
b1100010110001011011100000001000 -
0+
1$
1'
1.
1!
#84000
0!
#84500
1!
#85000
0!
#85500
1%
1)
b100011111111000000011110011001 (
1&
1#
1!
#86000
0!
#86500
0&
0#
0%
1+
0$
0'
0.
1!
#87000
0!
#87500
1%
0)
b0 (
1&
1#
b100011111111000000011110011001 "
b100011111111000000011110011001 ,
b100011111111000000011110011001 -
0+
1$
1'
1.
1!
#88000
0!
#88500
1)
b1010011101001111011110011101100 (
0&
0#
0%
1+
0$
0'
0.
1!
#89000
0!
#89500
0)
b0 (
b1010011101001111011110011101100 "
b1010011101001111011110011101100 ,
b1010011101001111011110011101100 -
0+
1$
1'
1.
1!
#90000
0!
#90500
1)
b1110011001100110101100111100000 (
1!
#91000
0!
#91500
1%
1&
1#
1!
#92000
0!
#92500
0&
0#
0%
1+
0$
0'
0.
1!
#93000
0!
#93500
1%
0)
b0 (
1&
1#
b1110011001100110101100111100000 "
b1110011001100110101100111100000 ,
b1110011001100110101100111100000 -
0+
1$
1'
1.
1!
#94000
0!
#94500
0&
0#
0%
1+
0$
0'
0.
1!
#95000
0!
#95500
1)
b10110000001000101010010111001101 (
b0 "
b0 ,
b0 -
1!
#96000
0!
#96500
1%
0)
b0 (
1&
1#
b10110000001000101010010111001101 "
b10110000001000101010010111001101 ,
b10110000001000101010010111001101 -
0+
1$
1'
1.
1!
#97000
0!
#97500
0&
0#
0%
1+
0$
0'
0.
1!
#98000
0!
#98500
1)
b10010000101010110101010111000010 (
1&
1#
b0 "
b0 ,
b0 -
1!
#99000
0!
#99500
0)
b0 (
1%
b10010000101010110101010111000010 "
b10010000101010110101010111000010 ,
b10010000101010110101010111000010 -
0+
1$
1'
1.
1!
#100000
0!
#100500
0&
0#
0%
1+
0$
0'
0.
1!
#101000
0!
#101500
1&
1#
b0 "
b0 ,
b0 -
1!
#102000
0!
#102500
1!
#103000
0!
#103500
1)
b10010000100111110101101101001011 (
1!
#104000
0!
#104500
0)
b0 (
1%
b10010000100111110101101101001011 "
b10010000100111110101101101001011 ,
b10010000100111110101101101001011 -
0+
1$
1'
1.
1!
#105000
0!
#105500
0&
0#
0%
1+
0$
0'
0.
1!
#106000
0!
#106500
b0 "
b0 ,
b0 -
1!
#107000
0!
#107500
1)
b110101000110100011010110101010 (
1!
#108000
0!
#108500
0)
b0 (
b110101000110100011010110101010 "
b110101000110100011010110101010 ,
b110101000110100011010110101010 -
0+
1$
1'
1.
1!
#109000
0!
#109500
1%
1&
1#
1!
#110000
0!
#110500
0&
0#
0%
1+
0$
0'
0.
1!
#111000
0!
#111500
b0 "
b0 ,
b0 -
1!
#112000
0!
#112500
1!
#113000
0!
#113500
1!
#114000
0!
#114500
1)
b10100100101011111110101001100111 (
1!
#115000
0!
#115500
1%
0)
b0 (
1&
1#
b10100100101011111110101001100111 "
b10100100101011111110101001100111 ,
b10100100101011111110101001100111 -
0+
1$
1'
1.
1!
#116000
0!
#116500
0&
0#
0%
1+
0$
0'
0.
1!
#117000
0!
#117500
1)
b10010000101110100101100110001010 (
1&
1#
b0 "
b0 ,
b0 -
1!
#118000
0!
#118500
0)
b0 (
1%
b10010000101110100101100110001010 "
b10010000101110100101100110001010 ,
b10010000101110100101100110001010 -
0+
1$
1'
1.
1!
#119000
0!
#119500
0&
0#
0%
1+
0$
0'
0.
1!
#120000
0!
#120500
b0 "
b0 ,
b0 -
1!
#121000
0!
#121500
1)
b10000111111010010001110001101000 (
1&
1#
1!
#122000
0!
#122500
0)
b0 (
1%
b10000111111010010001110001101000 "
b10000111111010010001110001101000 ,
b10000111111010010001110001101000 -
0+
1$
1'
1.
1!
#123000
0!
#123500
1)
b1000010111011000100010100110110 (
0&
0#
0%
1+
0$
0'
0.
1!
#124000
0!
#124500
0)
b0 (
b1000010111011000100010100110110 "
b1000010111011000100010100110110 ,
b1000010111011000100010100110110 -
0+
1$
1'
1.
1!
#125000
0!
#125500
1!
#126000
0!
#126500
1%
1)
b11111010000000101110110101101 (
1&
1#
1!
#127000
0!
#127500
0&
0#
0%
1+
0$
0'
0.
1!
#128000
0!
#128500
0)
b0 (
b11111010000000101110110101101 "
b11111010000000101110110101101 ,
b11111010000000101110110101101 -
0+
1$
1'
1.
1!
#129000
0!
#129500
1)
b1010001011110111010010111001010 (
1!
#130000
0!
#130500
1!
#131000
0!
#131500
1%
1&
1#
1!
#132000
0!
#132500
0&
0#
0%
1+
0$
0'
0.
1!
#133000
0!
#133500
0)
b0 (
b1010001011110111010010111001010 "
b1010001011110111010010111001010 ,
b1010001011110111010010111001010 -
0+
1$
1'
1.
1!
#134000
0!
#134500
1!
#135000
0!
#135500
1)
b11000100110101100110011111110100 (
1!
#136000
0!
#136500
1!
#137000
0!
#137500
1!
#138000
0!
#138500
1%
1&
1#
1!
#139000
0!
#139500
0&
0#
0%
1+
0$
0'
0.
1!
#140000
0!
#140500
0)
b0 (
b11000100110101100110011111110100 "
b11000100110101100110011111110100 ,
b11000100110101100110011111110100 -
0+
1$
1'
1.
1!
#141000
0!
#141500
1)
b1010101101110100010010110001101 (
1!
#142000
0!
#142500
1%
1&
1#
1!
#143000
0!
#143500
0&
0#
0%
1+
0$
0'
0.
1!
#144000
0!
#144500
1%
0)
b0 (
1&
1#
b1010101101110100010010110001101 "
b1010101101110100010010110001101 ,
b1010101101110100010010110001101 -
0+
1$
1'
1.
1!
#145000
0!
#145500
0&
0#
0%
1+
0$
0'
0.
1!
#146000
0!
#146500
b0 "
b0 ,
b0 -
1!
#147000
0!
#147500
1)
b11110111111000000001100011001010 (
1&
1#
1!
#148000
0!
#148500
0)
b0 (
1%
b11110111111000000001100011001010 "
b11110111111000000001100011001010 ,
b11110111111000000001100011001010 -
0+
1$
1'
1.
1!
#149000
0!
#149500
0&
0#
0%
1+
0$
0'
0.
1!
#150000
0!
#150500
1&
1#
b0 "
b0 ,
b0 -
1!
#151000
0!
#151500
1)
b10011011110110000000010001000001 (
1!
#152000
0!
#152500
0)
b0 (
1%
b10011011110110000000010001000001 "
b10011011110110000000010001000001 ,
b10011011110110000000010001000001 -
0+
1$
1'
1.
1!
#153000
0!
#153500
1)
b11101100100100011001011101000 (
0&
0#
0%
1+
0$
0'
0.
1!
#154000
0!
#154500
0)
b0 (
b11101100100100011001011101000 "
b11101100100100011001011101000 ,
b11101100100100011001011101000 -
0+
1$
1'
1.
1!
#155000
0!
#155500
1!
#156000
0!
#156500
1%
1&
1#
1!
#157000
0!
#157500
0&
0#
0%
1+
0$
0'
0.
1!
#158000
0!
#158500
1)
b11010000110011100100010000111001 (
b0 "
b0 ,
b0 -
1!
#159000
0!
#159500
1%
0)
b0 (
1&
1#
b11010000110011100100010000111001 "
b11010000110011100100010000111001 ,
b11010000110011100100010000111001 -
0+
1$
1'
1.
1!
#160000
0!
#160500
0&
0#
0%
1+
0$
0'
0.
1!
#161000
0!
#161500
b0 "
b0 ,
b0 -
1!
#162000
0!
#162500
1)
b110111011110000010011101101010 (
1!
#163000
0!
#163500
1%
0)
b0 (
1&
1#
b110111011110000010011101101010 "
b110111011110000010011101101010 ,
b110111011110000010011101101010 -
0+
1$
1'
1.
1!
#164000
0!
#164500
1)
b11110010110001011100111110010 (
0&
0#
0%
1+
0$
0'
0.
1!
#165000
0!
#165500
1%
0)
b0 (
1&
1#
b11110010110001011100111110010 "
b11110010110001011100111110010 ,
b11110010110001011100111110010 -
0+
1$
1'
1.
1!
#166000
0!
#166500
1)
b10100001010100000111000001001111 (
0&
0#
0%
1+
0$
0'
0.
1!
#167000
0!
#167500
0)
b0 (
b10100001010100000111000001001111 "
b10100001010100000111000001001111 ,
b10100001010100000111000001001111 -
0+
1$
1'
1.
1!
#168000
0!
#168500
1%
1)
b101001100000100100101011010 (
1&
1#
1!
#169000
0!
#169500
0&
0#
0%
1+
0$
0'
0.
1!
#170000
0!
#170500
0)
b0 (
b101001100000100100101011010 "
b101001100000100100101011010 ,
b101001100000100100101011010 -
0+
1$
1'
1.
1!
#171000
0!
#171500
1%
1&
1#
1!
#172000
0!
#172500
0&
0#
0%
1+
0$
0'
0.
1!
#173000
0!
#173500
b0 "
b0 ,
b0 -
1!
#174000
0!
#174500
1!
#175000
0!
#175500
1!
#176000
0!
#176500
1)
b110011001111010001010011010101 (
1!
#177000
0!
#177500
0)
b0 (
b110011001111010001010011010101 "
b110011001111010001010011010101 ,
b110011001111010001010011010101 -
0+
1$
1'
1.
1!
#178000
0!
#178500
1)
b1000010010111000010001000 (
1!
#179000
0!
#179500
1%
1&
1#
1!
#180000
0!
#180500
0&
0#
0%
1+
0$
0'
0.
1!
#181000
0!
#181500
0)
b0 (
b1000010010111000010001000 "
b1000010010111000010001000 ,
b1000010010111000010001000 -
0+
1$
1'
1.
1!
#182000
0!
#182500
1)
b11111101110001010101000010001100 (
1!
#183000
0!
#183500
1!
#184000
0!
#184500
1%
1&
1#
1!
#185000
0!
#185500
0&
0#
0%
1+
0$
0'
0.
1!
#186000
0!
#186500
1%
0)
b0 (
1&
1#
b11111101110001010101000010001100 "
b11111101110001010101000010001100 ,
b11111101110001010101000010001100 -
0+
1$
1'
1.
1!
#187000
0!
#187500
1)
b1111100100110101100011111101010 (
0&
0#
0%
1+
0$
0'
0.
1!
#188000
0!
#188500
1%
0)
b0 (
1&
1#
b1111100100110101100011111101010 "
b1111100100110101100011111101010 ,
b1111100100110101100011111101010 -
0+
1$
1'
1.
1!
#189000
0!
#189500
0&
0#
0%
1+
0$
0'
0.
1!
#190000
0!
#190500
1&
1#
b0 "
b0 ,
b0 -
1!
#191000
0!
#191500
1)
b10101011110110011011000000100011 (
1!
#192000
0!
#192500
0)
b0 (
1%
b10101011110110011011000000100011 "
b10101011110110011011000000100011 ,
b10101011110110011011000000100011 -
0+
1$
1'
1.
1!
#193000
0!
#193500
1)
b11000000001011111001000111011001 (
0&
0#
0%
1+
0$
0'
0.
1!
#194000
0!
#194500
1%
0)
b0 (
1&
1#
b11000000001011111001000111011001 "
b11000000001011111001000111011001 ,
b11000000001011111001000111011001 -
0+
1$
1'
1.
1!
#195000
0!
#195500
1)
b10101100011001010101111101110100 (
0&
0#
0%
1+
0$
0'
0.
1!
#196000
0!
#196500
1%
0)
b0 (
1&
1#
b10101100011001010101111101110100 "
b10101100011001010101111101110100 ,
b10101100011001010101111101110100 -
0+
1$
1'
1.
1!
#197000
0!
#197500
1)
b1001101000110011010110100001001 (
0&
0#
0%
1+
0$
0'
0.
1!
#198000
0!
#198500
1%
0)
b0 (
1&
1#
b1001101000110011010110100001001 "
b1001101000110011010110100001001 ,
b1001101000110011010110100001001 -
0+
1$
1'
1.
1!
#199000
0!
#199500
1)
b110111001110110000100110101100 (
0&
0#
0%
1+
0$
0'
0.
1!
#200000
0!
#200500
1%
0)
b0 (
1&
1#
b110111001110110000100110101100 "
b110111001110110000100110101100 ,
b110111001110110000100110101100 -
0+
1$
1'
1.
1!
#201000
0!
#201500
0&
0#
0%
1+
0$
0'
0.
1!
#202000
0!
#202500
1)
b111100101010101111111011110111 (
1&
1#
b0 "
b0 ,
b0 -
1!
#203000
0!
#203500
0)
b0 (
1%
b111100101010101111111011110111 "
b111100101010101111111011110111 ,
b111100101010101111111011110111 -
0+
1$
1'
1.
1!
#204000
0!
#204500
0&
0#
0%
1+
0$
0'
0.
1!
#205000
0!
#205500
1&
1#
b0 "
b0 ,
b0 -
1!
#206000
0!
#206500
1!
#207000
0!
#207500
1)
b10111011110100111011110100001 (
1!
#208000
0!
#208500
0)
b0 (
1%
b10111011110100111011110100001 "
b10111011110100111011110100001 ,
b10111011110100111011110100001 -
0+
1$
1'
1.
1!
#209000
0!
#209500
0&
0#
0%
1+
0$
0'
0.
1!
#210000
0!
#210500
b0 "
b0 ,
b0 -
1!
#211000
0!
#211500
1)
b11000100010011000011100011111110 (
1&
1#
1!
#212000
0!
#212500
0)
b0 (
1%
b11000100010011000011100011111110 "
b11000100010011000011100011111110 ,
b11000100010011000011100011111110 -
0+
1$
1'
1.
1!
#213000
0!
#213500
1)
b1110001111010100100101101111100 (
0&
0#
0%
1+
0$
0'
0.
1!
#214000
0!
#214500
0)
b0 (
b1110001111010100100101101111100 "
b1110001111010100100101101111100 ,
b1110001111010100100101101111100 -
0+
1$
1'
1.
1!
#215000
0!
#215500
1%
1&
1#
1!
#216000
0!
#216500
1)
b10001111110001111011110111101111 (
0&
0#
0%
1+
0$
0'
0.
1!
#217000
0!
#217500
1%
0)
b0 (
1&
1#
b10001111110001111011110111101111 "
b10001111110001111011110111101111 ,
b10001111110001111011110111101111 -
0+
1$
1'
1.
1!
#218000
0!
#218500
1)
b11010010001100000111000011001101 (
0&
0#
0%
1+
0$
0'
0.
1!
#219000
0!
#219500
1%
0)
b0 (
1&
1#
b11010010001100000111000011001101 "
b11010010001100000111000011001101 ,
b11010010001100000111000011001101 -
0+
1$
1'
1.
1!
#220000
0!
#220500
1)
b10011111011010110111100010000100 (
0&
0#
0%
1+
0$
0'
0.
1!
#221000
0!
#221500
1%
0)
b0 (
1&
1#
b10011111011010110111100010000100 "
b10011111011010110111100010000100 ,
b10011111011010110111100010000100 -
0+
1$
1'
1.
1!
#222000
0!
#222500
1)
b10101111011001110111110011111011 (
0&
0#
0%
1+
0$
0'
0.
1!
#223000
0!
#223500
0)
b0 (
b10101111011001110111110011111011 "
b10101111011001110111110011111011 ,
b10101111011001110111110011111011 -
0+
1$
1'
1.
1!
#224000
0!
#224500
1%
1)
b11101101110010101010001001111000 (
1&
1#
1!
#225000
0!
#225500
0&
0#
0%
1+
0$
0'
0.
1!
#226000
0!
#226500
0)
b0 (
b11101101110010101010001001111000 "
b11101101110010101010001001111000 ,
b11101101110010101010001001111000 -
0+
1$
1'
1.
1!
#227000
0!
#227500
1%
1)
b11111110101110010101101100011110 (
1&
1#
1!
#228000
0!
#228500
0&
0#
0%
1+
0$
0'
0.
1!
#229000
0!
#229500
1%
0)
b0 (
1&
1#
b11111110101110010101101100011110 "
b11111110101110010101101100011110 ,
b11111110101110010101101100011110 -
0+
1$
1'
1.
1!
#230000
0!
#230500
1)
b1000001111011101001010100001100 (
0&
0#
0%
1+
0$
0'
0.
1!
#231000
0!
#231500
1%
0)
b0 (
1&
1#
b1000001111011101001010100001100 "
b1000001111011101001010100001100 ,
b1000001111011101001010100001100 -
0+
1$
1'
1.
1!
#232000
0!
#232500
1)
b1001100000111001101011011011010 (
0&
0#
0%
1+
0$
0'
0.
1!
#233000
0!
#233500
0)
b0 (
b1001100000111001101011011011010 "
b1001100000111001101011011011010 ,
b1001100000111001101011011011010 -
0+
1$
1'
1.
1!
#234000
0!
#234500
1%
1)
b1101010000011100100010100111101 (
1&
1#
1!
#235000
0!
#235500
0&
0#
0%
1+
0$
0'
0.
1!
#236000
0!
#236500
0)
b0 (
b1101010000011100100010100111101 "
b1101010000011100100010100111101 ,
b1101010000011100100010100111101 -
0+
1$
1'
1.
1!
#237000
0!
#237500
1)
b1001110001100111001000001100100 (
1!
#238000
0!
#238500
1%
1&
1#
1!
#239000
0!
#239500
0&
0#
0%
1+
0$
0'
0.
1!
#240000
0!
#240500
0)
b0 (
b1001110001100111001000001100100 "
b1001110001100111001000001100100 ,
b1001110001100111001000001100100 -
0+
1$
1'
1.
1!
#241000
0!
#241500
1!
#242000
0!
#242500
1%
1)
b10000011101100111110001010101101 (
1&
1#
1!
#243000
0!
#243500
0&
0#
0%
1+
0$
0'
0.
1!
#244000
0!
#244500
1%
0)
b0 (
1&
1#
b10000011101100111110001010101101 "
b10000011101100111110001010101101 ,
b10000011101100111110001010101101 -
0+
1$
1'
1.
1!
#245000
0!
#245500
0&
0#
0%
1+
0$
0'
0.
1!
#246000
0!
#246500
1)
b1011101111110010101100111110100 (
1&
1#
b0 "
b0 ,
b0 -
1!
#247000
0!
#247500
0)
b0 (
1%
b1011101111110010101100111110100 "
b1011101111110010101100111110100 ,
b1011101111110010101100111110100 -
0+
1$
1'
1.
1!
#248000
0!
#248500
0&
0#
0%
1+
0$
0'
0.
1!
#249000
0!
#249500
b0 "
b0 ,
b0 -
1!
#250000
0!
#250500
1&
1#
1!
#251000
0!
#251500
1!
#252000
0!
#252500
1)
b1011111111010011000111001010001 (
1!
#253000
0!
#253500
0)
b0 (
1%
b1011111111010011000111001010001 "
b1011111111010011000111001010001 ,
b1011111111010011000111001010001 -
0+
1$
1'
1.
1!
#254000
0!
#254500
1)
b10100010001010000000000110110011 (
0&
0#
0%
1+
0$
0'
0.
1!
#255000
0!
#255500
0)
b0 (
b10100010001010000000000110110011 "
b10100010001010000000000110110011 ,
b10100010001010000000000110110011 -
0+
1$
1'
1.
1!
#256000
0!
#256500
1)
b1101010010011111001111110011111 (
1!
#257000
0!
#257500
1!
#258000
0!
#258500
1%
1&
1#
1!
#259000
0!
#259500
0&
0#
0%
1+
0$
0'
0.
1!
#260000
0!
#260500
0)
b0 (
b1101010010011111001111110011111 "
b1101010010011111001111110011111 ,
b1101010010011111001111110011111 -
0+
1$
1'
1.
1!
#261000
0!
#261500
1%
1)
b1000010010100110000110010000100 (
1&
1#
1!
#262000
0!
#262500
0&
0#
0%
1+
0$
0'
0.
1!
#263000
0!
#263500
1%
0)
b0 (
1&
1#
b1000010010100110000110010000100 "
b1000010010100110000110010000100 ,
b1000010010100110000110010000100 -
0+
1$
1'
1.
1!
#264000
0!
#264500
0&
0#
0%
1+
0$
0'
0.
1!
#265000
0!
#265500
1)
b10101100111110011010111 (
1&
1#
b0 "
b0 ,
b0 -
1!
#266000
0!
#266500
0)
b0 (
1%
b10101100111110011010111 "
b10101100111110011010111 ,
b10101100111110011010111 -
0+
1$
1'
1.
1!
#267000
0!
#267500
1)
b10111010101100100011100001111000 (
0&
0#
0%
1+
0$
0'
0.
1!
#268000
0!
#268500
1%
0)
b0 (
1&
1#
b10111010101100100011100001111000 "
b10111010101100100011100001111000 ,
b10111010101100100011100001111000 -
0+
1$
1'
1.
1!
#269000
0!
#269500
0&
0#
0%
1+
0$
0'
0.
1!
#270000
0!
#270500
1)
b11011000111000100000111011111 (
1&
1#
b0 "
b0 ,
b0 -
1!
#271000
0!
#271500
0)
b0 (
1%
b11011000111000100000111011111 "
b11011000111000100000111011111 ,
b11011000111000100000111011111 -
0+
1$
1'
1.
1!
#272000
0!
#272500
1)
b1111001100101101011001001101100 (
0&
0#
0%
1+
0$
0'
0.
1!
#273000
0!
#273500
1%
0)
b0 (
1&
1#
b1111001100101101011001001101100 "
b1111001100101101011001001101100 ,
b1111001100101101011001001101100 -
0+
1$
1'
1.
1!
#274000
0!
