streamTest/streamReg_m2s/streamReg_m2s.v
// Generator : SpinalHDL v1.7.0a    git head : 150a9b9067020722818dfb17df4a23ac712a7af8
// Component : streamReg_m2s
// Git hash  : 3a903e741cbbe310a98c75dc1ebbd289cb1c87a4

`timescale 1ns/1ps

module streamReg_m2s (
  input               io_s_in_valid,
  output reg          io_s_in_ready,
  input      [31:0]   io_s_in_payload,
  output              io_m_out_valid,
  input               io_m_out_ready,
  output     [31:0]   io_m_out_payload,
  input               clk,
  input               reset
);

  wire                io_s_in_m2sPipe_valid;
  wire                io_s_in_m2sPipe_ready;
  wire       [31:0]   io_s_in_m2sPipe_payload;
  reg                 io_s_in_rValid;
  reg        [31:0]   io_s_in_rData;
  wire                when_Stream_l368;

  always @(*) begin
    io_s_in_ready = io_s_in_m2sPipe_ready;
    if(when_Stream_l368) begin
      io_s_in_ready = 1'b1;
    end
  end

  assign when_Stream_l368 = (! io_s_in_m2sPipe_valid);
  assign io_s_in_m2sPipe_valid = io_s_in_rValid;
  assign io_s_in_m2sPipe_payload = io_s_in_rData;
  assign io_m_out_valid = io_s_in_m2sPipe_valid;
  assign io_s_in_m2sPipe_ready = io_m_out_ready;
  assign io_m_out_payload = io_s_in_m2sPipe_payload;
  always @(posedge clk or posedge reset) begin
    if(reset) begin
      io_s_in_rValid <= 1'b0;
    end else begin
      if(io_s_in_ready) begin
        io_s_in_rValid <= io_s_in_valid;
      end
    end
  end

  always @(posedge clk) begin
    if(io_s_in_ready) begin
      io_s_in_rData <= io_s_in_payload;
    end
  end
  
  initial begin
    $dumpfile("streamReg_m2s_test.vcd");
    $dumpvars(0, streamReg_m2s);
  end


endmodule

streamTest/streamReg_m2s/streamReg_m2s_test.vcd
$date
	Thu May 26 13:28:31 2022
$end
$version
	Icarus Verilog
$end
$timescale
	1ps
$end
$scope module streamReg_m2s $end
$var wire 1 ! clk $end
$var wire 32 " io_m_out_payload [31:0] $end
$var wire 1 # io_m_out_ready $end
$var wire 1 $ io_m_out_valid $end
$var wire 1 % io_s_in_m2sPipe_ready $end
$var wire 32 & io_s_in_payload [31:0] $end
$var wire 1 ' io_s_in_valid $end
$var wire 1 ( reset $end
$var wire 1 ) when_Stream_l368 $end
$var wire 1 * io_s_in_m2sPipe_valid $end
$var wire 32 + io_s_in_m2sPipe_payload [31:0] $end
$var reg 32 , io_s_in_rData [31:0] $end
$var reg 1 * io_s_in_rValid $end
$var reg 1 - io_s_in_ready $end
$upscope $end
$enddefinitions $end
#0
$dumpvars
1-
bx ,
bx +
0*
1)
1(
z'
bz &
z%
0$
z#
bx "
0!
$end
#1000
1-
0'
b0 &
0%
0#
0(
#1500
b0 "
b0 +
b0 ,
1!
#2000
0!
#2500
1!
#3000
0!
#3500
1!
#4000
0!
#4500
1!
#5000
0!
#5500
1'
1!
#6000
0!
#6500
1%
1#
1-
0)
1$
1*
1!
#7000
0!
#7500
0-
0'
0%
0#
1!
#8000
0!
#8500
1-
1'
b10111011000100000101000101010111 &
1%
1#
1!
#9000
0!
#9500
0-
0'
b0 &
0%
0#
b10111011000100000101000101010111 "
b10111011000100000101000101010111 +
b10111011000100000101000101010111 ,
1!
#10000
0!
#10500
1-
1'
b1111001101111011011011000010001 &
1%
1#
1!
#11000
0!
#11500
0-
0'
b0 &
0%
0#
b1111001101111011011011000010001 "
b1111001101111011011011000010001 +
b1111001101111011011011000010001 ,
1!
#12000
0!
#12500
1!
#13000
0!
#13500
1!
#14000
0!
#14500
1!
#15000
0!
#15500
1-
1'
b10011000101011101001000110101 &
1%
1#
1!
#16000
0!
#16500
0-
0'
b0 &
0%
0#
b10011000101011101001000110101 "
b10011000101011101001000110101 +
b10011000101011101001000110101 ,
1!
#17000
0!
#17500
1'
b11011100101010100101101100001010 &
1!
#18000
0!
#18500
1-
1%
1#
1!
#19000
0!
#19500
0-
0'
b0 &
0%
0#
b11011100101010100101101100001010 "
b11011100101010100101101100001010 +
b11011100101010100101101100001010 ,
1!
#20000
0!
#20500
1!
#21000
0!
#21500
1'
b1110000010110110111110011110001 &
1!
#22000
0!
#22500
1-
1%
1#
1!
#23000
0!
#23500
0-
0'
b0 &
0%
0#
b1110000010110110111110011110001 "
b1110000010110110111110011110001 +
b1110000010110110111110011110001 ,
1!
#24000
0!
#24500
1-
1'
b1010111001011101011110110100011 &
1%
1#
1!
#25000
0!
#25500
0-
0'
b0 &
0%
0#
b1010111001011101011110110100011 "
b1010111001011101011110110100011 +
b1010111001011101011110110100011 ,
1!
#26000
0!
#26500
1-
1%
1#
1!
#27000
0!
#27500
1-
1'
b110111111100110100111011011110 &
0%
0#
b0 "
b0 +
b0 ,
1)
0$
0*
1!
#28000
0!
#28500
0'
b0 &
0-
b110111111100110100111011011110 "
b110111111100110100111011011110 +
b110111111100110100111011011110 ,
0)
1$
1*
1!
#29000
0!
#29500
1-
1%
1#
1!
#30000
0!
#30500
1-
1'
b1100011001000011001101000110000 &
0%
0#
b0 "
b0 +
b0 ,
1)
0$
0*
1!
#31000
0!
#31500
0'
b0 &
1%
1#
1-
b1100011001000011001101000110000 "
b1100011001000011001101000110000 +
b1100011001000011001101000110000 ,
0)
1$
1*
1!
#32000
0!
#32500
1-
0%
0#
b0 "
b0 +
b0 ,
1)
0$
0*
1!
#33000
0!
#33500
1'
b11111011010010110110101000011100 &
1!
#34000
0!
#34500
0'
b0 &
1%
1#
1-
b11111011010010110110101000011100 "
b11111011010010110110101000011100 +
b11111011010010110110101000011100 ,
0)
1$
1*
1!
#35000
0!
#35500
1-
0%
0#
b0 "
b0 +
b0 ,
1)
0$
0*
1!
#36000
0!
#36500
1!
#37000
0!
#37500
1!
#38000
0!
#38500
1'
b1111110111111010110000101100001 &
1%
1#
1!
#39000
0!
#39500
0'
b0 &
b1111110111111010110000101100001 "
b1111110111111010110000101100001 +
b1111110111111010110000101100001 ,
0)
1$
1*
1!
#40000
0!
#40500
1-
1'
b100010101011110000101011010011 &
0%
0#
b0 "
b0 +
b0 ,
1)
0$
0*
1!
#41000
0!
#41500
0'
b0 &
0-
b100010101011110000101011010011 "
b100010101011110000101011010011 +
b100010101011110000101011010011 ,
0)
1$
1*
1!
#42000
0!
#42500
1'
b11011110110011001100100111000010 &
1!
#43000
0!
#43500
1-
1%
1#
1!
#44000
0!
#44500
0-
0'
b0 &
0%
0#
b11011110110011001100100111000010 "
b11011110110011001100100111000010 +
b11011110110011001100100111000010 ,
1!
#45000
0!
#45500
1!
#46000
0!
#46500
1'
b10011001011001111100010101010000 &
1!
#47000
0!
#47500
1-
1%
1#
1!
#48000
0!
#48500
0-
0'
b0 &
0%
0#
b10011001011001111100010101010000 "
b10011001011001111100010101010000 +
b10011001011001111100010101010000 ,
1!
#49000
0!
#49500
1'
b11000010000000110010100000001 &
1!
#50000
0!
#50500
1-
1%
1#
1!
#51000
0!
#51500
0-
0'
b0 &
0%
0#
b11000010000000110010100000001 "
b11000010000000110010100000001 +
b11000010000000110010100000001 ,
1!
#52000
0!
#52500
1'
b11001011101110001110101011001100 &
1!
#53000
0!
#53500
1!
#54000
0!
#54500
1-
1%
1#
1!
#55000
0!
#55500
0-
0'
b0 &
0%
0#
b11001011101110001110101011001100 "
b11001011101110001110101011001100 +
b11001011101110001110101011001100 ,
1!
#56000
0!
#56500
1-
1'
b101011001100000010100000100110 &
1%
1#
1!
#57000
0!
#57500
0-
0'
b0 &
0%
0#
b101011001100000010100000100110 "
b101011001100000010100000100110 +
b101011001100000010100000100110 ,
1!
#58000
0!
#58500
1-
1'
b11111110101110000001001011101110 &
1%
1#
1!
#59000
0!
#59500
0-
0'
b0 &
0%
0#
b11111110101110000001001011101110 "
b11111110101110000001001011101110 +
b11111110101110000001001011101110 ,
1!
#60000
0!
#60500
1'
b1101011010011101000101100101011 &
1!
#61000
0!
#61500
1-
1%
1#
1!
#62000
0!
#62500
0-
0'
b0 &
0%
0#
b1101011010011101000101100101011 "
b1101011010011101000101100101011 +
b1101011010011101000101100101011 ,
1!
#63000
0!
#63500
1!
#64000
0!
#64500
1-
1'
b1001001010000110000010000000011 &
1%
1#
1!
#65000
0!
#65500
0-
0'
b0 &
0%
0#
b1001001010000110000010000000011 "
b1001001010000110000010000000011 +
b1001001010000110000010000000011 ,
1!
#66000
0!
#66500
1-
1%
1#
1!
#67000
0!
#67500
1-
1'
b1100000100010100000001001001110 &
0%
0#
b0 "
b0 +
b0 ,
1)
0$
0*
1!
#68000
0!
#68500
0'
b0 &
1%
1#
1-
b1100000100010100000001001001110 "
b1100000100010100000001001001110 +
b1100000100010100000001001001110 ,
0)
1$
1*
1!
#69000
0!
#69500
1-
1'
b1110111111100001010010101100100 &
0%
0#
b0 "
b0 +
b0 ,
1)
0$
0*
1!
#70000
0!
#70500
0'
b0 &
1%
1#
1-
b1110111111100001010010101100100 "
b1110111111100001010010101100100 +
b1110111111100001010010101100100 ,
0)
1$
1*
1!
#71000
0!
#71500
1-
0%
0#
b0 "
b0 +
b0 ,
1)
0$
0*
1!
#72000
0!
#72500
1%
1#
1!
#73000
0!
#73500
1'
b111000011011001101111010011001 &
1!
#74000
0!
#74500
0'
b0 &
b111000011011001101111010011001 "
b111000011011001101111010011001 +
b111000011011001101111010011001 ,
0)
1$
1*
1!
#75000
0!
#75500
1-
0%
0#
b0 "
b0 +
b0 ,
1)
0$
0*
1!
#76000
0!
#76500
1'
b1000011011101001000011010001 &
1!
#77000
0!
#77500
0'
b0 &
1%
1#
1-
b1000011011101001000011010001 "
b1000011011101001000011010001 +
b1000011011101001000011010001 ,
0)
1$
1*
1!
#78000
0!
#78500
1-
0%
0#
b0 "
b0 +
b0 ,
1)
0$
0*
1!
#79000
0!
#79500
1!
#80000
0!
#80500
1%
1#
1!
#81000
0!
#81500
1!
#82000
0!
#82500
1'
b11010100010001100101011000111000 &
1!
#83000
0!
#83500
0'
b0 &
b11010100010001100101011000111000 "
b11010100010001100101011000111000 +
b11010100010001100101011000111000 ,
0)
1$
1*
1!
#84000
0!
#84500
1-
1'
b1000110110101100011100010000010 &
0%
0#
b0 "
b0 +
b0 ,
1)
0$
0*
1!
#85000
0!
#85500
0'
b0 &
0-
b1000110110101100011100010000010 "
b1000110110101100011100010000010 +
b1000110110101100011100010000010 ,
0)
1$
1*
1!
#86000
0!
#86500
1!
#87000
0!
#87500
1-
1%
1#
1!
#88000
0!
#88500
1-
1'
b11110100100111110101101001100001 &
0%
0#
b0 "
b0 +
b0 ,
1)
0$
0*
1!
#89000
0!
#89500
0'
b0 &
0-
b11110100100111110101101001100001 "
b11110100100111110101101001100001 +
b11110100100111110101101001100001 ,
0)
1$
1*
1!
#90000
0!
#90500
1!
#91000
0!
#91500
1-
1'
b1111101101101010100110111101011 &
1%
1#
1!
#92000
0!
#92500
0-
0'
b0 &
0%
0#
b1111101101101010100110111101011 "
b1111101101101010100110111101011 +
b1111101101101010100110111101011 ,
1!
#93000
0!
#93500
1-
1%
1#
1!
#94000
0!
#94500
1-
0%
0#
b0 "
b0 +
b0 ,
1)
0$
0*
1!
#95000
0!
#95500
1'
b1001100111111111000100001100111 &
1!
#96000
0!
#96500
0'
b0 &
0-
b1001100111111111000100001100111 "
b1001100111111111000100001100111 +
b1001100111111111000100001100111 ,
0)
1$
1*
1!
#97000
0!
#97500
1'
b10001011101110101100111110000001 &
1!
#98000
0!
#98500
1!
#99000
0!
#99500
1-
1%
1#
1!
#100000
0!
#100500
0-
0'
b0 &
0%
0#
b10001011101110101100111110000001 "
b10001011101110101100111110000001 +
b10001011101110101100111110000001 ,
1!
#101000
0!
#101500
1-
1'
b101000010110000001110011010100 &
1%
1#
1!
#102000
0!
#102500
0-
0'
b0 &
0%
0#
b101000010110000001110011010100 "
b101000010110000001110011010100 +
b101000010110000001110011010100 ,
1!
#103000
0!
#103500
1-
1%
1#
1!
#104000
0!
#104500
1-
0%
0#
b0 "
b0 +
b0 ,
1)
0$
0*
1!
#105000
0!
#105500
1'
b1010110011000100111111110111111 &
1!
#106000
0!
#106500
0'
b0 &
0-
b1010110011000100111111110111111 "
b1010110011000100111111110111111 +
b1010110011000100111111110111111 ,
0)
1$
1*
1!
#107000
0!
#107500
1!
#108000
0!
#108500
1-
1%
1#
1!
#109000
0!
#109500
1-
1'
b1100100010000111011010011101110 &
0%
0#
b0 "
b0 +
b0 ,
1)
0$
0*
1!
#110000
0!
#110500
0'
b0 &
1%
1#
1-
b1100100010000111011010011101110 "
b1100100010000111011010011101110 +
b1100100010000111011010011101110 ,
0)
1$
1*
1!
#111000
0!
#111500
1-
1'
b10111010011001100001000111010 &
0%
0#
b0 "
b0 +
b0 ,
1)
0$
0*
1!
#112000
0!
#112500
0'
b0 &
1%
1#
1-
b10111010011001100001000111010 "
b10111010011001100001000111010 +
b10111010011001100001000111010 ,
0)
1$
1*
1!
#113000
0!
#113500
1-
0%
0#
b0 "
b0 +
b0 ,
1)
0$
0*
1!
#114000
0!
#114500
1'
b11110100011100101100110001010000 &
1%
1#
1!
#115000
0!
#115500
0'
b0 &
b11110100011100101100110001010000 "
b11110100011100101100110001010000 +
b11110100011100101100110001010000 ,
0)
1$
1*
1!
#116000
0!
#116500
1-
0%
0#
b0 "
b0 +
b0 ,
1)
0$
0*
1!
#117000
0!
#117500
1!
#118000
0!
#118500
1%
1#
1!
#119000
0!
#119500
1'
b10101010100011111110000000110001 &
1!
#120000
0!
#120500
0'
b0 &
b10101010100011111110000000110001 "
b10101010100011111110000000110001 +
b10101010100011111110000000110001 ,
0)
1$
1*
1!
#121000
0!
#121500
1-
0%
0#
b0 "
b0 +
b0 ,
1)
0$
0*
1!
#122000
0!
#122500
1'
b11011100101100000010011111001100 &
1!
#123000
0!
#123500
0'
b0 &
1%
1#
1-
b11011100101100000010011111001100 "
b11011100101100000010011111001100 +
b11011100101100000010011111001100 ,
0)
1$
1*
1!
#124000
0!
#124500
1-
1'
b110110000111001101011101100001 &
0%
0#
b0 "
b0 +
b0 ,
1)
0$
0*
1!
#125000
0!
#125500
0'
b0 &
0-
b110110000111001101011101100001 "
b110110000111001101011101100001 +
b110110000111001101011101100001 ,
0)
1$
1*
1!
#126000
0!
#126500
1'
b1000010100100010010011101101101 &
1!
#127000
0!
#127500
1-
1%
1#
1!
#128000
0!
#128500
0-
0'
b0 &
0%
0#
b1000010100100010010011101101101 "
b1000010100100010010011101101101 +
b1000010100100010010011101101101 ,
1!
#129000
0!
#129500
1'
b1111000100100100000110010010 &
1!
#130000
0!
#130500
1-
1%
1#
1!
#131000
0!
#131500
0-
0'
b0 &
0%
0#
b1111000100100100000110010010 "
b1111000100100100000110010010 +
b1111000100100100000110010010 ,
1!
#132000
0!
#132500
1!
#133000
0!
#133500
1-
1%
1#
1!
#134000
0!
#134500
1-
1'
b1011011100100111100011011001110 &
0%
0#
b0 "
b0 +
b0 ,
1)
0$
0*
1!
#135000
0!
#135500
0'
b0 &
1%
1#
1-
b1011011100100111100011011001110 "
b1011011100100111100011011001110 +
b1011011100100111100011011001110 ,
0)
1$
1*
1!
#136000
0!
#136500
1-
0%
0#
b0 "
b0 +
b0 ,
1)
0$
0*
1!
#137000
0!
#137500
1'
b10111110001100101000101111000000 &
1!
#138000
0!
#138500
0'
b0 &
1%
1#
1-
b10111110001100101000101111000000 "
b10111110001100101000101111000000 +
b10111110001100101000101111000000 ,
0)
1$
1*
1!
#139000
0!
#139500
1-
0%
0#
b0 "
b0 +
b0 ,
1)
0$
0*
1!
#140000
0!
#140500
1%
1#
1!
#141000
0!
#141500
1!
#142000
0!
#142500
1!
#143000
0!
#143500
1!
#144000
0!
#144500
1!
#145000
0!
#145500
1!
#146000
0!
#146500
1'
b1100000111111100001110000010 &
1!
#147000
0!
#147500
0'
b0 &
b1100000111111100001110000010 "
b1100000111111100001110000010 +
b1100000111111100001110000010 ,
0)
1$
1*
1!
#148000
0!
#148500
1-
1'
b1111000000001011110100110111010 &
0%
0#
b0 "
b0 +
b0 ,
1)
0$
0*
1!
#149000
0!
#149500
0'
b0 &
0-
b1111000000001011110100110111010 "
b1111000000001011110100110111010 +
b1111000000001011110100110111010 ,
0)
1$
1*
1!
#150000
0!
#150500
1-
1'
b1101001010000000111111000001010 &
1%
1#
1!
#151000
0!
#151500
0-
0'
b0 &
0%
0#
b1101001010000000111111000001010 "
b1101001010000000111111000001010 +
b1101001010000000111111000001010 ,
1!
#152000
0!
#152500
1!
#153000
0!
#153500
1-
1'
b11000100100111110111010010101101 &
1%
1#
1!
#154000
0!
#154500
0-
0'
b0 &
0%
0#
b11000100100111110111010010101101 "
b11000100100111110111010010101101 +
b11000100100111110111010010101101 ,
1!
#155000
0!
#155500
1-
1%
1#
1!
#156000
0!
#156500
1-
0%
0#
b0 "
b0 +
b0 ,
1)
0$
0*
1!
#157000
0!
#157500
1!
#158000
0!
#158500
1'
b1000001101101101110101100010010 &
1!
#159000
0!
#159500
0'
b0 &
0-
b1000001101101101110101100010010 "
b1000001101101101110101100010010 +
b1000001101101101110101100010010 ,
0)
1$
1*
1!
#160000
0!
#160500
1-
1'
b101000101000001101110011000 &
1%
1#
1!
#161000
0!
#161500
0-
0'
b0 &
0%
0#
b101000101000001101110011000 "
b101000101000001101110011000 +
b101000101000001101110011000 ,
1!
#162000
0!
#162500
1-
1%
1#
1!
#163000
0!
#163500
1-
1'
b10111111100000111101010100100111 &
0%
0#
b0 "
b0 +
b0 ,
1)
0$
0*
1!
#164000
0!
#164500
0'
b0 &
1%
1#
1-
b10111111100000111101010100100111 "
b10111111100000111101010100100111 +
b10111111100000111101010100100111 ,
0)
1$
1*
1!
#165000
0!
#165500
1-
1'
b1100000111111100010101110101001 &
0%
0#
b0 "
b0 +
b0 ,
1)
0$
0*
1!
#166000
0!
#166500
0'
b0 &
1%
1#
1-
b1100000111111100010101110101001 "
b1100000111111100010101110101001 +
b1100000111111100010101110101001 ,
0)
1$
1*
1!
#167000
0!
#167500
1-
1'
b100000111100111111000001111111 &
0%
0#
b0 "
b0 +
b0 ,
1)
0$
0*
1!
#168000
0!
#168500
0'
b0 &
1%
1#
1-
b100000111100111111000001111111 "
b100000111100111111000001111111 +
b100000111100111111000001111111 ,
0)
1$
1*
1!
#169000
0!
#169500
1-
1'
b10000101010110111110000010101101 &
0%
0#
b0 "
b0 +
b0 ,
1)
0$
0*
1!
#170000
0!
#170500
0'
b0 &
0-
b10000101010110111110000010101101 "
b10000101010110111110000010101101 +
b10000101010110111110000010101101 ,
0)
1$
1*
1!
#171000
0!
#171500
1-
1'
b1111011001011111110000011111001 &
1%
1#
1!
#172000
0!
#172500
0-
0'
b0 &
0%
0#
b1111011001011111110000011111001 "
b1111011001011111110000011111001 +
b1111011001011111110000011111001 ,
1!
#173000
0!
#173500
1-
1%
1#
1!
#174000
0!
#174500
1-
0%
0#
b0 "
b0 +
b0 ,
1)
0$
0*
1!
#175000
0!
#175500
1'
b10110111100110100101110010010101 &
1!
#176000
0!
#176500
0'
b0 &
0-
b10110111100110100101110010010101 "
b10110111100110100101110010010101 +
b10110111100110100101110010010101 ,
0)
1$
1*
1!
#177000
0!
#177500
1!
#178000
0!
#178500
1'
b11100011011111000111111110 &
1!
#179000
0!
#179500
1!
#180000
0!
#180500
1!
#181000
0!
#181500
1-
1%
1#
1!
#182000
0!
#182500
0-
0'
b0 &
0%
0#
b11100011011111000111111110 "
b11100011011111000111111110 +
b11100011011111000111111110 ,
1!
#183000
0!
#183500
1'
b10010100001001101100000101111011 &
1!
#184000
0!
#184500
1!
#185000
0!
#185500
1-
1%
1#
1!
#186000
0!
#186500
0-
0'
b0 &
0%
0#
b10010100001001101100000101111011 "
b10010100001001101100000101111011 +
b10010100001001101100000101111011 ,
1!
#187000
0!
#187500
1!
#188000
0!
#188500
1-
1%
1#
1!
#189000
0!
#189500
1-
1'
b1001101011100101100101101110011 &
0%
0#
b0 "
b0 +
b0 ,
1)
0$
0*
1!
#190000
0!
#190500
0'
b0 &
1%
1#
1-
b1001101011100101100101101110011 "
b1001101011100101100101101110011 +
b1001101011100101100101101110011 ,
0)
1$
1*
1!
#191000
0!
#191500
1-
1'
b11101010001010101000101111110011 &
0%
0#
b0 "
b0 +
b0 ,
1)
0$
0*
1!
#192000
0!
#192500
0'
b0 &
1%
1#
1-
b11101010001010101000101111110011 "
b11101010001010101000101111110011 +
b11101010001010101000101111110011 ,
0)
1$
1*
1!
#193000
0!
#193500
1-
0%
0#
b0 "
b0 +
b0 ,
1)
0$
0*
1!
#194000
0!
#194500
1%
1#
1!
#195000
0!
#195500
1'
b11101010000000001011101111111001 &
1!
#196000
0!
#196500
0'
b0 &
b11101010000000001011101111111001 "
b11101010000000001011101111111001 +
b11101010000000001011101111111001 ,
0)
1$
1*
1!
#197000
0!
#197500
1-
0%
0#
b0 "
b0 +
b0 ,
1)
0$
0*
1!
#198000
0!
#198500
1'
b10101111000100100111010001001100 &
1%
1#
1!
#199000
0!
#199500
0'
b0 &
b10101111000100100111010001001100 "
b10101111000100100111010001001100 +
b10101111000100100111010001001100 ,
0)
1$
1*
1!
#200000
0!
#200500
1-
0%
0#
b0 "
b0 +
b0 ,
1)
0$
0*
1!
#201000
0!
#201500
1'
b10111101001001100011000000101111 &
1!
#202000
0!
#202500
0'
b0 &
0-
b10111101001001100011000000101111 "
b10111101001001100011000000101111 +
b10111101001001100011000000101111 ,
0)
1$
1*
1!
#203000
0!
#203500
1'
b10001010111010001001000000001110 &
1!
#204000
0!
#204500
1!
#205000
0!
#205500
1-
1%
1#
1!
#206000
0!
#206500
0-
0'
b0 &
0%
0#
b10001010111010001001000000001110 "
b10001010111010001001000000001110 +
b10001010111010001001000000001110 ,
1!
#207000
0!
#207500
1-
1'
b10010011101110011000000010100001 &
1%
1#
1!
#208000
0!
#208500
0-
0'
b0 &
0%
0#
b10010011101110011000000010100001 "
b10010011101110011000000010100001 +
b10010011101110011000000010100001 ,
1!
#209000
0!
#209500
1'
b10110111011100011111101010100011 &
1!
#210000
0!
#210500
1!
#211000
0!
#211500
1-
1%
1#
1!
#212000
0!
#212500
0-
0'
b0 &
0%
0#
b10110111011100011111101010100011 "
b10110111011100011111101010100011 +
b10110111011100011111101010100011 ,
1!
#213000
0!
#213500
1-
1%
1#
1!
#214000
0!
#214500
1-
0%
0#
b0 "
b0 +
b0 ,
1)
0$
0*
1!
#215000
0!
#215500
1%
1#
1!
#216000
0!
#216500
1'
b1010011011001010101101010110000 &
1!
#217000
0!
#217500
0'
b0 &
b1010011011001010101101010110000 "
b1010011011001010101101010110000 +
b1010011011001010101101010110000 ,
0)
1$
1*
1!
#218000
0!
#218500
1-
1'
b11001001100010011011111100010010 &
0%
0#
b0 "
b0 +
b0 ,
1)
0$
0*
1!
#219000
0!
#219500
0'
b0 &
0-
b11001001100010011011111100010010 "
b11001001100010011011111100010010 +
b11001001100010011011111100010010 ,
0)
1$
1*
1!
#220000
0!
#220500
1'
b110100101010101010001010100110 &
1!
#221000
0!
#221500
1!
#222000
0!
#222500
1-
1%
1#
1!
#223000
0!
#223500
0-
0'
b0 &
0%
0#
b110100101010101010001010100110 "
b110100101010101010001010100110 +
b110100101010101010001010100110 ,
1!
#224000
0!
#224500
1!
#225000
0!
#225500
1'
b1001010110010010100000111100111 &
1!
#226000
0!
#226500
1!
#227000
0!
#227500
1-
1%
1#
1!
#228000
0!
#228500
0-
0'
b0 &
0%
0#
b1001010110010010100000111100111 "
b1001010110010010100000111100111 +
b1001010110010010100000111100111 ,
1!
#229000
0!
#229500
1!
#230000
0!
#230500
1-
1%
1#
1!
#231000
0!
#231500
1-
1'
b1000011111001010011101111011100 &
0%
0#
b0 "
b0 +
b0 ,
1)
0$
0*
1!
#232000
0!
#232500
0'
b0 &
1%
1#
1-
b1000011111001010011101111011100 "
b1000011111001010011101111011100 +
b1000011111001010011101111011100 ,
0)
1$
1*
1!
#233000
0!
#233500
1-
1'
b11100100010110010110000011101001 &
0%
0#
b0 "
b0 +
b0 ,
1)
0$
0*
1!
#234000
0!
#234500
0'
b0 &
1%
1#
1-
b11100100010110010110000011101001 "
b11100100010110010110000011101001 +
b11100100010110010110000011101001 ,
0)
1$
1*
1!
#235000
0!
#235500
1-
0%
0#
b0 "
b0 +
b0 ,
1)
0$
0*
1!
#236000
0!
#236500
1!
#237000
0!
#237500
1'
b101101000111001010101001010000 &
1!
#238000
0!
#238500
0'
b0 &
1%
1#
1-
b101101000111001010101001010000 "
b101101000111001010101001010000 +
b101101000111001010101001010000 ,
0)
1$
1*
1!
#239000
0!
#239500
1-
1'
b10010101001111011010011001010110 &
0%
0#
b0 "
b0 +
b0 ,
1)
0$
0*
1!
#240000
0!
#240500
0'
b0 &
1%
1#
1-
b10010101001111011010011001010110 "
b10010101001111011010011001010110 +
b10010101001111011010011001010110 ,
0)
1$
1*
1!
#241000
0!
#241500
1-
0%
0#
b0 "
b0 +
b0 ,
1)
0$
0*
1!
#242000
0!
#242500
1'
b1010001110110011011010111101010 &
1!
#243000
0!
#243500
0'
b0 &
0-
b1010001110110011011010111101010 "
b1010001110110011011010111101010 +
b1010001110110011011010111101010 ,
0)
1$
1*
1!
#244000
0!
#244500
1!
#245000
0!
#245500
1!
#246000
0!
#246500
1!
#247000
0!
#247500
1!
#248000
0!
#248500
1-
1%
1#
1!
#249000
0!
#249500
1-
0%
0#
b0 "
b0 +
b0 ,
1)
0$
0*
1!
#250000
0!
#250500
1%
1#
1!
#251000
0!
#251500
1'
b10100001001111101001101010100011 &
1!
#252000
0!
#252500
0'
b0 &
b10100001001111101001101010100011 "
b10100001001111101001101010100011 +
b10100001001111101001101010100011 ,
0)
1$
1*
1!
#253000
0!
#253500
1-
1'
b1110011011010101001010111100101 &
0%
0#
b0 "
b0 +
b0 ,
1)
0$
0*
1!
#254000
0!
#254500
0'
b0 &
1%
1#
1-
b1110011011010101001010111100101 "
b1110011011010101001010111100101 +
b1110011011010101001010111100101 ,
0)
1$
1*
1!
#255000
0!
#255500
1-
0%
0#
b0 "
b0 +
b0 ,
1)
0$
0*
1!
#256000
0!
#256500
1%
1#
1!
#257000
0!
#257500
1!
#258000
0!
#258500
1!
#259000
0!
#259500
1!
#260000
0!
#260500
1!
#261000
0!
#261500
1'
b1011010101010111111110001111001 &
1!
#262000
0!
#262500
0'
b0 &
b1011010101010111111110001111001 "
b1011010101010111111110001111001 +
b1011010101010111111110001111001 ,
0)
1$
1*
1!
#263000
0!
#263500
1-
0%
0#
b0 "
b0 +
b0 ,
1)
0$
0*
1!
#264000
0!
#264500
1'
b111010010110000010100001101110 &
1%
1#
1!
#265000
0!
#265500
0'
b0 &
b111010010110000010100001101110 "
b111010010110000010100001101110 +
b111010010110000010100001101110 ,
0)
1$
1*
1!
#266000
0!
#266500
1-
0%
0#
b0 "
b0 +
b0 ,
1)
0$
0*
1!
#267000
0!
#267500
1!
#268000
0!
#268500
1'
b100000011001111100010101101101 &
1!
#269000
0!
#269500
0'
b0 &
0-
b100000011001111100010101101101 "
b100000011001111100010101101101 +
b100000011001111100010101101101 ,
0)
1$
1*
1!
#270000
0!
#270500
1-
1%
1#
1!
#271000
0!
#271500
1-
0%
0#
b0 "
b0 +
b0 ,
1)
0$
0*
1!
#272000
0!
#272500
1!
#273000
0!
#273500
1%
1#
1!
#274000
0!
#274500
1'
b11001010011101100101100110101101 &
1!
#275000
0!
#275500
0'
b0 &
b11001010011101100101100110101101 "
b11001010011101100101100110101101 +
b11001010011101100101100110101101 ,
0)
1$
1*
1!
#276000
0!
#276500
1-
0%
0#
b0 "
b0 +
b0 ,
1)
0$
0*
1!
#277000
0!
#277500
1%
1#
1!
#278000
0!
#278500
1'
b11100101010000011000111010101001 &
1!
#279000
0!
#279500
0'
b0 &
b11100101010000011000111010101001 "
b11100101010000011000111010101001 +
b11100101010000011000111010101001 ,
0)
1$
1*
1!
#280000
0!
#280500
1-
0%
0#
b0 "
b0 +
b0 ,
1)
0$
0*
1!
#281000
0!
#281500
1'
b11011101100111011000110100000100 &
1%
1#
1!
#282000
0!
#282500
0'
b0 &
b11011101100111011000110100000100 "
b11011101100111011000110100000100 +
b11011101100111011000110100000100 ,
0)
1$
1*
1!
#283000
0!
#283500
1-
0%
0#
b0 "
b0 +
b0 ,
1)
0$
0*
1!
#284000
0!
#284500
1!
#285000
0!
#285500
1'
b1001001010110101101110000110100 &
1%
1#
1!
#286000
0!
#286500
0'
b0 &
b1001001010110101101110000110100 "
b1001001010110101101110000110100 +
b1001001010110101101110000110100 ,
0)
1$
1*
1!
#287000
0!
#287500
1-
0%
0#
b0 "
b0 +
b0 ,
1)
0$
0*
1!
#288000
0!
#288500
1%
1#
1!
#289000
0!
#289500
1!
#290000
0!
#290500
1'
b10111010010000100100100011000000 &
1!
#291000
0!
#291500
0'
b0 &
b10111010010000100100100011000000 "
b10111010010000100100100011000000 +
b10111010010000100100100011000000 ,
0)
1$
1*
1!
#292000
0!
#292500
1-
0%
0#
b0 "
b0 +
b0 ,
1)
0$
0*
1!
#293000
0!
#293500
1%
1#
1!
#294000
0!
#294500
1'
b1011100111101000000100111011001 &
1!
#295000
0!
#295500
0'
b0 &
b1011100111101000000100111011001 "
b1011100111101000000100111011001 +
b1011100111101000000100111011001 ,
0)
1$
1*
1!
#296000
0!
#296500
1-
1'
b10000101110111110000101000001010 &
0%
0#
b0 "
b0 +
b0 ,
1)
0$
0*
1!
#297000
0!
#297500
0'
b0 &
0-
b10000101110111110000101000001010 "
b10000101110111110000101000001010 +
b10000101110111110000101000001010 ,
0)
1$
1*
1!
#298000
0!
#298500
1-
1'
b11001010110000100110011110000110 &
1%
1#
1!
#299000
0!
#299500
0-
0'
b0 &
0%
0#
b11001010110000100110011110000110 "
b11001010110000100110011110000110 +
b11001010110000100110011110000110 ,
1!
#300000
0!
