streamTest/stream_Reg/streamReg_s2m/streamReg_s2m.v
// Generator : SpinalHDL v1.7.0a    git head : 150a9b9067020722818dfb17df4a23ac712a7af8
// Component : streamReg_s2m
// Git hash  : 3a903e741cbbe310a98c75dc1ebbd289cb1c87a4

`timescale 1ns/1ps

module streamReg_s2m (
  input               io_s_in_valid,
  output              io_s_in_ready,
  input      [31:0]   io_s_in_payload,
  output              io_m_out_valid,
  input               io_m_out_ready,
  output     [31:0]   io_m_out_payload,
  input               clk,
  input               reset
);

  wire                io_s_in_s2mPipe_valid;
  wire                io_s_in_s2mPipe_ready;
  wire       [31:0]   io_s_in_s2mPipe_payload;
  reg                 io_s_in_rValid;
  reg        [31:0]   io_s_in_rData;

  assign io_s_in_ready = (! io_s_in_rValid);
  assign io_s_in_s2mPipe_valid = (io_s_in_valid || io_s_in_rValid);
  assign io_s_in_s2mPipe_payload = (io_s_in_rValid ? io_s_in_rData : io_s_in_payload);
  assign io_m_out_valid = io_s_in_s2mPipe_valid;
  assign io_s_in_s2mPipe_ready = io_m_out_ready;
  assign io_m_out_payload = io_s_in_s2mPipe_payload;
  always @(posedge clk or posedge reset) begin
    if(reset) begin
      io_s_in_rValid <= 1'b0;
    end else begin
      if(io_s_in_valid) begin
        io_s_in_rValid <= 1'b1;
      end
      if(io_s_in_s2mPipe_ready) begin
        io_s_in_rValid <= 1'b0;
      end
    end
  end

  always @(posedge clk) begin
    if(io_s_in_ready) begin
      io_s_in_rData <= io_s_in_payload;
    end
  end
  
  initial begin
    $dumpfile("streamReg_s2m_test.vcd");
    $dumpvars(0, streamReg_s2m);
  end



endmodule

streamTest/stream_Reg/streamReg_s2m/streamReg_s2m_test.vcd
$date
	Thu May 26 13:32:08 2022
$end
$version
	Icarus Verilog
$end
$timescale
	1ps
$end
$scope module streamReg_s2m $end
$var wire 1 ! clk $end
$var wire 32 " io_m_out_payload [31:0] $end
$var wire 1 # io_m_out_ready $end
$var wire 1 $ io_m_out_valid $end
$var wire 32 % io_s_in_payload [31:0] $end
$var wire 1 & io_s_in_s2mPipe_ready $end
$var wire 1 ' io_s_in_s2mPipe_valid $end
$var wire 1 ( io_s_in_valid $end
$var wire 1 ) reset $end
$var wire 32 * io_s_in_s2mPipe_payload [31:0] $end
$var wire 1 + io_s_in_ready $end
$var reg 32 , io_s_in_rData [31:0] $end
$var reg 1 - io_s_in_rValid $end
$upscope $end
$enddefinitions $end
#0
$dumpvars
0-
bx ,
1+
bz *
1)
z(
x'
z&
bz %
x$
z#
bz "
0!
$end
#1000
0$
0'
b0 "
b0 *
0(
b0 %
0&
0#
0)
#1500
b0 ,
1!
#2000
0!
#2500
1!
#3000
0!
#3500
1!
#4000
0!
#4500
1$
1'
1(
1&
1#
1!
#5000
0!
#5500
0&
0#
1+
0-
1!
#6000
0!
#6500
0(
1&
1#
0+
1-
1!
#7000
0!
#7500
0&
0#
0$
0'
1+
0-
1!
#8000
0!
#8500
1&
1#
1!
#9000
0!
#9500
1!
#10000
0!
#10500
1!
#11000
0!
#11500
1$
1'
b1110010100110110000010001100010 "
b1110010100110110000010001100010 *
1(
b1110010100110110000010001100010 %
1!
#12000
0!
#12500
0$
0'
b0 "
b0 *
0(
b0 %
0&
0#
b1110010100110110000010001100010 ,
1+
0-
1!
#13000
0!
#13500
1&
1#
b0 ,
1!
#14000
0!
#14500
1$
1'
b10100010000101010000101101010110 "
b10100010000101010000101101010110 *
1(
b10100010000101010000101101010110 %
1!
#15000
0!
#15500
0$
0'
b0 "
b0 *
0(
b0 %
0&
0#
b10100010000101010000101101010110 ,
1+
0-
1!
#16000
0!
#16500
1$
1'
b1101110110101000100001010000 "
b1101110110101000100001010000 *
1(
b1101110110101000100001010000 %
1&
1#
b0 ,
1!
#17000
0!
#17500
0$
0'
b0 "
b0 *
0(
b0 %
0&
0#
b1101110110101000100001010000 ,
1+
0-
1!
#18000
0!
#18500
1&
1#
b0 ,
1!
#19000
0!
#19500
1$
1'
b110001100111000011010011100010 "
b110001100111000011010011100010 *
1(
b110001100111000011010011100010 %
1!
#20000
0!
#20500
0$
0'
b0 "
b0 *
0(
b0 %
0&
0#
b110001100111000011010011100010 ,
1+
0-
1!
#21000
0!
#21500
1$
1'
b10100001101000000100111101011011 "
b10100001101000000100111101011011 *
1(
b10100001101000000100111101011011 %
b0 ,
1!
#22000
0!
#22500
0(
b0 %
1&
1#
b10100001101000000100111101011011 ,
0+
1-
1!
#23000
0!
#23500
0&
0#
b0 "
b0 *
0$
0'
1+
0-
1!
#24000
0!
#24500
b0 ,
1!
#25000
0!
#25500
1!
#26000
0!
#26500
1&
1#
1!
#27000
0!
#27500
1$
1'
b1011100100100010110110110100111 "
b1011100100100010110110110100111 *
1(
b1011100100100010110110110100111 %
1!
#28000
0!
#28500
0$
0'
b0 "
b0 *
0(
b0 %
0&
0#
b1011100100100010110110110100111 ,
1+
0-
1!
#29000
0!
#29500
b0 ,
1!
#30000
0!
#30500
1$
1'
b11101011111000110101111111110010 "
b11101011111000110101111111110010 *
1(
b11101011111000110101111111110010 %
1!
#31000
0!
#31500
0(
b0 %
1&
1#
b11101011111000110101111111110010 ,
0+
1-
1!
#32000
0!
#32500
0&
0#
b0 "
b0 *
0$
0'
1+
0-
1!
#33000
0!
#33500
1$
1'
b11011100111001000111111111111011 "
b11011100111001000111111111111011 *
1(
b11011100111001000111111111111011 %
1&
1#
b0 ,
1!
#34000
0!
#34500
0$
0'
b0 "
b0 *
0(
b0 %
0&
0#
b11011100111001000111111111111011 ,
1+
0-
1!
#35000
0!
#35500
b0 ,
1!
#36000
0!
#36500
1$
1'
b1100110000111100101111100111010 "
b1100110000111100101111100111010 *
1(
b1100110000111100101111100111010 %
1!
#37000
0!
#37500
0(
b0 %
b1100110000111100101111100111010 ,
0+
1-
1!
#38000
0!
#38500
1(
b10001000001001001101101000000000 %
1&
1#
1!
#39000
0!
#39500
0&
0#
b10001000001001001101101000000000 "
b10001000001001001101101000000000 *
1+
0-
1!
#40000
0!
#40500
0(
b0 %
1&
1#
b10001000001001001101101000000000 ,
0+
1-
1!
#41000
0!
#41500
1(
b11011011100010100001101100000111 %
0&
0#
b11011011100010100001101100000111 "
b11011011100010100001101100000111 *
1$
1'
1+
0-
1!
#42000
0!
#42500
0(
b0 %
1&
1#
b11011011100010100001101100000111 ,
0+
1-
1!
#43000
0!
#43500
0&
0#
b0 "
b0 *
0$
0'
1+
0-
1!
#44000
0!
#44500
1$
1'
b10010001101010011010110001010011 "
b10010001101010011010110001010011 *
1(
b10010001101010011010110001010011 %
1&
1#
b0 ,
1!
#45000
0!
#45500
0$
0'
b0 "
b0 *
0(
b0 %
0&
0#
b10010001101010011010110001010011 ,
1+
0-
1!
#46000
0!
#46500
1$
1'
b1111001000111010000011001100101 "
b1111001000111010000011001100101 *
1(
b1111001000111010000011001100101 %
b0 ,
1!
#47000
0!
#47500
0(
b0 %
b1111001000111010000011001100101 ,
0+
1-
1!
#48000
0!
#48500
1(
b10110001110001011001100001100 %
1!
#49000
0!
#49500
1!
#50000
0!
#50500
1&
1#
1!
#51000
0!
#51500
0&
0#
b10110001110001011001100001100 "
b10110001110001011001100001100 *
1+
0-
1!
#52000
0!
#52500
0(
b0 %
1&
1#
b10110001110001011001100001100 ,
0+
1-
1!
#53000
0!
#53500
1(
b100111110100010010110111010110 %
0&
0#
b100111110100010010110111010110 "
b100111110100010010110111010110 *
1$
1'
1+
0-
1!
#54000
0!
#54500
0(
b0 %
b100111110100010010110111010110 ,
0+
1-
1!
#55000
0!
#55500
1&
1#
1!
#56000
0!
#56500
1(
b11100111101110000101010100011010 %
0&
0#
b11100111101110000101010100011010 "
b11100111101110000101010100011010 *
1$
1'
1+
0-
1!
#57000
0!
#57500
0(
b0 %
b11100111101110000101010100011010 ,
0+
1-
1!
#58000
0!
#58500
1&
1#
1!
#59000
0!
#59500
0&
0#
b0 "
b0 *
0$
0'
1+
0-
1!
#60000
0!
#60500
b0 ,
1!
#61000
0!
#61500
1$
1'
b11011110101110010111110101110111 "
b11011110101110010111110101110111 *
1(
b11011110101110010111110101110111 %
1&
1#
1!
#62000
0!
#62500
0$
0'
b0 "
b0 *
0(
b0 %
0&
0#
b11011110101110010111110101110111 ,
1+
0-
1!
#63000
0!
#63500
1$
1'
b1000110011010001101001111000110 "
b1000110011010001101001111000110 *
1(
b1000110011010001101001111000110 %
b0 ,
1!
#64000
0!
#64500
0(
b0 %
b1000110011010001101001111000110 ,
0+
1-
1!
#65000
0!
#65500
1(
b11010101111001000011111101110 %
1&
1#
1!
#66000
0!
#66500
0&
0#
b11010101111001000011111101110 "
b11010101111001000011111101110 *
1+
0-
1!
#67000
0!
#67500
0(
b0 %
1&
1#
b11010101111001000011111101110 ,
0+
1-
1!
#68000
0!
#68500
1(
b11001101011111000110111000010010 %
0&
0#
b11001101011111000110111000010010 "
b11001101011111000110111000010010 *
1$
1'
1+
0-
1!
#69000
0!
#69500
0(
b0 %
1&
1#
b11001101011111000110111000010010 ,
0+
1-
1!
#70000
0!
#70500
0&
0#
b0 "
b0 *
0$
0'
1+
0-
1!
#71000
0!
#71500
1&
1#
b0 ,
1!
#72000
0!
#72500
1$
1'
b1000010000000001000001110111110 "
b1000010000000001000001110111110 *
1(
b1000010000000001000001110111110 %
1!
#73000
0!
#73500
0$
0'
b0 "
b0 *
0(
b0 %
0&
0#
b1000010000000001000001110111110 ,
1+
0-
1!
#74000
0!
#74500
1$
1'
b1100000011011000100101101010000 "
b1100000011011000100101101010000 *
1(
b1100000011011000100101101010000 %
b0 ,
1!
#75000
0!
#75500
0(
b0 %
1&
1#
b1100000011011000100101101010000 ,
0+
1-
1!
#76000
0!
#76500
1(
b1010110101011011111010001011001 %
0&
0#
b1010110101011011111010001011001 "
b1010110101011011111010001011001 *
1$
1'
1+
0-
1!
#77000
0!
#77500
0(
b0 %
1&
1#
b1010110101011011111010001011001 ,
0+
1-
1!
#78000
0!
#78500
1(
b11001110011011101000011010111011 %
0&
0#
b11001110011011101000011010111011 "
b11001110011011101000011010111011 *
1$
1'
1+
0-
1!
#79000
0!
#79500
0(
b0 %
1&
1#
b11001110011011101000011010111011 ,
0+
1-
1!
#80000
0!
#80500
1(
b10100101010011001101010110111000 %
0&
0#
b10100101010011001101010110111000 "
b10100101010011001101010110111000 *
1$
1'
1+
0-
1!
#81000
0!
#81500
0(
b0 %
b10100101010011001101010110111000 ,
0+
1-
1!
#82000
0!
#82500
1!
#83000
0!
#83500
1(
b11000001111000110110110101101101 %
1&
1#
1!
#84000
0!
#84500
0&
0#
b11000001111000110110110101101101 "
b11000001111000110110110101101101 *
1+
0-
1!
#85000
0!
#85500
0(
b0 %
b11000001111000110110110101101101 ,
0+
1-
1!
#86000
0!
#86500
1(
b10010010100010011001101000100010 %
1!
#87000
0!
#87500
1!
#88000
0!
#88500
1&
1#
1!
#89000
0!
#89500
0&
0#
b10010010100010011001101000100010 "
b10010010100010011001101000100010 *
1+
0-
1!
#90000
0!
#90500
0(
b0 %
1&
1#
b10010010100010011001101000100010 ,
0+
1-
1!
#91000
0!
#91500
0&
0#
b0 "
b0 *
0$
0'
1+
0-
1!
#92000
0!
#92500
b0 ,
1!
#93000
0!
#93500
1$
1'
b1000101011110011010010100000010 "
b1000101011110011010010100000010 *
1(
b1000101011110011010010100000010 %
1&
1#
1!
#94000
0!
#94500
0$
0'
b0 "
b0 *
0(
b0 %
0&
0#
b1000101011110011010010100000010 ,
1+
0-
1!
#95000
0!
#95500
1$
1'
b1110011000100101100010111000101 "
b1110011000100101100010111000101 *
1(
b1110011000100101100010111000101 %
b0 ,
1!
#96000
0!
#96500
0(
b0 %
1&
1#
b1110011000100101100010111000101 ,
0+
1-
1!
#97000
0!
#97500
1(
b10001000011110101110100001011011 %
0&
0#
b10001000011110101110100001011011 "
b10001000011110101110100001011011 *
1$
1'
1+
0-
1!
#98000
0!
#98500
0(
b0 %
1&
1#
b10001000011110101110100001011011 ,
0+
1-
1!
#99000
0!
#99500
1(
b1101001011100001100111111110 %
0&
0#
b1101001011100001100111111110 "
b1101001011100001100111111110 *
1$
1'
1+
0-
1!
#100000
0!
#100500
0(
b0 %
b1101001011100001100111111110 ,
0+
1-
1!
#101000
0!
#101500
1(
b10110001110010000010010111000 %
1&
1#
1!
#102000
0!
#102500
0&
0#
b10110001110010000010010111000 "
b10110001110010000010010111000 *
1+
0-
1!
#103000
0!
#103500
0(
b0 %
b10110001110010000010010111000 ,
0+
1-
1!
#104000
0!
#104500
1(
b10110101000101010110101100111011 %
1&
1#
1!
#105000
0!
#105500
0&
0#
b10110101000101010110101100111011 "
b10110101000101010110101100111011 *
1+
0-
1!
#106000
0!
#106500
0(
b0 %
1&
1#
b10110101000101010110101100111011 ,
0+
1-
1!
#107000
0!
#107500
0&
0#
b0 "
b0 *
0$
0'
1+
0-
1!
#108000
0!
#108500
1&
1#
b0 ,
1!
#109000
0!
#109500
1!
#110000
0!
#110500
1!
#111000
0!
#111500
1!
#112000
0!
#112500
1!
#113000
0!
#113500
1!
#114000
0!
#114500
1!
#115000
0!
#115500
1!
#116000
0!
#116500
1!
#117000
0!
#117500
1$
1'
b11100000000001001110001111011110 "
b11100000000001001110001111011110 *
1(
b11100000000001001110001111011110 %
1!
#118000
0!
#118500
0$
0'
b0 "
b0 *
0(
b0 %
0&
0#
b11100000000001001110001111011110 ,
1+
0-
1!
#119000
0!
#119500
1&
1#
b0 ,
1!
#120000
0!
#120500
1$
1'
b10101100101100100011001111100101 "
b10101100101100100011001111100101 *
1(
b10101100101100100011001111100101 %
1!
#121000
0!
#121500
0$
0'
b0 "
b0 *
0(
b0 %
0&
0#
b10101100101100100011001111100101 ,
1+
0-
1!
#122000
0!
#122500
1$
1'
b11011100010100111101111011110110 "
b11011100010100111101111011110110 *
1(
b11011100010100111101111011110110 %
b0 ,
1!
#123000
0!
#123500
0(
b0 %
b11011100010100111101111011110110 ,
0+
1-
1!
#124000
0!
#124500
1(
b11110010011011101110001011110010 %
1&
1#
1!
#125000
0!
#125500
0&
0#
b11110010011011101110001011110010 "
b11110010011011101110001011110010 *
1+
0-
1!
#126000
0!
#126500
0(
b0 %
1&
1#
b11110010011011101110001011110010 ,
0+
1-
1!
#127000
0!
#127500
0&
0#
b0 "
b0 *
0$
0'
1+
0-
1!
#128000
0!
#128500
1&
1#
b0 ,
1!
#129000
0!
#129500
1!
#130000
0!
#130500
1!
#131000
0!
#131500
1!
#132000
0!
#132500
1$
1'
b10100111100010001111001011100111 "
b10100111100010001111001011100111 *
1(
b10100111100010001111001011100111 %
1!
#133000
0!
#133500
0$
0'
b0 "
b0 *
0(
b0 %
0&
0#
b10100111100010001111001011100111 ,
1+
0-
1!
#134000
0!
#134500
1$
1'
b1110110110001001111001111010001 "
b1110110110001001111001111010001 *
1(
b1110110110001001111001111010001 %
b0 ,
1!
#135000
0!
#135500
0(
b0 %
b1110110110001001111001111010001 ,
0+
1-
1!
#136000
0!
#136500
1&
1#
1!
#137000
0!
#137500
1(
b1100111010100010101010101001100 %
0&
0#
b1100111010100010101010101001100 "
b1100111010100010101010101001100 *
1$
1'
1+
0-
1!
#138000
0!
#138500
0(
b0 %
b1100111010100010101010101001100 ,
0+
1-
1!
#139000
0!
#139500
1&
1#
1!
#140000
0!
#140500
0&
0#
b0 "
b0 *
0$
0'
1+
0-
1!
#141000
0!
#141500
1$
1'
b10111101100011001001001001001111 "
b10111101100011001001001001001111 *
1(
b10111101100011001001001001001111 %
b0 ,
1!
#142000
0!
#142500
0(
b0 %
1&
1#
b10111101100011001001001001001111 ,
0+
1-
1!
#143000
0!
#143500
0&
0#
b0 "
b0 *
0$
0'
1+
0-
1!
#144000
0!
#144500
b0 ,
1!
#145000
0!
#145500
1$
1'
b11010011011101100111101110110110 "
b11010011011101100111101110110110 *
1(
b11010011011101100111101110110110 %
1&
1#
1!
#146000
0!
#146500
0$
0'
b0 "
b0 *
0(
b0 %
0&
0#
b11010011011101100111101110110110 ,
1+
0-
1!
#147000
0!
#147500
1&
1#
b0 ,
1!
#148000
0!
#148500
1!
#149000
0!
#149500
1$
1'
b11000110001101100101001110111110 "
b11000110001101100101001110111110 *
1(
b11000110001101100101001110111110 %
1!
#150000
0!
#150500
0$
0'
b0 "
b0 *
0(
b0 %
0&
0#
b11000110001101100101001110111110 ,
1+
0-
1!
#151000
0!
#151500
1$
1'
b10001011101000010101100100011010 "
b10001011101000010101100100011010 *
1(
b10001011101000010101100100011010 %
1&
1#
b0 ,
1!
#152000
0!
#152500
0$
0'
b0 "
b0 *
0(
b0 %
0&
0#
b10001011101000010101100100011010 ,
1+
0-
1!
#153000
0!
#153500
b0 ,
1!
#154000
0!
#154500
1!
#155000
0!
#155500
1$
1'
b10100101010111010110000001010100 "
b10100101010111010110000001010100 *
1(
b10100101010111010110000001010100 %
1&
1#
1!
#156000
0!
#156500
0$
0'
b0 "
b0 *
0(
b0 %
0&
0#
b10100101010111010110000001010100 ,
1+
0-
1!
#157000
0!
#157500
1$
1'
b11101000001000010110111101111100 "
b11101000001000010110111101111100 *
1(
b11101000001000010110111101111100 %
1&
1#
b0 ,
1!
#158000
0!
#158500
0$
0'
b0 "
b0 *
0(
b0 %
0&
0#
b11101000001000010110111101111100 ,
1+
0-
1!
#159000
0!
#159500
b0 ,
1!
#160000
0!
#160500
1!
#161000
0!
#161500
1&
1#
1!
#162000
0!
#162500
1!
#163000
0!
#163500
1$
1'
b11110110011001100001001001100010 "
b11110110011001100001001001100010 *
1(
b11110110011001100001001001100010 %
1!
#164000
0!
#164500
0$
0'
b0 "
b0 *
0(
b0 %
0&
0#
b11110110011001100001001001100010 ,
1+
0-
1!
#165000
0!
#165500
1$
1'
b11100010111001100100011000101011 "
b11100010111001100100011000101011 *
1(
b11100010111001100100011000101011 %
b0 ,
1!
#166000
0!
#166500
0(
b0 %
1&
1#
b11100010111001100100011000101011 ,
0+
1-
1!
#167000
0!
#167500
1(
b11100100001110011100001110011010 %
0&
0#
b11100100001110011100001110011010 "
b11100100001110011100001110011010 *
1$
1'
1+
0-
1!
#168000
0!
#168500
0(
b0 %
b11100100001110011100001110011010 ,
0+
1-
1!
#169000
0!
#169500
1!
#170000
0!
#170500
1&
1#
1!
#171000
0!
#171500
0&
0#
b0 "
b0 *
0$
0'
1+
0-
1!
#172000
0!
#172500
b0 ,
1!
#173000
0!
#173500
1!
#174000
0!
#174500
1$
1'
b111010101011110111101101000001 "
b111010101011110111101101000001 *
1(
b111010101011110111101101000001 %
1!
#175000
0!
#175500
0(
b0 %
b111010101011110111101101000001 ,
0+
1-
1!
#176000
0!
#176500
1(
b11010100011101100001000110110000 %
1!
#177000
0!
#177500
1&
1#
1!
#178000
0!
#178500
0&
0#
b11010100011101100001000110110000 "
b11010100011101100001000110110000 *
1+
0-
1!
#179000
0!
#179500
0(
b0 %
b11010100011101100001000110110000 ,
0+
1-
1!
#180000
0!
#180500
1(
b11101001010011011100001101111000 %
1!
#181000
0!
#181500
1&
1#
1!
#182000
0!
#182500
0&
0#
b11101001010011011100001101111000 "
b11101001010011011100001101111000 *
1+
0-
1!
#183000
0!
#183500
0(
b0 %
1&
1#
b11101001010011011100001101111000 ,
0+
1-
1!
#184000
0!
#184500
1(
b11011110101100100100101110100000 %
0&
0#
b11011110101100100100101110100000 "
b11011110101100100100101110100000 *
1$
1'
1+
0-
1!
#185000
0!
#185500
0(
b0 %
b11011110101100100100101110100000 ,
0+
1-
1!
#186000
0!
#186500
1!
#187000
0!
#187500
1(
b10000101011111110110010101110111 %
1&
1#
1!
#188000
0!
#188500
0&
0#
b10000101011111110110010101110111 "
b10000101011111110110010101110111 *
1+
0-
1!
#189000
0!
#189500
0(
b0 %
1&
1#
b10000101011111110110010101110111 ,
0+
1-
1!
#190000
0!
#190500
1(
b1100000110001011101110010001 %
0&
0#
b1100000110001011101110010001 "
b1100000110001011101110010001 *
1$
1'
1+
0-
1!
#191000
0!
#191500
0(
b0 %
b1100000110001011101110010001 ,
0+
1-
1!
#192000
0!
#192500
1(
b1011011100011110111011100101010 %
1&
1#
1!
#193000
0!
#193500
0&
0#
b1011011100011110111011100101010 "
b1011011100011110111011100101010 *
1+
0-
1!
#194000
0!
#194500
0(
b0 %
b1011011100011110111011100101010 ,
0+
1-
1!
#195000
0!
#195500
1!
#196000
0!
#196500
1(
b11001010010101000000110110100010 %
1&
1#
1!
#197000
0!
#197500
0&
0#
b11001010010101000000110110100010 "
b11001010010101000000110110100010 *
1+
0-
1!
#198000
0!
#198500
0(
b0 %
1&
1#
b11001010010101000000110110100010 ,
0+
1-
1!
#199000
0!
#199500
1(
b10111111111100100101111001111000 %
0&
0#
b10111111111100100101111001111000 "
b10111111111100100101111001111000 *
1$
1'
1+
0-
1!
#200000
0!
#200500
0(
b0 %
b10111111111100100101111001111000 ,
0+
1-
1!
#201000
0!
#201500
1&
1#
1!
#202000
0!
#202500
1(
b1001110010000000011100011000101 %
0&
0#
b1001110010000000011100011000101 "
b1001110010000000011100011000101 *
1$
1'
1+
0-
1!
#203000
0!
#203500
0(
b0 %
b1001110010000000011100011000101 ,
0+
1-
1!
#204000
0!
#204500
1!
#205000
0!
#205500
1&
1#
1!
#206000
0!
#206500
1(
b1101101011001011011010111100111 %
0&
0#
b1101101011001011011010111100111 "
b1101101011001011011010111100111 *
1$
1'
1+
0-
1!
#207000
0!
#207500
0(
b0 %
1&
1#
b1101101011001011011010111100111 ,
0+
1-
1!
#208000
0!
#208500
1(
b11101111011101110101110111011000 %
0&
0#
b11101111011101110101110111011000 "
b11101111011101110101110111011000 *
1$
1'
1+
0-
1!
#209000
0!
#209500
0(
b0 %
1&
1#
b11101111011101110101110111011000 ,
0+
1-
1!
#210000
0!
#210500
0&
0#
b0 "
b0 *
0$
0'
1+
0-
1!
#211000
0!
#211500
1$
1'
b10000101001111000000010000101001 "
b10000101001111000000010000101001 *
1(
b10000101001111000000010000101001 %
1&
1#
b0 ,
1!
#212000
0!
#212500
0$
0'
b0 "
b0 *
0(
b0 %
0&
0#
b10000101001111000000010000101001 ,
1+
0-
1!
#213000
0!
#213500
1&
1#
b0 ,
1!
#214000
0!
#214500
1!
#215000
0!
#215500
1!
#216000
0!
#216500
1$
1'
b11100110011001000110010110000100 "
b11100110011001000110010110000100 *
1(
b11100110011001000110010110000100 %
1!
#217000
0!
#217500
0$
0'
b0 "
b0 *
0(
b0 %
0&
0#
b11100110011001000110010110000100 ,
1+
0-
1!
#218000
0!
#218500
1$
1'
b11110100010110110110001101111001 "
b11110100010110110110001101111001 *
1(
b11110100010110110110001101111001 %
b0 ,
1!
#219000
0!
#219500
0(
b0 %
b11110100010110110110001101111001 ,
0+
1-
1!
#220000
0!
#220500
1(
b11110000011000001111010100000010 %
1!
#221000
0!
#221500
1&
1#
1!
#222000
0!
#222500
0&
0#
b11110000011000001111010100000010 "
b11110000011000001111010100000010 *
1+
0-
1!
#223000
0!
#223500
0(
b0 %
1&
1#
b11110000011000001111010100000010 ,
0+
1-
1!
#224000
0!
#224500
0&
0#
b0 "
b0 *
0$
0'
1+
0-
1!
#225000
0!
#225500
b0 ,
1!
#226000
0!
#226500
1$
1'
b11011010001110100011010110111 "
b11011010001110100011010110111 *
1(
b11011010001110100011010110111 %
1!
#227000
0!
#227500
0(
b0 %
b11011010001110100011010110111 ,
0+
1-
1!
#228000
0!
#228500
1!
#229000
0!
#229500
1!
#230000
0!
#230500
1(
b11111110001100000100010101101000 %
1&
1#
1!
#231000
0!
#231500
0&
0#
b11111110001100000100010101101000 "
b11111110001100000100010101101000 *
1+
0-
1!
#232000
0!
#232500
0(
b0 %
1&
1#
b11111110001100000100010101101000 ,
0+
1-
1!
#233000
0!
#233500
0&
0#
b0 "
b0 *
0$
0'
1+
0-
1!
#234000
0!
#234500
1$
1'
b11001001000000011110010110011011 "
b11001001000000011110010110011011 *
1(
b11001001000000011110010110011011 %
b0 ,
1!
#235000
0!
#235500
0(
b0 %
b11001001000000011110010110011011 ,
0+
1-
1!
#236000
0!
#236500
1!
#237000
0!
#237500
1(
b10100110010110110110010000001 %
1&
1#
1!
#238000
0!
#238500
0&
0#
b10100110010110110110010000001 "
b10100110010110110110010000001 *
1+
0-
1!
#239000
0!
#239500
0(
b0 %
1&
1#
b10100110010110110110010000001 ,
0+
1-
1!
#240000
0!
#240500
0&
0#
b0 "
b0 *
0$
0'
1+
0-
1!
#241000
0!
#241500
1$
1'
b11101101110101011001100010111001 "
b11101101110101011001100010111001 *
1(
b11101101110101011001100010111001 %
b0 ,
1!
#242000
0!
#242500
0(
b0 %
1&
1#
b11101101110101011001100010111001 ,
0+
1-
1!
#243000
0!
#243500
0&
0#
b0 "
b0 *
0$
0'
1+
0-
1!
#244000
0!
#244500
1$
1'
b1100011111011000001011011110000 "
b1100011111011000001011011110000 *
1(
b1100011111011000001011011110000 %
1&
1#
b0 ,
1!
#245000
0!
#245500
0$
0'
b0 "
b0 *
0(
b0 %
0&
0#
b1100011111011000001011011110000 ,
1+
0-
1!
#246000
0!
#246500
b0 ,
1!
#247000
0!
#247500
1!
#248000
0!
#248500
1&
1#
1!
#249000
0!
#249500
1$
1'
b1000100001010110010010010101001 "
b1000100001010110010010010101001 *
1(
b1000100001010110010010010101001 %
1!
#250000
0!
#250500
0$
0'
b0 "
b0 *
0(
b0 %
0&
0#
b1000100001010110010010010101001 ,
1+
0-
1!
#251000
0!
#251500
1$
1'
b10111011110001010101001001100010 "
b10111011110001010101001001100010 *
1(
b10111011110001010101001001100010 %
b0 ,
1!
#252000
0!
#252500
0(
b0 %
1&
1#
b10111011110001010101001001100010 ,
0+
1-
1!
#253000
0!
#253500
0&
0#
b0 "
b0 *
0$
0'
1+
0-
1!
#254000
0!
#254500
b0 ,
1!
#255000
0!
#255500
1&
1#
1!
#256000
0!
#256500
1!
#257000
0!
#257500
1$
1'
b110001010101110111011110001010 "
b110001010101110111011110001010 *
1(
b110001010101110111011110001010 %
1!
#258000
0!
#258500
0$
0'
b0 "
b0 *
0(
b0 %
0&
0#
b110001010101110111011110001010 ,
1+
0-
1!
#259000
0!
#259500
b0 ,
1!
#260000
0!
#260500
1$
1'
b10100000101011010011110110010111 "
b10100000101011010011110110010111 *
1(
b10100000101011010011110110010111 %
1&
1#
1!
#261000
0!
#261500
0$
0'
b0 "
b0 *
0(
b0 %
0&
0#
b10100000101011010011110110010111 ,
1+
0-
1!
#262000
0!
#262500
1$
1'
b10001111110010001001001010111010 "
b10001111110010001001001010111010 *
1(
b10001111110010001001001010111010 %
b0 ,
1!
#263000
0!
#263500
0(
b0 %
b10001111110010001001001010111010 ,
0+
1-
1!
#264000
0!
#264500
1&
1#
1!
#265000
0!
#265500
1(
b10000110100101011100010010100010 %
0&
0#
b10000110100101011100010010100010 "
b10000110100101011100010010100010 *
1$
1'
1+
0-
1!
#266000
0!
#266500
0(
b0 %
b10000110100101011100010010100010 ,
0+
1-
1!
#267000
0!
#267500
1(
b1000001000011011010111111011110 %
1&
1#
1!
#268000
0!
#268500
0&
0#
b1000001000011011010111111011110 "
b1000001000011011010111111011110 *
1+
0-
1!
#269000
0!
#269500
0(
b0 %
1&
1#
b1000001000011011010111111011110 ,
0+
1-
1!
#270000
0!
#270500
0&
0#
b0 "
b0 *
0$
0'
1+
0-
1!
#271000
0!
#271500
1&
1#
b0 ,
1!
#272000
0!
#272500
1$
1'
b1001001010110110100100011001101 "
b1001001010110110100100011001101 *
1(
b1001001010110110100100011001101 %
1!
#273000
0!
#273500
0$
0'
b0 "
b0 *
0(
b0 %
0&
0#
b1001001010110110100100011001101 ,
1+
0-
1!
#274000
0!
#274500
1$
1'
b1111110101111001011010000001000 "
b1111110101111001011010000001000 *
1(
b1111110101111001011010000001000 %
1&
1#
b0 ,
1!
#275000
0!
#275500
0$
0'
b0 "
b0 *
0(
b0 %
0&
0#
b1111110101111001011010000001000 ,
1+
0-
1!
#276000
0!
#276500
1$
1'
b10111000100011100010000000100000 "
b10111000100011100010000000100000 *
1(
b10111000100011100010000000100000 %
1&
1#
b0 ,
1!
#277000
0!
#277500
0$
0'
b0 "
b0 *
0(
b0 %
0&
0#
b10111000100011100010000000100000 ,
1+
0-
1!
#278000
0!
#278500
b0 ,
1!
#279000
0!
#279500
1$
1'
b1110110000100111000110101000001 "
b1110110000100111000110101000001 *
1(
b1110110000100111000110101000001 %
1&
1#
1!
#280000
0!
#280500
0$
0'
b0 "
b0 *
0(
b0 %
0&
0#
b1110110000100111000110101000001 ,
1+
0-
1!
#281000
0!
#281500
1&
1#
b0 ,
1!
#282000
0!
#282500
1!
#283000
0!
#283500
1$
1'
b11000101000010000110101001001011 "
b11000101000010000110101001001011 *
1(
b11000101000010000110101001001011 %
1!
#284000
0!
#284500
0$
0'
b0 "
b0 *
0(
b0 %
0&
0#
b11000101000010000110101001001011 ,
1+
0-
1!
#285000
0!
#285500
1$
1'
b1100011110100000100001010011110 "
b1100011110100000100001010011110 *
1(
b1100011110100000100001010011110 %
b0 ,
1!
#286000
0!
#286500
0(
b0 %
b1100011110100000100001010011110 ,
0+
1-
1!
#287000
0!
#287500
1(
b11111101010110000100111111101101 %
1!
#288000
0!
#288500
1!
#289000
0!
#289500
1&
1#
1!
#290000
0!
#290500
0&
0#
b11111101010110000100111111101101 "
b11111101010110000100111111101101 *
1+
0-
1!
#291000
0!
#291500
0(
b0 %
1&
1#
b11111101010110000100111111101101 ,
0+
1-
1!
#292000
0!
#292500
1(
b111100111110110010010001100111 %
0&
0#
b111100111110110010010001100111 "
b111100111110110010010001100111 *
1$
1'
1+
0-
1!
#293000
0!
#293500
0(
b0 %
b111100111110110010010001100111 ,
0+
1-
1!
#294000
0!
#294500
1(
b1001001101011011101110111111010 %
1&
1#
1!
#295000
0!
