streamTest/streamArbiter/streamArbiter_1.v
// Generator : SpinalHDL v1.7.0a    git head : 150a9b9067020722818dfb17df4a23ac712a7af8
// Component : streamArbiter_1
// Git hash  : 3a903e741cbbe310a98c75dc1ebbd289cb1c87a4

`timescale 1ns/1ps

module streamArbiter_1 (
  input               io_s_in_0_valid,
  output              io_s_in_0_ready,
  input      [31:0]   io_s_in_0_payload,
  input               io_s_in_1_valid,
  output              io_s_in_1_ready,
  input      [31:0]   io_s_in_1_payload,
  input               io_s_in_2_valid,
  output              io_s_in_2_ready,
  input      [31:0]   io_s_in_2_payload,
  input               io_s_in_3_valid,
  output              io_s_in_3_ready,
  input      [31:0]   io_s_in_3_payload,
  output              io_m_out_valid,
  input               io_m_out_ready,
  output     [31:0]   io_m_out_payload,
  input               clk,
  input               reset
);

  wire                streamArbiter_2_io_output_ready;
  wire                streamArbiter_2_io_inputs_0_ready;
  wire                streamArbiter_2_io_inputs_1_ready;
  wire                streamArbiter_2_io_inputs_2_ready;
  wire                streamArbiter_2_io_inputs_3_ready;
  wire                streamArbiter_2_io_output_valid;
  wire       [31:0]   streamArbiter_2_io_output_payload;
  wire       [1:0]    streamArbiter_2_io_chosen;
  wire       [3:0]    streamArbiter_2_io_chosenOH;
  wire                streamArbiter_2_io_output_s2mPipe_valid;
  reg                 streamArbiter_2_io_output_s2mPipe_ready;
  wire       [31:0]   streamArbiter_2_io_output_s2mPipe_payload;
  reg                 streamArbiter_2_io_output_rValid;
  reg        [31:0]   streamArbiter_2_io_output_rData;
  wire                streamArbiter_2_io_output_s2mPipe_m2sPipe_valid;
  wire                streamArbiter_2_io_output_s2mPipe_m2sPipe_ready;
  wire       [31:0]   streamArbiter_2_io_output_s2mPipe_m2sPipe_payload;
  reg                 streamArbiter_2_io_output_s2mPipe_rValid;
  reg        [31:0]   streamArbiter_2_io_output_s2mPipe_rData;
  wire                when_Stream_l368;

  StreamArbiter streamArbiter_2 (
    .io_inputs_0_valid   (io_s_in_0_valid                        ), //i
    .io_inputs_0_ready   (streamArbiter_2_io_inputs_0_ready      ), //o
    .io_inputs_0_payload (io_s_in_0_payload[31:0]                ), //i
    .io_inputs_1_valid   (io_s_in_1_valid                        ), //i
    .io_inputs_1_ready   (streamArbiter_2_io_inputs_1_ready      ), //o
    .io_inputs_1_payload (io_s_in_1_payload[31:0]                ), //i
    .io_inputs_2_valid   (io_s_in_2_valid                        ), //i
    .io_inputs_2_ready   (streamArbiter_2_io_inputs_2_ready      ), //o
    .io_inputs_2_payload (io_s_in_2_payload[31:0]                ), //i
    .io_inputs_3_valid   (io_s_in_3_valid                        ), //i
    .io_inputs_3_ready   (streamArbiter_2_io_inputs_3_ready      ), //o
    .io_inputs_3_payload (io_s_in_3_payload[31:0]                ), //i
    .io_output_valid     (streamArbiter_2_io_output_valid        ), //o
    .io_output_ready     (streamArbiter_2_io_output_ready        ), //i
    .io_output_payload   (streamArbiter_2_io_output_payload[31:0]), //o
    .io_chosen           (streamArbiter_2_io_chosen[1:0]         ), //o
    .io_chosenOH         (streamArbiter_2_io_chosenOH[3:0]       ), //o
    .clk                 (clk                                    ), //i
    .reset               (reset                                  )  //i
  );
  assign io_s_in_0_ready = streamArbiter_2_io_inputs_0_ready;
  assign io_s_in_1_ready = streamArbiter_2_io_inputs_1_ready;
  assign io_s_in_2_ready = streamArbiter_2_io_inputs_2_ready;
  assign io_s_in_3_ready = streamArbiter_2_io_inputs_3_ready;
  assign streamArbiter_2_io_output_ready = (! streamArbiter_2_io_output_rValid);
  assign streamArbiter_2_io_output_s2mPipe_valid = (streamArbiter_2_io_output_valid || streamArbiter_2_io_output_rValid);
  assign streamArbiter_2_io_output_s2mPipe_payload = (streamArbiter_2_io_output_rValid ? streamArbiter_2_io_output_rData : streamArbiter_2_io_output_payload);
  always @(*) begin
    streamArbiter_2_io_output_s2mPipe_ready = streamArbiter_2_io_output_s2mPipe_m2sPipe_ready;
    if(when_Stream_l368) begin
      streamArbiter_2_io_output_s2mPipe_ready = 1'b1;
    end
  end

  assign when_Stream_l368 = (! streamArbiter_2_io_output_s2mPipe_m2sPipe_valid);
  assign streamArbiter_2_io_output_s2mPipe_m2sPipe_valid = streamArbiter_2_io_output_s2mPipe_rValid;
  assign streamArbiter_2_io_output_s2mPipe_m2sPipe_payload = streamArbiter_2_io_output_s2mPipe_rData;
  assign io_m_out_valid = streamArbiter_2_io_output_s2mPipe_m2sPipe_valid;
  assign streamArbiter_2_io_output_s2mPipe_m2sPipe_ready = io_m_out_ready;
  assign io_m_out_payload = streamArbiter_2_io_output_s2mPipe_m2sPipe_payload;
  always @(posedge clk or posedge reset) begin
    if(reset) begin
      streamArbiter_2_io_output_rValid <= 1'b0;
      streamArbiter_2_io_output_s2mPipe_rValid <= 1'b0;
    end else begin
      if(streamArbiter_2_io_output_valid) begin
        streamArbiter_2_io_output_rValid <= 1'b1;
      end
      if(streamArbiter_2_io_output_s2mPipe_ready) begin
        streamArbiter_2_io_output_rValid <= 1'b0;
      end
      if(streamArbiter_2_io_output_s2mPipe_ready) begin
        streamArbiter_2_io_output_s2mPipe_rValid <= streamArbiter_2_io_output_s2mPipe_valid;
      end
    end
  end

  always @(posedge clk) begin
    if(streamArbiter_2_io_output_ready) begin
      streamArbiter_2_io_output_rData <= streamArbiter_2_io_output_payload;
    end
    if(streamArbiter_2_io_output_s2mPipe_ready) begin
      streamArbiter_2_io_output_s2mPipe_rData <= streamArbiter_2_io_output_s2mPipe_payload;
    end
  end


endmodule

module StreamArbiter (
  input               io_inputs_0_valid,
  output              io_inputs_0_ready,
  input      [31:0]   io_inputs_0_payload,
  input               io_inputs_1_valid,
  output              io_inputs_1_ready,
  input      [31:0]   io_inputs_1_payload,
  input               io_inputs_2_valid,
  output              io_inputs_2_ready,
  input      [31:0]   io_inputs_2_payload,
  input               io_inputs_3_valid,
  output              io_inputs_3_ready,
  input      [31:0]   io_inputs_3_payload,
  output              io_output_valid,
  input               io_output_ready,
  output     [31:0]   io_output_payload,
  output     [1:0]    io_chosen,
  output     [3:0]    io_chosenOH,
  input               clk,
  input               reset
);

  wire       [7:0]    _zz__zz_maskProposal_0_2;
  wire       [7:0]    _zz__zz_maskProposal_0_2_1;
  wire       [3:0]    _zz__zz_maskProposal_0_2_2;
  reg        [31:0]   _zz_io_output_payload_2;
  wire       [1:0]    _zz_io_output_payload_3;
  reg                 locked;
  wire                maskProposal_0;
  wire                maskProposal_1;
  wire                maskProposal_2;
  wire                maskProposal_3;
  reg                 maskLocked_0;
  reg                 maskLocked_1;
  reg                 maskLocked_2;
  reg                 maskLocked_3;
  wire                maskRouted_0;
  wire                maskRouted_1;
  wire                maskRouted_2;
  wire                maskRouted_3;
  wire       [3:0]    _zz_maskProposal_0;
  wire       [7:0]    _zz_maskProposal_0_1;
  wire       [7:0]    _zz_maskProposal_0_2;
  wire       [3:0]    _zz_maskProposal_0_3;
  wire                io_output_fire;
  wire                _zz_io_output_payload;
  wire                _zz_io_output_payload_1;
  wire                _zz_io_chosen;
  wire                _zz_io_chosen_1;
  wire                _zz_io_chosen_2;

  assign _zz__zz_maskProposal_0_2 = (_zz_maskProposal_0_1 - _zz__zz_maskProposal_0_2_1);
  assign _zz__zz_maskProposal_0_2_2 = {maskLocked_2,{maskLocked_1,{maskLocked_0,maskLocked_3}}};
  assign _zz__zz_maskProposal_0_2_1 = {4'd0, _zz__zz_maskProposal_0_2_2};
  assign _zz_io_output_payload_3 = {_zz_io_output_payload_1,_zz_io_output_payload};
  always @(*) begin
    case(_zz_io_output_payload_3)
      2'b00 : _zz_io_output_payload_2 = io_inputs_0_payload;
      2'b01 : _zz_io_output_payload_2 = io_inputs_1_payload;
      2'b10 : _zz_io_output_payload_2 = io_inputs_2_payload;
      default : _zz_io_output_payload_2 = io_inputs_3_payload;
    endcase
  end

  assign maskRouted_0 = (locked ? maskLocked_0 : maskProposal_0);
  assign maskRouted_1 = (locked ? maskLocked_1 : maskProposal_1);
  assign maskRouted_2 = (locked ? maskLocked_2 : maskProposal_2);
  assign maskRouted_3 = (locked ? maskLocked_3 : maskProposal_3);
  assign _zz_maskProposal_0 = {io_inputs_3_valid,{io_inputs_2_valid,{io_inputs_1_valid,io_inputs_0_valid}}};
  assign _zz_maskProposal_0_1 = {_zz_maskProposal_0,_zz_maskProposal_0};
  assign _zz_maskProposal_0_2 = (_zz_maskProposal_0_1 & (~ _zz__zz_maskProposal_0_2));
  assign _zz_maskProposal_0_3 = (_zz_maskProposal_0_2[7 : 4] | _zz_maskProposal_0_2[3 : 0]);
  assign maskProposal_0 = _zz_maskProposal_0_3[0];
  assign maskProposal_1 = _zz_maskProposal_0_3[1];
  assign maskProposal_2 = _zz_maskProposal_0_3[2];
  assign maskProposal_3 = _zz_maskProposal_0_3[3];
  assign io_output_fire = (io_output_valid && io_output_ready);
  assign io_output_valid = ((((io_inputs_0_valid && maskRouted_0) || (io_inputs_1_valid && maskRouted_1)) || (io_inputs_2_valid && maskRouted_2)) || (io_inputs_3_valid && maskRouted_3));
  assign _zz_io_output_payload = (maskRouted_1 || maskRouted_3);
  assign _zz_io_output_payload_1 = (maskRouted_2 || maskRouted_3);
  assign io_output_payload = _zz_io_output_payload_2;
  assign io_inputs_0_ready = (maskRouted_0 && io_output_ready);
  assign io_inputs_1_ready = (maskRouted_1 && io_output_ready);
  assign io_inputs_2_ready = (maskRouted_2 && io_output_ready);
  assign io_inputs_3_ready = (maskRouted_3 && io_output_ready);
  assign io_chosenOH = {maskRouted_3,{maskRouted_2,{maskRouted_1,maskRouted_0}}};
  assign _zz_io_chosen = io_chosenOH[3];
  assign _zz_io_chosen_1 = (io_chosenOH[1] || _zz_io_chosen);
  assign _zz_io_chosen_2 = (io_chosenOH[2] || _zz_io_chosen);
  assign io_chosen = {_zz_io_chosen_2,_zz_io_chosen_1};
  always @(posedge clk or posedge reset) begin
    if(reset) begin
      locked <= 1'b0;
      maskLocked_0 <= 1'b0;
      maskLocked_1 <= 1'b0;
      maskLocked_2 <= 1'b0;
      maskLocked_3 <= 1'b1;
    end else begin
      if(io_output_valid) begin
        maskLocked_0 <= maskRouted_0;
        maskLocked_1 <= maskRouted_1;
        maskLocked_2 <= maskRouted_2;
        maskLocked_3 <= maskRouted_3;
      end
      if(io_output_valid) begin
        locked <= 1'b1;
      end
      if(io_output_fire) begin
        locked <= 1'b0;
      end
    end
  end

  initial begin
    $dumpfile("streamArbiter_1_test.vcd");
    $dumpvars(0, streamArbiter_1);
  end


endmodule

streamTest/streamArbiter/streamArbiter_1_test.vcd
$date
	Thu May 26 14:22:26 2022
$end
$version
	Icarus Verilog
$end
$timescale
	1ps
$end
$scope module streamArbiter_1 $end
$var wire 1 ! clk $end
$var wire 32 " io_m_out_payload [31:0] $end
$var wire 1 # io_m_out_ready $end
$var wire 1 $ io_m_out_valid $end
$var wire 32 % io_s_in_0_payload [31:0] $end
$var wire 1 & io_s_in_0_ready $end
$var wire 1 ' io_s_in_0_valid $end
$var wire 32 ( io_s_in_1_payload [31:0] $end
$var wire 1 ) io_s_in_1_ready $end
$var wire 1 * io_s_in_1_valid $end
$var wire 32 + io_s_in_2_payload [31:0] $end
$var wire 1 , io_s_in_2_ready $end
$var wire 1 - io_s_in_2_valid $end
$var wire 32 . io_s_in_3_payload [31:0] $end
$var wire 1 / io_s_in_3_ready $end
$var wire 1 0 io_s_in_3_valid $end
$var wire 1 1 reset $end
$var wire 1 2 streamArbiter_2_io_output_s2mPipe_m2sPipe_ready $end
$var wire 1 3 streamArbiter_2_io_output_s2mPipe_valid $end
$var wire 1 4 when_Stream_l368 $end
$var wire 1 5 streamArbiter_2_io_output_valid $end
$var wire 32 6 streamArbiter_2_io_output_s2mPipe_payload [31:0] $end
$var wire 1 7 streamArbiter_2_io_output_s2mPipe_m2sPipe_valid $end
$var wire 32 8 streamArbiter_2_io_output_s2mPipe_m2sPipe_payload [31:0] $end
$var wire 1 9 streamArbiter_2_io_output_ready $end
$var wire 32 : streamArbiter_2_io_output_payload [31:0] $end
$var wire 1 ; streamArbiter_2_io_inputs_3_ready $end
$var wire 1 < streamArbiter_2_io_inputs_2_ready $end
$var wire 1 = streamArbiter_2_io_inputs_1_ready $end
$var wire 1 > streamArbiter_2_io_inputs_0_ready $end
$var wire 4 ? streamArbiter_2_io_chosenOH [3:0] $end
$var wire 2 @ streamArbiter_2_io_chosen [1:0] $end
$var reg 32 A streamArbiter_2_io_output_rData [31:0] $end
$var reg 1 B streamArbiter_2_io_output_rValid $end
$var reg 32 C streamArbiter_2_io_output_s2mPipe_rData [31:0] $end
$var reg 1 7 streamArbiter_2_io_output_s2mPipe_rValid $end
$var reg 1 D streamArbiter_2_io_output_s2mPipe_ready $end
$scope module streamArbiter_2 $end
$var wire 1 E _zz_io_chosen_1 $end
$var wire 1 F _zz_io_chosen_2 $end
$var wire 1 G _zz_io_output_payload $end
$var wire 1 H _zz_io_output_payload_1 $end
$var wire 8 I _zz_maskProposal_0_2 [7:0] $end
$var wire 4 J _zz_maskProposal_0_3 [3:0] $end
$var wire 1 ! clk $end
$var wire 32 K io_inputs_0_payload [31:0] $end
$var wire 1 > io_inputs_0_ready $end
$var wire 1 ' io_inputs_0_valid $end
$var wire 32 L io_inputs_1_payload [31:0] $end
$var wire 1 = io_inputs_1_ready $end
$var wire 1 * io_inputs_1_valid $end
$var wire 32 M io_inputs_2_payload [31:0] $end
$var wire 1 < io_inputs_2_ready $end
$var wire 1 - io_inputs_2_valid $end
$var wire 32 N io_inputs_3_payload [31:0] $end
$var wire 1 ; io_inputs_3_ready $end
$var wire 1 0 io_inputs_3_valid $end
$var wire 1 O io_output_fire $end
$var wire 32 P io_output_payload [31:0] $end
$var wire 1 9 io_output_ready $end
$var wire 1 5 io_output_valid $end
$var wire 1 1 reset $end
$var wire 1 Q maskRouted_3 $end
$var wire 1 R maskRouted_2 $end
$var wire 1 S maskRouted_1 $end
$var wire 1 T maskRouted_0 $end
$var wire 1 U maskProposal_3 $end
$var wire 1 V maskProposal_2 $end
$var wire 1 W maskProposal_1 $end
$var wire 1 X maskProposal_0 $end
$var wire 4 Y io_chosenOH [3:0] $end
$var wire 2 Z io_chosen [1:0] $end
$var wire 8 [ _zz_maskProposal_0_1 [7:0] $end
$var wire 4 \ _zz_maskProposal_0 [3:0] $end
$var wire 2 ] _zz_io_output_payload_3 [1:0] $end
$var wire 1 ^ _zz_io_chosen $end
$var wire 4 _ _zz__zz_maskProposal_0_2_2 [3:0] $end
$var wire 8 ` _zz__zz_maskProposal_0_2_1 [7:0] $end
$var wire 8 a _zz__zz_maskProposal_0_2 [7:0] $end
$var reg 32 b _zz_io_output_payload_2 [31:0] $end
$var reg 1 c locked $end
$var reg 1 d maskLocked_0 $end
$var reg 1 e maskLocked_1 $end
$var reg 1 f maskLocked_2 $end
$var reg 1 g maskLocked_3 $end
$upscope $end
$upscope $end
$enddefinitions $end
#0
$dumpvars
1g
0f
0e
0d
0c
bz b
bx a
b1 `
b1 _
x^
bx ]
bz \
bz [
bx Z
bx Y
xX
xW
xV
xU
xT
xS
xR
xQ
bz P
xO
bz N
bz M
bz L
bz K
bx J
bx I
xH
xG
xF
xE
1D
bx C
0B
bx A
bx @
bx ?
x>
x=
x<
x;
bz :
19
bx 8
07
bz 6
x5
14
x3
z2
11
z0
x/
bz .
z-
x,
bz +
z*
x)
bz (
z'
x&
bz %
0$
z#
bx "
0!
$end
#1000
0F
b0 @
b0 Z
0E
0&
0>
0)
0=
0,
0<
0^
0/
0;
0H
b0 ]
0G
0O
03
0T
0S
0R
b0 ?
b0 Y
0Q
05
0X
0W
0V
0U
b0 J
b0 6
b0 I
b0 :
b0 P
b0 b
1D
b11111111 a
0'
b0 %
b0 K
0*
b0 (
b0 L
0-
b0 +
b0 M
b0 [
b0 \
00
b0 .
b0 N
02
0#
01
#1500
b0 "
b0 8
b0 C
b0 A
1!
#2000
0!
#2500
1!
#3000
0!
#3500
1O
13
15
1&
1>
b1 ?
b1 Y
1T
1X
b1 J
b1 I
12
1#
1'
b110010 a
b110011 [
b11 \
1*
1!
#4000
0!
#4500
0F
0,
0<
0^
0/
0;
0H
0R
0Q
0V
0U
1-
b11111111 [
b1111 \
10
b1 @
b1 Z
1E
0&
0>
1)
1=
b1 ]
1G
0T
b10 ?
b10 Y
1S
0X
1W
b10 J
b10 I
0c
0g
b11111101 a
b10 `
b10 _
1d
04
1$
17
19
0B
1!
#5000
0!
#5500
0D
02
0#
b11011101 [
b1101 \
0*
0E
b10 @
b10 Z
1F
0)
0=
0G
1,
1<
b10 ]
1H
0S
b100 ?
b100 Y
1R
0W
1V
b100 J
b100 I
19
0B
0c
1e
b11011001 a
b100 `
b100 _
0d
1!
#6000
0!
#6500
0S
0W
1*
b11101011100101010000111110100101 (
b11101011100101010000111110100101 L
b10111011 [
b1011 \
0-
b11 @
b11 Z
1E
1^
b11 ]
1G
0R
b1000 ?
b1000 Y
1Q
0V
1U
b1000 J
b1000 I
0O
0,
0<
0c
1f
b10110011 a
b1000 `
b1000 _
0e
09
1B
1!
#7000
0!
#7500
0V
1D
12
1#
b11111111 [
b1111 \
1-
b10101001011010010010000100011010 +
b10101001011010010010000100011010 M
1X
0U
b1 J
b1 I
1c
1g
b11111110 a
b1 `
b1 _
0f
1!
#8000
0!
#8500
0D
02
0#
1O
1/
1;
19
0B
1!
#9000
0!
#9500
b1110110 a
b1110111 [
b111 \
00
0F
b0 @
b0 Z
0E
15
0^
0H
b0 ]
0G
0O
0/
0;
1T
b1 ?
b1 Y
0Q
09
1B
0c
1!
#10000
0!
#10500
0U
1D
12
1#
b11111111 [
b1111 \
10
b100000000110111100000110110111 .
b100000000110111100000110110111 N
0X
1W
b10 J
b10 I
1c
0g
b11111101 a
b10 `
b10 _
1d
1!
#11000
0!
#11500
0D
02
0#
1O
1&
1>
19
0B
1!
#12000
0!
#12500
1D
12
1#
b11101100 a
b11101110 [
b1110 \
0'
b1 @
b1 Z
1E
b11101011100101010000111110100101 :
b11101011100101010000111110100101 P
b11101011100101010000111110100101 b
b1 ]
1G
0T
b10 ?
b10 Y
1S
0O
0&
0>
0c
09
1B
1!
#13000
0!
#13500
0D
02
0#
0W
1V
b100 J
b100 I
1O
1)
1=
b11101011100101010000111110100101 6
19
0B
1c
1e
b11101010 a
b100 `
b100 _
0d
1!
#14000
0!
#14500
1D
12
1#
b11001000 a
b11001100 [
b1100 \
0*
b0 (
b0 L
0E
b10 @
b10 Z
1F
b10101001011010010010000100011010 :
b10101001011010010010000100011010 P
b10101001011010010010000100011010 b
0G
b10 ]
1H
0S
b100 ?
b100 Y
1R
0O
0)
0=
0c
09
1B
b11101011100101010000111110100101 A
1!
#15000
0!
#15500
0D
02
0#
0V
1U
b1000 J
b1000 I
1O
1,
1<
b10101001011010010010000100011010 6
19
0B
1c
1f
b11000100 a
b1000 `
b1000 _
0e
b11101011100101010000111110100101 "
b11101011100101010000111110100101 8
b11101011100101010000111110100101 C
1!
#16000
0!
#16500
0T
0X
b1000 J
1D
b1000 I
12
1#
1'
b101010000000010110110001111111 %
b101010000000010110110001111111 K
b10010001 a
b10011001 [
b1001 \
0-
b0 +
b0 M
b11 @
b11 Z
1E
b100000000110111100000110110111 :
b100000000110111100000110110111 P
b100000000110111100000110110111 b
1^
b11 ]
1G
0R
b1000 ?
b1000 Y
1Q
0O
0,
0<
0c
09
1B
b10101001011010010010000100011010 A
1!
#17000
0!
#17500
0V
0D
02
0#
b11011101 [
b1101 \
1-
b10010100001110001100000001010000 +
b10010100001110001100000001010000 M
1X
0U
b1 J
b1 I
1O
1/
1;
b100000000110111100000110110111 6
19
0B
1c
1g
b11011100 a
b1 `
b1 _
0f
b10101001011010010010000100011010 "
b10101001011010010010000100011010 8
b10101001011010010010000100011010 C
1!
#18000
0!
#18500
1D
12
1#
b1010100 a
b1010101 [
b101 \
00
b0 .
b0 N
0F
b0 @
b0 Z
0E
b101010000000010110110001111111 :
b101010000000010110110001111111 P
b101010000000010110110001111111 b
15
0^
0H
b0 ]
0G
1T
b1 ?
b1 Y
0Q
0O
0/
0;
0c
09
1B
b100000000110111100000110110111 A
1!
#19000
0!
#19500
0D
02
0#
0X
1V
b100 J
b100 I
1O
1&
1>
b101010000000010110110001111111 6
19
0B
1c
0g
b1010011 a
b10 `
b10 _
1d
b100000000110111100000110110111 "
b100000000110111100000110110111 8
b100000000110111100000110110111 C
1!
#20000
0!
#20500
1E
1G
0V
1S
1W
b10 J
b10 I
0'
b0 %
b0 K
b1100100 a
b1100110 [
b110 \
1*
b100010010010100111100000100110 (
b100010010010100111100000100110 L
b1 @
b1 Z
0F
b100010010010100111100000100110 :
b100010010010100111100000100110 P
b100010010010100111100000100110 b
b1 ]
0H
0T
b10 ?
b10 Y
0R
0O
0&
0>
0c
09
1B
b101010000000010110110001111111 A
1!
#21000
0!
#21500
0X
b1110111 [
b111 \
1'
b1011000000010111100010111111001 %
b1011000000010111100010111111001 K
0W
1V
b100 J
b100 I
1c
1e
b1110011 a
b100 `
b100 _
0d
1!
#22000
0!
#22500
0U
b100 J
b100 I
b11111011 a
b11111111 [
b1111 \
10
b11100101001001011000100000100 .
b11100101001001011000100000100 N
1!
#23000
0!
#23500
1!
#24000
0!
#24500
1!
#25000
0!
#25500
1!
#26000
0!
#26500
1!
#27000
0!
#27500
1D
12
1#
1!
#28000
0!
#28500
0D
02
0#
1O
1)
1=
b100010010010100111100000100110 6
19
0B
b101010000000010110110001111111 "
b101010000000010110110001111111 8
b101010000000010110110001111111 C
1!
#29000
0!
#29500
1D
12
1#
b11011001 a
b11011101 [
b1101 \
0*
b0 (
b0 L
0E
b10 @
b10 Z
1F
b10010100001110001100000001010000 :
b10010100001110001100000001010000 P
b10010100001110001100000001010000 b
0G
b10 ]
1H
0O
0)
0=
0S
b100 ?
b100 Y
1R
09
1B
0c
b100010010010100111100000100110 A
1!
#30000
0!
#30500
0W
0D
02
0#
b11111111 [
b1111 \
1*
b111101110010010010000011101011 (
b111101110010010010000011101011 L
0V
1U
b1000 J
b1000 I
1O
1,
1<
b10010100001110001100000001010000 6
1c
1f
b11110111 a
b1000 `
b1000 _
0e
19
0B
b100010010010100111100000100110 "
b100010010010100111100000100110 8
b100010010010100111100000100110 C
1!
#31000
0!
#31500
b10110011 a
b10111011 [
b1011 \
0-
b0 +
b0 M
b11 @
b11 Z
1E
b11100101001001011000100000100 :
b11100101001001011000100000100 P
b11100101001001011000100000100 b
1^
b11 ]
1G
0O
0,
0<
0R
b1000 ?
b1000 Y
1Q
09
1B
0c
b10010100001110001100000001010000 A
1!
#32000
0!
#32500
0V
b11111111 [
b1111 \
1-
b100101111011100010000110101 +
b100101111011100010000110101 M
1X
0U
b1 J
b1 I
1c
1g
b11111110 a
b1 `
b1 _
0f
1!
#33000
0!
#33500
1!
#34000
0!
#34500
1D
12
1#
1!
#35000
0!
#35500
0D
02
0#
1O
1/
1;
b11100101001001011000100000100 6
19
0B
b10010100001110001100000001010000 "
b10010100001110001100000001010000 8
b10010100001110001100000001010000 C
1!
#36000
0!
#36500
b1110110 a
b1110111 [
b111 \
00
b0 .
b0 N
0F
b0 @
b0 Z
0E
b1011000000010111100010111111001 :
b1011000000010111100010111111001 P
b1011000000010111100010111111001 b
15
0^
0H
b0 ]
0G
1T
b1 ?
b1 Y
0Q
0O
0/
0;
0c
09
1B
b11100101001001011000100000100 A
1!
#37000
0!
#37500
0U
b11111111 [
b1111 \
10
b10010000111000000100001010001110 .
b10010000111000000100001010001110 N
0X
1W
b10 J
b10 I
1c
0g
b11111101 a
b10 `
b10 _
1d
1!
#38000
0!
#38500
1!
#39000
0!
#39500
1!
#40000
0!
#40500
1D
12
1#
1!
#41000
0!
#41500
0D
02
0#
1O
1&
1>
b1011000000010111100010111111001 6
19
0B
b11100101001001011000100000100 "
b11100101001001011000100000100 8
b11100101001001011000100000100 C
1!
#42000
0!
#42500
1D
12
1#
b11101100 a
b11101110 [
b1110 \
0'
b0 %
b0 K
b1 @
b1 Z
1E
b111101110010010010000011101011 :
b111101110010010010000011101011 P
b111101110010010010000011101011 b
b1 ]
1G
0T
b10 ?
b10 Y
1S
0O
0&
0>
0c
09
1B
b1011000000010111100010111111001 A
1!
#43000
0!
#43500
0D
02
0#
0W
1V
b100 J
b100 I
1O
1)
1=
b111101110010010010000011101011 6
19
0B
1c
1e
b11101010 a
b100 `
b100 _
0d
b1011000000010111100010111111001 "
b1011000000010111100010111111001 8
b1011000000010111100010111111001 C
1!
#44000
0!
#44500
0T
0X
b100 J
b100 I
1'
b10101110110010001110110011000010 %
b10101110110010001110110011000010 K
b11011001 a
b11011101 [
b1101 \
0*
b0 (
b0 L
0E
b10 @
b10 Z
1F
b100101111011100010000110101 :
b100101111011100010000110101 P
b100101111011100010000110101 b
0G
b10 ]
1H
0S
b100 ?
b100 Y
1R
0O
0)
0=
0c
09
1B
b111101110010010010000011101011 A
1!
#45000
0!
#45500
0W
1D
12
1#
b11111111 [
b1111 \
1*
b111100010111110001001010101 (
b111100010111110001001010101 L
0V
1U
b1000 J
b1000 I
1c
1f
b11110111 a
b1000 `
b1000 _
0e
1!
#46000
0!
#46500
0D
02
0#
1O
1,
1<
b100101111011100010000110101 6
19
0B
b111101110010010010000011101011 "
b111101110010010010000011101011 8
b111101110010010010000011101011 C
1!
#47000
0!
#47500
1D
12
1#
b10110011 a
b10111011 [
b1011 \
0-
b0 +
b0 M
b11 @
b11 Z
1E
b10010000111000000100001010001110 :
b10010000111000000100001010001110 P
b10010000111000000100001010001110 b
1^
b11 ]
1G
0O
0,
0<
0R
b1000 ?
b1000 Y
1Q
09
1B
0c
b100101111011100010000110101 A
1!
#48000
0!
#48500
0D
02
0#
1X
0U
b1 J
b1 I
1O
1/
1;
b10010000111000000100001010001110 6
1c
1g
b10111010 a
b1 `
b1 _
0f
19
0B
b100101111011100010000110101 "
b100101111011100010000110101 8
b100101111011100010000110101 C
1!
#49000
0!
#49500
b110010 a
b110011 [
b11 \
00
b0 .
b0 N
0F
b0 @
b0 Z
0E
b10101110110010001110110011000010 :
b10101110110010001110110011000010 P
b10101110110010001110110011000010 b
15
0^
0H
b0 ]
0G
0O
0/
0;
1T
b1 ?
b1 Y
0Q
09
1B
0c
b10010000111000000100001010001110 A
1!
#50000
0!
#50500
0V
0U
1D
12
1#
1-
b11011101111001101001011011001011 +
b11011101111001101001011011001011 M
b11111111 [
b1111 \
10
b10001000011101100111100111011010 .
b10001000011101100111100111011010 N
0X
1W
b10 J
b10 I
1c
0g
b11111101 a
b10 `
b10 _
1d
1!
#51000
0!
#51500
0D
02
0#
1O
1&
1>
b10101110110010001110110011000010 6
19
0B
b10010000111000000100001010001110 "
b10010000111000000100001010001110 8
b10010000111000000100001010001110 C
1!
#52000
0!
#52500
b11101100 a
b11101110 [
b1110 \
0'
b0 %
b0 K
b1 @
b1 Z
1E
b111100010111110001001010101 :
b111100010111110001001010101 P
b111100010111110001001010101 b
b1 ]
1G
0T
b10 ?
b10 Y
1S
0O
0&
0>
0c
09
1B
b10101110110010001110110011000010 A
1!
#53000
0!
#53500
0X
b11111111 [
b1111 \
1'
b1111010011010110010100011011010 %
b1111010011010110010100011011010 K
0W
1V
b100 J
b100 I
1c
1e
b11111011 a
b100 `
b100 _
0d
1!
#54000
0!
#54500
1!
#55000
0!
#55500
1D
12
1#
1!
#56000
0!
#56500
0D
02
0#
1O
1)
1=
b111100010111110001001010101 6
19
0B
b10101110110010001110110011000010 "
b10101110110010001110110011000010 8
b10101110110010001110110011000010 C
1!
#57000
0!
#57500
b11011001 a
b11011101 [
b1101 \
0*
b0 (
b0 L
0E
b10 @
b10 Z
1F
b11011101111001101001011011001011 :
b11011101111001101001011011001011 P
b11011101111001101001011011001011 b
0G
b10 ]
1H
0O
0)
0=
0S
b100 ?
b100 Y
1R
09
1B
0c
b111100010111110001001010101 A
1!
#58000
0!
#58500
1D
12
1#
0V
1U
b1000 J
b1000 I
1c
1f
b11010101 a
b1000 `
b1000 _
0e
1!
#59000
0!
#59500
0D
02
0#
1O
1,
1<
b11011101111001101001011011001011 6
19
0B
b111100010111110001001010101 "
b111100010111110001001010101 8
b111100010111110001001010101 C
1!
#60000
0!
#60500
1D
12
1#
b10010001 a
b10011001 [
b1001 \
0-
b0 +
b0 M
b11 @
b11 Z
1E
b10001000011101100111100111011010 :
b10001000011101100111100111011010 P
b10001000011101100111100111011010 b
1^
b11 ]
1G
0R
b1000 ?
b1000 Y
1Q
0O
0,
0<
0c
09
1B
b11011101111001101001011011001011 A
1!
#61000
0!
#61500
0W
0D
02
0#
b10111011 [
b1011 \
1*
b11100000100100101010000110110 (
b11100000100100101010000110110 L
1X
0U
b1 J
b1 I
1O
1/
1;
b10001000011101100111100111011010 6
19
0B
1c
1g
b10111010 a
b1 `
b1 _
0f
b11011101111001101001011011001011 "
b11011101111001101001011011001011 8
b11011101111001101001011011001011 C
1!
#62000
0!
#62500
0R
0V
b1 J
1D
b1 I
12
1#
1-
b11001100101100110001110110100001 +
b11001100101100110001110110100001 M
b1110110 a
b1110111 [
b111 \
00
b0 .
b0 N
0F
b0 @
b0 Z
0E
b1111010011010110010100011011010 :
b1111010011010110010100011011010 P
b1111010011010110010100011011010 b
15
0^
0H
b0 ]
0G
1T
b1 ?
b1 Y
0Q
0O
0/
0;
0c
09
1B
b10001000011101100111100111011010 A
1!
#63000
0!
#63500
0D
02
0#
0X
1W
b10 J
b10 I
1O
1&
1>
b1111010011010110010100011011010 6
19
0B
1c
0g
b1110101 a
b10 `
b10 _
1d
b10001000011101100111100111011010 "
b10001000011101100111100111011010 8
b10001000011101100111100111011010 C
1!
#64000
0!
