timer/apb3Timer/Apb3Timer.v
// Generator : SpinalHDL v1.6.4    git head : 598c18959149eb18e5eee5b0aa3eef01ecaa41a1
// Component : Apb3Timer
// Git hash  : 89d7543c7219f82d1991c9174f1b313aba4435ca

`timescale 1ns/1ps 

module Apb3Timer (
  input      [7:0]    io_apb_PADDR,
  input      [0:0]    io_apb_PSEL,
  input               io_apb_PENABLE,
  output              io_apb_PREADY,
  input               io_apb_PWRITE,
  input      [31:0]   io_apb_PWDATA,
  output reg [31:0]   io_apb_PRDATA,
  output              io_apb_PSLVERROR,
  output              io_fullA,
  output              io_fullB,
  input               io_external_tick,
  input               io_external_clear,
  input               clk,
  input               reset
);

  wire                timerA_io_tick;
  wire                timerA_io_clear;
  wire                timerB_io_tick;
  wire                timerB_io_clear;
  wire                timerA_io_full;
  wire       [15:0]   timerA_io_value;
  wire                timerB_io_full;
  wire       [7:0]    timerB_io_value;
  reg        [3:0]    clockDivider_counter;
  wire                clockDivider_full;
  wire                apbCtrl_askWrite;
  wire                apbCtrl_askRead;
  wire                apbCtrl_doWrite;
  wire                apbCtrl_doRead;
  reg        [2:0]    bridgeA_ticksEnable;
  reg        [1:0]    bridgeA_clearEnable;
  reg                 bridgeA_busClearing;
  reg        [15:0]   timerA_io_limit_driver;
  reg                 when_Timer_l67;
  reg                 when_Timer_l72;
  reg        [2:0]    bridgeB_ticksEnable;
  reg        [1:0]    bridgeB_clearEnable;
  reg                 bridgeB_busClearing;
  reg        [7:0]    timerB_io_limit_driver;
  reg                 when_Timer_l67_1;
  reg                 when_Timer_l72_1;

  Timer timerA (
    .io_tick     (timerA_io_tick                ), //i
    .io_clear    (timerA_io_clear               ), //i
    .io_limit    (timerA_io_limit_driver[15:0]  ), //i
    .io_full     (timerA_io_full                ), //o
    .io_value    (timerA_io_value[15:0]         ), //o
    .clk         (clk                           ), //i
    .reset       (reset                         )  //i
  );
  Timer_1 timerB (
    .io_tick     (timerB_io_tick               ), //i
    .io_clear    (timerB_io_clear              ), //i
    .io_limit    (timerB_io_limit_driver[7:0]  ), //i
    .io_full     (timerB_io_full               ), //o
    .io_value    (timerB_io_value[7:0]         ), //o
    .clk         (clk                          ), //i
    .reset       (reset                        )  //i
  );
  assign clockDivider_full = (clockDivider_counter == 4'b1111);
  assign io_apb_PREADY = 1'b1;
  always @(*) begin
    io_apb_PRDATA = 32'h0;
    case(io_apb_PADDR)
      8'h0 : begin
        io_apb_PRDATA[2 : 0] = bridgeA_ticksEnable;
        io_apb_PRDATA[17 : 16] = bridgeA_clearEnable;
      end
      8'h04 : begin
        io_apb_PRDATA[15 : 0] = timerA_io_limit_driver;
      end
      8'h08 : begin
        io_apb_PRDATA[15 : 0] = timerA_io_value;
      end
      8'h10 : begin
        io_apb_PRDATA[2 : 0] = bridgeB_ticksEnable;
        io_apb_PRDATA[17 : 16] = bridgeB_clearEnable;
      end
      8'h14 : begin
        io_apb_PRDATA[7 : 0] = timerB_io_limit_driver;
      end
      8'h18 : begin
        io_apb_PRDATA[7 : 0] = timerB_io_value;
      end
      default : begin
      end
    endcase
  end

  assign io_apb_PSLVERROR = 1'b0;
  assign apbCtrl_askWrite = ((io_apb_PSEL[0] && io_apb_PENABLE) && io_apb_PWRITE);
  assign apbCtrl_askRead = ((io_apb_PSEL[0] && io_apb_PENABLE) && (! io_apb_PWRITE));
  assign apbCtrl_doWrite = (((io_apb_PSEL[0] && io_apb_PENABLE) && io_apb_PREADY) && io_apb_PWRITE);
  assign apbCtrl_doRead = (((io_apb_PSEL[0] && io_apb_PENABLE) && io_apb_PREADY) && (! io_apb_PWRITE));
  always @(*) begin
    bridgeA_busClearing = 1'b0;
    if(when_Timer_l67) begin
      bridgeA_busClearing = 1'b1;
    end
    if(when_Timer_l72) begin
      bridgeA_busClearing = 1'b1;
    end
  end

  assign timerA_io_tick = (|(bridgeA_ticksEnable & {io_external_tick,{clockDivider_full,1'b1}}));
  assign timerA_io_clear = ((|(bridgeA_clearEnable & {io_external_clear,timerA_io_full})) || bridgeA_busClearing);
  always @(*) begin
    when_Timer_l67 = 1'b0;
    case(io_apb_PADDR)
      8'h04 : begin
        if(apbCtrl_doWrite) begin
          when_Timer_l67 = 1'b1;
        end
      end
      default : begin
      end
    endcase
  end

  always @(*) begin
    when_Timer_l72 = 1'b0;
    case(io_apb_PADDR)
      8'h08 : begin
        if(apbCtrl_doWrite) begin
          when_Timer_l72 = 1'b1;
        end
      end
      default : begin
      end
    endcase
  end

  always @(*) begin
    bridgeB_busClearing = 1'b0;
    if(when_Timer_l67_1) begin
      bridgeB_busClearing = 1'b1;
    end
    if(when_Timer_l72_1) begin
      bridgeB_busClearing = 1'b1;
    end
  end

  assign timerB_io_tick = (|(bridgeB_ticksEnable & {io_external_tick,{clockDivider_full,1'b1}}));
  assign timerB_io_clear = ((|(bridgeB_clearEnable & {io_external_clear,timerB_io_full})) || bridgeB_busClearing);
  always @(*) begin
    when_Timer_l67_1 = 1'b0;
    case(io_apb_PADDR)
      8'h14 : begin
        if(apbCtrl_doWrite) begin
          when_Timer_l67_1 = 1'b1;
        end
      end
      default : begin
      end
    endcase
  end

  always @(*) begin
    when_Timer_l72_1 = 1'b0;
    case(io_apb_PADDR)
      8'h18 : begin
        if(apbCtrl_doWrite) begin
          when_Timer_l72_1 = 1'b1;
        end
      end
      default : begin
      end
    endcase
  end

  assign io_fullA = timerA_io_full;
  assign io_fullB = timerB_io_full;
  always @(posedge clk or posedge reset) begin
    if(reset) begin
      clockDivider_counter <= 4'b0000;
      bridgeA_ticksEnable <= 3'b000;
      bridgeA_clearEnable <= 2'b00;
      bridgeB_ticksEnable <= 3'b000;
      bridgeB_clearEnable <= 2'b00;
    end else begin
      clockDivider_counter <= (clockDivider_counter + 4'b0001);
      case(io_apb_PADDR)
        8'h0 : begin
          if(apbCtrl_doWrite) begin
            bridgeA_ticksEnable <= io_apb_PWDATA[2 : 0];
            bridgeA_clearEnable <= io_apb_PWDATA[17 : 16];
          end
        end
        8'h10 : begin
          if(apbCtrl_doWrite) begin
            bridgeB_ticksEnable <= io_apb_PWDATA[2 : 0];
            bridgeB_clearEnable <= io_apb_PWDATA[17 : 16];
          end
        end
        default : begin
        end
      endcase
    end
  end

  always @(posedge clk) begin
    case(io_apb_PADDR)
      8'h04 : begin
        if(apbCtrl_doWrite) begin
          timerA_io_limit_driver <= io_apb_PWDATA[15 : 0];
        end
      end
      8'h14 : begin
        if(apbCtrl_doWrite) begin
          timerB_io_limit_driver <= io_apb_PWDATA[7 : 0];
        end
      end
      default : begin
      end
    endcase
  end


endmodule

module Timer_1 (
  input               io_tick,
  input               io_clear,
  input      [7:0]    io_limit,
  output              io_full,
  output     [7:0]    io_value,
  input               clk,
  input               reset
);

  reg        [7:0]    counter;
  wire                when_Timer_l22;

  assign when_Timer_l22 = (io_tick && (! io_full));
  assign io_full = (counter == io_limit);
  assign io_value = counter;
  always @(posedge clk) begin
    if(when_Timer_l22) begin
      counter <= (counter + 8'h01);
    end
    if(io_clear) begin
      counter <= 8'h0;
    end
  end


endmodule

module Timer (
  input               io_tick,
  input               io_clear,
  input      [15:0]   io_limit,
  output              io_full,
  output     [15:0]   io_value,
  input               clk,
  input               reset
);

  reg        [15:0]   counter;
  wire                when_Timer_l22;

  assign when_Timer_l22 = (io_tick && (! io_full));
  assign io_full = (counter == io_limit);
  assign io_value = counter;
  always @(posedge clk) begin
    if(when_Timer_l22) begin
      counter <= (counter + 16'h0001);
    end
    if(io_clear) begin
      counter <= 16'h0;
    end
  end

  `ifdef COCOTB_SIM
  initial begin
    $dumpfile("Apb3Timer_test.vcd");
    $dumpvars(0,Apb3Timer);
  end
  `endif


endmodule

timer/apb3Timer/Apb3Timer_test.vcd
$date
	Tue Mar 29 23:46:31 2022
$end
$version
	Icarus Verilog
$end
$timescale
	1ps
$end
$scope module Apb3Timer $end
$var wire 1 ! apbCtrl_askRead $end
$var wire 1 " apbCtrl_askWrite $end
$var wire 1 # apbCtrl_doRead $end
$var wire 1 $ apbCtrl_doWrite $end
$var wire 1 % clk $end
$var wire 8 & io_apb_PADDR [7:0] $end
$var wire 1 ' io_apb_PENABLE $end
$var wire 1 ( io_apb_PREADY $end
$var wire 1 ) io_apb_PSEL $end
$var wire 1 * io_apb_PSLVERROR $end
$var wire 32 + io_apb_PWDATA [31:0] $end
$var wire 1 , io_apb_PWRITE $end
$var wire 1 - io_external_clear $end
$var wire 1 . io_external_tick $end
$var wire 1 / io_fullA $end
$var wire 1 0 io_fullB $end
$var wire 1 1 reset $end
$var wire 1 2 timerA_io_clear $end
$var wire 1 3 timerB_io_clear $end
$var wire 8 4 timerB_io_value [7:0] $end
$var wire 1 5 timerB_io_tick $end
$var wire 1 6 timerB_io_full $end
$var wire 16 7 timerA_io_value [15:0] $end
$var wire 1 8 timerA_io_tick $end
$var wire 1 9 timerA_io_full $end
$var wire 1 : clockDivider_full $end
$var reg 1 ; bridgeA_busClearing $end
$var reg 2 < bridgeA_clearEnable [1:0] $end
$var reg 3 = bridgeA_ticksEnable [2:0] $end
$var reg 1 > bridgeB_busClearing $end
$var reg 2 ? bridgeB_clearEnable [1:0] $end
$var reg 3 @ bridgeB_ticksEnable [2:0] $end
$var reg 4 A clockDivider_counter [3:0] $end
$var reg 32 B io_apb_PRDATA [31:0] $end
$var reg 16 C timerA_io_limit_driver [15:0] $end
$var reg 8 D timerB_io_limit_driver [7:0] $end
$var reg 1 E when_Timer_l67 $end
$var reg 1 F when_Timer_l67_1 $end
$var reg 1 G when_Timer_l72 $end
$var reg 1 H when_Timer_l72_1 $end
$scope module timerA $end
$var wire 1 % clk $end
$var wire 1 2 io_clear $end
$var wire 16 I io_limit [15:0] $end
$var wire 1 8 io_tick $end
$var wire 16 J io_value [15:0] $end
$var wire 1 1 reset $end
$var wire 1 K when_Timer_l22 $end
$var wire 1 9 io_full $end
$var reg 16 L counter [15:0] $end
$upscope $end
$scope module timerB $end
$var wire 1 % clk $end
$var wire 1 3 io_clear $end
$var wire 8 M io_limit [7:0] $end
$var wire 1 5 io_tick $end
$var wire 8 N io_value [7:0] $end
$var wire 1 1 reset $end
$var wire 1 O when_Timer_l22 $end
$var wire 1 6 io_full $end
$var reg 8 P counter [7:0] $end
$upscope $end
$upscope $end
$enddefinitions $end
#0
$dumpvars
bx P
0O
bx N
bx M
bx L
0K
bx J
bx I
0H
0G
0F
0E
bx D
bx C
b0 B
b0 A
b0 @
b0 ?
0>
b0 =
b0 <
0;
0:
x9
08
bx 7
x6
05
bx 4
03
02
11
x0
x/
z.
z-
z,
bz +
0*
z)
1(
z'
bz &
1%
x$
x#
x"
x!
$end
#500
01
#1000
0%
#1500
b1 A
1%
#2000
0%
#2500
b10 A
1%
#3000
0%
#3500
b11 A
1%
#4000
0%
#4500
b100 A
1%
#5000
0%
#5500
b101 A
1%
#6000
0%
#6500
b110 A
1%
#7000
0%
#7500
b111 A
1%
#8000
0%
#8500
b1000 A
1%
#9000
0%
#9500
b1001 A
1%
#10000
0%
#10500
12
1;
1E
1$
1"
b0xxxxxxxxxxxxxxxx B
0!
0#
b100 &
1)
1'
1,
b10 +
b1010 A
1%
#11000
0%
#11500
02
13
0;
1>
0E
1F
b10100 &
b11 +
b0xxxxxxxx B
0/
09
b10 C
b10 I
b0 7
b0 J
b0 L
b1011 A
1%
#12000
0%
#12500
b11 B
00
06
b0 4
b0 N
b0 P
b11 D
b11 M
b1100 A
1%
#13000
0%
#13500
03
02
0>
0;
0"
0$
1!
1#
0F
0E
b10 B
0,
b100 &
b1101 A
1%
#14000
0%
#14500
b0 B
1"
1$
0!
0#
b0 &
1,
b111 +
b1110 A
1%
#15000
0%
#15500
02
0;
0"
0$
1!
1#
0G
0,
b1000 &
1K
b0 B
18
b111 =
1:
b1111 A
1%
#16000
0%
#16500
b1 B
b1 7
b1 J
b1 L
0:
b0 A
1%
#17000
0%
#17500
0K
b10 B
1/
19
b10 7
b10 J
b10 L
b1 A
1%
#18000
0%
#18500
b10 A
1%
#19000
0%
#19500
b11 A
1%
#20000
0%
#20500
b100 A
1%
#21000
0%
#21500
b11 B
b10100 &
b101 A
1%
#22000
0%
#22500
b0 B
1"
1$
0!
0#
b10000 &
1,
b110 A
1%
#23000
0%
#23500
03
0>
0"
0$
1!
1#
0H
0,
b11000 &
1O
b0 B
15
b111 @
b111 A
1%
#24000
0%
#24500
b1 B
b1 4
b1 N
b1 P
b1000 A
1%
#25000
0%
#25500
b10 B
b10 4
b10 N
b10 P
b1001 A
1%
#26000
0%
#26500
0O
b11 B
10
16
b11 4
b11 N
b11 P
b1010 A
1%
#27000
0%
#27500
b1011 A
1%
#28000
0%
#28500
b1100 A
1%
#29000
0%
#29500
b1101 A
1%
#30000
0%
#30500
b1110 A
1%
#31000
0%
#31500
1:
b1111 A
1%
#32000
0%
#32500
0:
b0 A
1%
#33000
0%
#33500
b1 A
1%
#34000
0%
#34500
b10 A
1%
#35000
0%
#35500
b11 A
1%
#36000
0%
#36500
b100 A
1%
#37000
0%
#37500
b101 A
1%
#38000
0%
#38500
b110 A
1%
#39000
0%
#39500
b111 A
1%
#40000
0%
#40500
b1000 A
1%
#41000
0%
#41500
b1001 A
1%
#42000
0%
#42500
b1010 A
1%
#43000
0%
#43500
b1011 A
1%
#44000
0%
#44500
b1100 A
1%
#45000
0%
#45500
b1101 A
1%
#46000
0%
#46500
b1110 A
1%
#47000
0%
#47500
12
1;
1E
b10 B
1"
1$
0!
0#
b100 &
1,
b10 +
1:
b1111 A
1%
#48000
0%
#48500
13
02
1>
0;
1F
0E
b10100 &
1K
b11 B
0/
09
b0 7
b0 J
b0 L
0:
b0 A
1%
#49000
0%
#49500
1O
b10 B
b10 D
b10 M
00
06
b0 4
b0 N
b0 P
b1 7
b1 J
b1 L
b1 A
1%
#50000
0%
#50500
02
03
0;
0>
0"
0$
1!
1#
0E
0F
0,
b100 &
0K
b10 B
1/
19
b10 7
b10 J
b10 L
b0 4
b0 N
b0 P
b10 A
1%
#51000
0%
#51500
1"
1$
0!
0#
b0 &
1,
b111 +
b111 B
b1 4
b1 N
b1 P
b11 A
1%
#52000
0%
#52500
02
0;
0"
0$
1!
1#
0G
0,
b1000 &
0O
b10 B
10
16
b10 4
b10 N
b10 P
b100 A
1%
#53000
0%
#53500
b101 A
1%
#54000
0%
#54500
b110 A
1%
#55000
0%
#55500
b111 A
1%
#56000
0%
#56500
b1000 A
1%
#57000
0%
#57500
b1001 A
1%
#58000
0%
#58500
b10 B
b10100 &
b1010 A
1%
#59000
0%
#59500
b111 B
1"
1$
0!
0#
b10000 &
1,
b1011 A
1%
#60000
0%
#60500
03
0>
0"
0$
1!
1#
0H
b10 B
0,
b11000 &
b1100 A
1%
#61000
0%
#61500
b1101 A
1%
#62000
0%
#62500
b1110 A
1%
#63000
0%
#63500
1:
b1111 A
1%
#64000
0%
#64500
0:
b0 A
1%
#65000
0%
#65500
b1 A
1%
#66000
0%
#66500
b10 A
1%
#67000
0%
#67500
b11 A
1%
#68000
0%
#68500
b100 A
1%
#69000
0%
#69500
b101 A
1%
#70000
0%
#70500
b110 A
1%
#71000
0%
#71500
b111 A
1%
#72000
0%
#72500
b1000 A
1%
#73000
0%
#73500
b1001 A
1%
#74000
0%
#74500
b1010 A
1%
#75000
0%
#75500
b1011 A
1%
#76000
0%
#76500
b1100 A
1%
#77000
0%
#77500
b1101 A
1%
#78000
0%
#78500
b1110 A
1%
#79000
0%
#79500
1:
b1111 A
1%
#80000
0%
#80500
0:
b0 A
1%
#81000
0%
#81500
b1 A
1%
#82000
0%
#82500
b10 A
1%
#83000
0%
#83500
12
1;
1E
b10 B
1"
1$
0!
0#
b100 &
1,
b1100 +
b11 A
1%
#84000
0%
#84500
02
13
0;
1>
0E
1F
b10100 &
b11 +
1K
b10 B
b0 7
b0 J
b0 L
0/
09
b1100 C
b1100 I
b100 A
1%
#85000
0%
#85500
1O
b11 B
b11 D
b11 M
00
06
b0 4
b0 N
b0 P
b1 7
b1 J
b1 L
b101 A
1%
#86000
0%
#86500
03
02
0>
0;
0"
0$
1!
1#
0F
0E
0,
b100 &
b1100 B
b10 7
b10 J
b10 L
b0 4
b0 N
b0 P
b110 A
1%
#87000
0%
#87500
1"
1$
0!
0#
b0 &
1,
b111 +
b111 B
b1 4
b1 N
b1 P
b11 7
b11 J
b11 L
b111 A
1%
#88000
0%
#88500
02
0;
0"
0$
1!
1#
0G
0,
b1000 &
b100 B
b100 7
b100 J
b100 L
b10 4
b10 N
b10 P
b1000 A
1%
#89000
0%
#89500
0O
b101 B
10
16
b11 4
b11 N
b11 P
b101 7
b101 J
b101 L
b1001 A
1%
#90000
0%
#90500
b110 B
b110 7
b110 J
b110 L
b1010 A
1%
#91000
0%
#91500
b111 B
b111 7
b111 J
b111 L
b1011 A
1%
#92000
0%
#92500
b1000 B
b1000 7
b1000 J
b1000 L
b1100 A
1%
#93000
0%
#93500
b1001 B
b1001 7
b1001 J
b1001 L
b1101 A
1%
#94000
0%
#94500
b1010 B
b1010 7
b1010 J
b1010 L
b1110 A
1%
#95000
0%
#95500
b1011 B
b1011 7
b1011 J
b1011 L
1:
b1111 A
1%
#96000
0%
#96500
0K
b1100 B
1/
19
b1100 7
b1100 J
b1100 L
0:
b0 A
1%
#97000
0%
#97500
b1 A
1%
#98000
0%
#98500
b10 A
1%
#99000
0%
#99500
b11 A
1%
#100000
0%
#100500
b100 A
1%
#101000
0%
#101500
b101 A
1%
#102000
0%
#102500
b110 A
1%
#103000
0%
#103500
b111 A
1%
#104000
0%
#104500
b11 B
b10100 &
b1000 A
1%
#105000
0%
#105500
b111 B
1"
1$
0!
0#
b10000 &
1,
b1001 A
1%
#106000
0%
#106500
03
0>
0"
0$
1!
1#
0H
b11 B
0,
b11000 &
b1010 A
1%
#107000
0%
#107500
b1011 A
1%
#108000
0%
#108500
b1100 A
1%
#109000
0%
#109500
b1101 A
1%
#110000
0%
#110500
b1110 A
1%
#111000
0%
#111500
1:
b1111 A
1%
#112000
0%
#112500
0:
b0 A
1%
#113000
0%
#113500
b1 A
1%
#114000
0%
#114500
b10 A
1%
#115000
0%
#115500
b11 A
1%
#116000
0%
#116500
b100 A
1%
#117000
0%
#117500
b101 A
1%
#118000
0%
#118500
b110 A
1%
#119000
0%
#119500
b111 A
1%
#120000
0%
#120500
b1000 A
1%
#121000
0%
#121500
b1001 A
1%
#122000
0%
#122500
b1010 A
1%
#123000
0%
#123500
b1011 A
1%
#124000
0%
#124500
b1100 A
1%
#125000
0%
#125500
b1101 A
1%
#126000
0%
#126500
b1110 A
1%
#127000
0%
#127500
1:
b1111 A
1%
#128000
0%
#128500
0:
b0 A
1%
#129000
0%
#129500
b1 A
1%
#130000
0%
#130500
12
1;
1E
b1100 B
1"
1$
0!
0#
b100 &
1,
b11 +
b10 A
1%
#131000
0%
#131500
13
02
1>
0;
1F
0E
b10100 &
b1 +
1K
b11 B
b11 C
b11 I
0/
09
b0 7
b0 J
b0 L
b11 A
1%
#132000
0%
#132500
1O
b1 B
b1 7
b1 J
b1 L
b0 4
b0 N
b0 P
00
06
b1 D
b1 M
b100 A
1%
#133000
0%
#133500
02
03
0;
0>
0"
0$
1!
1#
0E
0F
0,
b100 &
b11 B
00
06
b0 4
b0 N
b0 P
b10 7
b10 J
b10 L
b101 A
1%
#134000
0%
#134500
1"
1$
0!
0#
b0 &
1,
b111 +
0K
0O
b111 B
1/
19
b11 7
b11 J
b11 L
10
16
b1 4
b1 N
b1 P
b110 A
1%
#135000
0%
#135500
02
0;
0"
0$
1!
1#
0G
b11 B
0,
b1000 &
b111 A
1%
#136000
0%
#136500
b1000 A
1%
#137000
0%
#137500
b1001 A
1%
#138000
0%
#138500
b1010 A
1%
#139000
0%
#139500
b1011 A
1%
#140000
0%
#140500
b1100 A
1%
#141000
0%
#141500
b1101 A
1%
#142000
0%
#142500
b1 B
b10100 &
b1110 A
1%
#143000
0%
#143500
b111 B
1"
1$
0!
0#
b10000 &
1,
1:
b1111 A
1%
#144000
0%
#144500
03
0>
0"
0$
1!
1#
0H
b1 B
0,
b11000 &
0:
b0 A
1%
#145000
0%
#145500
b1 A
1%
#146000
0%
#146500
b10 A
1%
#147000
0%
#147500
b11 A
1%
#148000
0%
#148500
b100 A
1%
#149000
0%
#149500
b101 A
1%
#150000
0%
#150500
b110 A
1%
#151000
0%
#151500
b111 A
1%
#152000
0%
#152500
b1000 A
1%
#153000
0%
#153500
b1001 A
1%
#154000
0%
#154500
b1010 A
1%
#155000
0%
#155500
b1011 A
1%
#156000
0%
#156500
b1100 A
1%
#157000
0%
#157500
b1101 A
1%
#158000
0%
#158500
b1110 A
1%
#159000
0%
#159500
1:
b1111 A
1%
#160000
0%
#160500
0:
b0 A
1%
#161000
0%
#161500
b1 A
1%
#162000
0%
#162500
b10 A
1%
#163000
0%
#163500
b11 A
1%
#164000
0%
#164500
b100 A
1%
#165000
0%
#165500
b101 A
1%
#166000
0%
#166500
12
1;
1E
b11 B
1"
1$
0!
0#
b100 &
1,
b1101 +
b110 A
1%
#167000
0%
#167500
02
13
0;
1>
0E
1F
b10100 &
b1 +
1K
b1 B
b1101 C
b1101 I
0/
09
b0 7
b0 J
b0 L
b111 A
1%
#168000
0%
#168500
1O
b1 B
b1 7
b1 J
b1 L
00
06
b0 4
b0 N
b0 P
b1000 A
1%
#169000
0%
#169500
03
02
0>
0;
0"
0$
1!
1#
0F
0E
0,
b100 &
b1101 B
00
06
b0 4
b0 N
b0 P
b10 7
b10 J
b10 L
b1001 A
1%
#170000
0%
#170500
1"
1$
0!
0#
b0 &
1,
b111 +
0O
b111 B
b11 7
b11 J
b11 L
10
16
b1 4
b1 N
b1 P
b1010 A
1%
#171000
0%
#171500
02
0;
0"
0$
1!
1#
0G
0,
b1000 &
b100 B
b100 7
b100 J
b100 L
b1011 A
1%
#172000
0%
#172500
b101 B
b101 7
b101 J
b101 L
b1100 A
1%
#173000
0%
#173500
b110 B
b110 7
b110 J
b110 L
b1101 A
1%
#174000
0%
#174500
b111 B
b111 7
b111 J
b111 L
b1110 A
1%
#175000
0%
#175500
b1000 B
b1000 7
b1000 J
b1000 L
1:
b1111 A
1%
#176000
0%
#176500
b1001 B
b1001 7
b1001 J
b1001 L
0:
b0 A
1%
#177000
0%
#177500
b1010 B
b1010 7
b1010 J
b1010 L
b1 A
1%
#178000
0%
#178500
b1011 B
b1011 7
b1011 J
b1011 L
b10 A
1%
#179000
0%
#179500
b1100 B
b1100 7
b1100 J
b1100 L
b11 A
1%
#180000
0%
#180500
0K
b1101 B
1/
19
b1101 7
b1101 J
b1101 L
b100 A
1%
#181000
0%
#181500
b101 A
1%
#182000
0%
#182500
b110 A
1%
#183000
0%
#183500
b111 A
1%
#184000
0%
#184500
b1000 A
1%
#185000
0%
#185500
b1001 A
1%
#186000
0%
#186500
b1010 A
1%
#187000
0%
#187500
b1011 A
1%
#188000
0%
#188500
b1 B
b10100 &
b1100 A
1%
#189000
0%
#189500
b111 B
1"
1$
0!
0#
b10000 &
1,
b1101 A
1%
#190000
0%
#190500
03
0>
0"
0$
1!
1#
0H
b1 B
0,
b11000 &
b1110 A
1%
#191000
0%
#191500
1:
b1111 A
1%
#192000
0%
#192500
0:
b0 A
1%
#193000
0%
#193500
b1 A
1%
#194000
0%
#194500
b10 A
1%
#195000
0%
#195500
b11 A
1%
#196000
0%
#196500
b100 A
1%
#197000
0%
#197500
b101 A
1%
#198000
0%
#198500
b110 A
1%
#199000
0%
#199500
b111 A
1%
#200000
0%
#200500
b1000 A
1%
#201000
0%
#201500
b1001 A
1%
#202000
0%
#202500
b1010 A
1%
#203000
0%
#203500
b1011 A
1%
#204000
0%
#204500
b1100 A
1%
#205000
0%
#205500
b1101 A
1%
#206000
0%
#206500
b1110 A
1%
#207000
0%
#207500
1:
b1111 A
1%
#208000
0%
#208500
0:
b0 A
1%
#209000
0%
#209500
b1 A
1%
#210000
0%
#210500
b10 A
1%
#211000
0%
#211500
b11 A
1%
#212000
0%
#212500
12
1;
1E
b1101 B
1"
1$
0!
0#
b100 &
1,
b1010 +
b100 A
1%
#213000
0%
#213500
13
02
1>
0;
1F
0E
b10100 &
b101 +
1K
b1 B
b1010 C
b1010 I
0/
09
b0 7
b0 J
b0 L
b101 A
1%
#214000
0%
#214500
1O
b101 B
b1 7
b1 J
b1 L
b0 4
b0 N
b0 P
00
06
b101 D
b101 M
b110 A
1%
#215000
0%
#215500
02
03
0;
0>
0"
0$
1!
1#
0E
0F
0,
b100 &
b1010 B
b0 4
b0 N
b0 P
b10 7
b10 J
b10 L
b111 A
1%
#216000
0%
#216500
1"
1$
0!
0#
b0 &
1,
b111 +
b111 B
b11 7
b11 J
b11 L
b1 4
b1 N
b1 P
b1000 A
1%
#217000
0%
#217500
02
0;
0"
0$
1!
1#
0G
0,
b1000 &
b100 B
b10 4
b10 N
b10 P
b100 7
b100 J
b100 L
b1001 A
1%
#218000
0%
#218500
b101 B
b101 7
b101 J
b101 L
b11 4
b11 N
b11 P
b1010 A
1%
#219000
0%
#219500
b110 B
b100 4
b100 N
b100 P
b110 7
b110 J
b110 L
b1011 A
1%
#220000
0%
#220500
0O
b111 B
b111 7
b111 J
b111 L
10
16
b101 4
b101 N
b101 P
b1100 A
1%
#221000
0%
#221500
b1000 B
b1000 7
b1000 J
b1000 L
b1101 A
1%
#222000
0%
#222500
b1001 B
b1001 7
b1001 J
b1001 L
b1110 A
1%
#223000
0%
#223500
0K
b1010 B
1/
19
b1010 7
b1010 J
b1010 L
1:
b1111 A
1%
#224000
0%
#224500
0:
b0 A
1%
#225000
0%
#225500
b1 A
1%
#226000
0%
#226500
b10 A
1%
#227000
0%
#227500
b11 A
1%
#228000
0%
#228500
b100 A
1%
#229000
0%
#229500
b101 A
1%
#230000
0%
#230500
b110 A
1%
#231000
0%
#231500
b101 B
b10100 &
b111 A
1%
#232000
0%
#232500
b111 B
1"
1$
0!
0#
b10000 &
1,
b1000 A
1%
#233000
0%
#233500
03
0>
0"
0$
1!
1#
0H
b101 B
0,
b11000 &
b1001 A
1%
#234000
0%
#234500
b1010 A
1%
#235000
0%
#235500
b1011 A
1%
#236000
0%
#236500
b1100 A
1%
#237000
0%
#237500
b1101 A
1%
#238000
0%
#238500
b1110 A
1%
#239000
0%
#239500
1:
b1111 A
1%
#240000
0%
#240500
0:
b0 A
1%
#241000
0%
#241500
b1 A
1%
#242000
0%
#242500
b10 A
1%
#243000
0%
#243500
b11 A
1%
#244000
0%
#244500
b100 A
1%
#245000
0%
#245500
b101 A
1%
#246000
0%
#246500
b110 A
1%
#247000
0%
#247500
b111 A
1%
#248000
0%
#248500
b1000 A
1%
#249000
0%
#249500
b1001 A
1%
#250000
0%
#250500
b1010 A
1%
#251000
0%
#251500
b1011 A
1%
#252000
0%
#252500
b1100 A
1%
#253000
0%
#253500
b1101 A
1%
#254000
0%
#254500
b1110 A
1%
#255000
0%
#255500
1:
b1111 A
1%
#256000
0%
#256500
0:
b0 A
1%
#257000
0%
#257500
b1 A
1%
#258000
0%
#258500
b10 A
1%
#259000
0%
#259500
12
1;
1E
b1010 B
1"
1$
0!
0#
b100 &
1,
b1 +
b11 A
1%
#260000
0%
#260500
02
13
0;
1>
0E
1F
b10100 &
b10 +
1K
b101 B
b0 7
b0 J
b0 L
0/
09
b1 C
b1 I
b100 A
1%
#261000
0%
#261500
1O
0K
b10 B
b10 D
b10 M
00
06
b0 4
b0 N
b0 P
1/
19
b1 7
b1 J
b1 L
b101 A
1%
#262000
0%
#262500
03
02
0>
0;
0"
0$
1!
1#
0F
0E
0,
b100 &
b1 B
b0 4
b0 N
b0 P
b110 A
1%
#263000
0%
#263500
1"
1$
0!
0#
b0 &
1,
b111 +
b111 B
b1 4
b1 N
b1 P
b111 A
1%
#264000
0%
#264500
02
0;
0"
0$
1!
1#
0G
0,
b1000 &
0O
b1 B
10
16
b10 4
b10 N
b10 P
b1000 A
1%
#265000
0%
#265500
b1001 A
1%
#266000
0%
#266500
b1010 A
1%
#267000
0%
#267500
b1011 A
1%
#268000
0%
#268500
b1100 A
1%
#269000
0%
#269500
b10 B
b10100 &
b1101 A
1%
#270000
0%
#270500
b111 B
1"
1$
0!
0#
b10000 &
1,
b1110 A
1%
#271000
0%
#271500
03
0>
0"
0$
1!
1#
0H
b10 B
0,
b11000 &
1:
b1111 A
1%
#272000
0%
#272500
0:
b0 A
1%
#273000
0%
#273500
b1 A
1%
#274000
0%
#274500
b10 A
1%
#275000
0%
#275500
b11 A
1%
#276000
0%
#276500
b100 A
1%
#277000
0%
#277500
b101 A
1%
#278000
0%
#278500
b110 A
1%
#279000
0%
#279500
b111 A
1%
#280000
0%
#280500
b1000 A
1%
#281000
0%
#281500
b1001 A
1%
#282000
0%
#282500
b1010 A
1%
#283000
0%
#283500
b1011 A
1%
#284000
0%
#284500
b1100 A
1%
#285000
0%
#285500
b1101 A
1%
#286000
0%
#286500
b1110 A
1%
#287000
0%
#287500
1:
b1111 A
1%
#288000
0%
#288500
0:
b0 A
1%
#289000
0%
#289500
b1 A
1%
#290000
0%
#290500
b10 A
1%
#291000
0%
#291500
b11 A
1%
#292000
0%
#292500
b100 A
1%
#293000
0%
#293500
b101 A
1%
#294000
0%
#294500
12
1;
1E
b1 B
1"
1$
0!
0#
b100 &
1,
b1100 +
b110 A
1%
#295000
0%
#295500
13
02
1>
0;
1F
0E
b10100 &
b100 +
1K
b10 B
b1100 C
b1100 I
0/
09
b0 7
b0 J
b0 L
b111 A
1%
#296000
0%
#296500
1O
b100 B
b1 7
b1 J
b1 L
b0 4
b0 N
b0 P
00
06
b100 D
b100 M
b1000 A
1%
#297000
0%
