streamTest/streamArbiter/sequencialOrder/streamArbiterSequencialOrder.v
// Generator : SpinalHDL v1.7.0a    git head : 150a9b9067020722818dfb17df4a23ac712a7af8
// Component : streamArbiterSequencialOrder
// Git hash  : 3a903e741cbbe310a98c75dc1ebbd289cb1c87a4

`timescale 1ns/1ps

module streamArbiterSequencialOrder (
  input               io_s_in_0_valid,
  output              io_s_in_0_ready,
  input      [31:0]   io_s_in_0_payload,
  input               io_s_in_1_valid,
  output              io_s_in_1_ready,
  input      [31:0]   io_s_in_1_payload,
  input               io_s_in_2_valid,
  output              io_s_in_2_ready,
  input      [31:0]   io_s_in_2_payload,
  input               io_s_in_3_valid,
  output              io_s_in_3_ready,
  input      [31:0]   io_s_in_3_payload,
  output              io_m_out_valid,
  input               io_m_out_ready,
  output     [31:0]   io_m_out_payload,
  input               clk,
  input               reset
);

  wire                streamArbiter_1_io_output_ready;
  wire                streamArbiter_1_io_inputs_0_ready;
  wire                streamArbiter_1_io_inputs_1_ready;
  wire                streamArbiter_1_io_inputs_2_ready;
  wire                streamArbiter_1_io_inputs_3_ready;
  wire                streamArbiter_1_io_output_valid;
  wire       [31:0]   streamArbiter_1_io_output_payload;
  wire       [1:0]    streamArbiter_1_io_chosen;
  wire       [3:0]    streamArbiter_1_io_chosenOH;
  wire                streamArbiter_1_io_output_s2mPipe_valid;
  reg                 streamArbiter_1_io_output_s2mPipe_ready;
  wire       [31:0]   streamArbiter_1_io_output_s2mPipe_payload;
  reg                 streamArbiter_1_io_output_rValid;
  reg        [31:0]   streamArbiter_1_io_output_rData;
  wire                streamArbiter_1_io_output_s2mPipe_m2sPipe_valid;
  wire                streamArbiter_1_io_output_s2mPipe_m2sPipe_ready;
  wire       [31:0]   streamArbiter_1_io_output_s2mPipe_m2sPipe_payload;
  reg                 streamArbiter_1_io_output_s2mPipe_rValid;
  reg        [31:0]   streamArbiter_1_io_output_s2mPipe_rData;
  wire                when_Stream_l368;

  StreamArbiter streamArbiter_1 (
    .io_inputs_0_valid   (io_s_in_0_valid                        ), //i
    .io_inputs_0_ready   (streamArbiter_1_io_inputs_0_ready      ), //o
    .io_inputs_0_payload (io_s_in_0_payload[31:0]                ), //i
    .io_inputs_1_valid   (io_s_in_1_valid                        ), //i
    .io_inputs_1_ready   (streamArbiter_1_io_inputs_1_ready      ), //o
    .io_inputs_1_payload (io_s_in_1_payload[31:0]                ), //i
    .io_inputs_2_valid   (io_s_in_2_valid                        ), //i
    .io_inputs_2_ready   (streamArbiter_1_io_inputs_2_ready      ), //o
    .io_inputs_2_payload (io_s_in_2_payload[31:0]                ), //i
    .io_inputs_3_valid   (io_s_in_3_valid                        ), //i
    .io_inputs_3_ready   (streamArbiter_1_io_inputs_3_ready      ), //o
    .io_inputs_3_payload (io_s_in_3_payload[31:0]                ), //i
    .io_output_valid     (streamArbiter_1_io_output_valid        ), //o
    .io_output_ready     (streamArbiter_1_io_output_ready        ), //i
    .io_output_payload   (streamArbiter_1_io_output_payload[31:0]), //o
    .io_chosen           (streamArbiter_1_io_chosen[1:0]         ), //o
    .io_chosenOH         (streamArbiter_1_io_chosenOH[3:0]       ), //o
    .clk                 (clk                                    ), //i
    .reset               (reset                                  )  //i
  );
  assign io_s_in_0_ready = streamArbiter_1_io_inputs_0_ready;
  assign io_s_in_1_ready = streamArbiter_1_io_inputs_1_ready;
  assign io_s_in_2_ready = streamArbiter_1_io_inputs_2_ready;
  assign io_s_in_3_ready = streamArbiter_1_io_inputs_3_ready;
  assign streamArbiter_1_io_output_ready = (! streamArbiter_1_io_output_rValid);
  assign streamArbiter_1_io_output_s2mPipe_valid = (streamArbiter_1_io_output_valid || streamArbiter_1_io_output_rValid);
  assign streamArbiter_1_io_output_s2mPipe_payload = (streamArbiter_1_io_output_rValid ? streamArbiter_1_io_output_rData : streamArbiter_1_io_output_payload);
  always @(*) begin
    streamArbiter_1_io_output_s2mPipe_ready = streamArbiter_1_io_output_s2mPipe_m2sPipe_ready;
    if(when_Stream_l368) begin
      streamArbiter_1_io_output_s2mPipe_ready = 1'b1;
    end
  end

  assign when_Stream_l368 = (! streamArbiter_1_io_output_s2mPipe_m2sPipe_valid);
  assign streamArbiter_1_io_output_s2mPipe_m2sPipe_valid = streamArbiter_1_io_output_s2mPipe_rValid;
  assign streamArbiter_1_io_output_s2mPipe_m2sPipe_payload = streamArbiter_1_io_output_s2mPipe_rData;
  assign io_m_out_valid = streamArbiter_1_io_output_s2mPipe_m2sPipe_valid;
  assign streamArbiter_1_io_output_s2mPipe_m2sPipe_ready = io_m_out_ready;
  assign io_m_out_payload = streamArbiter_1_io_output_s2mPipe_m2sPipe_payload;
  always @(posedge clk or posedge reset) begin
    if(reset) begin
      streamArbiter_1_io_output_rValid <= 1'b0;
      streamArbiter_1_io_output_s2mPipe_rValid <= 1'b0;
    end else begin
      if(streamArbiter_1_io_output_valid) begin
        streamArbiter_1_io_output_rValid <= 1'b1;
      end
      if(streamArbiter_1_io_output_s2mPipe_ready) begin
        streamArbiter_1_io_output_rValid <= 1'b0;
      end
      if(streamArbiter_1_io_output_s2mPipe_ready) begin
        streamArbiter_1_io_output_s2mPipe_rValid <= streamArbiter_1_io_output_s2mPipe_valid;
      end
    end
  end

  always @(posedge clk) begin
    if(streamArbiter_1_io_output_ready) begin
      streamArbiter_1_io_output_rData <= streamArbiter_1_io_output_payload;
    end
    if(streamArbiter_1_io_output_s2mPipe_ready) begin
      streamArbiter_1_io_output_s2mPipe_rData <= streamArbiter_1_io_output_s2mPipe_payload;
    end
  end


endmodule

module StreamArbiter (
  input               io_inputs_0_valid,
  output              io_inputs_0_ready,
  input      [31:0]   io_inputs_0_payload,
  input               io_inputs_1_valid,
  output              io_inputs_1_ready,
  input      [31:0]   io_inputs_1_payload,
  input               io_inputs_2_valid,
  output              io_inputs_2_ready,
  input      [31:0]   io_inputs_2_payload,
  input               io_inputs_3_valid,
  output              io_inputs_3_ready,
  input      [31:0]   io_inputs_3_payload,
  output              io_output_valid,
  input               io_output_ready,
  output     [31:0]   io_output_payload,
  output     [1:0]    io_chosen,
  output     [3:0]    io_chosenOH,
  input               clk,
  input               reset
);

  wire       [1:0]    _zz_arbitration_counter_valueNext;
  wire       [0:0]    _zz_arbitration_counter_valueNext_1;
  reg        [31:0]   _zz_io_output_payload_2;
  wire       [1:0]    _zz_io_output_payload_3;
  reg                 locked;
  reg                 maskProposal_0;
  reg                 maskProposal_1;
  reg                 maskProposal_2;
  reg                 maskProposal_3;
  reg                 maskLocked_0;
  reg                 maskLocked_1;
  reg                 maskLocked_2;
  reg                 maskLocked_3;
  wire                maskRouted_0;
  wire                maskRouted_1;
  wire                maskRouted_2;
  wire                maskRouted_3;
  wire                io_output_fire;
  reg                 arbitration_counter_willIncrement;
  wire                arbitration_counter_willClear;
  reg        [1:0]    arbitration_counter_valueNext;
  reg        [1:0]    arbitration_counter_value;
  wire                arbitration_counter_willOverflowIfInc;
  wire                arbitration_counter_willOverflow;
  wire       [3:0]    _zz_1;
  wire                io_output_fire_1;
  wire                _zz_io_output_payload;
  wire                _zz_io_output_payload_1;
  wire                _zz_io_chosen;
  wire                _zz_io_chosen_1;
  wire                _zz_io_chosen_2;

  assign _zz_arbitration_counter_valueNext_1 = arbitration_counter_willIncrement;
  assign _zz_arbitration_counter_valueNext = {1'd0, _zz_arbitration_counter_valueNext_1};
  assign _zz_io_output_payload_3 = {_zz_io_output_payload_1,_zz_io_output_payload};
  always @(*) begin
    case(_zz_io_output_payload_3)
      2'b00 : _zz_io_output_payload_2 = io_inputs_0_payload;
      2'b01 : _zz_io_output_payload_2 = io_inputs_1_payload;
      2'b10 : _zz_io_output_payload_2 = io_inputs_2_payload;
      default : _zz_io_output_payload_2 = io_inputs_3_payload;
    endcase
  end

  assign maskRouted_0 = (locked ? maskLocked_0 : maskProposal_0);
  assign maskRouted_1 = (locked ? maskLocked_1 : maskProposal_1);
  assign maskRouted_2 = (locked ? maskLocked_2 : maskProposal_2);
  assign maskRouted_3 = (locked ? maskLocked_3 : maskProposal_3);
  assign io_output_fire = (io_output_valid && io_output_ready);
  always @(*) begin
    arbitration_counter_willIncrement = 1'b0;
    if(io_output_fire) begin
      arbitration_counter_willIncrement = 1'b1;
    end
  end

  assign arbitration_counter_willClear = 1'b0;
  assign arbitration_counter_willOverflowIfInc = (arbitration_counter_value == 2'b11);
  assign arbitration_counter_willOverflow = (arbitration_counter_willOverflowIfInc && arbitration_counter_willIncrement);
  always @(*) begin
    arbitration_counter_valueNext = (arbitration_counter_value + _zz_arbitration_counter_valueNext);
    if(arbitration_counter_willClear) begin
      arbitration_counter_valueNext = 2'b00;
    end
  end

  always @(*) begin
    maskProposal_0 = 1'b0;
    if(_zz_1[0]) begin
      maskProposal_0 = 1'b1;
    end
  end

  always @(*) begin
    maskProposal_1 = 1'b0;
    if(_zz_1[1]) begin
      maskProposal_1 = 1'b1;
    end
  end

  always @(*) begin
    maskProposal_2 = 1'b0;
    if(_zz_1[2]) begin
      maskProposal_2 = 1'b1;
    end
  end

  always @(*) begin
    maskProposal_3 = 1'b0;
    if(_zz_1[3]) begin
      maskProposal_3 = 1'b1;
    end
  end

  assign _zz_1 = ({3'd0,1'b1} <<< arbitration_counter_value);
  assign io_output_fire_1 = (io_output_valid && io_output_ready);
  assign io_output_valid = ((((io_inputs_0_valid && maskRouted_0) || (io_inputs_1_valid && maskRouted_1)) || (io_inputs_2_valid && maskRouted_2)) || (io_inputs_3_valid && maskRouted_3));
  assign _zz_io_output_payload = (maskRouted_1 || maskRouted_3);
  assign _zz_io_output_payload_1 = (maskRouted_2 || maskRouted_3);
  assign io_output_payload = _zz_io_output_payload_2;
  assign io_inputs_0_ready = (maskRouted_0 && io_output_ready);
  assign io_inputs_1_ready = (maskRouted_1 && io_output_ready);
  assign io_inputs_2_ready = (maskRouted_2 && io_output_ready);
  assign io_inputs_3_ready = (maskRouted_3 && io_output_ready);
  assign io_chosenOH = {maskRouted_3,{maskRouted_2,{maskRouted_1,maskRouted_0}}};
  assign _zz_io_chosen = io_chosenOH[3];
  assign _zz_io_chosen_1 = (io_chosenOH[1] || _zz_io_chosen);
  assign _zz_io_chosen_2 = (io_chosenOH[2] || _zz_io_chosen);
  assign io_chosen = {_zz_io_chosen_2,_zz_io_chosen_1};
  always @(posedge clk or posedge reset) begin
    if(reset) begin
      locked <= 1'b0;
      arbitration_counter_value <= 2'b00;
    end else begin
      arbitration_counter_value <= arbitration_counter_valueNext;
      if(io_output_valid) begin
        locked <= 1'b1;
      end
      if(io_output_fire_1) begin
        locked <= 1'b0;
      end
    end
  end

  always @(posedge clk) begin
    if(io_output_valid) begin
      maskLocked_0 <= maskRouted_0;
      maskLocked_1 <= maskRouted_1;
      maskLocked_2 <= maskRouted_2;
      maskLocked_3 <= maskRouted_3;
    end
  end

  initial begin
    $dumpfile("streamArbiterSequencialOrder_test.vcd");
    $dumpvars(0, streamArbiterSequencialOrder);
  end

endmodule

streamTest/streamArbiter/sequencialOrder/streamArbiterSequencialOrder_test.vcd
$date
	Fri May 27 01:26:43 2022
$end
$version
	Icarus Verilog
$end
$timescale
	1ps
$end
$scope module streamArbiterSequencialOrder $end
$var wire 1 ! clk $end
$var wire 32 " io_m_out_payload [31:0] $end
$var wire 1 # io_m_out_ready $end
$var wire 1 $ io_m_out_valid $end
$var wire 32 % io_s_in_0_payload [31:0] $end
$var wire 1 & io_s_in_0_ready $end
$var wire 1 ' io_s_in_0_valid $end
$var wire 32 ( io_s_in_1_payload [31:0] $end
$var wire 1 ) io_s_in_1_ready $end
$var wire 1 * io_s_in_1_valid $end
$var wire 32 + io_s_in_2_payload [31:0] $end
$var wire 1 , io_s_in_2_ready $end
$var wire 1 - io_s_in_2_valid $end
$var wire 32 . io_s_in_3_payload [31:0] $end
$var wire 1 / io_s_in_3_ready $end
$var wire 1 0 io_s_in_3_valid $end
$var wire 1 1 reset $end
$var wire 1 2 streamArbiter_1_io_output_s2mPipe_m2sPipe_ready $end
$var wire 1 3 streamArbiter_1_io_output_s2mPipe_valid $end
$var wire 1 4 when_Stream_l368 $end
$var wire 1 5 streamArbiter_1_io_output_valid $end
$var wire 32 6 streamArbiter_1_io_output_s2mPipe_payload [31:0] $end
$var wire 1 7 streamArbiter_1_io_output_s2mPipe_m2sPipe_valid $end
$var wire 32 8 streamArbiter_1_io_output_s2mPipe_m2sPipe_payload [31:0] $end
$var wire 1 9 streamArbiter_1_io_output_ready $end
$var wire 32 : streamArbiter_1_io_output_payload [31:0] $end
$var wire 1 ; streamArbiter_1_io_inputs_3_ready $end
$var wire 1 < streamArbiter_1_io_inputs_2_ready $end
$var wire 1 = streamArbiter_1_io_inputs_1_ready $end
$var wire 1 > streamArbiter_1_io_inputs_0_ready $end
$var wire 4 ? streamArbiter_1_io_chosenOH [3:0] $end
$var wire 2 @ streamArbiter_1_io_chosen [1:0] $end
$var reg 32 A streamArbiter_1_io_output_rData [31:0] $end
$var reg 1 B streamArbiter_1_io_output_rValid $end
$var reg 32 C streamArbiter_1_io_output_s2mPipe_rData [31:0] $end
$var reg 1 7 streamArbiter_1_io_output_s2mPipe_rValid $end
$var reg 1 D streamArbiter_1_io_output_s2mPipe_ready $end
$scope module streamArbiter_1 $end
$var wire 1 E _zz_arbitration_counter_valueNext_1 $end
$var wire 1 F _zz_io_chosen_1 $end
$var wire 1 G _zz_io_chosen_2 $end
$var wire 1 H _zz_io_output_payload $end
$var wire 1 I _zz_io_output_payload_1 $end
$var wire 1 J arbitration_counter_willClear $end
$var wire 1 K arbitration_counter_willOverflow $end
$var wire 1 ! clk $end
$var wire 32 L io_inputs_0_payload [31:0] $end
$var wire 1 > io_inputs_0_ready $end
$var wire 1 ' io_inputs_0_valid $end
$var wire 32 M io_inputs_1_payload [31:0] $end
$var wire 1 = io_inputs_1_ready $end
$var wire 1 * io_inputs_1_valid $end
$var wire 32 N io_inputs_2_payload [31:0] $end
$var wire 1 < io_inputs_2_ready $end
$var wire 1 - io_inputs_2_valid $end
$var wire 32 O io_inputs_3_payload [31:0] $end
$var wire 1 ; io_inputs_3_ready $end
$var wire 1 0 io_inputs_3_valid $end
$var wire 1 P io_output_fire $end
$var wire 1 Q io_output_fire_1 $end
$var wire 32 R io_output_payload [31:0] $end
$var wire 1 9 io_output_ready $end
$var wire 1 5 io_output_valid $end
$var wire 1 1 reset $end
$var wire 1 S maskRouted_3 $end
$var wire 1 T maskRouted_2 $end
$var wire 1 U maskRouted_1 $end
$var wire 1 V maskRouted_0 $end
$var wire 4 W io_chosenOH [3:0] $end
$var wire 2 X io_chosen [1:0] $end
$var wire 1 Y arbitration_counter_willOverflowIfInc $end
$var wire 2 Z _zz_io_output_payload_3 [1:0] $end
$var wire 1 [ _zz_io_chosen $end
$var wire 2 \ _zz_arbitration_counter_valueNext [1:0] $end
$var wire 4 ] _zz_1 [3:0] $end
$var reg 32 ^ _zz_io_output_payload_2 [31:0] $end
$var reg 2 _ arbitration_counter_value [1:0] $end
$var reg 2 ` arbitration_counter_valueNext [1:0] $end
$var reg 1 a arbitration_counter_willIncrement $end
$var reg 1 b locked $end
$var reg 1 c maskLocked_0 $end
$var reg 1 d maskLocked_1 $end
$var reg 1 e maskLocked_2 $end
$var reg 1 f maskLocked_3 $end
$var reg 1 g maskProposal_0 $end
$var reg 1 h maskProposal_1 $end
$var reg 1 i maskProposal_2 $end
$var reg 1 j maskProposal_3 $end
$upscope $end
$upscope $end
$enddefinitions $end
#0
$dumpvars
0j
0i
0h
1g
xf
xe
xd
xc
0b
xa
bx `
b0 _
bz ^
b1 ]
b0x \
0[
b0 Z
0Y
b0 X
b1 W
1V
0U
0T
0S
bz R
xQ
xP
bz O
bz N
bz M
bz L
0K
0J
0I
0H
0G
0F
xE
1D
bx C
0B
bx A
b0 @
b1 ?
1>
0=
0<
0;
bz :
19
bx 8
07
bz 6
x5
14
x3
z2
11
z0
0/
bz .
z-
0,
bz +
z*
0)
bz (
z'
1&
bz %
0$
z#
bx "
0!
$end
#1000
b0 `
b0 \
0E
0a
0Q
0P
03
05
b0 6
b0 :
b0 R
b0 ^
1D
0'
b0 %
b0 L
0*
b0 (
b0 M
0-
b0 +
b0 N
00
b0 .
b0 O
02
0#
01
#1500
b0 "
b0 8
b0 C
b0 A
1!
#2000
0!
#2500
1!
#3000
0!
#3500
1*
10
1!
#4000
0!
#4500
b1 `
b1 \
1E
1a
1Q
1P
13
15
12
1#
1'
1-
1!
#5000
0!
#5500
b1 @
b1 X
1F
b1 Z
1H
0&
0>
1)
1=
0V
b10 ?
b10 W
1U
b10 `
0g
1h
0f
0e
0d
1c
04
1$
17
19
0B
0b
b10 ]
b1 _
1!
#6000
0!
#6500
0D
02
0#
0*
0F
b10 @
b10 X
1G
0)
0=
0H
1,
1<
b10 Z
1I
0U
b100 ?
b100 W
1T
b11 `
1i
0h
1d
0c
0b
b100 ]
b10 _
19
0B
1!
#7000
0!
#7500
1D
12
1#
0-
b11 @
b11 X
1F
b0 \
0E
0a
1[
b11 Z
1H
0P
0Q
0,
0<
0T
b1000 ?
b1000 W
1S
b11 `
0K
0i
1j
1e
0d
09
1B
0b
1Y
b1000 ]
b11 _
1!
#8000
0!
#8500
0D
02
0#
1*
b10110111010110100101000111110100 (
b10110111010110100101000111110100 M
1K
b0 `
b1 \
1E
1a
1P
1Q
1/
1;
1f
0e
1b
19
0B
1!
#9000
0!
#9500
1D
12
1#
1-
b1011110100010011000110011010100 +
b1011110100010011000110011010100 N
00
0G
b0 @
b0 X
0F
15
b0 \
0E
0a
0[
0I
b0 Z
0H
0P
0Q
0/
0;
1V
b1 ?
b1 W
0S
b0 `
0K
0j
1g
09
1B
0b
0Y
b1 ]
b0 _
1!
#10000
0!
#10500
0D
02
0#
10
b11000011011111011110001011110111 .
b11000011011111011110001011110111 O
b1 `
b1 \
1E
1a
1P
1Q
1&
1>
0f
1c
1b
19
0B
1!
#11000
0!
#11500
1D
12
1#
0'
b1 @
b1 X
1F
b10110111010110100101000111110100 :
b10110111010110100101000111110100 R
b10110111010110100101000111110100 ^
b0 \
0E
0a
b1 Z
1H
0P
0Q
0&
0>
0V
b10 ?
b10 W
1U
b1 `
0g
1h
09
1B
0b
b10 ]
b1 _
1!
#12000
0!
#12500
0D
02
0#
b10 `
b1 \
1E
1a
1P
1Q
1)
1=
b10110111010110100101000111110100 6
1d
0c
1b
19
0B
1!
#13000
0!
#13500
1D
12
1#
1'
b11111110100101110100110010000010 %
b11111110100101110100110010000010 L
0*
b0 (
b0 M
0F
b10 @
b10 X
1G
b1011110100010011000110011010100 :
b1011110100010011000110011010100 R
b1011110100010011000110011010100 ^
b0 \
0E
0a
0H
b10 Z
1I
0P
0Q
0)
0=
0U
b100 ?
b100 W
1T
b10 `
1i
0h
b10110111010110100101000111110100 A
09
1B
0b
b100 ]
b10 _
1!
#14000
0!
#14500
0D
02
0#
b11 `
b1 \
1E
1a
1P
1Q
1,
1<
b1011110100010011000110011010100 6
b10110111010110100101000111110100 "
b10110111010110100101000111110100 8
b10110111010110100101000111110100 C
1e
0d
1b
19
0B
1!
#15000
0!
#15500
1*
b1010000100000100001111010 (
b1010000100000100001111010 M
0-
b0 +
b0 N
b11 @
b11 X
1F
b11000011011111011110001011110111 :
b11000011011111011110001011110111 R
b11000011011111011110001011110111 ^
b0 \
0E
0a
1[
b11 Z
1H
0P
0Q
0,
0<
0T
b1000 ?
b1000 W
1S
b11 `
0K
0i
1j
b1011110100010011000110011010100 A
09
1B
0b
1Y
b1000 ]
b11 _
1!
#16000
0!
#16500
1D
12
1#
1f
0e
1b
1!
#17000
0!
#17500
0D
02
0#
1-
b1001011101000010111101111000 +
b1001011101000010111101111000 N
1K
b0 `
b1 \
1E
1a
1P
1Q
1/
1;
b11000011011111011110001011110111 6
b1011110100010011000110011010100 "
b1011110100010011000110011010100 8
b1011110100010011000110011010100 C
19
0B
1!
#18000
0!
#18500
00
b0 .
b0 O
0G
b0 @
b0 X
0F
b11111110100101110100110010000010 :
b11111110100101110100110010000010 R
b11111110100101110100110010000010 ^
15
0[
0I
b0 Z
0H
b0 \
0E
0a
1V
b1 ?
b1 W
0S
b0 `
0K
0j
1g
0P
0Q
0/
0;
b11000011011111011110001011110111 A
0b
0Y
b1 ]
b0 _
09
1B
1!
#19000
0!
#19500
10
b1011011011100101011001011111101 .
b1011011011100101011001011111101 O
0f
1c
1b
1!
#20000
0!
#20500
1D
12
1#
1!
#21000
0!
#21500
0D
02
0#
b1 `
b1 \
1E
1a
1P
1Q
1&
1>
b11111110100101110100110010000010 6
b11000011011111011110001011110111 "
b11000011011111011110001011110111 8
b11000011011111011110001011110111 C
19
0B
1!
#22000
0!
#22500
0'
b0 %
b0 L
b1 @
b1 X
1F
b1010000100000100001111010 :
b1010000100000100001111010 R
b1010000100000100001111010 ^
b1 Z
1H
b0 \
0E
0a
0V
b10 ?
b10 W
1U
b1 `
0g
1h
0P
0Q
0&
0>
b11111110100101110100110010000010 A
0b
b10 ]
b1 _
09
1B
1!
#23000
0!
#23500
1'
b10001111100100011000101111101100 %
b10001111100100011000101111101100 L
1d
0c
1b
1!
#24000
0!
#24500
1D
12
1#
1!
#25000
0!
#25500
0D
02
0#
b10 `
b1 \
1E
1a
1P
1Q
1)
1=
b1010000100000100001111010 6
b11111110100101110100110010000010 "
b11111110100101110100110010000010 8
b11111110100101110100110010000010 C
19
0B
1!
#26000
0!
#26500
1D
12
1#
0*
b0 (
b0 M
0F
b10 @
b10 X
1G
b1001011101000010111101111000 :
b1001011101000010111101111000 R
b1001011101000010111101111000 ^
0H
b10 Z
1I
b0 \
0E
0a
0U
b100 ?
b100 W
1T
b10 `
1i
0h
0P
0Q
0)
0=
b1010000100000100001111010 A
0b
b100 ]
b10 _
09
1B
1!
#27000
0!
#27500
0D
02
0#
b11 `
b1 \
1E
1a
1P
1Q
1,
1<
b1001011101000010111101111000 6
1e
0d
b1010000100000100001111010 "
b1010000100000100001111010 8
b1010000100000100001111010 C
19
0B
1b
1!
#28000
0!
#28500
1*
b1000000001111000110101001110111 (
b1000000001111000110101001110111 M
0-
b0 +
b0 N
b11 @
b11 X
1F
b1011011011100101011001011111101 :
b1011011011100101011001011111101 R
b1011011011100101011001011111101 ^
1[
b11 Z
1H
b0 \
0E
0a
0T
b1000 ?
b1000 W
1S
b11 `
0K
0i
1j
0P
0Q
0,
0<
b1001011101000010111101111000 A
0b
1Y
b1000 ]
b11 _
09
1B
1!
#29000
0!
#29500
1D
12
1#
1-
b101010100010001011010000111010 +
b101010100010001011010000111010 N
1f
0e
1b
1!
#30000
0!
#30500
0D
02
0#
1K
b0 `
b1 \
1E
1a
1P
1Q
1/
1;
b1011011011100101011001011111101 6
b1001011101000010111101111000 "
b1001011101000010111101111000 8
b1001011101000010111101111000 C
19
0B
1!
#31000
0!
#31500
1D
12
1#
00
b0 .
b0 O
0G
b0 @
b0 X
0F
b10001111100100011000101111101100 :
b10001111100100011000101111101100 R
b10001111100100011000101111101100 ^
15
b0 \
0E
0a
0[
0I
b0 Z
0H
0P
0Q
0/
0;
1V
b1 ?
b1 W
0S
b0 `
0K
0j
1g
b1011011011100101011001011111101 A
09
1B
0b
0Y
b1 ]
b0 _
1!
#32000
0!
#32500
0D
02
0#
b1 `
b1 \
1E
1a
1P
1Q
1&
1>
b10001111100100011000101111101100 6
b1011011011100101011001011111101 "
b1011011011100101011001011111101 8
b1011011011100101011001011111101 C
0f
1c
1b
19
0B
1!
#33000
0!
#33500
0'
b0 %
b0 L
b1 @
b1 X
1F
b1000000001111000110101001110111 :
b1000000001111000110101001110111 R
b1000000001111000110101001110111 ^
b0 \
0E
0a
b1 Z
1H
0P
0Q
0&
0>
0V
b10 ?
b10 W
1U
b1 `
0g
1h
b10001111100100011000101111101100 A
09
1B
0b
b10 ]
b1 _
1!
#34000
0!
#34500
10
b11101110110010011010111000101101 .
b11101110110010011010111000101101 O
1d
0c
1b
1!
#35000
0!
#35500
1!
#36000
0!
#36500
1D
12
1#
1!
#37000
0!
#37500
0D
02
0#
1'
b1111101110000110101111011110100 %
b1111101110000110101111011110100 L
b10 `
b1 \
1E
1a
1P
1Q
1)
1=
b1000000001111000110101001110111 6
b10001111100100011000101111101100 "
b10001111100100011000101111101100 8
b10001111100100011000101111101100 C
19
0B
1!
#38000
0!
#38500
1D
12
1#
0*
b0 (
b0 M
0F
b10 @
b10 X
1G
b101010100010001011010000111010 :
b101010100010001011010000111010 R
b101010100010001011010000111010 ^
0H
b10 Z
1I
b0 \
0E
0a
0U
b100 ?
b100 W
1T
b10 `
1i
0h
0P
0Q
0)
0=
b1000000001111000110101001110111 A
0b
b100 ]
b10 _
09
1B
1!
#39000
0!
#39500
0D
02
0#
1*
b10001001100001111011000111000011 (
b10001001100001111011000111000011 M
b11 `
b1 \
1E
1a
1P
1Q
1,
1<
b101010100010001011010000111010 6
1e
0d
b1000000001111000110101001110111 "
b1000000001111000110101001110111 8
b1000000001111000110101001110111 C
19
0B
1b
1!
#40000
0!
#40500
0-
b0 +
b0 N
b11 @
b11 X
1F
b11101110110010011010111000101101 :
b11101110110010011010111000101101 R
b11101110110010011010111000101101 ^
1[
b11 Z
1H
b0 \
0E
0a
0T
b1000 ?
b1000 W
1S
b11 `
0K
0i
1j
0P
0Q
0,
0<
b101010100010001011010000111010 A
0b
1Y
b1000 ]
b11 _
09
1B
1!
#41000
0!
#41500
1D
12
1#
1-
b11110000011000011100100101100100 +
b11110000011000011100100101100100 N
1f
0e
1b
1!
#42000
0!
#42500
0D
02
0#
1K
b0 `
b1 \
1E
1a
1P
1Q
1/
1;
b11101110110010011010111000101101 6
b101010100010001011010000111010 "
b101010100010001011010000111010 8
b101010100010001011010000111010 C
19
0B
1!
#43000
0!
#43500
00
b0 .
b0 O
0G
b0 @
b0 X
0F
b1111101110000110101111011110100 :
b1111101110000110101111011110100 R
b1111101110000110101111011110100 ^
15
b0 \
0E
0a
0[
0I
b0 Z
0H
0P
0Q
0/
0;
1V
b1 ?
b1 W
0S
b0 `
0K
0j
1g
b11101110110010011010111000101101 A
09
1B
0b
0Y
b1 ]
b0 _
1!
#44000
0!
#44500
1D
12
1#
0f
1c
1b
1!
#45000
0!
#45500
0D
02
0#
b1 `
b1 \
1E
1a
1P
1Q
1&
1>
b1111101110000110101111011110100 6
b11101110110010011010111000101101 "
b11101110110010011010111000101101 8
b11101110110010011010111000101101 C
19
0B
1!
#46000
0!
#46500
1D
12
1#
0'
b0 %
b0 L
10
b1100101010110001000110011010100 .
b1100101010110001000110011010100 O
b1 @
b1 X
1F
b10001001100001111011000111000011 :
b10001001100001111011000111000011 R
b10001001100001111011000111000011 ^
b1 Z
1H
b0 \
0E
0a
0V
b10 ?
b10 W
1U
b1 `
0g
1h
0P
0Q
0&
0>
b1111101110000110101111011110100 A
0b
b10 ]
b1 _
09
1B
1!
#47000
0!
#47500
0D
02
0#
1'
b11111100000100111011100111011011 %
b11111100000100111011100111011011 L
b10 `
b1 \
1E
1a
1P
1Q
1)
1=
b10001001100001111011000111000011 6
1d
0c
b1111101110000110101111011110100 "
b1111101110000110101111011110100 8
b1111101110000110101111011110100 C
19
0B
1b
1!
#48000
0!
#48500
0*
b0 (
b0 M
0F
b10 @
b10 X
1G
b11110000011000011100100101100100 :
b11110000011000011100100101100100 R
b11110000011000011100100101100100 ^
0H
b10 Z
1I
b0 \
0E
0a
0U
b100 ?
b100 W
1T
b10 `
1i
0h
0P
0Q
0)
0=
b10001001100001111011000111000011 A
0b
b100 ]
b10 _
09
1B
1!
#49000
0!
#49500
1D
12
1#
1e
0d
1b
1!
#50000
0!
#50500
0D
02
0#
1*
b11110001110101111100001001011101 (
b11110001110101111100001001011101 M
b11 `
b1 \
1E
1a
1P
1Q
1,
1<
b11110000011000011100100101100100 6
b10001001100001111011000111000011 "
b10001001100001111011000111000011 8
b10001001100001111011000111000011 C
19
0B
1!
#51000
0!
#51500
1D
12
1#
0-
b0 +
b0 N
b11 @
b11 X
1F
b1100101010110001000110011010100 :
b1100101010110001000110011010100 R
b1100101010110001000110011010100 ^
b0 \
0E
0a
1[
b11 Z
1H
0P
0Q
0,
0<
0T
b1000 ?
b1000 W
1S
b11 `
0K
0i
1j
b11110000011000011100100101100100 A
09
1B
0b
1Y
b1000 ]
b11 _
1!
#52000
0!
#52500
0D
02
0#
1-
b11101101011011110001101000 +
b11101101011011110001101000 N
1K
b0 `
b1 \
1E
1a
1P
1Q
1/
1;
b1100101010110001000110011010100 6
b11110000011000011100100101100100 "
b11110000011000011100100101100100 8
b11110000011000011100100101100100 C
1f
0e
1b
19
0B
1!
#53000
0!
#53500
00
b0 .
b0 O
0G
b0 @
b0 X
0F
b11111100000100111011100111011011 :
b11111100000100111011100111011011 R
b11111100000100111011100111011011 ^
15
b0 \
0E
0a
0[
0I
b0 Z
0H
0P
0Q
0/
0;
1V
b1 ?
b1 W
0S
b0 `
0K
0j
1g
b1100101010110001000110011010100 A
09
1B
0b
0Y
b1 ]
b0 _
1!
#54000
0!
#54500
10
b1101011010100101101011011001100 .
b1101011010100101101011011001100 O
0f
1c
1b
1!
#55000
0!
#55500
1D
12
1#
1!
#56000
0!
#56500
0D
02
0#
b1 `
b1 \
1E
1a
1P
1Q
1&
1>
b11111100000100111011100111011011 6
b1100101010110001000110011010100 "
b1100101010110001000110011010100 8
b1100101010110001000110011010100 C
19
0B
1!
#57000
0!
