streamTest/stream_Reg/streamReg/streamReg.v
// Generator : SpinalHDL v1.7.0a    git head : 150a9b9067020722818dfb17df4a23ac712a7af8
// Component : streamReg
// Git hash  : 3a903e741cbbe310a98c75dc1ebbd289cb1c87a4

`timescale 1ns/1ps

module streamReg (
  input               io_s_in_valid,
  output              io_s_in_ready,
  input      [31:0]   io_s_in_payload,
  output              io_m_out_valid,
  input               io_m_out_ready,
  output     [31:0]   io_m_out_payload,
  input               clk,
  input               reset
);

  wire                io_s_in_s2mPipe_valid;
  reg                 io_s_in_s2mPipe_ready;
  wire       [31:0]   io_s_in_s2mPipe_payload;
  reg                 io_s_in_rValid;
  reg        [31:0]   io_s_in_rData;
  wire                io_s_in_s2mPipe_m2sPipe_valid;
  wire                io_s_in_s2mPipe_m2sPipe_ready;
  wire       [31:0]   io_s_in_s2mPipe_m2sPipe_payload;
  reg                 io_s_in_s2mPipe_rValid;
  reg        [31:0]   io_s_in_s2mPipe_rData;
  wire                when_Stream_l368;

  assign io_s_in_ready = (! io_s_in_rValid);
  assign io_s_in_s2mPipe_valid = (io_s_in_valid || io_s_in_rValid);
  assign io_s_in_s2mPipe_payload = (io_s_in_rValid ? io_s_in_rData : io_s_in_payload);
  always @(*) begin
    io_s_in_s2mPipe_ready = io_s_in_s2mPipe_m2sPipe_ready;
    if(when_Stream_l368) begin
      io_s_in_s2mPipe_ready = 1'b1;
    end
  end

  assign when_Stream_l368 = (! io_s_in_s2mPipe_m2sPipe_valid);
  assign io_s_in_s2mPipe_m2sPipe_valid = io_s_in_s2mPipe_rValid;
  assign io_s_in_s2mPipe_m2sPipe_payload = io_s_in_s2mPipe_rData;
  assign io_m_out_valid = io_s_in_s2mPipe_m2sPipe_valid;
  assign io_s_in_s2mPipe_m2sPipe_ready = io_m_out_ready;
  assign io_m_out_payload = io_s_in_s2mPipe_m2sPipe_payload;
  always @(posedge clk or posedge reset) begin
    if(reset) begin
      io_s_in_rValid <= 1'b0;
      io_s_in_s2mPipe_rValid <= 1'b0;
    end else begin
      if(io_s_in_valid) begin
        io_s_in_rValid <= 1'b1;
      end
      if(io_s_in_s2mPipe_ready) begin
        io_s_in_rValid <= 1'b0;
      end
      if(io_s_in_s2mPipe_ready) begin
        io_s_in_s2mPipe_rValid <= io_s_in_s2mPipe_valid;
      end
    end
  end

  always @(posedge clk) begin
    if(io_s_in_ready) begin
      io_s_in_rData <= io_s_in_payload;
    end
    if(io_s_in_s2mPipe_ready) begin
      io_s_in_s2mPipe_rData <= io_s_in_s2mPipe_payload;
    end
  end

  initial begin
    $dumpfile("streamReg_test.vcd");
    $dumpvars(0, streamReg);
  end


endmodule

streamTest/streamReg/streamReg_test.vcd
$date
	Thu May 26 09:01:12 2022
$end
$version
	Icarus Verilog
$end
$timescale
	1ps
$end
$scope module streamReg $end
$var wire 1 ! clk $end
$var wire 32 " io_m_out_payload [31:0] $end
$var wire 1 # io_m_out_ready $end
$var wire 1 $ io_m_out_valid $end
$var wire 32 % io_s_in_payload [31:0] $end
$var wire 1 & io_s_in_s2mPipe_m2sPipe_ready $end
$var wire 1 ' io_s_in_s2mPipe_valid $end
$var wire 1 ( io_s_in_valid $end
$var wire 1 ) reset $end
$var wire 1 * when_Stream_l368 $end
$var wire 32 + io_s_in_s2mPipe_payload [31:0] $end
$var wire 1 , io_s_in_s2mPipe_m2sPipe_valid $end
$var wire 32 - io_s_in_s2mPipe_m2sPipe_payload [31:0] $end
$var wire 1 . io_s_in_ready $end
$var reg 32 / io_s_in_rData [31:0] $end
$var reg 1 0 io_s_in_rValid $end
$var reg 32 1 io_s_in_s2mPipe_rData [31:0] $end
$var reg 1 , io_s_in_s2mPipe_rValid $end
$var reg 1 2 io_s_in_s2mPipe_ready $end
$upscope $end
$enddefinitions $end
#0
$dumpvars
12
bx 1
00
bx /
1.
bx -
0,
bz +
1*
1)
z(
x'
z&
bz %
0$
z#
bx "
0!
$end
#1000
0'
b0 +
12
0(
b0 %
0&
0#
0)
#1500
b0 "
b0 -
b0 1
b0 /
1!
#2000
0!
#2500
1!
#3000
0!
#3500
1!
#4000
0!
#4500
1!
#5000
0!
#5500
1&
1#
1!
#6000
0!
#6500
1'
1(
1!
#7000
0!
#7500
0*
1$
1,
1.
00
1!
#8000
0!
#8500
0'
02
0(
0&
0#
1.
00
1!
#9000
0!
#9500
1!
#10000
0!
#10500
1'
b10011100110000100010110001000011 +
12
1(
b10011100110000100010110001000011 %
1&
1#
1!
#11000
0!
#11500
0'
b0 +
02
0(
b0 %
0&
0#
b10011100110000100010110001000011 "
b10011100110000100010110001000011 -
b10011100110000100010110001000011 1
b10011100110000100010110001000011 /
1.
00
1!
#12000
0!
#12500
b0 /
1!
#13000
0!
#13500
12
1&
1#
1!
#14000
0!
#14500
12
0&
0#
b0 "
b0 -
b0 1
1*
0$
0,
1!
#15000
0!
#15500
1!
#16000
0!
#16500
1'
b1000000000100010111000 +
1(
b1000000000100010111000 %
1&
1#
1!
#17000
0!
#17500
0'
b0 +
0(
b0 %
b1000000000100010111000 "
b1000000000100010111000 -
b1000000000100010111000 1
b1000000000100010111000 /
0*
1$
1,
1.
00
1!
#18000
0!
#18500
12
0&
0#
b0 "
b0 -
b0 1
b0 /
1*
0$
0,
1!
#19000
0!
#19500
1'
b11111100111010000011000000100001 +
1(
b11111100111010000011000000100001 %
1!
#20000
0!
#20500
0'
b0 +
0(
b0 %
02
b11111100111010000011000000100001 "
b11111100111010000011000000100001 -
b11111100111010000011000000100001 1
b11111100111010000011000000100001 /
0*
1$
1,
1.
00
1!
#21000
0!
#21500
12
1&
1#
b0 /
1!
#22000
0!
#22500
1'
b11011110011011100110001011101 +
12
1(
b11011110011011100110001011101 %
0&
0#
b0 "
b0 -
b0 1
1*
0$
0,
1!
#23000
0!
#23500
0'
b0 +
0(
b0 %
02
b11011110011011100110001011101 "
b11011110011011100110001011101 -
b11011110011011100110001011101 1
b11011110011011100110001011101 /
0*
1$
1,
1.
00
1!
#24000
0!
#24500
12
1&
1#
b0 /
1!
#25000
0!
#25500
1'
b10110110000001110011100011100111 +
12
1(
b10110110000001110011100011100111 %
0&
0#
b0 "
b0 -
b0 1
1*
0$
0,
1!
#26000
0!
#26500
0'
b0 +
0(
b0 %
1&
1#
12
b10110110000001110011100011100111 "
b10110110000001110011100011100111 -
b10110110000001110011100011100111 1
b10110110000001110011100011100111 /
0*
1$
1,
1.
00
1!
#27000
0!
#27500
1'
b11110000110111011111101001101010 +
12
1(
b11110000110111011111101001101010 %
0&
0#
b0 "
b0 -
b0 1
b0 /
1*
0$
0,
1!
#28000
0!
#28500
0'
b0 +
0(
b0 %
1&
1#
12
b11110000110111011111101001101010 "
b11110000110111011111101001101010 -
b11110000110111011111101001101010 1
b11110000110111011111101001101010 /
0*
1$
1,
1.
00
1!
#29000
0!
#29500
1'
b1000101010011010011001100101111 +
12
1(
b1000101010011010011001100101111 %
0&
0#
b0 "
b0 -
b0 1
b0 /
1*
0$
0,
1!
#30000
0!
#30500
0'
b0 +
0(
b0 %
1&
1#
12
b1000101010011010011001100101111 "
b1000101010011010011001100101111 -
b1000101010011010011001100101111 1
b1000101010011010011001100101111 /
0*
1$
1,
1.
00
1!
#31000
0!
#31500
1'
b100011000001111011000000001110 +
12
1(
b100011000001111011000000001110 %
0&
0#
b0 "
b0 -
b0 1
b0 /
1*
0$
0,
1!
#32000
0!
#32500
0'
b0 +
0(
b0 %
1&
1#
12
b100011000001111011000000001110 "
b100011000001111011000000001110 -
b100011000001111011000000001110 1
b100011000001111011000000001110 /
0*
1$
1,
1.
00
1!
#33000
0!
#33500
1'
b10110110111010010000110111111 +
12
1(
b10110110111010010000110111111 %
0&
0#
b0 "
b0 -
b0 1
b0 /
1*
0$
0,
1!
#34000
0!
#34500
0'
b0 +
0(
b0 %
1&
1#
12
b10110110111010010000110111111 "
b10110110111010010000110111111 -
b10110110111010010000110111111 1
b10110110111010010000110111111 /
0*
1$
1,
1.
00
1!
#35000
0!
#35500
1'
b11000011000110001001100001100 +
12
1(
b11000011000110001001100001100 %
0&
0#
b0 "
b0 -
b0 1
b0 /
1*
0$
0,
1!
#36000
0!
#36500
0'
b0 +
0(
b0 %
1&
1#
12
b11000011000110001001100001100 "
b11000011000110001001100001100 -
b11000011000110001001100001100 1
b11000011000110001001100001100 /
0*
1$
1,
1.
00
1!
#37000
0!
#37500
12
0&
0#
b0 "
b0 -
b0 1
b0 /
1*
0$
0,
1!
#38000
0!
#38500
1&
1#
1!
#39000
0!
#39500
1!
#40000
0!
#40500
1'
b10110110010010000100010011100111 +
1(
b10110110010010000100010011100111 %
1!
#41000
0!
#41500
0'
b0 +
0(
b0 %
b10110110010010000100010011100111 "
b10110110010010000100010011100111 -
b10110110010010000100010011100111 1
b10110110010010000100010011100111 /
0*
1$
1,
1.
00
1!
#42000
0!
#42500
12
0&
0#
b0 "
b0 -
b0 1
b0 /
1*
0$
0,
1!
#43000
0!
#43500
1!
#44000
0!
#44500
1'
b11010111000011000111101111011001 +
1(
b11010111000011000111101111011001 %
1!
#45000
0!
#45500
0'
b0 +
0(
b0 %
02
b11010111000011000111101111011001 "
b11010111000011000111101111011001 -
b11010111000011000111101111011001 1
b11010111000011000111101111011001 /
0*
1$
1,
1.
00
1!
#46000
0!
#46500
b0 /
1!
#47000
0!
#47500
1!
#48000
0!
#48500
1'
b1101110100010110101100111000110 +
12
1(
b1101110100010110101100111000110 %
1&
1#
1!
#49000
0!
#49500
0'
b0 +
02
0(
b0 %
0&
0#
b1101110100010110101100111000110 "
b1101110100010110101100111000110 -
b1101110100010110101100111000110 1
b1101110100010110101100111000110 /
1.
00
1!
#50000
0!
#50500
b0 /
1!
#51000
0!
#51500
1!
#52000
0!
#52500
1'
b100101000011111111000000 +
12
1(
b100101000011111111000000 %
1&
1#
1!
#53000
0!
#53500
0'
b0 +
02
0(
b0 %
0&
0#
b100101000011111111000000 "
b100101000011111111000000 -
b100101000011111111000000 1
b100101000011111111000000 /
1.
00
1!
#54000
0!
#54500
12
1&
1#
b0 /
1!
#55000
0!
#55500
1'
b11001101010010000010011010011011 +
12
1(
b11001101010010000010011010011011 %
0&
0#
b0 "
b0 -
b0 1
1*
0$
0,
1!
#56000
0!
#56500
0'
b0 +
0(
b0 %
1&
1#
12
b11001101010010000010011010011011 "
b11001101010010000010011010011011 -
b11001101010010000010011010011011 1
b11001101010010000010011010011011 /
0*
1$
1,
1.
00
1!
#57000
0!
#57500
12
0&
0#
b0 "
b0 -
b0 1
b0 /
1*
0$
0,
1!
#58000
0!
#58500
1'
b11001001011100101111010101100111 +
1(
b11001001011100101111010101100111 %
1&
1#
1!
#59000
0!
#59500
0'
b0 +
0(
b0 %
b11001001011100101111010101100111 "
b11001001011100101111010101100111 -
b11001001011100101111010101100111 1
b11001001011100101111010101100111 /
0*
1$
1,
1.
00
1!
#60000
0!
#60500
1'
b1011100100001101110111110001100 +
12
1(
b1011100100001101110111110001100 %
0&
0#
b0 "
b0 -
b0 1
b0 /
1*
0$
0,
1!
#61000
0!
#61500
0'
b0 +
0(
b0 %
1&
1#
12
b1011100100001101110111110001100 "
b1011100100001101110111110001100 -
b1011100100001101110111110001100 1
b1011100100001101110111110001100 /
0*
1$
1,
1.
00
1!
#62000
0!
#62500
12
0&
0#
b0 "
b0 -
b0 1
b0 /
1*
0$
0,
1!
#63000
0!
#63500
1'
b1000000000000010011111000111110 +
1(
b1000000000000010011111000111110 %
1!
#64000
0!
#64500
0'
b0 +
0(
b0 %
1&
1#
12
b1000000000000010011111000111110 "
b1000000000000010011111000111110 -
b1000000000000010011111000111110 1
b1000000000000010011111000111110 /
0*
1$
1,
1.
00
1!
#65000
0!
#65500
1'
b100010111100011010111111100100 +
12
1(
b100010111100011010111111100100 %
0&
0#
b0 "
b0 -
b0 1
b0 /
1*
0$
0,
1!
#66000
0!
#66500
0'
b0 +
0(
b0 %
02
b100010111100011010111111100100 "
b100010111100011010111111100100 -
b100010111100011010111111100100 1
b100010111100011010111111100100 /
0*
1$
1,
1.
00
1!
#67000
0!
#67500
1'
b10100000010100110000111101010100 +
1(
b10100000010100110000111101010100 %
b0 /
1!
#68000
0!
#68500
12
0(
b0 %
1&
1#
b10100000010100110000111101010100 /
0.
10
1!
#69000
0!
#69500
02
0&
0#
b0 +
0'
b10100000010100110000111101010100 "
b10100000010100110000111101010100 -
b10100000010100110000111101010100 1
1.
00
1!
#70000
0!
#70500
b0 /
1!
#71000
0!
#71500
12
1&
1#
1!
#72000
0!
#72500
12
0&
0#
b0 "
b0 -
b0 1
1*
0$
0,
1!
#73000
0!
#73500
1'
b11100010101010001100010101000010 +
1(
b11100010101010001100010101000010 %
1!
#74000
0!
#74500
0'
b0 +
0(
b0 %
1&
1#
12
b11100010101010001100010101000010 "
b11100010101010001100010101000010 -
b11100010101010001100010101000010 1
b11100010101010001100010101000010 /
0*
1$
1,
1.
00
1!
#75000
0!
#75500
12
0&
0#
b0 "
b0 -
b0 1
b0 /
1*
0$
0,
1!
#76000
0!
#76500
1'
b1101111110001111010101000110010 +
1(
b1101111110001111010101000110010 %
1&
1#
1!
#77000
0!
#77500
0'
b0 +
0(
b0 %
b1101111110001111010101000110010 "
b1101111110001111010101000110010 -
b1101111110001111010101000110010 1
b1101111110001111010101000110010 /
0*
1$
1,
1.
00
1!
#78000
0!
#78500
12
0&
0#
b0 "
b0 -
b0 1
b0 /
1*
0$
0,
1!
#79000
0!
#79500
1!
#80000
0!
#80500
1&
1#
1!
#81000
0!
#81500
1'
b1110111010101101001100111000101 +
1(
b1110111010101101001100111000101 %
1!
#82000
0!
#82500
0'
b0 +
0(
b0 %
b1110111010101101001100111000101 "
b1110111010101101001100111000101 -
b1110111010101101001100111000101 1
b1110111010101101001100111000101 /
0*
1$
1,
1.
00
1!
#83000
0!
#83500
12
0&
0#
b0 "
b0 -
b0 1
b0 /
1*
0$
0,
1!
#84000
0!
#84500
1'
b1101011100010000101010101011011 +
1(
b1101011100010000101010101011011 %
1!
#85000
0!
#85500
0'
b0 +
0(
b0 %
1&
1#
12
b1101011100010000101010101011011 "
b1101011100010000101010101011011 -
b1101011100010000101010101011011 1
b1101011100010000101010101011011 /
0*
1$
1,
1.
00
1!
#86000
0!
#86500
12
0&
0#
b0 "
b0 -
b0 1
b0 /
1*
0$
0,
1!
#87000
0!
#87500
1&
1#
1!
#88000
0!
#88500
1!
#89000
0!
#89500
1!
#90000
0!
#90500
1!
#91000
0!
#91500
1'
b11100110011111111010111000111111 +
1(
b11100110011111111010111000111111 %
1!
#92000
0!
#92500
0'
b0 +
0(
b0 %
b11100110011111111010111000111111 "
b11100110011111111010111000111111 -
b11100110011111111010111000111111 1
b11100110011111111010111000111111 /
0*
1$
1,
1.
00
1!
#93000
0!
#93500
12
0&
0#
b0 "
b0 -
b0 1
b0 /
1*
0$
0,
1!
#94000
0!
#94500
1&
1#
1!
#95000
0!
#95500
1!
#96000
0!
#96500
1'
b100001100100110111110100110 +
1(
b100001100100110111110100110 %
1!
#97000
0!
#97500
0'
b0 +
0(
b0 %
b100001100100110111110100110 "
b100001100100110111110100110 -
b100001100100110111110100110 1
b100001100100110111110100110 /
0*
1$
1,
1.
00
1!
#98000
0!
#98500
12
0&
0#
b0 "
b0 -
b0 1
b0 /
1*
0$
0,
1!
#99000
0!
#99500
1'
b11011101100100111000001100001011 +
1(
b11011101100100111000001100001011 %
1&
1#
1!
#100000
0!
#100500
0'
b0 +
0(
b0 %
b11011101100100111000001100001011 "
b11011101100100111000001100001011 -
b11011101100100111000001100001011 1
b11011101100100111000001100001011 /
0*
1$
1,
1.
00
1!
#101000
0!
#101500
12
0&
0#
b0 "
b0 -
b0 1
b0 /
1*
0$
0,
1!
#102000
0!
#102500
1!
#103000
0!
#103500
1'
b11010011000100110101101100001 +
1(
b11010011000100110101101100001 %
1!
#104000
0!
#104500
0'
b0 +
0(
b0 %
1&
1#
12
b11010011000100110101101100001 "
b11010011000100110101101100001 -
b11010011000100110101101100001 1
b11010011000100110101101100001 /
0*
1$
1,
1.
00
1!
#105000
0!
#105500
1'
b10010011101001011100000110011 +
12
1(
b10010011101001011100000110011 %
0&
0#
b0 "
b0 -
b0 1
b0 /
1*
0$
0,
1!
#106000
0!
#106500
0'
b0 +
0(
b0 %
02
b10010011101001011100000110011 "
b10010011101001011100000110011 -
b10010011101001011100000110011 1
b10010011101001011100000110011 /
0*
1$
1,
1.
00
1!
#107000
0!
#107500
12
1&
1#
b0 /
1!
#108000
0!
#108500
12
0&
0#
b0 "
b0 -
b0 1
1*
0$
0,
1!
#109000
0!
#109500
1!
#110000
0!
#110500
1&
1#
1!
#111000
0!
#111500
1!
#112000
0!
#112500
1'
b10110101010110001001101000 +
1(
b10110101010110001001101000 %
1!
#113000
0!
#113500
0'
b0 +
0(
b0 %
b10110101010110001001101000 "
b10110101010110001001101000 -
b10110101010110001001101000 1
b10110101010110001001101000 /
0*
1$
1,
1.
00
1!
#114000
0!
#114500
1'
b10111011100001001101110001010001 +
12
1(
b10111011100001001101110001010001 %
0&
0#
b0 "
b0 -
b0 1
b0 /
1*
0$
0,
1!
#115000
0!
#115500
0'
b0 +
0(
b0 %
02
b10111011100001001101110001010001 "
b10111011100001001101110001010001 -
b10111011100001001101110001010001 1
b10111011100001001101110001010001 /
0*
1$
1,
1.
00
1!
#116000
0!
#116500
b0 /
1!
#117000
0!
#117500
12
1&
1#
1!
#118000
0!
#118500
12
0&
0#
b0 "
b0 -
b0 1
1*
0$
0,
1!
#119000
0!
#119500
1&
1#
1!
#120000
0!
#120500
1!
#121000
0!
#121500
1!
#122000
0!
#122500
1!
#123000
0!
#123500
1'
b11110000100000011001111110011111 +
1(
b11110000100000011001111110011111 %
1!
#124000
0!
#124500
0'
b0 +
0(
b0 %
b11110000100000011001111110011111 "
b11110000100000011001111110011111 -
b11110000100000011001111110011111 1
b11110000100000011001111110011111 /
0*
1$
1,
1.
00
1!
#125000
0!
#125500
1'
b101110100001111100101001110001 +
12
1(
b101110100001111100101001110001 %
0&
0#
b0 "
b0 -
b0 1
b0 /
1*
0$
0,
1!
#126000
0!
#126500
0'
b0 +
0(
b0 %
02
b101110100001111100101001110001 "
b101110100001111100101001110001 -
b101110100001111100101001110001 1
b101110100001111100101001110001 /
0*
1$
1,
1.
00
1!
#127000
0!
#127500
1'
b110100011011100000110100001010 +
1(
b110100011011100000110100001010 %
b0 /
1!
#128000
0!
#128500
12
0(
b0 %
1&
1#
b110100011011100000110100001010 /
0.
10
1!
#129000
0!
#129500
02
1(
b10001001000110110101110010100111 %
0&
0#
b10001001000110110101110010100111 +
1'
b110100011011100000110100001010 "
b110100011011100000110100001010 -
b110100011011100000110100001010 1
1.
00
1!
#130000
0!
#130500
12
0(
b0 %
1&
1#
b10001001000110110101110010100111 /
0.
10
1!
#131000
0!
#131500
02
0&
0#
b0 +
0'
b10001001000110110101110010100111 "
b10001001000110110101110010100111 -
b10001001000110110101110010100111 1
1.
00
1!
#132000
0!
#132500
1'
b10110011010000000111100000111110 +
1(
b10110011010000000111100000111110 %
b0 /
1!
#133000
0!
#133500
12
0(
b0 %
1&
1#
b10110011010000000111100000111110 /
0.
10
1!
#134000
0!
#134500
02
0&
0#
b0 +
0'
b10110011010000000111100000111110 "
b10110011010000000111100000111110 -
b10110011010000000111100000111110 1
1.
00
1!
#135000
0!
#135500
b0 /
1!
#136000
0!
#136500
1'
b10101000000101000111101110000 +
1(
b10101000000101000111101110000 %
1!
#137000
0!
#137500
0(
b0 %
b10101000000101000111101110000 /
0.
10
1!
#138000
0!
#138500
12
1&
1#
1!
#139000
0!
#139500
02
1(
b1011110011011101100000101010111 %
0&
0#
b1011110011011101100000101010111 +
1'
b10101000000101000111101110000 "
b10101000000101000111101110000 -
b10101000000101000111101110000 1
1.
00
1!
#140000
0!
#140500
12
0(
b0 %
1&
1#
b1011110011011101100000101010111 /
0.
10
1!
#141000
0!
#141500
02
0&
0#
b0 +
0'
b1011110011011101100000101010111 "
b1011110011011101100000101010111 -
b1011110011011101100000101010111 1
1.
00
1!
#142000
0!
#142500
b0 /
1!
#143000
0!
#143500
1'
b11001111111000011110111000010010 +
12
1(
b11001111111000011110111000010010 %
1&
1#
1!
#144000
0!
#144500
0'
b0 +
02
0(
b0 %
0&
0#
b11001111111000011110111000010010 "
b11001111111000011110111000010010 -
b11001111111000011110111000010010 1
b11001111111000011110111000010010 /
1.
00
1!
#145000
0!
#145500
1'
b10010000100011111110001010000111 +
1(
b10010000100011111110001010000111 %
b0 /
1!
#146000
0!
#146500
0(
b0 %
b10010000100011111110001010000111 /
0.
10
1!
#147000
0!
#147500
1!
#148000
0!
#148500
1(
b1010011110110001111111111010010 %
1!
#149000
0!
#149500
1!
#150000
0!
#150500
1!
#151000
0!
#151500
1!
#152000
0!
#152500
1!
#153000
0!
#153500
1!
#154000
0!
#154500
12
1&
1#
1!
#155000
0!
#155500
02
0&
0#
b1010011110110001111111111010010 +
b10010000100011111110001010000111 "
b10010000100011111110001010000111 -
b10010000100011111110001010000111 1
1.
00
1!
#156000
0!
#156500
0(
b0 %
b1010011110110001111111111010010 /
0.
10
1!
#157000
0!
#157500
12
1&
1#
1!
#158000
0!
#158500
02
0&
0#
b0 +
0'
b1010011110110001111111111010010 "
b1010011110110001111111111010010 -
b1010011110110001111111111010010 1
1.
00
1!
#159000
0!
#159500
b0 /
1!
#160000
0!
#160500
1'
b11100010001001111100001100011000 +
12
1(
b11100010001001111100001100011000 %
1&
1#
1!
#161000
0!
#161500
0'
b0 +
02
0(
b0 %
0&
0#
b11100010001001111100001100011000 "
b11100010001001111100001100011000 -
b11100010001001111100001100011000 1
b11100010001001111100001100011000 /
1.
00
1!
#162000
0!
#162500
1'
b1011011110010001000111010110010 +
12
1(
b1011011110010001000111010110010 %
1&
1#
b0 /
1!
#163000
0!
#163500
0'
b0 +
02
0(
b0 %
0&
0#
b1011011110010001000111010110010 "
b1011011110010001000111010110010 -
b1011011110010001000111010110010 1
b1011011110010001000111010110010 /
1.
00
1!
#164000
0!
#164500
1'
b1111000101111001010000010011110 +
1(
b1111000101111001010000010011110 %
b0 /
1!
#165000
0!
#165500
12
0(
b0 %
1&
1#
b1111000101111001010000010011110 /
0.
10
1!
#166000
0!
#166500
02
0&
0#
b0 +
0'
b1111000101111001010000010011110 "
b1111000101111001010000010011110 -
b1111000101111001010000010011110 1
1.
00
1!
#167000
0!
#167500
1'
b1101000100100010001111000001101 +
1(
b1101000100100010001111000001101 %
b0 /
1!
#168000
0!
#168500
12
0(
b0 %
1&
1#
b1101000100100010001111000001101 /
0.
10
1!
#169000
0!
#169500
02
1(
b110000011101110111111010000011 %
0&
0#
b110000011101110111111010000011 +
1'
b1101000100100010001111000001101 "
b1101000100100010001111000001101 -
b1101000100100010001111000001101 1
1.
00
1!
#170000
0!
#170500
12
0(
b0 %
1&
1#
b110000011101110111111010000011 /
0.
10
1!
#171000
0!
#171500
02
1(
b11010100100001110101001100010011 %
0&
0#
b11010100100001110101001100010011 +
1'
b110000011101110111111010000011 "
b110000011101110111111010000011 -
b110000011101110111111010000011 1
1.
00
1!
#172000
0!
#172500
0(
b0 %
b11010100100001110101001100010011 /
0.
10
1!
#173000
0!
#173500
12
1&
1#
1!
#174000
0!
#174500
02
0&
0#
b0 +
0'
b11010100100001110101001100010011 "
b11010100100001110101001100010011 -
b11010100100001110101001100010011 1
1.
00
1!
#175000
0!
#175500
12
1&
1#
b0 /
1!
#176000
0!
#176500
12
0&
0#
b0 "
b0 -
b0 1
1*
0$
0,
1!
#177000
0!
#177500
1!
#178000
0!
#178500
1'
b11000010010100110100010001010101 +
1(
b11000010010100110100010001010101 %
1!
#179000
0!
#179500
0'
b0 +
0(
b0 %
02
b11000010010100110100010001010101 "
b11000010010100110100010001010101 -
b11000010010100110100010001010101 1
b11000010010100110100010001010101 /
0*
1$
1,
1.
00
1!
#180000
0!
#180500
1'
b10111000001111001000100000101 +
12
1(
b10111000001111001000100000101 %
1&
1#
b0 /
1!
#181000
0!
#181500
0'
b0 +
02
0(
b0 %
0&
0#
b10111000001111001000100000101 "
b10111000001111001000100000101 -
b10111000001111001000100000101 1
b10111000001111001000100000101 /
1.
00
1!
#182000
0!
#182500
1'
b11000110000000110111100100001000 +
12
1(
b11000110000000110111100100001000 %
1&
1#
b0 /
1!
#183000
0!
#183500
0'
b0 +
02
0(
b0 %
0&
0#
b11000110000000110111100100001000 "
b11000110000000110111100100001000 -
b11000110000000110111100100001000 1
b11000110000000110111100100001000 /
1.
00
1!
#184000
0!
#184500
1'
b1100100111110011100110011000111 +
1(
b1100100111110011100110011000111 %
b0 /
1!
#185000
0!
#185500
12
0(
b0 %
1&
1#
b1100100111110011100110011000111 /
0.
10
1!
#186000
0!
#186500
02
1(
b11001011101001011011011000000101 %
0&
0#
b11001011101001011011011000000101 +
1'
b1100100111110011100110011000111 "
b1100100111110011100110011000111 -
b1100100111110011100110011000111 1
1.
00
1!
#187000
0!
#187500
0(
b0 %
b11001011101001011011011000000101 /
0.
10
1!
#188000
0!
#188500
12
1(
b1101000000001100101010001000001 %
1&
1#
1!
#189000
0!
#189500
02
0&
0#
b1101000000001100101010001000001 +
b11001011101001011011011000000101 "
b11001011101001011011011000000101 -
b11001011101001011011011000000101 1
1.
00
1!
#190000
0!
#190500
0(
b0 %
b1101000000001100101010001000001 /
0.
10
1!
#191000
0!
#191500
12
1(
b11000001111010000111011110011100 %
1&
1#
1!
#192000
0!
#192500
02
0&
0#
b11000001111010000111011110011100 +
b1101000000001100101010001000001 "
b1101000000001100101010001000001 -
b1101000000001100101010001000001 1
1.
00
1!
#193000
0!
#193500
0(
b0 %
b11000001111010000111011110011100 /
0.
10
1!
#194000
0!
#194500
12
1(
b100100000000101000011110111000 %
1&
1#
1!
#195000
0!
#195500
02
0&
0#
b100100000000101000011110111000 +
b11000001111010000111011110011100 "
b11000001111010000111011110011100 -
b11000001111010000111011110011100 1
1.
00
1!
#196000
0!
#196500
0(
b0 %
b100100000000101000011110111000 /
0.
10
1!
#197000
0!
#197500
12
1(
b11011000111110001001100000110 %
1&
1#
1!
#198000
0!
#198500
02
0&
0#
b11011000111110001001100000110 +
b100100000000101000011110111000 "
b100100000000101000011110111000 -
b100100000000101000011110111000 1
1.
00
1!
#199000
0!
#199500
12
0(
b0 %
1&
1#
b11011000111110001001100000110 /
0.
10
1!
#200000
0!
#200500
02
0&
0#
b0 +
0'
b11011000111110001001100000110 "
b11011000111110001001100000110 -
b11011000111110001001100000110 1
1.
00
1!
#201000
0!
#201500
1'
b1010111100011101100010110110000 +
1(
b1010111100011101100010110110000 %
b0 /
1!
#202000
0!
#202500
12
0(
b0 %
1&
1#
b1010111100011101100010110110000 /
0.
10
1!
#203000
0!
#203500
02
1(
b100101011111001110111110010000 %
0&
0#
b100101011111001110111110010000 +
1'
b1010111100011101100010110110000 "
b1010111100011101100010110110000 -
b1010111100011101100010110110000 1
1.
00
1!
#204000
0!
#204500
0(
b0 %
b100101011111001110111110010000 /
0.
10
1!
#205000
0!
#205500
1(
b1111101001000011011001101111 %
1!
#206000
0!
#206500
12
1&
1#
1!
#207000
0!
#207500
02
0&
0#
b1111101001000011011001101111 +
b100101011111001110111110010000 "
b100101011111001110111110010000 -
b100101011111001110111110010000 1
1.
00
1!
#208000
0!
#208500
0(
b0 %
b1111101001000011011001101111 /
0.
10
1!
#209000
0!
#209500
1(
b1110111011001001101100101101101 %
1!
#210000
0!
#210500
12
1&
1#
1!
#211000
0!
#211500
02
0&
0#
b1110111011001001101100101101101 +
b1111101001000011011001101111 "
b1111101001000011011001101111 -
b1111101001000011011001101111 1
1.
00
1!
#212000
0!
#212500
12
0(
b0 %
1&
1#
b1110111011001001101100101101101 /
0.
10
1!
#213000
0!
#213500
02
0&
0#
b0 +
0'
b1110111011001001101100101101101 "
b1110111011001001101100101101101 -
b1110111011001001101100101101101 1
1.
00
1!
#214000
0!
#214500
1'
b10101010000010110011001111101110 +
12
1(
b10101010000010110011001111101110 %
1&
1#
b0 /
1!
#215000
0!
#215500
0'
b0 +
02
0(
b0 %
0&
0#
b10101010000010110011001111101110 "
b10101010000010110011001111101110 -
b10101010000010110011001111101110 1
b10101010000010110011001111101110 /
1.
00
1!
#216000
0!
#216500
12
1&
1#
b0 /
1!
#217000
0!
#217500
12
0&
0#
b0 "
b0 -
b0 1
1*
0$
0,
1!
#218000
0!
#218500
1&
1#
1!
#219000
0!
#219500
1!
#220000
0!
#220500
1'
b11111011101101111001011100111110 +
1(
b11111011101101111001011100111110 %
1!
#221000
0!
#221500
0'
b0 +
0(
b0 %
b11111011101101111001011100111110 "
b11111011101101111001011100111110 -
b11111011101101111001011100111110 1
b11111011101101111001011100111110 /
0*
1$
1,
1.
00
1!
#222000
0!
#222500
12
0&
0#
b0 "
b0 -
b0 1
b0 /
1*
0$
0,
1!
#223000
0!
#223500
1'
b11000010101011000101110100001010 +
1(
b11000010101011000101110100001010 %
1&
1#
1!
#224000
0!
#224500
0'
b0 +
0(
b0 %
b11000010101011000101110100001010 "
b11000010101011000101110100001010 -
b11000010101011000101110100001010 1
b11000010101011000101110100001010 /
0*
1$
1,
1.
00
1!
#225000
0!
#225500
1'
b100110101001000101000010111100 +
12
1(
b100110101001000101000010111100 %
0&
0#
b0 "
b0 -
b0 1
b0 /
1*
0$
0,
1!
#226000
0!
#226500
0'
b0 +
0(
b0 %
02
b100110101001000101000010111100 "
b100110101001000101000010111100 -
b100110101001000101000010111100 1
b100110101001000101000010111100 /
0*
1$
1,
1.
00
1!
#227000
0!
#227500
12
1&
1#
b0 /
1!
#228000
0!
#228500
12
0&
0#
b0 "
b0 -
b0 1
1*
0$
0,
1!
#229000
0!
#229500
1&
1#
1!
