pwm/ApbPwm.v
// Generator : SpinalHDL v1.6.4    git head : 598c18959149eb18e5eee5b0aa3eef01ecaa41a1
// Component : ApbPwm
// Git hash  : 89d7543c7219f82d1991c9174f1b313aba4435ca

`timescale 1ns/1ps 

module ApbPwm (
  input      [0:0]    io_apb_PSEL,
  input               io_apb_PENABLE,
  input               io_apb_PWRITE,
  input      [7:0]    io_apb_PADDR,
  input      [31:0]   io_apb_PWDATA,
  output reg [31:0]   io_apb_PRDATA,
  output              io_apb_PREADY,
  output              io_pwm,
  input               clk,
  input               reset
);

  wire       [7:0]    _zz_io_apb_PRDATA;
  wire       [31:0]   _zz_logic_dutyCycle;
  reg                 logic_enable;
  reg        [7:0]    logic_timer;
  reg        [7:0]    logic_dutyCycle;
  reg                 logic_output;
  wire                when_ApbPwm_l50;
  wire                when_ApbPwm_l54;
  wire                control_doWrite;

  assign _zz_io_apb_PRDATA = logic_dutyCycle;
  assign _zz_logic_dutyCycle = io_apb_PWDATA;
  assign when_ApbPwm_l50 = (logic_timer == 8'h0);
  assign when_ApbPwm_l54 = (logic_timer == logic_dutyCycle);
  assign io_pwm = logic_output;
  assign control_doWrite = ((io_apb_PSEL[0] && io_apb_PENABLE) && io_apb_PWRITE);
  always @(*) begin
    io_apb_PRDATA = 32'h0;
    case(io_apb_PADDR)
      8'h0 : begin
        io_apb_PRDATA[0] = logic_enable;
      end
      8'h04 : begin
        io_apb_PRDATA = {24'd0, _zz_io_apb_PRDATA};
      end
      default : begin
      end
    endcase
  end

  assign io_apb_PREADY = 1'b1;
  always @(posedge clk or posedge reset) begin
    if(reset) begin
      logic_enable <= 1'b0;
      logic_timer <= 8'h0;
      logic_output <= 1'b0;
    end else begin
      if(logic_enable) begin
        logic_timer <= (logic_timer + 8'h01);
      end
      if(when_ApbPwm_l50) begin
        logic_output <= 1'b1;
      end
      if(when_ApbPwm_l54) begin
        logic_output <= 1'b0;
      end
      case(io_apb_PADDR)
        8'h0 : begin
          if(control_doWrite) begin
            logic_enable <= io_apb_PWDATA[0];
          end
        end
        default : begin
        end
      endcase
    end
  end

  always @(posedge clk) begin
    case(io_apb_PADDR)
      8'h04 : begin
        if(control_doWrite) begin
          logic_dutyCycle <= _zz_logic_dutyCycle[7:0];
        end
      end
      default : begin
      end
    endcase
  end

  initial begin
    $dumpfile("ApbPwm.vcd");
    $dumpvars(0, ApbPwm);
  end


endmodule

pwm/ApbPwm.vcd
$date
	Sun Apr  3 08:10:32 2022
$end
$version
	Icarus Verilog
$end
$timescale
	1ps
$end
$scope module ApbPwm $end
$var wire 8 ! _zz_io_apb_PRDATA [7:0] $end
$var wire 32 " _zz_logic_dutyCycle [31:0] $end
$var wire 1 # clk $end
$var wire 1 $ control_doWrite $end
$var wire 8 % io_apb_PADDR [7:0] $end
$var wire 1 & io_apb_PENABLE $end
$var wire 1 ' io_apb_PREADY $end
$var wire 1 ( io_apb_PSEL $end
$var wire 32 ) io_apb_PWDATA [31:0] $end
$var wire 1 * io_apb_PWRITE $end
$var wire 1 + io_pwm $end
$var wire 1 , reset $end
$var wire 1 - when_ApbPwm_l54 $end
$var wire 1 . when_ApbPwm_l50 $end
$var reg 32 / io_apb_PRDATA [31:0] $end
$var reg 8 0 logic_dutyCycle [7:0] $end
$var reg 1 1 logic_enable $end
$var reg 1 2 logic_output $end
$var reg 8 3 logic_timer [7:0] $end
$upscope $end
$enddefinitions $end
#0
$dumpvars
b0 3
02
01
bx 0
b0 /
1.
x-
1,
0+
z*
bz )
z(
1'
z&
bz %
x$
0#
bz "
bx !
$end
#500
1+
12
1#
0,
#1000
0#
#1500
1$
1#
1(
1&
1*
b0 %
b11111111111111111111111111111111 "
b11111111111111111111111111111111 )
#2000
0#
#2500
b1 /
11
1#
#3000
0#
#3500
0-
b11000000 !
b11000000 0
0.
b1 3
b11000000 /
1#
b100 %
b11000000 "
b11000000 )
#4000
0#
#4500
b10 3
1#
#5000
0#
#5500
b11 3
0$
b0 /
1#
0(
0*
b11 %
b11011100100011101100011111100001 "
b11011100100011101100011111100001 )
#6000
0#
#6500
b100 3
1#
#7000
0#
#7500
b101 3
1#
#8000
0#
#8500
b110 3
1#
#9000
0#
#9500
b111 3
1#
#10000
0#
#10500
b1000 3
1#
#11000
0#
#11500
b1001 3
1#
#12000
0#
#12500
b1010 3
1#
#13000
0#
#13500
b1011 3
1#
#14000
0#
#14500
b1100 3
1#
#15000
0#
#15500
b1101 3
1#
#16000
0#
#16500
b1110 3
1#
#17000
0#
#17500
b1111 3
1#
#18000
0#
#18500
b10000 3
1#
#19000
0#
#19500
b10001 3
1#
#20000
0#
#20500
b10010 3
1#
#21000
0#
#21500
b10011 3
1#
#22000
0#
#22500
b10100 3
1#
#23000
0#
#23500
b10101 3
1#
#24000
0#
#24500
b10110 3
1#
#25000
0#
#25500
b10111 3
1#
#26000
0#
#26500
b11000 3
1#
#27000
0#
#27500
b11001 3
1#
#28000
0#
#28500
b11010 3
1#
#29000
0#
#29500
b11011 3
1#
#30000
0#
#30500
b11100 3
1#
#31000
0#
#31500
b11101 3
1#
#32000
0#
#32500
b11110 3
1#
#33000
0#
#33500
b11111 3
1#
#34000
0#
#34500
b100000 3
1#
#35000
0#
#35500
b100001 3
1#
#36000
0#
#36500
b100010 3
1#
#37000
0#
#37500
b100011 3
1#
#38000
0#
#38500
b100100 3
1#
#39000
0#
#39500
b100101 3
1#
#40000
0#
#40500
b100110 3
1#
#41000
0#
#41500
b100111 3
1#
#42000
0#
#42500
b101000 3
1#
#43000
0#
#43500
b101001 3
1#
#44000
0#
#44500
b101010 3
1#
#45000
0#
#45500
b101011 3
1#
#46000
0#
#46500
b101100 3
1#
#47000
0#
#47500
b101101 3
1#
#48000
0#
#48500
b101110 3
1#
#49000
0#
#49500
b101111 3
1#
#50000
0#
#50500
b110000 3
1#
#51000
0#
#51500
b110001 3
1#
#52000
0#
#52500
b110010 3
1#
#53000
0#
#53500
b110011 3
1#
#54000
0#
#54500
b110100 3
1#
#55000
0#
#55500
b110101 3
1#
#56000
0#
#56500
b110110 3
1#
#57000
0#
#57500
b110111 3
1#
#58000
0#
#58500
b111000 3
1#
#59000
0#
#59500
b111001 3
1#
#60000
0#
#60500
b111010 3
1#
#61000
0#
#61500
b111011 3
1#
#62000
0#
#62500
b111100 3
1#
#63000
0#
#63500
b111101 3
1#
#64000
0#
#64500
b111110 3
1#
#65000
0#
#65500
b111111 3
1#
#66000
0#
#66500
b1000000 3
1#
#67000
0#
#67500
b1000001 3
1#
#68000
0#
#68500
b1000010 3
1#
#69000
0#
#69500
b1000011 3
1#
#70000
0#
#70500
b1000100 3
1#
#71000
0#
#71500
b1000101 3
1#
#72000
0#
#72500
b1000110 3
1#
#73000
0#
#73500
b1000111 3
1#
#74000
0#
#74500
b1001000 3
1#
#75000
0#
#75500
b1001001 3
1#
#76000
0#
#76500
b1001010 3
1#
#77000
0#
#77500
b1001011 3
1#
#78000
0#
#78500
b1001100 3
1#
#79000
0#
#79500
b1001101 3
1#
#80000
0#
#80500
b1001110 3
1#
#81000
0#
#81500
b1001111 3
1#
#82000
0#
#82500
b1010000 3
1#
#83000
0#
#83500
b1010001 3
1#
#84000
0#
#84500
b1010010 3
1#
#85000
0#
#85500
b1010011 3
1#
#86000
0#
#86500
b1010100 3
1#
#87000
0#
#87500
b1010101 3
1#
#88000
0#
#88500
b1010110 3
1#
#89000
0#
#89500
b1010111 3
1#
#90000
0#
#90500
b1011000 3
1#
#91000
0#
#91500
b1011001 3
1#
#92000
0#
#92500
b1011010 3
1#
#93000
0#
#93500
b1011011 3
1#
#94000
0#
#94500
b1011100 3
1#
#95000
0#
#95500
b1011101 3
1#
#96000
0#
#96500
b1011110 3
1#
#97000
0#
#97500
b1011111 3
1#
#98000
0#
#98500
b1100000 3
1#
#99000
0#
#99500
b1100001 3
1#
#100000
0#
#100500
b1100010 3
1#
#101000
0#
#101500
b1100011 3
1#
#102000
0#
#102500
b1100100 3
1#
#103000
0#
#103500
b1100101 3
1#
#104000
0#
#104500
b1100110 3
1#
#105000
0#
#105500
b1100111 3
1#
#106000
0#
#106500
b1101000 3
1#
#107000
0#
#107500
b1101001 3
1#
#108000
0#
#108500
b1101010 3
1#
#109000
0#
#109500
b1101011 3
1#
#110000
0#
#110500
b1101100 3
1#
#111000
0#
#111500
b1101101 3
1#
#112000
0#
#112500
b1101110 3
1#
#113000
0#
#113500
b1101111 3
1#
#114000
0#
#114500
b1110000 3
1#
#115000
0#
#115500
b1110001 3
1#
#116000
0#
#116500
b1110010 3
1#
#117000
0#
#117500
b1110011 3
1#
#118000
0#
#118500
b1110100 3
1#
#119000
0#
#119500
b1110101 3
1#
#120000
0#
#120500
b1110110 3
1#
#121000
0#
#121500
b1110111 3
1#
#122000
0#
#122500
b1111000 3
1#
#123000
0#
#123500
b1111001 3
1#
#124000
0#
#124500
b1111010 3
1#
#125000
0#
#125500
b1111011 3
1#
#126000
0#
#126500
b1111100 3
1#
#127000
0#
#127500
b1111101 3
1#
#128000
0#
#128500
b1111110 3
1#
#129000
0#
#129500
b1111111 3
1#
#130000
0#
#130500
b10000000 3
1#
#131000
0#
#131500
b10000001 3
1#
#132000
0#
#132500
b10000010 3
1#
#133000
0#
#133500
b10000011 3
1#
#134000
0#
#134500
b10000100 3
1#
#135000
0#
#135500
b10000101 3
1#
#136000
0#
#136500
b10000110 3
1#
#137000
0#
#137500
b10000111 3
1#
#138000
0#
#138500
b10001000 3
1#
#139000
0#
#139500
b10001001 3
1#
#140000
0#
#140500
b10001010 3
1#
#141000
0#
#141500
b10001011 3
1#
#142000
0#
#142500
b10001100 3
1#
#143000
0#
#143500
b10001101 3
1#
#144000
0#
#144500
b10001110 3
1#
#145000
0#
#145500
b10001111 3
1#
#146000
0#
#146500
b10010000 3
1#
#147000
0#
#147500
b10010001 3
1#
#148000
0#
#148500
b10010010 3
1#
#149000
0#
#149500
b10010011 3
1#
#150000
0#
#150500
b10010100 3
1#
#151000
0#
#151500
b10010101 3
1#
#152000
0#
#152500
b10010110 3
1#
#153000
0#
#153500
b10010111 3
1#
#154000
0#
#154500
b10011000 3
1#
#155000
0#
#155500
b10011001 3
1#
#156000
0#
#156500
b10011010 3
1#
#157000
0#
#157500
b10011011 3
1#
#158000
0#
#158500
b10011100 3
1#
#159000
0#
#159500
b10011101 3
1#
#160000
0#
#160500
b10011110 3
1#
#161000
0#
#161500
b10011111 3
1#
#162000
0#
#162500
b10100000 3
1#
#163000
0#
#163500
b10100001 3
1#
#164000
0#
#164500
b10100010 3
1#
#165000
0#
#165500
b10100011 3
1#
#166000
0#
#166500
b10100100 3
1#
#167000
0#
#167500
b10100101 3
1#
#168000
0#
#168500
b10100110 3
1#
#169000
0#
#169500
b10100111 3
1#
#170000
0#
#170500
b10101000 3
1#
#171000
0#
#171500
b10101001 3
1#
#172000
0#
#172500
b10101010 3
1#
#173000
0#
#173500
b10101011 3
1#
#174000
0#
#174500
b10101100 3
1#
#175000
0#
#175500
b10101101 3
1#
#176000
0#
#176500
b10101110 3
1#
#177000
0#
#177500
b10101111 3
1#
#178000
0#
#178500
b10110000 3
1#
#179000
0#
#179500
b10110001 3
1#
#180000
0#
#180500
b10110010 3
1#
#181000
0#
#181500
b10110011 3
1#
#182000
0#
#182500
b10110100 3
1#
#183000
0#
#183500
b10110101 3
1#
#184000
0#
#184500
b10110110 3
1#
#185000
0#
#185500
b10110111 3
1#
#186000
0#
#186500
b10111000 3
1#
#187000
0#
#187500
b10111001 3
1#
#188000
0#
#188500
b10111010 3
1#
#189000
0#
#189500
b10111011 3
1#
#190000
0#
#190500
b10111100 3
1#
#191000
0#
#191500
b10111101 3
1#
#192000
0#
#192500
b10111110 3
1#
#193000
0#
#193500
b10111111 3
1#
#194000
0#
#194500
1-
b11000000 3
1#
#195000
0#
#195500
0+
02
0-
b11000001 3
1#
#196000
0#
#196500
b11000010 3
1#
#197000
0#
#197500
b11000011 3
1#
#198000
0#
#198500
b11000100 3
1#
#199000
0#
#199500
b11000101 3
1#
#200000
0#
#200500
b11000110 3
1#
#201000
0#
#201500
b11000111 3
1#
#202000
0#
#202500
b11001000 3
1#
#203000
0#
#203500
b11001001 3
1#
#204000
0#
#204500
b11001010 3
1#
#205000
0#
#205500
b11001011 3
1#
#206000
0#
#206500
b11001100 3
1#
#207000
0#
#207500
b11001101 3
1#
#208000
0#
#208500
b11001110 3
1#
#209000
0#
#209500
b11001111 3
1#
#210000
0#
#210500
b11010000 3
1#
#211000
0#
#211500
b11010001 3
1#
#212000
0#
#212500
b11010010 3
1#
#213000
0#
#213500
b11010011 3
1#
#214000
0#
#214500
b11010100 3
1#
#215000
0#
#215500
b11010101 3
1#
#216000
0#
#216500
b11010110 3
1#
#217000
0#
#217500
b11010111 3
1#
#218000
0#
#218500
b11011000 3
1#
#219000
0#
#219500
b11011001 3
1#
#220000
0#
#220500
b11011010 3
1#
#221000
0#
#221500
b11011011 3
1#
#222000
0#
#222500
b11011100 3
1#
#223000
0#
#223500
b11011101 3
1#
#224000
0#
#224500
b11011110 3
1#
#225000
0#
#225500
b11011111 3
1#
#226000
0#
#226500
b11100000 3
1#
#227000
0#
#227500
b11100001 3
1#
#228000
0#
#228500
b11100010 3
1#
#229000
0#
#229500
b11100011 3
1#
#230000
0#
#230500
b11100100 3
1#
#231000
0#
#231500
b11100101 3
1#
#232000
0#
#232500
b11100110 3
1#
#233000
0#
#233500
b11100111 3
1#
#234000
0#
#234500
b11101000 3
1#
#235000
0#
#235500
b11101001 3
1#
#236000
0#
#236500
b11101010 3
1#
#237000
0#
#237500
b11101011 3
1#
#238000
0#
#238500
b11101100 3
1#
#239000
0#
#239500
b11101101 3
1#
#240000
0#
#240500
b11101110 3
1#
#241000
0#
#241500
b11101111 3
1#
#242000
0#
#242500
b11110000 3
1#
#243000
0#
#243500
b11110001 3
1#
#244000
0#
#244500
b11110010 3
1#
#245000
0#
#245500
b11110011 3
1#
#246000
0#
#246500
b11110100 3
1#
#247000
0#
#247500
b11110101 3
1#
#248000
0#
#248500
b11110110 3
1#
#249000
0#
#249500
b11110111 3
1#
#250000
0#
#250500
b11111000 3
1#
#251000
0#
#251500
b11111001 3
1#
#252000
0#
#252500
b11111010 3
1#
#253000
0#
#253500
b11111011 3
1#
#254000
0#
#254500
b11111100 3
1#
#255000
0#
#255500
b11111101 3
1#
#256000
0#
#256500
b11111110 3
1#
#257000
0#
#257500
b11111111 3
1#
#258000
0#
#258500
1.
b0 3
1#
#259000
0#
#259500
1+
12
0.
b1 3
1#
#260000
0#
#260500
b10 3
1#
#261000
0#
#261500
b11 3
1#
#262000
0#
#262500
b100 3
1#
#263000
0#
#263500
b101 3
1#
#264000
0#
#264500
b110 3
1#
#265000
0#
#265500
b111 3
1#
#266000
0#
#266500
b1000 3
1#
#267000
0#
#267500
b1001 3
1#
#268000
0#
#268500
b1010 3
1#
#269000
0#
#269500
b1011 3
1#
#270000
0#
#270500
b1100 3
1#
#271000
0#
#271500
b1101 3
1#
#272000
0#
#272500
b1110 3
1#
#273000
0#
#273500
b1111 3
1#
#274000
0#
#274500
b10000 3
1#
#275000
0#
#275500
b10001 3
1#
#276000
0#
#276500
b10010 3
1#
#277000
0#
#277500
b10011 3
1#
#278000
0#
#278500
b10100 3
1#
#279000
0#
#279500
b10101 3
1#
#280000
0#
#280500
b10110 3
1#
#281000
0#
#281500
b10111 3
1#
#282000
0#
#282500
b11000 3
1#
#283000
0#
#283500
b11001 3
1#
#284000
0#
#284500
b11010 3
1#
#285000
0#
#285500
b11011 3
1#
#286000
0#
#286500
b11100 3
1#
#287000
0#
#287500
b11101 3
1#
#288000
0#
#288500
b11110 3
1#
#289000
0#
#289500
b11111 3
1#
#290000
0#
#290500
b100000 3
1#
#291000
0#
#291500
b100001 3
1#
#292000
0#
#292500
b100010 3
1#
#293000
0#
#293500
b100011 3
1#
#294000
0#
#294500
b100100 3
1#
#295000
0#
#295500
b100101 3
1#
#296000
0#
#296500
b100110 3
1#
#297000
0#
#297500
b100111 3
1#
#298000
0#
#298500
b101000 3
1#
#299000
0#
#299500
b101001 3
1#
#300000
0#
#300500
b101010 3
1#
#301000
0#
#301500
b101011 3
1#
#302000
0#
#302500
b101100 3
1#
#303000
0#
#303500
b101101 3
1#
#304000
0#
#304500
b101110 3
1#
#305000
0#
#305500
b101111 3
1#
#306000
0#
#306500
b110000 3
1#
#307000
0#
#307500
b110001 3
1#
#308000
0#
#308500
b110010 3
1#
#309000
0#
#309500
b110011 3
1#
#310000
0#
#310500
b110100 3
1#
#311000
0#
#311500
b110101 3
1#
#312000
0#
#312500
b110110 3
1#
#313000
0#
#313500
b110111 3
1#
#314000
0#
#314500
b111000 3
1#
#315000
0#
#315500
b111001 3
1#
#316000
0#
#316500
b111010 3
1#
#317000
0#
#317500
b111011 3
1#
#318000
0#
#318500
b111100 3
1#
#319000
0#
#319500
b111101 3
1#
#320000
0#
#320500
b111110 3
1#
#321000
0#
#321500
b111111 3
1#
#322000
0#
#322500
b1000000 3
1#
#323000
0#
#323500
b1000001 3
1#
#324000
0#
#324500
b1000010 3
1#
#325000
0#
#325500
b1000011 3
1#
#326000
0#
#326500
b1000100 3
1#
#327000
0#
#327500
b1000101 3
1#
#328000
0#
#328500
b1000110 3
1#
#329000
0#
#329500
b1000111 3
1#
#330000
0#
#330500
b1001000 3
1#
#331000
0#
#331500
b1001001 3
1#
#332000
0#
#332500
b1001010 3
1#
#333000
0#
#333500
b1001011 3
1#
#334000
0#
#334500
b1001100 3
1#
#335000
0#
#335500
b1001101 3
1#
#336000
0#
#336500
b1001110 3
1#
#337000
0#
#337500
b1001111 3
1#
#338000
0#
#338500
b1010000 3
1#
#339000
0#
#339500
b1010001 3
1#
#340000
0#
#340500
b1010010 3
1#
#341000
0#
#341500
b1010011 3
1#
#342000
0#
#342500
b1010100 3
1#
#343000
0#
#343500
b1010101 3
1#
#344000
0#
#344500
b1010110 3
1#
#345000
0#
#345500
b1010111 3
1#
#346000
0#
#346500
b1011000 3
1#
#347000
0#
#347500
b1011001 3
1#
#348000
0#
#348500
b1011010 3
1#
#349000
0#
#349500
b1011011 3
1#
#350000
0#
#350500
b1011100 3
1#
#351000
0#
#351500
b1011101 3
1#
#352000
0#
#352500
b1011110 3
1#
#353000
0#
#353500
b1011111 3
1#
#354000
0#
#354500
b1100000 3
1#
#355000
0#
#355500
b1100001 3
1#
#356000
0#
#356500
b1100010 3
1#
#357000
0#
#357500
b1100011 3
1#
#358000
0#
#358500
b1100100 3
1#
#359000
0#
#359500
b1100101 3
1#
#360000
0#
#360500
b1100110 3
1#
#361000
0#
#361500
b1100111 3
1#
#362000
0#
#362500
b1101000 3
1#
#363000
0#
#363500
b1101001 3
1#
#364000
0#
#364500
b1101010 3
1#
#365000
0#
#365500
b1101011 3
1#
#366000
0#
#366500
b1101100 3
1#
#367000
0#
#367500
b1101101 3
1#
#368000
0#
#368500
b1101110 3
1#
#369000
0#
#369500
b1101111 3
1#
#370000
0#
#370500
b1110000 3
1#
#371000
0#
#371500
b1110001 3
1#
#372000
0#
#372500
b1110010 3
1#
#373000
0#
#373500
b1110011 3
1#
#374000
0#
#374500
b1110100 3
1#
#375000
0#
#375500
b1110101 3
1#
#376000
0#
#376500
b1110110 3
1#
#377000
0#
#377500
b1110111 3
1#
#378000
0#
#378500
b1111000 3
1#
#379000
0#
#379500
b1111001 3
1#
#380000
0#
#380500
b1111010 3
1#
#381000
0#
#381500
b1111011 3
1#
#382000
0#
#382500
b1111100 3
1#
#383000
0#
#383500
b1111101 3
1#
#384000
0#
#384500
b1111110 3
1#
#385000
0#
#385500
b1111111 3
1#
#386000
0#
#386500
b10000000 3
1#
#387000
0#
#387500
b10000001 3
1#
#388000
0#
#388500
b10000010 3
1#
#389000
0#
#389500
b10000011 3
1#
#390000
0#
#390500
b10000100 3
1#
#391000
0#
#391500
b10000101 3
1#
#392000
0#
#392500
b10000110 3
1#
#393000
0#
#393500
b10000111 3
1#
#394000
0#
#394500
b10001000 3
1#
#395000
0#
#395500
b10001001 3
1#
#396000
0#
#396500
b10001010 3
1#
#397000
0#
#397500
b10001011 3
1#
#398000
0#
#398500
b10001100 3
1#
#399000
0#
#399500
b10001101 3
1#
#400000
0#
#400500
b10001110 3
1#
#401000
0#
#401500
b10001111 3
1#
#402000
0#
#402500
b10010000 3
1#
#403000
0#
#403500
b10010001 3
1#
#404000
0#
#404500
b10010010 3
1#
#405000
0#
#405500
b10010011 3
1#
#406000
0#
#406500
b10010100 3
1#
#407000
0#
#407500
b10010101 3
1#
#408000
0#
#408500
b10010110 3
1#
#409000
0#
#409500
b10010111 3
1#
#410000
0#
#410500
b10011000 3
1#
#411000
0#
#411500
b10011001 3
1#
#412000
0#
#412500
b10011010 3
1#
#413000
0#
#413500
b10011011 3
1#
#414000
0#
#414500
b10011100 3
1#
#415000
0#
#415500
b10011101 3
1#
#416000
0#
#416500
b10011110 3
1#
#417000
0#
#417500
b10011111 3
1#
#418000
0#
#418500
b10100000 3
1#
#419000
0#
#419500
b10100001 3
1#
#420000
0#
#420500
b10100010 3
1#
#421000
0#
#421500
b10100011 3
1#
#422000
0#
#422500
b10100100 3
1#
#423000
0#
#423500
b10100101 3
1#
#424000
0#
#424500
b10100110 3
1#
#425000
0#
#425500
b10100111 3
1#
#426000
0#
#426500
b10101000 3
1#
#427000
0#
#427500
b10101001 3
1#
#428000
0#
#428500
b10101010 3
1#
#429000
0#
#429500
b10101011 3
1#
#430000
0#
#430500
b10101100 3
1#
#431000
0#
#431500
b10101101 3
1#
#432000
0#
#432500
b10101110 3
1#
#433000
0#
#433500
b10101111 3
1#
#434000
0#
#434500
b10110000 3
1#
#435000
0#
#435500
b10110001 3
1#
#436000
0#
#436500
b10110010 3
1#
#437000
0#
#437500
b10110011 3
1#
#438000
0#
#438500
b10110100 3
1#
#439000
0#
#439500
b10110101 3
1#
#440000
0#
#440500
b10110110 3
1#
#441000
0#
#441500
b10110111 3
1#
#442000
0#
#442500
b10111000 3
1#
#443000
0#
#443500
b10111001 3
1#
#444000
0#
#444500
b10111010 3
1#
#445000
0#
#445500
b10111011 3
1#
#446000
0#
#446500
b10111100 3
1#
#447000
0#
#447500
b10111101 3
1#
#448000
0#
#448500
b10111110 3
1#
#449000
0#
#449500
b10111111 3
1#
#450000
0#
#450500
1-
b11000000 3
1#
#451000
0#
#451500
0+
02
0-
b11000001 3
1#
#452000
0#
#452500
b11000010 3
1#
#453000
0#
#453500
b11000011 3
1#
#454000
0#
#454500
b11000100 3
1#
#455000
0#
#455500
b11000101 3
1#
#456000
0#
#456500
b11000110 3
1#
#457000
0#
#457500
b11000111 3
1#
#458000
0#
#458500
b11001000 3
1#
#459000
0#
#459500
b11001001 3
1#
#460000
0#
#460500
b11001010 3
1#
#461000
0#
#461500
b11001011 3
1#
#462000
0#
#462500
b11001100 3
1#
#463000
0#
#463500
b11001101 3
1#
#464000
0#
#464500
b11001110 3
1#
#465000
0#
#465500
b11001111 3
1#
#466000
0#
#466500
b11010000 3
1#
#467000
0#
#467500
b11010001 3
1#
#468000
0#
#468500
b11010010 3
1#
#469000
0#
#469500
b11010011 3
1#
#470000
0#
#470500
b11010100 3
1#
#471000
0#
#471500
b11010101 3
1#
#472000
0#
#472500
b11010110 3
1#
#473000
0#
#473500
b11010111 3
1#
#474000
0#
#474500
b11011000 3
1#
#475000
0#
#475500
b11011001 3
1#
#476000
0#
#476500
b11011010 3
1#
#477000
0#
#477500
b11011011 3
1#
#478000
0#
#478500
b11011100 3
1#
#479000
0#
#479500
b11011101 3
1#
#480000
0#
#480500
b11011110 3
1#
#481000
0#
#481500
b11011111 3
1#
#482000
0#
#482500
b11100000 3
1#
#483000
0#
#483500
b11100001 3
1#
#484000
0#
#484500
b11100010 3
1#
#485000
0#
#485500
b11100011 3
1#
#486000
0#
#486500
b11100100 3
1#
#487000
0#
#487500
b11100101 3
1#
#488000
0#
#488500
b11100110 3
1#
#489000
0#
#489500
b11100111 3
1#
#490000
0#
#490500
b11101000 3
1#
#491000
0#
#491500
b11101001 3
1#
#492000
0#
#492500
b11101010 3
1#
#493000
0#
#493500
b11101011 3
1#
#494000
0#
#494500
b11101100 3
1#
#495000
0#
#495500
b11101101 3
1#
#496000
0#
#496500
b11101110 3
1#
#497000
0#
#497500
b11101111 3
1#
#498000
0#
#498500
b11110000 3
1#
#499000
0#
#499500
b11110001 3
1#
#500000
0#
#500500
b11110010 3
1#
#501000
0#
#501500
b11110011 3
1#
#502000
0#
#502500
b11110100 3
1#
#503000
0#
#503500
b11110101 3
1#
#504000
0#
#504500
b11110110 3
1#
#505000
0#
#505500
b11110111 3
1#
#506000
0#
#506500
b11111000 3
1#
#507000
0#
#507500
b11111001 3
1#
#508000
0#
#508500
b11111010 3
1#
#509000
0#
#509500
b11111011 3
1#
#510000
0#
#510500
b11111100 3
1#
#511000
0#
#511500
b11111101 3
1#
#512000
0#
#512500
b11111110 3
1#
#513000
0#
#513500
b11111111 3
1#
#514000
0#
#514500
1.
b0 3
1#
#515000
0#
#515500
1+
12
0.
b1 3
1#
#516000
0#
#516500
b10 3
1#
#517000
0#
#517500
b11 3
1#
#518000
0#
#518500
b100 3
1#
#519000
0#
#519500
b101 3
1#
#520000
0#
#520500
b110 3
1#
#521000
0#
#521500
b111 3
1#
#522000
0#
#522500
b1000 3
1#
#523000
0#
#523500
b1001 3
1#
#524000
0#
#524500
b1010 3
1#
#525000
0#
#525500
b1011 3
1#
#526000
0#
#526500
b1100 3
1#
#527000
0#
#527500
b1101 3
1#
#528000
0#
#528500
b1110 3
1#
#529000
0#
#529500
b1111 3
1#
#530000
0#
#530500
b10000 3
1#
#531000
0#
#531500
b10001 3
1#
#532000
0#
#532500
b10010 3
1#
#533000
0#
#533500
b10011 3
1#
#534000
0#
#534500
b10100 3
1#
#535000
0#
#535500
b10101 3
1#
#536000
0#
#536500
b10110 3
1#
#537000
0#
#537500
b10111 3
1#
#538000
0#
#538500
b11000 3
1#
#539000
0#
#539500
b11001 3
1#
#540000
0#
#540500
b11010 3
1#
#541000
0#
#541500
b11011 3
1#
#542000
0#
#542500
b11100 3
1#
#543000
0#
#543500
b11101 3
1#
#544000
0#
#544500
b11110 3
1#
#545000
0#
#545500
b11111 3
1#
#546000
0#
#546500
b100000 3
1#
#547000
0#
#547500
b100001 3
1#
#548000
0#
#548500
b100010 3
1#
#549000
0#
#549500
b100011 3
1#
#550000
0#
#550500
b100100 3
1#
#551000
0#
#551500
b100101 3
1#
#552000
0#
#552500
b100110 3
1#
#553000
0#
#553500
b100111 3
1#
#554000
0#
#554500
b101000 3
1#
#555000
0#
#555500
b101001 3
1#
#556000
0#
#556500
b101010 3
1#
#557000
0#
#557500
b101011 3
1#
#558000
0#
#558500
b101100 3
1#
#559000
0#
#559500
b101101 3
1#
#560000
0#
#560500
b101110 3
1#
#561000
0#
#561500
b101111 3
1#
#562000
0#
#562500
b110000 3
1#
#563000
0#
#563500
b110001 3
1#
#564000
0#
#564500
b110010 3
1#
#565000
0#
#565500
b110011 3
1#
#566000
0#
#566500
b110100 3
1#
#567000
0#
#567500
b110101 3
1#
#568000
0#
#568500
b110110 3
1#
#569000
0#
#569500
b110111 3
1#
#570000
0#
#570500
b111000 3
1#
#571000
0#
#571500
b111001 3
1#
#572000
0#
#572500
b111010 3
1#
#573000
0#
#573500
b111011 3
1#
#574000
0#
#574500
b111100 3
1#
#575000
0#
#575500
b111101 3
1#
#576000
0#
#576500
b111110 3
1#
#577000
0#
#577500
b111111 3
1#
#578000
0#
#578500
b1000000 3
1#
#579000
0#
#579500
b1000001 3
1#
#580000
0#
#580500
b1000010 3
1#
#581000
0#
#581500
b1000011 3
1#
#582000
0#
#582500
b1000100 3
1#
#583000
0#
#583500
b1000101 3
1#
#584000
0#
#584500
b1000110 3
1#
#585000
0#
#585500
b1000111 3
1#
#586000
0#
#586500
b1001000 3
1#
#587000
0#
#587500
b1001001 3
1#
#588000
0#
#588500
b1001010 3
1#
#589000
0#
#589500
b1001011 3
1#
#590000
0#
#590500
b1001100 3
1#
#591000
0#
#591500
b1001101 3
1#
#592000
0#
#592500
b1001110 3
1#
#593000
0#
#593500
b1001111 3
1#
#594000
0#
#594500
b1010000 3
1#
#595000
0#
#595500
b1010001 3
1#
#596000
0#
#596500
b1010010 3
1#
#597000
0#
#597500
b1010011 3
1#
#598000
0#
#598500
b1010100 3
1#
#599000
0#
#599500
b1010101 3
1#
#600000
0#
#600500
b1010110 3
1#
#601000
0#
#601500
b1010111 3
1#
#602000
0#
#602500
b1011000 3
1#
#603000
0#
#603500
b1011001 3
1#
#604000
0#
#604500
b1011010 3
1#
#605000
0#
#605500
b1011011 3
1#
#606000
0#
#606500
b1011100 3
1#
#607000
0#
#607500
b1011101 3
1#
#608000
0#
#608500
b1011110 3
1#
#609000
0#
#609500
b1011111 3
1#
#610000
0#
#610500
b1100000 3
1#
#611000
0#
#611500
b1100001 3
1#
#612000
0#
#612500
b1100010 3
1#
#613000
0#
#613500
b1100011 3
1#
#614000
0#
#614500
b1100100 3
1#
#615000
0#
#615500
b1100101 3
1#
#616000
0#
#616500
b1100110 3
1#
#617000
0#
#617500
b1100111 3
1#
#618000
0#
#618500
b1101000 3
1#
#619000
0#
#619500
b1101001 3
1#
#620000
0#
#620500
b1101010 3
1#
#621000
0#
#621500
b1101011 3
1#
#622000
0#
#622500
b1101100 3
1#
#623000
0#
#623500
b1101101 3
1#
#624000
0#
#624500
b1101110 3
1#
#625000
0#
#625500
b1101111 3
1#
#626000
0#
#626500
b1110000 3
1#
#627000
0#
#627500
b1110001 3
1#
#628000
0#
#628500
b1110010 3
1#
#629000
0#
#629500
b1110011 3
1#
#630000
0#
