18_axi_sram/rtl/sram.v
module sram (
    clk,
    cs,
    we,
    rstn,
    io_addr,
    io_din,
    io_dout
);

parameter MEMSIZE = 8;
parameter WORDSIZE= 32;

input wire clk,cs,we,rstn;
input wire [WORDSIZE - 1 : 0] io_din;
input wire [MEMSIZE - 1 : 0] io_addr;
output reg [WORDSIZE - 1 : 0] io_dout;

reg [WORDSIZE - 1 : 0] ram [MEMSIZE -1 : 0];

integer i ;

always @(posedge clk or negedge rstn) begin
    if(~rstn)
        for(i = 0 ; i< MEMSIZE ; i=i+1) begin
            ram[i] <= 'd0;
        end
    else if(cs) begin
            if(we) begin
                ram[io_addr] <= io_din;
                io_dout <= 'd0;
            end
            else
                io_dout <= ram[io_addr];
    end
end
    
endmodule

18_axi_sram/rtl/axi_sram.v
module axi_sram (
    //--- Global signals ---//
    ACLK,
    ARESETn,

    //--- Write address channel signals ---//
    AWID,
    AWADDR,
    AWLEN,
    AWSIZE,
    AWBURST,
    //AWLOCK, //AXI3 ONLY
    AWCACHE,
    AWPROT,
    AWQOS, //AXI4 ONLY
    AWREGION, //AXI4 ONLY
    AWUSER, //AXI4 ONLY , USER IDENTIFY

    AWVALID,
    AWREADY,

    //--- Write data channel signals ---//
    WID,
    WDATA,
    WSTRB,
    WLAST,
    WUSER,

    WVALID,
    WREADY,

    //--- Write response channel signals ---//
    BID,
    BRESP,
    BUSER,

    BVALID,
    BREADY,

    //--- Read address channel signals ---//
    ARID,
    ARADDR,
    ARLEN,
    ARSIZE,
    ARBURST,
    ARLOCK,
    ARCACHE,
    ARPROT,
    ARQOS,
    ARREGION,
    ARUSER,

    ARVALID,
    ARREADY,

    //--- Read data channel signals ---//
    RID,
    RDATA,
    RRESP,
    RLAST,
    RUSER,

    RVALID,
    RREADY

    //--- Low-power interface signals ---//
);

parameter START_ADDR = 'b0; //定义该组件的起始地址
parameter ADDR_RANGE = 'hFFF + 1; //定义该组件的地址范围

parameter AxID_WIDTH = 3;
parameter AxADDR_WIDTH = 32;
parameter AxLEN_WIDTH = 8;
parameter AxSIZE_WIDTH = 3;
parameter AxBURST_WIDTH = 2;
parameter AxCACHE_WIDTH = 4;
parameter AxPROT_WIDTH = 3;
parameter AxQOS_WIDTH = 4; //AXI4 ONLY
parameter AxREGION_WIDTH = 4; //AXI4 ONLY
parameter USER_WIDTH = 2; //AXI4 ONLY , USER IDENTIFY
parameter BEAT_WIDTH = 8; //一个BEAT,占据一个地址
parameter DATA_WIDTH = BEAT_WIDTH*128; //128 byte , 1024 bits

parameter RESP_WIDTH = 2;
//--- Global signals ---//
input wire ACLK,ARESETn;

//--- Write address channel signals ---//
input wire [AxID_WIDTH - 1 : 0] AWID; // master ID
input wire [AxADDR_WIDTH - 1 : 0] AWADDR; // 初始地址 slave 的地址分配是每 4KB 一个 slave， 也就是 0~0xFFF, 注意不要跨过4KB 边界，否则会访问到下一个slave
input wire [AxLEN_WIDTH - 1 : 0] AWLEN; // 要接收的burst的数量 也就是要用几个周期来接收burst
input wire [AxSIZE_WIDTH - 1 : 0] AWSIZE; // 要接收的burst的长度（一个burst占多少字节）
input wire [AxBURST_WIDTH - 1 : 0] AWBURST; // 要接收的burst类型 FIXED 地址固定 INCR 地址增加 WRAP 地址循环增加
//input wire AWLOCK ;
input wire [AxCACHE_WIDTH - 1 : 0] AWCACHE;
input wire [AxPROT_WIDTH - 1 : 0] AWPROT;
input wire [AxQOS_WIDTH - 1 : 0] AWQOS; //AXI4 ONLY
input wire [AxREGION_WIDTH - 1 : 0] AWREGION; //AXI4 ONLY
input wire [USER_WIDTH - 1 : 0] AWUSER; //AXI4 ONLY
input wire AWVALID;
output reg AWREADY;

//--- Write data channel signals ---//
input wire [AxID_WIDTH - 1 : 0] WID; //AXI3 ONLY
input wire [BEAT_WIDTH - 1 : 0] WDATA;
input wire WSTRB;
input wire WLAST;
input wire [USER_WIDTH - 1 : 0] WUSER;
input wire WVALID;
output reg WREADY;


//---Write response channel signals ---//
output reg [AxID_WIDTH - 1 : 0] BID;
output reg [RESP_WIDTH - 1 : 0] BRESP;
output reg [USER_WIDTH - 1 : 0] BUSER; //AXI4 ONLY
output reg BVALID;
input wire BREADY;


//--- Read address channel signals ---//
input wire [AxID_WIDTH - 1 : 0] ARID;
input wire [AxADDR_WIDTH - 1 : 0] ARADDR;
input wire [AxLEN_WIDTH - 1 : 0] ARLEN;
input wire [AxSIZE_WIDTH - 1 : 0] ARSIZE;
input wire [AxBURST_WIDTH - 1 : 0] ARBURST;
input wire ARLOCK;
input wire [AxCACHE_WIDTH - 1 : 0] ARCACHE;
input wire [AxPROT_WIDTH - 1 : 0] ARPROT;
input wire [AxQOS_WIDTH - 1 : 0] ARQOS; //AXI4 ONLY
input wire [AxREGION_WIDTH - 1 : 0] ARREGION; //AXI4 ONLY
input wire [USER_WIDTH - 1 : 0] ARUSER; //AXI4 ONLY
input wire ARVALID;
output reg ARREADY;

//--- Read data channel signals ---//
output reg [AxID_WIDTH - 1 : 0] RID;
output reg [BEAT_WIDTH - 1 : 0] RDATA;
output reg [RESP_WIDTH - 1 : 0] RRESP;
output reg RLAST;
output reg [USER_WIDTH - 1 : 0] RUSER; //AXI4 ONLY
output reg RVALID;
input wire RREADY;

//--- Burst type decode ---//
localparam [AxBURST_WIDTH - 1:0]
FIXED  = 2'b00,
INCR = 2'b01,
WRAP = 2'b10;

//---xRESP decode ---//
localparam [RESP_WIDTH - 1:0]
OKAY = 2'b00,
EXOKAY = 2'b01,
SLVERR = 2'b10,
DECERR = 2'b11;
 
//--- machine state decode ---//
localparam [1:0]
IDLE = 2'b00,
W_DATA = 2'b01,
W_DATA_LAST = 2'b10,
R_DATA = 2'b11;

//--- state machine variable ---//
reg [1:0] state_current;
reg [1:0] state_next;

//--- 1. state transfer block ---//
always @(posedge ACLK or negedge ARESETn) 
    if(~ARESETn) begin
        state_current <= IDLE;
        //state_next <= IDLE;
    end else
        state_current <= state_next;

//--- 2. state switch block ---//
always @(*) begin
    case (state_current)
        IDLE : begin
                if(AWVALID && AWREADY)
                    state_next = W_DATA;
                else if(ARVALID & ARREADY)
                    state_next = R_DATA;
                else
                    state_next = IDLE;
                end

        W_DATA : begin
                    if(WVALID && WREADY)
                        //if(WLAST)
                        if(counter == AxLEN - 1) begin
                            state_next = W_DATA_LAST;
                        end
                        else
                            state_next = W_DATA;
                    else
                        state_next = W_DATA;
                end

        W_DATA_LAST : begin
                        if(BVALID && BREADY)
                            state_next = IDLE;
                        else
                            state_next = W_DATA_LAST;
                    end


        default : begin                   //R_DATA
                    if(RVALID && RREADY)
                        if(counter == AxLEN - 1) begin
                            state_next = IDLE;
                            RLAST = 'b1;
                        end
                        else
                            state_next = R_DATA;
                    else
                        state_next = R_DATA;
                end
    endcase
end


//--- 3. state response block ---//    
reg [AxID_WIDTH - 1 : 0] AxID;
reg [AxADDR_WIDTH - 1 : 0] AxADDR; //初始地址
reg [AxLEN_WIDTH - 1 : 0] AxLEN; //burst 长度，也就是经历几个周期data channel 才会关闭
reg [AxSIZE_WIDTH - 1 : 0] AxSIZE; //每个burst的大小，也就是一次地址增加几个字节
reg [AxBURST_WIDTH - 1 : 0] AxBURST; //burst传输的类型，FIXED, INCR , WRAP

reg s0_cs,s0_we;
reg [AxADDR_WIDTH - 1 : 0] s0_ADDR;
reg [BEAT_WIDTH - 1 : 0] s0_din;
wire [BEAT_WIDTH - 1 : 0] s0_dout;

reg [AxLEN_WIDTH - 1 : 0] counter; //记录读取数据的次数，最大值为AxLEN - 1;

reg [RESP_WIDTH - 1 : 0] resp;

always @(posedge ACLK or negedge ARESETn) begin
    if(~ARESETn) begin
        AxID <= 'b0;
        AxADDR <= 'b0;
        AxLEN <= 'b0;
        AxSIZE <= 'b0;
        AxBURST <= 'b0;

        AWREADY <= 1'b0;
        WREADY <= 1'b0;
        BVALID <=1'b0;

        ARREADY <= 1'b0;
        RVALID <= 1'b0;

        s0_cs <= 1'b0;
        s0_we <= 1'b0;

        BID <= 'b0;
        BRESP <= 'b0;
        BUSER <= 'b0;
        BVALID <= 'b1;

        RID <= 1'b0;
        RVALID <= 1'b0;
        RLAST <= 1'b0;

        counter <= 'b0;

        resp <= OKAY;
    end else begin
        case (state_current)
            IDLE : begin
                    s0_cs <= 1'b0;

                    BVALID <= 1'b0;
                    RVALID <= 1'b0;
                    RLAST <= 1'b0;

                    counter <= 'b0;

                    if(AWVALID) begin
                        if((AWADDR >= START_ADDR) && (AWADDR + AWLEN*AWSIZE < ADDR_RANGE)) begin
                            AxID <= AWID;
                            AxADDR <= AWADDR;
                            AxLEN <= AWLEN;
                            AxSIZE <= AWSIZE;
                            AxBURST <= AWBURST;
                            AWREADY <= 1'b1;
                        end else
                            resp <= SLVERR;
                            //$error("Error : Write ADDR out of range");
                            //$finish;
                        end
                    else if(ARVALID) begin
                            if((ARADDR >= START_ADDR) && (ARADDR + ARLEN*ARSIZE < ADDR_RANGE)) begin
                                AxID <= ARID;
                                AxADDR <= ARADDR;
                                AxLEN <= ARLEN;
                                AxSIZE <= ARSIZE;
                                AxBURST <= ARBURST;
                                ARREADY <= 1'b1;
                            end else
                                resp <= SLVERR;
                                //$error("Error : Read ADDR out or range");
                                //$finish;
                        end
                end
            W_DATA : begin

                        AWREADY <= 1'b0;
                        WREADY <= 1'b0;

                        if(WVALID) begin
                            s0_cs <= 1'b1;
                            s0_we <= 1'b1;
                            s0_ADDR <= AxADDR;
                            s0_din <= WDATA;

                            WREADY <= 1'b1;
                            counter <= counter + 1;

                            case(AxBURST)
                                FIXED : AxADDR <= AxADDR;
                                INCR : AxADDR <= AxADDR + 2**AxSIZE;
                                WRAP : AxADDR <= AxADDR + 2**AxSIZE; //？？？ 未写WRAP逻辑
                                default : ;// $error("Error : BURST type error!");
                            endcase

                        end 
                    end
            W_DATA_LAST : begin

                            WREADY <= 1'b0;
                            s0_cs <= 1'b0;
                            s0_we <= 1'b0;
                            counter <= 'b0;

                            BID <= AxID;
                            BRESP <= resp;
                            BUSER <= 'b0;

                            BVALID <= 1'b1;
                        end

            default : begin
                
                        ARREADY <= 1'b0;

                        RID <= AxID;
                        s0_cs <= 1'b1;
                        s0_we <= 1'b0;
                        s0_ADDR <= AxADDR;
                        RDATA <=  s0_dout;
                        RRESP <= resp;
                        RUSER <= 'b0;

                        RVALID <= 1'b1;

                        case(AxBURST)
                            FIXED : AxADDR <= AxADDR;
                            INCR : AxADDR <= AxADDR + 2**AxSIZE;
                            WRAP : AxADDR <= AxADDR + 2**AxSIZE; //？？？ 未写WRAP逻辑
                            default : ;//$error("Error : BURST type error!");
                        endcase

                        counter <= counter + 1;
                        // if(counter == AxLEN - 1)
                        //     RLAST <= 1'b1;
                        // else
                        //     counter <= counter + 1;
                    end
        endcase
    end
end


sram #(
    .MEMSIZE(100), //一共4096个地址
    .WORDSIZE(BEAT_WIDTH) //每个地址下可以存1个字节，也就是8bits
)
s0(
    .clk(ACLK),
    .cs(s0_cs),
    .we(s0_we),
    .rstn(ARESETn),
    .io_addr(s0_ADDR),
    .io_din(s0_din),
    .io_dout(s0_dout)
);

	initial begin
		$dumpfile("axi_sram_test.vcd");
		$dumpvars(0,axi_sram);
	end


endmodule

18_axi_sram/axi_sram_test.vcd
$date
	Mon May 16 23:18:14 2022
$end
$version
	Icarus Verilog
$end
$timescale
	1ps
$end
$scope module axi_sram $end
$var wire 1 ! ACLK $end
$var wire 32 " ARADDR [31:0] $end
$var wire 2 # ARBURST [1:0] $end
$var wire 4 $ ARCACHE [3:0] $end
$var wire 1 % ARESETn $end
$var wire 3 & ARID [2:0] $end
$var wire 8 ' ARLEN [7:0] $end
$var wire 1 ( ARLOCK $end
$var wire 3 ) ARPROT [2:0] $end
$var wire 4 * ARQOS [3:0] $end
$var wire 4 + ARREGION [3:0] $end
$var wire 3 , ARSIZE [2:0] $end
$var wire 2 - ARUSER [1:0] $end
$var wire 1 . ARVALID $end
$var wire 32 / AWADDR [31:0] $end
$var wire 2 0 AWBURST [1:0] $end
$var wire 4 1 AWCACHE [3:0] $end
$var wire 3 2 AWID [2:0] $end
$var wire 8 3 AWLEN [7:0] $end
$var wire 3 4 AWPROT [2:0] $end
$var wire 4 5 AWQOS [3:0] $end
$var wire 4 6 AWREGION [3:0] $end
$var wire 3 7 AWSIZE [2:0] $end
$var wire 2 8 AWUSER [1:0] $end
$var wire 1 9 AWVALID $end
$var wire 1 : BREADY $end
$var wire 1 ; RREADY $end
$var wire 8 < WDATA [7:0] $end
$var wire 3 = WID [2:0] $end
$var wire 1 > WLAST $end
$var wire 1 ? WSTRB $end
$var wire 2 @ WUSER [1:0] $end
$var wire 1 A WVALID $end
$var wire 8 B s0_dout [7:0] $end
$var reg 1 C ARREADY $end
$var reg 1 D AWREADY $end
$var reg 32 E AxADDR [31:0] $end
$var reg 2 F AxBURST [1:0] $end
$var reg 3 G AxID [2:0] $end
$var reg 8 H AxLEN [7:0] $end
$var reg 3 I AxSIZE [2:0] $end
$var reg 3 J BID [2:0] $end
$var reg 2 K BRESP [1:0] $end
$var reg 2 L BUSER [1:0] $end
$var reg 1 M BVALID $end
$var reg 8 N RDATA [7:0] $end
$var reg 3 O RID [2:0] $end
$var reg 1 P RLAST $end
$var reg 2 Q RRESP [1:0] $end
$var reg 2 R RUSER [1:0] $end
$var reg 1 S RVALID $end
$var reg 1 T WREADY $end
$var reg 8 U counter [7:0] $end
$var reg 2 V resp [1:0] $end
$var reg 32 W s0_ADDR [31:0] $end
$var reg 1 X s0_cs $end
$var reg 8 Y s0_din [7:0] $end
$var reg 1 Z s0_we $end
$var reg 2 [ state_current [1:0] $end
$var reg 2 \ state_next [1:0] $end
$scope module s0 $end
$var wire 1 ! clk $end
$var wire 1 X cs $end
$var wire 100 ] io_addr [99:0] $end
$var wire 8 ^ io_din [7:0] $end
$var wire 1 % rstn $end
$var wire 1 Z we $end
$var reg 8 _ io_dout [7:0] $end
$var integer 32 ` i [31:0] $end
$upscope $end
$upscope $end
$enddefinitions $end
#0
$dumpvars
bx `
bx _
bx ^
b0xxxxxxxxxxxxxxxxxxxxxxxxxxxxxxxx ]
b11 \
b11 [
0Z
bx Y
1X
bx W
bx V
bx U
xT
1S
b0 R
bx Q
xP
bx O
bx N
xM
bx L
bx K
bx J
bx I
bx H
bx G
bx F
bx E
xD
0C
bx B
zA
bz @
z?
z>
bz =
bz <
z;
z:
z9
bz 8
bz 7
bz 6
bz 5
bz 4
bz 3
bz 2
bz 1
bz 0
bz /
z.
bz -
bz ,
bz +
bz *
bz )
z(
bz '
bz &
1%
bz $
bz #
bz "
1!
$end
#500
b0 \
b0 V
b0 U
0P
b0 O
b0 L
b0 K
b0 J
0X
0S
1M
0T
0D
b0 F
b0 I
b0 H
b0 E
b0 G
b0 [
b1100100 `
0!
0%
#1000
0M
1%
1!
#1500
0!
#2000
b1 2
b0 /
b1000 3
b0 7
b1 0
19
1!
#2500
0!
#3000
b1 \
1D
b1 F
b1000 H
b1 G
1!
#3500
0!
#4000
b1 [
1!
#4500
0!
#5000
09
0D
1!
#5500
0!
#6000
b1 =
b11 <
1A
1!
#6500
0!
#7000
b1 E
b1 U
1T
b11 Y
b11 ^
b0 ]
b0 W
1Z
1X
1!
#7500
0!
#8000
b10 E
b10 U
b1 ]
b1 W
1T
b0 B
b0 _
1!
#8500
0!
#9000
b11 E
b11 U
b10 ]
b10 W
1T
1!
#9500
0!
#10000
b101 <
b100 E
b100 U
b11 ]
b11 W
1T
1!
#10500
0!
#11000
b0 <
b101 E
b101 U
b101 Y
b101 ^
b100 ]
b100 W
1T
1!
#11500
0!
#12000
b10 <
b110 E
b110 U
b0 Y
b0 ^
b101 ]
b101 W
1T
1!
#12500
0!
#13000
b0 <
b10 \
b111 E
b111 U
b10 Y
b10 ^
b110 ]
b110 W
1T
1!
#13500
0!
#14000
b11 <
1>
b1000 E
b1000 U
b0 Y
b0 ^
b111 ]
b111 W
1T
b10 [
1!
#14500
0!
#15000
b0 \
0A
0>
1:
1M
b1 J
b0 U
0Z
0X
0T
1!
#15500
0!
#16000
0:
b0 [
1!
#16500
0!
#17000
0M
1!
#17500
0!
#18000
b1 &
b0 "
b1000 '
b0 ,
b1 #
1.
1!
#18500
0!
#19000
b11 \
1C
b0 E
1!
#19500
0!
#20000
b11 [
1!
#20500
0!
#21000
0.
b1 U
b1 E
1S
b0 Q
b0 N
b0 ]
b0 W
1X
b1 O
0C
1!
#21500
0!
#22000
1;
b10 U
b10 E
b1 ]
b1 W
b11 B
b11 _
1!
#22500
0!
#23000
b11 U
b11 E
b11 N
b10 ]
b10 W
1!
#23500
0!
#24000
b100 U
b100 E
b11 ]
b11 W
1!
#24500
0!
#25000
b101 U
b101 E
b100 ]
b100 W
1!
#25500
0!
#26000
b110 U
b110 E
b101 ]
b101 W
b101 B
b101 _
1!
#26500
0!
#27000
1P
b0 \
b0 B
b0 _
b111 U
b111 E
b101 N
b110 ]
b110 W
1!
#27500
0!
#28000
b1000 U
b1000 E
b0 N
b111 ]
b111 W
b0 [
b10 B
b10 _
1!
#28500
0!
#29000
b0 B
b0 _
b0 U
0P
0S
0X
1!
