streamTest/streamArbiter/lowerFirst/streamArbiterLowerFirst.v
// Generator : SpinalHDL v1.7.0a    git head : 150a9b9067020722818dfb17df4a23ac712a7af8
// Component : streamArbiterLowerFirst
// Git hash  : 3a903e741cbbe310a98c75dc1ebbd289cb1c87a4

`timescale 1ns/1ps

module streamArbiterLowerFirst (
  input               io_s_in_0_valid,
  output              io_s_in_0_ready,
  input      [31:0]   io_s_in_0_payload,
  input               io_s_in_1_valid,
  output              io_s_in_1_ready,
  input      [31:0]   io_s_in_1_payload,
  input               io_s_in_2_valid,
  output              io_s_in_2_ready,
  input      [31:0]   io_s_in_2_payload,
  input               io_s_in_3_valid,
  output              io_s_in_3_ready,
  input      [31:0]   io_s_in_3_payload,
  output              io_m_out_valid,
  input               io_m_out_ready,
  output     [31:0]   io_m_out_payload,
  input               clk,
  input               reset
);

  wire                streamArbiter_1_io_output_ready;
  wire                streamArbiter_1_io_inputs_0_ready;
  wire                streamArbiter_1_io_inputs_1_ready;
  wire                streamArbiter_1_io_inputs_2_ready;
  wire                streamArbiter_1_io_inputs_3_ready;
  wire                streamArbiter_1_io_output_valid;
  wire       [31:0]   streamArbiter_1_io_output_payload;
  wire       [1:0]    streamArbiter_1_io_chosen;
  wire       [3:0]    streamArbiter_1_io_chosenOH;
  wire                streamArbiter_1_io_output_s2mPipe_valid;
  reg                 streamArbiter_1_io_output_s2mPipe_ready;
  wire       [31:0]   streamArbiter_1_io_output_s2mPipe_payload;
  reg                 streamArbiter_1_io_output_rValid;
  reg        [31:0]   streamArbiter_1_io_output_rData;
  wire                streamArbiter_1_io_output_s2mPipe_m2sPipe_valid;
  wire                streamArbiter_1_io_output_s2mPipe_m2sPipe_ready;
  wire       [31:0]   streamArbiter_1_io_output_s2mPipe_m2sPipe_payload;
  reg                 streamArbiter_1_io_output_s2mPipe_rValid;
  reg        [31:0]   streamArbiter_1_io_output_s2mPipe_rData;
  wire                when_Stream_l368;

  StreamArbiter streamArbiter_1 (
    .io_inputs_0_valid   (io_s_in_0_valid                        ), //i
    .io_inputs_0_ready   (streamArbiter_1_io_inputs_0_ready      ), //o
    .io_inputs_0_payload (io_s_in_0_payload[31:0]                ), //i
    .io_inputs_1_valid   (io_s_in_1_valid                        ), //i
    .io_inputs_1_ready   (streamArbiter_1_io_inputs_1_ready      ), //o
    .io_inputs_1_payload (io_s_in_1_payload[31:0]                ), //i
    .io_inputs_2_valid   (io_s_in_2_valid                        ), //i
    .io_inputs_2_ready   (streamArbiter_1_io_inputs_2_ready      ), //o
    .io_inputs_2_payload (io_s_in_2_payload[31:0]                ), //i
    .io_inputs_3_valid   (io_s_in_3_valid                        ), //i
    .io_inputs_3_ready   (streamArbiter_1_io_inputs_3_ready      ), //o
    .io_inputs_3_payload (io_s_in_3_payload[31:0]                ), //i
    .io_output_valid     (streamArbiter_1_io_output_valid        ), //o
    .io_output_ready     (streamArbiter_1_io_output_ready        ), //i
    .io_output_payload   (streamArbiter_1_io_output_payload[31:0]), //o
    .io_chosen           (streamArbiter_1_io_chosen[1:0]         ), //o
    .io_chosenOH         (streamArbiter_1_io_chosenOH[3:0]       ), //o
    .clk                 (clk                                    ), //i
    .reset               (reset                                  )  //i
  );
  assign io_s_in_0_ready = streamArbiter_1_io_inputs_0_ready;
  assign io_s_in_1_ready = streamArbiter_1_io_inputs_1_ready;
  assign io_s_in_2_ready = streamArbiter_1_io_inputs_2_ready;
  assign io_s_in_3_ready = streamArbiter_1_io_inputs_3_ready;
  assign streamArbiter_1_io_output_ready = (! streamArbiter_1_io_output_rValid);
  assign streamArbiter_1_io_output_s2mPipe_valid = (streamArbiter_1_io_output_valid || streamArbiter_1_io_output_rValid);
  assign streamArbiter_1_io_output_s2mPipe_payload = (streamArbiter_1_io_output_rValid ? streamArbiter_1_io_output_rData : streamArbiter_1_io_output_payload);
  always @(*) begin
    streamArbiter_1_io_output_s2mPipe_ready = streamArbiter_1_io_output_s2mPipe_m2sPipe_ready;
    if(when_Stream_l368) begin
      streamArbiter_1_io_output_s2mPipe_ready = 1'b1;
    end
  end

  assign when_Stream_l368 = (! streamArbiter_1_io_output_s2mPipe_m2sPipe_valid);
  assign streamArbiter_1_io_output_s2mPipe_m2sPipe_valid = streamArbiter_1_io_output_s2mPipe_rValid;
  assign streamArbiter_1_io_output_s2mPipe_m2sPipe_payload = streamArbiter_1_io_output_s2mPipe_rData;
  assign io_m_out_valid = streamArbiter_1_io_output_s2mPipe_m2sPipe_valid;
  assign streamArbiter_1_io_output_s2mPipe_m2sPipe_ready = io_m_out_ready;
  assign io_m_out_payload = streamArbiter_1_io_output_s2mPipe_m2sPipe_payload;
  always @(posedge clk or posedge reset) begin
    if(reset) begin
      streamArbiter_1_io_output_rValid <= 1'b0;
      streamArbiter_1_io_output_s2mPipe_rValid <= 1'b0;
    end else begin
      if(streamArbiter_1_io_output_valid) begin
        streamArbiter_1_io_output_rValid <= 1'b1;
      end
      if(streamArbiter_1_io_output_s2mPipe_ready) begin
        streamArbiter_1_io_output_rValid <= 1'b0;
      end
      if(streamArbiter_1_io_output_s2mPipe_ready) begin
        streamArbiter_1_io_output_s2mPipe_rValid <= streamArbiter_1_io_output_s2mPipe_valid;
      end
    end
  end

  always @(posedge clk) begin
    if(streamArbiter_1_io_output_ready) begin
      streamArbiter_1_io_output_rData <= streamArbiter_1_io_output_payload;
    end
    if(streamArbiter_1_io_output_s2mPipe_ready) begin
      streamArbiter_1_io_output_s2mPipe_rData <= streamArbiter_1_io_output_s2mPipe_payload;
    end
  end


endmodule

module StreamArbiter (
  input               io_inputs_0_valid,
  output              io_inputs_0_ready,
  input      [31:0]   io_inputs_0_payload,
  input               io_inputs_1_valid,
  output              io_inputs_1_ready,
  input      [31:0]   io_inputs_1_payload,
  input               io_inputs_2_valid,
  output              io_inputs_2_ready,
  input      [31:0]   io_inputs_2_payload,
  input               io_inputs_3_valid,
  output              io_inputs_3_ready,
  input      [31:0]   io_inputs_3_payload,
  output              io_output_valid,
  input               io_output_ready,
  output     [31:0]   io_output_payload,
  output     [1:0]    io_chosen,
  output     [3:0]    io_chosenOH,
  input               clk,
  input               reset
);

  wire       [3:0]    _zz__zz_maskProposal_1_1;
  reg        [31:0]   _zz_io_output_payload_2;
  wire       [1:0]    _zz_io_output_payload_3;
  reg                 locked;
  wire                maskProposal_0;
  wire                maskProposal_1;
  wire                maskProposal_2;
  wire                maskProposal_3;
  reg                 maskLocked_0;
  reg                 maskLocked_1;
  reg                 maskLocked_2;
  reg                 maskLocked_3;
  wire                maskRouted_0;
  wire                maskRouted_1;
  wire                maskRouted_2;
  wire                maskRouted_3;
  wire       [3:0]    _zz_maskProposal_1;
  wire       [3:0]    _zz_maskProposal_1_1;
  wire                io_output_fire;
  wire                _zz_io_output_payload;
  wire                _zz_io_output_payload_1;
  wire                _zz_io_chosen;
  wire                _zz_io_chosen_1;
  wire                _zz_io_chosen_2;

  assign _zz__zz_maskProposal_1_1 = (_zz_maskProposal_1 - 4'b0001);
  assign _zz_io_output_payload_3 = {_zz_io_output_payload_1,_zz_io_output_payload};
  always @(*) begin
    case(_zz_io_output_payload_3)
      2'b00 : _zz_io_output_payload_2 = io_inputs_0_payload;
      2'b01 : _zz_io_output_payload_2 = io_inputs_1_payload;
      2'b10 : _zz_io_output_payload_2 = io_inputs_2_payload;
      default : _zz_io_output_payload_2 = io_inputs_3_payload;
    endcase
  end

  assign maskRouted_0 = (locked ? maskLocked_0 : maskProposal_0);
  assign maskRouted_1 = (locked ? maskLocked_1 : maskProposal_1);
  assign maskRouted_2 = (locked ? maskLocked_2 : maskProposal_2);
  assign maskRouted_3 = (locked ? maskLocked_3 : maskProposal_3);
  assign _zz_maskProposal_1 = {io_inputs_3_valid,{io_inputs_2_valid,{io_inputs_1_valid,io_inputs_0_valid}}};
  assign _zz_maskProposal_1_1 = (_zz_maskProposal_1 & (~ _zz__zz_maskProposal_1_1));
  assign maskProposal_0 = io_inputs_0_valid;
  assign maskProposal_1 = _zz_maskProposal_1_1[1];
  assign maskProposal_2 = _zz_maskProposal_1_1[2];
  assign maskProposal_3 = _zz_maskProposal_1_1[3];
  assign io_output_fire = (io_output_valid && io_output_ready);
  assign io_output_valid = ((((io_inputs_0_valid && maskRouted_0) || (io_inputs_1_valid && maskRouted_1)) || (io_inputs_2_valid && maskRouted_2)) || (io_inputs_3_valid && maskRouted_3));
  assign _zz_io_output_payload = (maskRouted_1 || maskRouted_3);
  assign _zz_io_output_payload_1 = (maskRouted_2 || maskRouted_3);
  assign io_output_payload = _zz_io_output_payload_2;
  assign io_inputs_0_ready = (maskRouted_0 && io_output_ready);
  assign io_inputs_1_ready = (maskRouted_1 && io_output_ready);
  assign io_inputs_2_ready = (maskRouted_2 && io_output_ready);
  assign io_inputs_3_ready = (maskRouted_3 && io_output_ready);
  assign io_chosenOH = {maskRouted_3,{maskRouted_2,{maskRouted_1,maskRouted_0}}};
  assign _zz_io_chosen = io_chosenOH[3];
  assign _zz_io_chosen_1 = (io_chosenOH[1] || _zz_io_chosen);
  assign _zz_io_chosen_2 = (io_chosenOH[2] || _zz_io_chosen);
  assign io_chosen = {_zz_io_chosen_2,_zz_io_chosen_1};
  always @(posedge clk or posedge reset) begin
    if(reset) begin
      locked <= 1'b0;
    end else begin
      if(io_output_valid) begin
        locked <= 1'b1;
      end
      if(io_output_fire) begin
        locked <= 1'b0;
      end
    end
  end

  always @(posedge clk) begin
    if(io_output_valid) begin
      maskLocked_0 <= maskRouted_0;
      maskLocked_1 <= maskRouted_1;
      maskLocked_2 <= maskRouted_2;
      maskLocked_3 <= maskRouted_3;
    end
  end
  
  initial begin
    $dumpfile("streamArbiterLowerFirst_test.vcd");
    $dumpvars(0, streamArbiterLowerFirst);
  end


endmodule

streamTest/streamArbiter/lowerFirst/streamArbiterLowerFirst_test.vcd
$date
	Mon May 30 14:08:33 2022
$end
$version
	Icarus Verilog
$end
$timescale
	1ps
$end
$scope module streamArbiterLowerFirst $end
$var wire 1 ! clk $end
$var wire 32 " io_m_out_payload [31:0] $end
$var wire 1 # io_m_out_ready $end
$var wire 1 $ io_m_out_valid $end
$var wire 32 % io_s_in_0_payload [31:0] $end
$var wire 1 & io_s_in_0_ready $end
$var wire 1 ' io_s_in_0_valid $end
$var wire 32 ( io_s_in_1_payload [31:0] $end
$var wire 1 ) io_s_in_1_ready $end
$var wire 1 * io_s_in_1_valid $end
$var wire 32 + io_s_in_2_payload [31:0] $end
$var wire 1 , io_s_in_2_ready $end
$var wire 1 - io_s_in_2_valid $end
$var wire 32 . io_s_in_3_payload [31:0] $end
$var wire 1 / io_s_in_3_ready $end
$var wire 1 0 io_s_in_3_valid $end
$var wire 1 1 reset $end
$var wire 1 2 streamArbiter_1_io_output_s2mPipe_m2sPipe_ready $end
$var wire 1 3 streamArbiter_1_io_output_s2mPipe_valid $end
$var wire 1 4 when_Stream_l368 $end
$var wire 1 5 streamArbiter_1_io_output_valid $end
$var wire 32 6 streamArbiter_1_io_output_s2mPipe_payload [31:0] $end
$var wire 1 7 streamArbiter_1_io_output_s2mPipe_m2sPipe_valid $end
$var wire 32 8 streamArbiter_1_io_output_s2mPipe_m2sPipe_payload [31:0] $end
$var wire 1 9 streamArbiter_1_io_output_ready $end
$var wire 32 : streamArbiter_1_io_output_payload [31:0] $end
$var wire 1 ; streamArbiter_1_io_inputs_3_ready $end
$var wire 1 < streamArbiter_1_io_inputs_2_ready $end
$var wire 1 = streamArbiter_1_io_inputs_1_ready $end
$var wire 1 > streamArbiter_1_io_inputs_0_ready $end
$var wire 4 ? streamArbiter_1_io_chosenOH [3:0] $end
$var wire 2 @ streamArbiter_1_io_chosen [1:0] $end
$var reg 32 A streamArbiter_1_io_output_rData [31:0] $end
$var reg 1 B streamArbiter_1_io_output_rValid $end
$var reg 32 C streamArbiter_1_io_output_s2mPipe_rData [31:0] $end
$var reg 1 7 streamArbiter_1_io_output_s2mPipe_rValid $end
$var reg 1 D streamArbiter_1_io_output_s2mPipe_ready $end
$scope module streamArbiter_1 $end
$var wire 1 E _zz_io_chosen_1 $end
$var wire 1 F _zz_io_chosen_2 $end
$var wire 1 G _zz_io_output_payload $end
$var wire 1 H _zz_io_output_payload_1 $end
$var wire 4 I _zz_maskProposal_1_1 [3:0] $end
$var wire 1 ! clk $end
$var wire 32 J io_inputs_0_payload [31:0] $end
$var wire 1 > io_inputs_0_ready $end
$var wire 1 ' io_inputs_0_valid $end
$var wire 32 K io_inputs_1_payload [31:0] $end
$var wire 1 = io_inputs_1_ready $end
$var wire 1 * io_inputs_1_valid $end
$var wire 32 L io_inputs_2_payload [31:0] $end
$var wire 1 < io_inputs_2_ready $end
$var wire 1 - io_inputs_2_valid $end
$var wire 32 M io_inputs_3_payload [31:0] $end
$var wire 1 ; io_inputs_3_ready $end
$var wire 1 0 io_inputs_3_valid $end
$var wire 1 N io_output_fire $end
$var wire 32 O io_output_payload [31:0] $end
$var wire 1 9 io_output_ready $end
$var wire 1 5 io_output_valid $end
$var wire 1 P maskProposal_0 $end
$var wire 1 1 reset $end
$var wire 1 Q maskRouted_3 $end
$var wire 1 R maskRouted_2 $end
$var wire 1 S maskRouted_1 $end
$var wire 1 T maskRouted_0 $end
$var wire 1 U maskProposal_3 $end
$var wire 1 V maskProposal_2 $end
$var wire 1 W maskProposal_1 $end
$var wire 4 X io_chosenOH [3:0] $end
$var wire 2 Y io_chosen [1:0] $end
$var wire 4 Z _zz_maskProposal_1 [3:0] $end
$var wire 2 [ _zz_io_output_payload_3 [1:0] $end
$var wire 1 \ _zz_io_chosen $end
$var wire 4 ] _zz__zz_maskProposal_1_1 [3:0] $end
$var reg 32 ^ _zz_io_output_payload_2 [31:0] $end
$var reg 1 _ locked $end
$var reg 1 ` maskLocked_0 $end
$var reg 1 a maskLocked_1 $end
$var reg 1 b maskLocked_2 $end
$var reg 1 c maskLocked_3 $end
$upscope $end
$upscope $end
$enddefinitions $end
#0
$dumpvars
xc
xb
xa
x`
0_
bz ^
bx ]
x\
bx [
bz Z
bx Y
bxz X
xW
xV
xU
zT
xS
xR
xQ
zP
bz O
xN
bz M
bz L
bz K
bz J
bx I
xH
xG
xF
xE
1D
bx C
0B
bx A
bx @
bxz ?
x>
x=
x<
x;
bz :
19
bx 8
07
bz 6
x5
14
x3
z2
11
z0
x/
bz .
z-
x,
bz +
z*
x)
bz (
z'
x&
bz %
0$
z#
bx "
0!
$end
#1000
0N
03
0F
b0 @
b0 Y
0E
05
0)
0=
0,
0<
0\
0/
0;
0H
b0 [
0G
0S
0R
0Q
0&
0>
0W
0V
0U
b0 6
b0 ?
b0 X
0T
b0 I
b0 :
b0 O
b0 ^
1D
0P
b1111 ]
0'
b0 %
b0 J
0*
b0 (
b0 K
0-
b0 +
b0 L
b0 Z
00
b0 .
b0 M
02
0#
01
#1500
b0 "
b0 8
b0 C
b0 A
1!
#2000
0!
#2500
1!
#3000
0!
#3500
1N
13
15
b1 @
b1 Y
1E
1)
1=
b1 [
1G
b10 ?
b10 X
1S
1W
b10 I
b1 ]
b10 Z
1*
1!
#4000
0!
#4500
0E
0)
0=
0G
b0 @
b0 Y
0F
0S
0\
0/
0;
b0 [
0H
0W
0Q
1&
1>
0U
b1 ?
b1 X
1T
b1 I
12
1#
1P
1'
b1010 ]
b1011 Z
10
1D
0c
0b
1a
0`
0_
04
1$
17
19
0B
1!
#5000
0!
#5500
0D
02
0#
0a
1`
19
0B
0_
1!
#6000
0!
#6500
b1 @
b1 Y
1E
b1 [
1G
15
1S
1W
1D
b10 ?
b10 X
0T
b10 I
12
1#
0P
b1001 ]
b1010 Z
0'
0N
0&
0>
0_
09
1B
1!
#7000
0!
#7500
0W
b1 I
0D
02
0#
1P
b1010 ]
b1011 Z
1'
b10111111001111111100011000001111 %
b10111111001111111100011000001111 J
1N
1)
1=
1a
0`
19
0B
1_
1!
#8000
0!
#8500
0F
0H
0R
0V
1D
b1 I
12
1#
0*
b1100 ]
b1101 Z
1-
b0 @
b0 Y
0E
b10111111001111111100011000001111 :
b10111111001111111100011000001111 O
b10111111001111111100011000001111 ^
b0 [
0G
1T
b1 ?
b1 X
0S
0N
0)
0=
0_
09
1B
1!
#9000
0!
#9500
0W
0D
b1 I
02
0#
b1110 ]
b1111 Z
1*
b111111011110101001010101000100 (
b111111011110101001010101000100 K
1N
1&
1>
b10111111001111111100011000001111 6
0a
1`
19
0B
1_
1!
#10000
0!
#10500
b1 @
b1 Y
1E
b1 [
1G
15
1S
1W
b10 ?
b10 X
0T
b10 I
b111111011110101001010101000100 :
b111111011110101001010101000100 O
b111111011110101001010101000100 ^
0P
b1101 ]
b1110 Z
0'
b0 %
b0 J
0N
0&
0>
b10111111001111111100011000001111 A
0_
09
1B
1!
#11000
0!
#11500
0W
b1 I
1D
12
1#
1P
b1110 ]
b1111 Z
1'
b1000011000010110111100000110000 %
b1000011000010110111100000110000 J
1a
0`
1_
1!
#12000
0!
#12500
0D
02
0#
1N
1)
1=
b111111011110101001010101000100 6
b10111111001111111100011000001111 "
b10111111001111111100011000001111 8
b10111111001111111100011000001111 C
19
0B
1!
#13000
0!
#13500
b1100 ]
b1101 Z
0*
b0 (
b0 K
b0 @
b0 Y
0E
b1000011000010110111100000110000 :
b1000011000010110111100000110000 O
b1000011000010110111100000110000 ^
b0 [
0G
0N
0)
0=
1T
b1 ?
b1 X
0S
b111111011110101001010101000100 A
09
1B
0_
1!
#14000
0!
#14500
0W
b1 I
b1110 ]
b1111 Z
1*
b111010010010010010010110111101 (
b111010010010010010010110111101 K
0a
1`
1_
1!
#15000
0!
#15500
1D
12
1#
1!
#16000
0!
#16500
0D
02
0#
1N
1&
1>
b1000011000010110111100000110000 6
b111111011110101001010101000100 "
b111111011110101001010101000100 8
b111111011110101001010101000100 C
19
0B
1!
#17000
0!
#17500
b1 @
b1 Y
1E
b1 [
1G
15
1S
1W
1D
b10 ?
b10 X
0T
b10 I
b111010010010010010010110111101 :
b111010010010010010010110111101 O
b111010010010010010010110111101 ^
12
1#
0P
b1101 ]
b1110 Z
0'
b0 %
b0 J
0N
0&
0>
b1000011000010110111100000110000 A
09
1B
0_
1!
#18000
0!
#18500
0D
02
0#
1N
1)
1=
b111010010010010010010110111101 6
b1000011000010110111100000110000 "
b1000011000010110111100000110000 8
b1000011000010110111100000110000 C
1a
0`
1_
19
0B
1!
#19000
0!
#19500
1F
1H
b10 @
b10 Y
0E
15
1R
b10 [
0G
1V
b100 ?
b100 X
0S
0W
b100 I
b0 :
b0 O
b0 ^
b1011 ]
b1100 Z
0*
b0 (
b0 K
0N
0)
0=
b111010010010010010010110111101 A
09
1B
0_
1!
#20000
0!
#20500
0V
b1 I
1P
1'
b110101111000000000010110000010 %
b110101111000000000010110000010 J
b1110 ]
b1111 Z
1*
b10110101010011000111001101001011 (
b10110101010011000111001101001011 K
1b
0a
1_
1!
#21000
0!
#21500
1!
#22000
0!
#22500
1D
12
1#
1!
#23000
0!
#23500
0D
02
0#
1N
1,
1<
b0 6
b111010010010010010010110111101 "
b111010010010010010010110111101 8
b111010010010010010010110111101 C
19
0B
1!
#24000
0!
#24500
b1010 ]
b1011 Z
0-
15
b0 @
b0 Y
0F
b110101111000000000010110000010 :
b110101111000000000010110000010 O
b110101111000000000010110000010 ^
b0 [
0H
1T
b1 ?
b1 X
0R
0N
0,
0<
b0 A
0_
09
1B
1!
#25000
0!
#25500
0V
1D
b1 I
12
1#
b1110 ]
b1111 Z
1-
b10100110101011101110001011101 +
b10100110101011101110001011101 L
0b
1`
1_
1!
#26000
0!
#26500
0D
02
0#
1N
1&
1>
b110101111000000000010110000010 6
b0 "
b0 8
b0 C
19
0B
1!
#27000
0!
#27500
b1 @
b1 Y
1E
b1 [
1G
15
1S
1W
1D
b10 ?
b10 X
0T
b10 I
b10110101010011000111001101001011 :
b10110101010011000111001101001011 O
b10110101010011000111001101001011 ^
12
1#
0P
b1101 ]
b1110 Z
0'
b0 %
b0 J
0N
0&
0>
b110101111000000000010110000010 A
09
1B
0_
1!
#28000
0!
#28500
0W
b1 I
0D
02
0#
1P
b1110 ]
b1111 Z
1'
b10101110000110110101010011010 %
b10101110000110110101010011010 J
1N
1)
1=
b10110101010011000111001101001011 6
b110101111000000000010110000010 "
b110101111000000000010110000010 8
b110101111000000000010110000010 C
1a
0`
1_
19
0B
1!
#29000
0!
#29500
b1100 ]
b1101 Z
0*
b0 (
b0 K
b0 @
b0 Y
0E
b10101110000110110101010011010 :
b10101110000110110101010011010 O
b10101110000110110101010011010 ^
b0 [
0G
0N
0)
0=
1T
b1 ?
b1 X
0S
b10110101010011000111001101001011 A
09
1B
0_
1!
#30000
0!
#30500
1D
12
1#
0a
1`
1_
1!
#31000
0!
#31500
0W
0D
b1 I
02
0#
b1110 ]
b1111 Z
1*
b1111011001111110000000010010101 (
b1111011001111110000000010010101 K
1N
1&
1>
b10101110000110110101010011010 6
b10110101010011000111001101001011 "
b10110101010011000111001101001011 8
b10110101010011000111001101001011 C
19
0B
1!
#32000
0!
#32500
b1 @
b1 Y
1E
b1 [
1G
15
1S
1W
1D
b10 ?
b10 X
0T
b10 I
b1111011001111110000000010010101 :
b1111011001111110000000010010101 O
b1111011001111110000000010010101 ^
12
1#
0P
b1101 ]
b1110 Z
0'
b0 %
b0 J
0N
0&
0>
b10101110000110110101010011010 A
0_
09
1B
1!
#33000
0!
#33500
0W
b1 I
0D
02
0#
1P
b1110 ]
b1111 Z
1'
b11110010100111111011110100000100 %
b11110010100111111011110100000100 J
1N
1)
1=
b1111011001111110000000010010101 6
1a
0`
b10101110000110110101010011010 "
b10101110000110110101010011010 8
b10101110000110110101010011010 C
19
0B
1_
1!
#34000
0!
#34500
1D
12
1#
b1100 ]
b1101 Z
0*
b0 (
b0 K
b0 @
b0 Y
0E
b11110010100111111011110100000100 :
b11110010100111111011110100000100 O
b11110010100111111011110100000100 ^
b0 [
0G
1T
b1 ?
b1 X
0S
0N
0)
0=
b1111011001111110000000010010101 A
0_
09
1B
1!
#35000
0!
#35500
0W
0D
b1 I
02
0#
b1110 ]
b1111 Z
1*
b10110111101010110101010011010100 (
b10110111101010110101010011010100 K
1N
1&
1>
b11110010100111111011110100000100 6
0a
1`
b1111011001111110000000010010101 "
b1111011001111110000000010010101 8
b1111011001111110000000010010101 C
19
0B
1_
1!
#36000
0!
#36500
b1 @
b1 Y
1E
b1 [
1G
15
1S
1W
1D
b10 ?
b10 X
0T
b10 I
b10110111101010110101010011010100 :
b10110111101010110101010011010100 O
b10110111101010110101010011010100 ^
12
1#
0P
b1101 ]
b1110 Z
0'
b0 %
b0 J
0N
0&
0>
b11110010100111111011110100000100 A
0_
09
1B
1!
#37000
0!
#37500
0W
b1 I
0D
02
0#
1P
b1110 ]
b1111 Z
1'
b10011100101111111100010010100101 %
b10011100101111111100010010100101 J
1N
1)
1=
b10110111101010110101010011010100 6
1a
0`
b11110010100111111011110100000100 "
b11110010100111111011110100000100 8
b11110010100111111011110100000100 C
19
0B
1_
1!
#38000
0!
#38500
1D
12
1#
b1100 ]
b1101 Z
0*
b0 (
b0 K
b0 @
b0 Y
0E
b10011100101111111100010010100101 :
b10011100101111111100010010100101 O
b10011100101111111100010010100101 ^
b0 [
0G
1T
b1 ?
b1 X
0S
0N
0)
0=
b10110111101010110101010011010100 A
0_
09
1B
1!
#39000
0!
#39500
0D
02
0#
1N
1&
1>
b10011100101111111100010010100101 6
0a
1`
b10110111101010110101010011010100 "
b10110111101010110101010011010100 8
b10110111101010110101010011010100 C
19
0B
1_
1!
#40000
0!
#40500
b1 @
b1 Y
1E
15
b1 [
1G
1S
1W
b10 ?
b10 X
0T
b10 I
b10100001001110110011110101010011 :
b10100001001110110011110101010011 O
b10100001001110110011110101010011 ^
0P
0'
b0 %
b0 J
b1101 ]
b1110 Z
1*
b10100001001110110011110101010011 (
b10100001001110110011110101010011 K
0N
0&
0>
b10011100101111111100010010100101 A
0_
09
1B
1!
#41000
0!
#41500
1a
0`
1_
1!
#42000
0!
#42500
1!
#43000
0!
#43500
0W
b1 I
1D
12
1#
1P
b1110 ]
b1111 Z
1'
b10110111000000000000010000 %
b10110111000000000000010000 J
1!
#44000
0!
#44500
0D
02
0#
1N
1)
1=
b10100001001110110011110101010011 6
b10011100101111111100010010100101 "
b10011100101111111100010010100101 8
b10011100101111111100010010100101 C
19
0B
1!
#45000
0!
#45500
1D
12
1#
b1100 ]
b1101 Z
0*
b0 (
b0 K
b0 @
b0 Y
0E
b10110111000000000000010000 :
b10110111000000000000010000 O
b10110111000000000000010000 ^
b0 [
0G
0N
0)
0=
1T
b1 ?
b1 X
0S
b10100001001110110011110101010011 A
09
1B
0_
1!
#46000
0!
#46500
0D
02
0#
1N
1&
1>
b10110111000000000000010000 6
b10100001001110110011110101010011 "
b10100001001110110011110101010011 8
b10100001001110110011110101010011 C
0a
1`
1_
19
0B
1!
#47000
0!
#47500
b10 @
b10 Y
1F
b10 [
1H
15
1R
1V
b100 ?
b100 X
0T
b100 I
b10100110101011101110001011101 :
b10100110101011101110001011101 O
b10100110101011101110001011101 ^
0P
b1011 ]
b1100 Z
0'
b0 %
b0 J
0N
0&
0>
b10110111000000000000010000 A
09
1B
0_
1!
#48000
0!
#48500
0V
b1 I
1P
1'
b1001100111000000000001111010001 %
b1001100111000000000001111010001 J
b1110 ]
b1111 Z
1*
b1010001101000101101011110011110 (
b1010001101000101101011110011110 K
1b
0`
1_
1!
#49000
0!
#49500
1D
12
1#
1!
#50000
0!
#50500
0D
02
0#
1N
1,
1<
b10100110101011101110001011101 6
b10110111000000000000010000 "
b10110111000000000000010000 8
b10110111000000000000010000 C
19
0B
1!
#51000
0!
#51500
b1010 ]
b1011 Z
0-
b0 +
b0 L
15
b0 @
b0 Y
0F
b1001100111000000000001111010001 :
b1001100111000000000001111010001 O
b1001100111000000000001111010001 ^
b0 [
0H
0N
0,
0<
1T
b1 ?
b1 X
0R
b10100110101011101110001011101 A
09
1B
0_
1!
#52000
0!
#52500
0b
1`
1_
1!
#53000
0!
#53500
0V
b1 I
b1110 ]
b1111 Z
1-
b11100111011110110110100110000010 +
b11100111011110110110100110000010 L
1!
#54000
0!
#54500
1!
#55000
0!
#55500
1D
12
1#
1!
#56000
0!
#56500
0D
02
0#
1N
1&
1>
b1001100111000000000001111010001 6
b10100110101011101110001011101 "
b10100110101011101110001011101 8
b10100110101011101110001011101 C
19
0B
1!
#57000
0!
#57500
b1 @
b1 Y
1E
b1 [
1G
15
1S
1W
1D
b10 ?
b10 X
0T
b10 I
b1010001101000101101011110011110 :
b1010001101000101101011110011110 O
b1010001101000101101011110011110 ^
12
1#
0P
b1101 ]
b1110 Z
0'
b0 %
b0 J
0N
0&
0>
b1001100111000000000001111010001 A
09
1B
0_
1!
#58000
0!
#58500
0W
b1 I
0D
02
0#
1P
b1110 ]
b1111 Z
1'
b100101000010001011010101100000 %
b100101000010001011010101100000 J
1N
1)
1=
b1010001101000101101011110011110 6
b1001100111000000000001111010001 "
b1001100111000000000001111010001 8
b1001100111000000000001111010001 C
1a
0`
1_
19
0B
1!
#59000
0!
#59500
1D
12
1#
b1100 ]
b1101 Z
0*
b0 (
b0 K
b0 @
b0 Y
0E
b100101000010001011010101100000 :
b100101000010001011010101100000 O
b100101000010001011010101100000 ^
b0 [
0G
0N
0)
0=
1T
b1 ?
b1 X
0S
b1010001101000101101011110011110 A
09
1B
0_
1!
#60000
0!
#60500
0W
0D
b1 I
02
0#
b1110 ]
b1111 Z
1*
b1111111000000100101111110000111 (
b1111111000000100101111110000111 K
1N
1&
1>
b100101000010001011010101100000 6
b1010001101000101101011110011110 "
b1010001101000101101011110011110 8
b1010001101000101101011110011110 C
0a
1`
1_
19
0B
1!
#61000
0!
#61500
b1 @
b1 Y
1E
b1 [
1G
15
1S
1W
b10 ?
b10 X
0T
b10 I
b1111111000000100101111110000111 :
b1111111000000100101111110000111 O
b1111111000000100101111110000111 ^
0P
b1101 ]
b1110 Z
0'
b0 %
b0 J
0N
0&
0>
b100101000010001011010101100000 A
09
1B
0_
1!
#62000
0!
#62500
1a
0`
1_
1!
#63000
0!
#63500
0W
b1 I
1P
b1110 ]
b1111 Z
1'
b110101100000111110010101101100 %
b110101100000111110010101101100 J
1!
#64000
0!
#64500
1!
#65000
0!
#65500
1D
12
1#
1!
#66000
0!
#66500
0D
02
0#
1N
1)
1=
b1111111000000100101111110000111 6
b100101000010001011010101100000 "
b100101000010001011010101100000 8
b100101000010001011010101100000 C
19
0B
1!
#67000
0!
#67500
1D
12
1#
b1100 ]
b1101 Z
0*
b0 (
b0 K
b0 @
b0 Y
0E
b110101100000111110010101101100 :
b110101100000111110010101101100 O
b110101100000111110010101101100 ^
b0 [
0G
0N
0)
0=
1T
b1 ?
b1 X
0S
b1111111000000100101111110000111 A
09
1B
0_
1!
#68000
0!
#68500
0D
02
0#
1N
1&
1>
b110101100000111110010101101100 6
b1111111000000100101111110000111 "
b1111111000000100101111110000111 8
b1111111000000100101111110000111 C
0a
1`
1_
19
0B
1!
#69000
0!
#69500
b10 @
b10 Y
1F
b10 [
1H
15
1R
1V
b100 ?
b100 X
0T
b100 I
b11100111011110110110100110000010 :
b11100111011110110110100110000010 O
b11100111011110110110100110000010 ^
0P
b1011 ]
b1100 Z
0'
b0 %
b0 J
0N
0&
0>
b110101100000111110010101101100 A
09
1B
0_
1!
#70000
0!
#70500
1W
0V
b10 I
1D
12
1#
b1101 ]
b1110 Z
1*
b10011011011110110101110111011100 (
b10011011011110110101110111011100 K
1b
0`
1_
1!
#71000
0!
#71500
0D
02
0#
1N
1,
1<
b11100111011110110110100110000010 6
b110101100000111110010101101100 "
b110101100000111110010101101100 8
b110101100000111110010101101100 C
19
0B
1!
#72000
0!
