streamTest/streamFIFO/streamFIFO/streamFIFO.v
// Generator : SpinalHDL v1.7.0a    git head : 150a9b9067020722818dfb17df4a23ac712a7af8
// Component : streamFIFO_1
// Git hash  : 3a903e741cbbe310a98c75dc1ebbd289cb1c87a4

`timescale 1ns/1ps

module streamFIFO (
  input               io_s_in_valid,
  output              io_s_in_ready,
  input      [31:0]   io_s_in_payload,
  output              io_m_out_valid,
  input               io_m_out_ready,
  output     [31:0]   io_m_out_payload,
  input               clk,
  input               reset
);

  wire                FIFO_io_push_ready;
  wire                FIFO_io_pop_valid;
  wire       [31:0]   FIFO_io_pop_payload;
  wire       [3:0]    FIFO_io_occupancy;
  wire       [3:0]    FIFO_io_availability;

  StreamFifo FIFO (
    .io_push_valid   (io_s_in_valid            ), //i
    .io_push_ready   (FIFO_io_push_ready       ), //o
    .io_push_payload (io_s_in_payload[31:0]    ), //i
    .io_pop_valid    (FIFO_io_pop_valid        ), //o
    .io_pop_ready    (io_m_out_ready           ), //i
    .io_pop_payload  (FIFO_io_pop_payload[31:0]), //o
    .io_flush        (1'b0                     ), //i
    .io_occupancy    (FIFO_io_occupancy[3:0]   ), //o
    .io_availability (FIFO_io_availability[3:0]), //o
    .clk             (clk                      ), //i
    .reset           (reset                    )  //i
  );
  assign io_s_in_ready = FIFO_io_push_ready;
  assign io_m_out_valid = FIFO_io_pop_valid;
  assign io_m_out_payload = FIFO_io_pop_payload;

endmodule

module StreamFifo (
  input               io_push_valid,
  output              io_push_ready,
  input      [31:0]   io_push_payload,
  output              io_pop_valid,
  input               io_pop_ready,
  output     [31:0]   io_pop_payload,
  input               io_flush,
  output     [3:0]    io_occupancy,
  output     [3:0]    io_availability,
  input               clk,
  input               reset
);

  reg        [31:0]   _zz_logic_ram_port0;
  wire       [2:0]    _zz_logic_pushPtr_valueNext;
  wire       [0:0]    _zz_logic_pushPtr_valueNext_1;
  wire       [2:0]    _zz_logic_popPtr_valueNext;
  wire       [0:0]    _zz_logic_popPtr_valueNext_1;
  wire                _zz_logic_ram_port;
  wire                _zz_io_pop_payload;
  wire       [2:0]    _zz_io_availability;
  reg                 _zz_1;
  reg                 logic_pushPtr_willIncrement;
  reg                 logic_pushPtr_willClear;
  reg        [2:0]    logic_pushPtr_valueNext;
  reg        [2:0]    logic_pushPtr_value;
  wire                logic_pushPtr_willOverflowIfInc;
  wire                logic_pushPtr_willOverflow;
  reg                 logic_popPtr_willIncrement;
  reg                 logic_popPtr_willClear;
  reg        [2:0]    logic_popPtr_valueNext;
  reg        [2:0]    logic_popPtr_value;
  wire                logic_popPtr_willOverflowIfInc;
  wire                logic_popPtr_willOverflow;
  wire                logic_ptrMatch;
  reg                 logic_risingOccupancy;
  wire                logic_pushing;
  wire                logic_popping;
  wire                logic_empty;
  wire                logic_full;
  reg                 _zz_io_pop_valid;
  wire                when_Stream_l1021;
  wire       [2:0]    logic_ptrDif;
  reg [31:0] logic_ram [0:7];

  assign _zz_logic_pushPtr_valueNext_1 = logic_pushPtr_willIncrement;
  assign _zz_logic_pushPtr_valueNext = {2'd0, _zz_logic_pushPtr_valueNext_1};
  assign _zz_logic_popPtr_valueNext_1 = logic_popPtr_willIncrement;
  assign _zz_logic_popPtr_valueNext = {2'd0, _zz_logic_popPtr_valueNext_1};
  assign _zz_io_availability = (logic_popPtr_value - logic_pushPtr_value);
  assign _zz_io_pop_payload = 1'b1;
  always @(posedge clk) begin
    if(_zz_io_pop_payload) begin
      _zz_logic_ram_port0 <= logic_ram[logic_popPtr_valueNext];
    end
  end

  always @(posedge clk) begin
    if(_zz_1) begin
      logic_ram[logic_pushPtr_value] <= io_push_payload;
    end
  end

  always @(*) begin
    _zz_1 = 1'b0;
    if(logic_pushing) begin
      _zz_1 = 1'b1;
    end
  end

  always @(*) begin
    logic_pushPtr_willIncrement = 1'b0;
    if(logic_pushing) begin
      logic_pushPtr_willIncrement = 1'b1;
    end
  end

  always @(*) begin
    logic_pushPtr_willClear = 1'b0;
    if(io_flush) begin
      logic_pushPtr_willClear = 1'b1;
    end
  end

  assign logic_pushPtr_willOverflowIfInc = (logic_pushPtr_value == 3'b111);
  assign logic_pushPtr_willOverflow = (logic_pushPtr_willOverflowIfInc && logic_pushPtr_willIncrement);
  always @(*) begin
    logic_pushPtr_valueNext = (logic_pushPtr_value + _zz_logic_pushPtr_valueNext);
    if(logic_pushPtr_willClear) begin
      logic_pushPtr_valueNext = 3'b000;
    end
  end

  always @(*) begin
    logic_popPtr_willIncrement = 1'b0;
    if(logic_popping) begin
      logic_popPtr_willIncrement = 1'b1;
    end
  end

  always @(*) begin
    logic_popPtr_willClear = 1'b0;
    if(io_flush) begin
      logic_popPtr_willClear = 1'b1;
    end
  end

  assign logic_popPtr_willOverflowIfInc = (logic_popPtr_value == 3'b111);
  assign logic_popPtr_willOverflow = (logic_popPtr_willOverflowIfInc && logic_popPtr_willIncrement);
  always @(*) begin
    logic_popPtr_valueNext = (logic_popPtr_value + _zz_logic_popPtr_valueNext);
    if(logic_popPtr_willClear) begin
      logic_popPtr_valueNext = 3'b000;
    end
  end

  assign logic_ptrMatch = (logic_pushPtr_value == logic_popPtr_value);
  assign logic_pushing = (io_push_valid && io_push_ready);
  assign logic_popping = (io_pop_valid && io_pop_ready);
  assign logic_empty = (logic_ptrMatch && (! logic_risingOccupancy));
  assign logic_full = (logic_ptrMatch && logic_risingOccupancy);
  assign io_push_ready = (! logic_full);
  assign io_pop_valid = ((! logic_empty) && (! (_zz_io_pop_valid && (! logic_full))));
  assign io_pop_payload = _zz_logic_ram_port0;
  assign when_Stream_l1021 = (logic_pushing != logic_popping);
  assign logic_ptrDif = (logic_pushPtr_value - logic_popPtr_value);
  assign io_occupancy = {(logic_risingOccupancy && logic_ptrMatch),logic_ptrDif};
  assign io_availability = {((! logic_risingOccupancy) && logic_ptrMatch),_zz_io_availability};
  always @(posedge clk or posedge reset) begin
    if(reset) begin
      logic_pushPtr_value <= 3'b000;
      logic_popPtr_value <= 3'b000;
      logic_risingOccupancy <= 1'b0;
      _zz_io_pop_valid <= 1'b0;
    end else begin
      logic_pushPtr_value <= logic_pushPtr_valueNext;
      logic_popPtr_value <= logic_popPtr_valueNext;
      _zz_io_pop_valid <= (logic_popPtr_valueNext == logic_pushPtr_value);
      if(when_Stream_l1021) begin
        logic_risingOccupancy <= logic_pushing;
      end
      if(io_flush) begin
        logic_risingOccupancy <= 1'b0;
      end
    end
  end
  
  initial begin
    $dumpfile("streamFIFO.vcd");
    $dumpvars(0, streamFIFO);
  end  


endmodule

streamTest/streamFIFO/streamFIFO/streamFIFO.vcd
$date
	Fri May 27 06:09:25 2022
$end
$version
	Icarus Verilog
$end
$timescale
	1ps
$end
$scope module streamFIFO $end
$var wire 1 ! clk $end
$var wire 32 " io_m_out_payload [31:0] $end
$var wire 1 # io_m_out_ready $end
$var wire 1 $ io_m_out_valid $end
$var wire 32 % io_s_in_payload [31:0] $end
$var wire 1 & io_s_in_ready $end
$var wire 1 ' io_s_in_valid $end
$var wire 1 ( reset $end
$var wire 1 ) FIFO_io_push_ready $end
$var wire 1 * FIFO_io_pop_valid $end
$var wire 32 + FIFO_io_pop_payload [31:0] $end
$var wire 4 , FIFO_io_occupancy [3:0] $end
$var wire 4 - FIFO_io_availability [3:0] $end
$scope module FIFO $end
$var wire 1 . _zz_io_pop_payload $end
$var wire 1 / _zz_logic_popPtr_valueNext_1 $end
$var wire 1 0 _zz_logic_pushPtr_valueNext_1 $end
$var wire 1 ! clk $end
$var wire 1 1 io_flush $end
$var wire 32 2 io_pop_payload [31:0] $end
$var wire 1 # io_pop_ready $end
$var wire 1 * io_pop_valid $end
$var wire 32 3 io_push_payload [31:0] $end
$var wire 1 ' io_push_valid $end
$var wire 1 4 logic_empty $end
$var wire 1 5 logic_full $end
$var wire 1 6 logic_popPtr_willOverflow $end
$var wire 1 7 logic_popping $end
$var wire 1 8 logic_pushPtr_willOverflow $end
$var wire 1 9 logic_pushing $end
$var wire 1 ( reset $end
$var wire 1 : when_Stream_l1021 $end
$var wire 1 ; logic_pushPtr_willOverflowIfInc $end
$var wire 1 < logic_ptrMatch $end
$var wire 3 = logic_ptrDif [2:0] $end
$var wire 1 > logic_popPtr_willOverflowIfInc $end
$var wire 1 ) io_push_ready $end
$var wire 4 ? io_occupancy [3:0] $end
$var wire 4 @ io_availability [3:0] $end
$var wire 3 A _zz_logic_pushPtr_valueNext [2:0] $end
$var wire 3 B _zz_logic_popPtr_valueNext [2:0] $end
$var wire 3 C _zz_io_availability [2:0] $end
$var reg 1 D _zz_1 $end
$var reg 1 E _zz_io_pop_valid $end
$var reg 32 F _zz_logic_ram_port0 [31:0] $end
$var reg 3 G logic_popPtr_value [2:0] $end
$var reg 3 H logic_popPtr_valueNext [2:0] $end
$var reg 1 I logic_popPtr_willClear $end
$var reg 1 J logic_popPtr_willIncrement $end
$var reg 3 K logic_pushPtr_value [2:0] $end
$var reg 3 L logic_pushPtr_valueNext [2:0] $end
$var reg 1 M logic_pushPtr_willClear $end
$var reg 1 N logic_pushPtr_willIncrement $end
$var reg 1 O logic_risingOccupancy $end
$upscope $end
$upscope $end
$enddefinitions $end
#0
$dumpvars
0O
xN
0M
bx L
b0 K
0J
0I
b0 H
b0 G
bx F
0E
xD
b0 C
b0 B
b0x A
b1000 @
b0 ?
0>
b0 =
1<
0;
x:
x9
08
07
06
05
14
bz 3
bx 2
01
x0
0/
1.
b1000 -
b0 ,
bx +
0*
1)
1(
z'
1&
bz %
0$
z#
bx "
0!
$end
#1000
b0 L
0:
b0 A
00
0N
0D
09
0'
b0 %
b0 3
0#
0(
#1500
1E
1!
#2000
0!
#2500
1!
#3000
0!
#3500
b1 L
1:
1D
b1 A
10
1N
19
1#
1'
1!
#4000
0!
#4500
b10 L
04
1O
b111 -
b111 @
b111 C
0<
b1 ,
b1 ?
b1 =
b1 K
1!
#5000
0!
#5500
b0 A
00
0N
0D
09
0'
b1 H
1:
b1 B
1/
1J
17
1$
1*
b10 L
0E
b110 -
b110 @
b110 C
b10 ,
b10 ?
b10 =
b10 K
b0 "
b0 +
b0 2
b0 F
1!
#6000
0!
#6500
0:
b0 B
0/
0J
07
0#
b1 H
0O
b111 -
b111 @
b111 C
b1 ,
b1 ?
b1 =
b1 G
1!
#7000
0!
#7500
b10 H
1:
b1 B
1/
1J
17
1#
1!
#8000
0!
#8500
0#
0:
b0 B
0/
0J
07
0$
0*
b10 H
14
1E
b1000 -
b1000 @
b0 C
1<
b0 ,
b0 ?
b0 =
b10 G
bx "
bx +
bx 2
bx F
1!
#9000
0!
#9500
1!
#10000
0!
#10500
b11 L
1:
1D
b1 A
10
1N
19
1'
b11111011011000111000011010011110 %
b11111011011000111000011010011110 3
1!
#11000
0!
#11500
0:
b0 A
00
0N
0D
09
0'
b0 %
b0 3
b11 L
04
1O
b111 -
b111 @
b111 C
0<
b1 ,
b1 ?
b1 =
b11 K
1!
#12000
0!
#12500
b11 H
b100 L
b1 B
1/
1J
1D
b1 A
10
1N
17
19
1#
1'
b1011000000110111111110011000000 %
b1011000000110111111110011000000 3
1$
1*
0E
b11111011011000111000011010011110 "
b11111011011000111000011010011110 +
b11111011011000111000011010011110 2
b11111011011000111000011010011110 F
1!
#13000
0!
#13500
b0 A
00
0N
0D
09
0#
0'
b0 %
b0 3
0:
b0 B
0/
0J
07
0$
0*
b11 H
b100 L
1E
b11 G
b111 -
b111 @
b111 C
b1 ,
b1 ?
b1 =
b100 K
bx "
bx +
bx 2
bx F
1!
#14000
0!
#14500
b101 L
1:
1D
b1 A
10
1N
19
1'
b101100011011101010101011011110 %
b101100011011101010101011011110 3
1$
1*
0E
b1011000000110111111110011000000 "
b1011000000110111111110011000000 +
b1011000000110111111110011000000 2
b1011000000110111111110011000000 F
1!
#15000
0!
#15500
b100 H
b1 B
1/
1J
b0 A
00
0N
0D
17
09
1#
0'
b0 %
b0 3
b101 L
b110 -
b110 @
b110 C
b10 ,
b10 ?
b10 =
b101 K
1!
#16000
0!
#16500
b110 L
b0 B
0/
0J
1D
b1 A
10
1N
07
19
0#
1'
b1011101011010000111000011010101 %
b1011101011010000111000011010101 3
b100 H
0O
b111 -
b111 @
b111 C
b1 ,
b1 ?
b1 =
b100 G
b101100011011101010101011011110 "
b101100011011101010101011011110 +
b101100011011101010101011011110 2
b101100011011101010101011011110 F
1!
#17000
0!
#17500
0:
b0 A
00
0N
0D
09
0'
b0 %
b0 3
b110 L
1O
b110 -
b110 @
b110 C
b10 ,
b10 ?
b10 =
b110 K
1!
#18000
0!
#18500
b111 L
1:
1D
b1 A
10
1N
19
1'
b11101111000100000100011011101111 %
b11101111000100000100011011101111 3
1!
#19000
0!
#19500
b101 H
b1 B
1/
1J
b0 A
00
0N
0D
17
09
1#
0'
b0 %
b0 3
b111 L
08
b101 -
b101 @
b101 C
1;
b11 ,
b11 ?
b11 =
b111 K
1!
#20000
0!
#20500
18
b0 L
b0 B
0/
0J
1D
b1 A
10
1N
07
19
0#
1'
b110010010011011101101011101111 %
b110010010011011101101011101111 3
b101 H
0O
b110 -
b110 @
b110 C
b10 ,
b10 ?
b10 =
b101 G
b1011101011010000111000011010101 "
b1011101011010000111000011010101 +
b1011101011010000111000011010101 2
b1011101011010000111000011010101 F
1!
#21000
0!
#21500
b110 H
b1 B
1/
1J
b0 A
00
0N
0D
17
09
1#
0'
b0 %
b0 3
b0 L
08
1O
b101 -
b101 @
b101 C
0;
b11 ,
b11 ?
b11 =
b0 K
1!
#22000
0!
#22500
b1 L
b0 B
0/
0J
1D
b1 A
10
1N
07
19
0#
1'
b100100001100101110111001011001 %
b100100001100101110111001011001 3
b110 H
0O
b110 -
b110 @
b110 C
b10 ,
b10 ?
b10 =
b110 G
b11101111000100000100011011101111 "
b11101111000100000100011011101111 +
b11101111000100000100011011101111 2
b11101111000100000100011011101111 F
1!
#23000
0!
#23500
b111 H
b1 B
1/
1J
b0 A
00
0N
0D
17
09
1#
0'
b0 %
b0 3
b1 L
1O
b101 -
b101 @
b101 C
b11 ,
b11 ?
b11 =
b1 K
1!
#24000
0!
#24500
b10 L
b0 B
0/
0J
1D
b1 A
10
1N
07
19
0#
1'
b10010110101101100111011101011 %
b10010110101101100111011101011 3
b111 H
06
0O
b110 -
b110 @
b110 C
1>
b10 ,
b10 ?
b10 =
b111 G
b110010010011011101101011101111 "
b110010010011011101101011101111 +
b110010010011011101101011101111 2
b110010010011011101101011101111 F
1!
#25000
0!
#25500
16
b0 H
b1 B
1/
1J
b0 A
00
0N
0D
17
09
1#
0'
b0 %
b0 3
b10 L
1O
b101 -
b101 @
b101 C
b11 ,
b11 ?
b11 =
b10 K
1!
#26000
0!
#26500
b11 L
b0 B
0/
0J
1D
b1 A
10
1N
07
19
0#
1'
b10111100011011011110000100011011 %
b10111100011011011110000100011011 3
b0 H
06
0O
b110 -
b110 @
b110 C
0>
b10 ,
b10 ?
b10 =
b0 G
b100100001100101110111001011001 "
b100100001100101110111001011001 +
b100100001100101110111001011001 2
b100100001100101110111001011001 F
1!
#27000
0!
#27500
0:
b0 A
00
0N
0D
09
0'
b0 %
b0 3
b11 L
1O
b101 -
b101 @
b101 C
b11 ,
b11 ?
b11 =
b11 K
1!
#28000
0!
#28500
b1 H
b100 L
b1 B
1/
1J
1D
b1 A
10
1N
17
19
1#
1'
b10010100110100010010110110100 %
b10010100110100010010110110100 3
1!
#29000
0!
#29500
b0 B
0/
0J
b0 A
00
0N
0D
07
09
0#
0'
b0 %
b0 3
b1 H
b100 L
b1 G
b101 -
b101 @
b101 C
b11 ,
b11 ?
b11 =
b100 K
b10010110101101100111011101011 "
b10010110101101100111011101011 +
b10010110101101100111011101011 2
b10010110101101100111011101011 F
1!
#30000
0!
#30500
1!
#31000
0!
#31500
b10 H
1:
b1 B
1/
1J
17
1#
1!
#32000
0!
#32500
b101 L
b0 B
0/
0J
1D
b1 A
10
1N
07
19
0#
1'
b1110000000000110001000001100101 %
b1110000000000110001000001100101 3
b10 H
0O
b110 -
b110 @
b110 C
b10 ,
b10 ?
b10 =
b10 G
b10111100011011011110000100011011 "
b10111100011011011110000100011011 +
b10111100011011011110000100011011 2
b10111100011011011110000100011011 F
1!
#33000
0!
#33500
0:
b0 A
00
0N
0D
09
0'
b0 %
b0 3
b101 L
1O
b101 -
b101 @
b101 C
b11 ,
b11 ?
b11 =
b101 K
1!
#34000
0!
#34500
b11 H
1:
b1 B
1/
1J
17
1#
1!
#35000
0!
#35500
b110 L
b0 B
0/
0J
1D
b1 A
10
1N
07
19
0#
1'
b111111101111000111010011110111 %
b111111101111000111010011110111 3
b11 H
0O
b110 -
b110 @
b110 C
b10 ,
b10 ?
b10 =
b11 G
b10010100110100010010110110100 "
b10010100110100010010110110100 +
b10010100110100010010110110100 2
b10010100110100010010110110100 F
1!
#36000
0!
#36500
b100 H
b1 B
1/
1J
b0 A
00
0N
0D
17
09
1#
0'
b0 %
b0 3
b110 L
1O
b101 -
b101 @
b101 C
b11 ,
b11 ?
b11 =
b110 K
1!
#37000
0!
#37500
0:
b0 B
0/
0J
07
0#
b100 H
0O
b110 -
b110 @
b110 C
b10 ,
b10 ?
b10 =
b100 G
b1110000000000110001000001100101 "
b1110000000000110001000001100101 +
b1110000000000110001000001100101 2
b1110000000000110001000001100101 F
1!
#38000
0!
#38500
b101 H
1:
b1 B
1/
1J
17
1#
1!
#39000
0!
#39500
b111 L
b0 B
0/
0J
1D
b1 A
10
1N
07
19
0#
1'
b11010111010001111010010110010011 %
b11010111010001111010010110010011 3
b101 H
b111 -
b111 @
b111 C
b1 ,
b1 ?
b1 =
b101 G
b111111101111000111010011110111 "
b111111101111000111010011110111 +
b111111101111000111010011110111 2
b111111101111000111010011110111 F
1!
#40000
0!
#40500
0:
b0 A
00
0N
0D
09
0'
b0 %
b0 3
b111 L
08
1O
b110 -
b110 @
b110 C
1;
b10 ,
b10 ?
b10 =
b111 K
1!
#41000
0!
#41500
1!
#42000
0!
#42500
b110 H
1:
b1 B
1/
1J
17
1#
1!
#43000
0!
#43500
18
b0 L
b0 B
0/
0J
1D
b1 A
10
1N
07
19
0#
1'
b1111010100111010010011111001000 %
b1111010100111010010011111001000 3
b110 H
0O
b111 -
b111 @
b111 C
b1 ,
b1 ?
b1 =
b110 G
b11010111010001111010010110010011 "
b11010111010001111010010110010011 +
b11010111010001111010010110010011 2
b11010111010001111010010110010011 F
1!
#44000
0!
#44500
0:
b0 A
00
0N
0D
09
0'
b0 %
b0 3
b0 L
08
1O
b110 -
b110 @
b110 C
0;
b10 ,
b10 ?
b10 =
b0 K
1!
#45000
0!
#45500
b1 L
1:
1D
b1 A
10
1N
19
1'
b11110011100100111010010000110011 %
b11110011100100111010010000110011 3
1!
#46000
0!
#46500
b111 H
b1 B
1/
1J
b0 A
00
0N
0D
17
09
1#
0'
b0 %
b0 3
b1 L
b101 -
b101 @
b101 C
b11 ,
b11 ?
b11 =
b1 K
1!
#47000
0!
#47500
b10 L
b0 B
0/
0J
1D
b1 A
10
1N
07
19
0#
1'
b11100001010010101010000010011100 %
b11100001010010101010000010011100 3
b111 H
06
0O
b110 -
b110 @
b110 C
1>
b10 ,
b10 ?
b10 =
b111 G
b1111010100111010010011111001000 "
b1111010100111010010011111001000 +
b1111010100111010010011111001000 2
b1111010100111010010011111001000 F
1!
#48000
0!
#48500
16
b0 H
b1 B
1/
1J
b0 A
00
0N
0D
17
09
1#
0'
b0 %
b0 3
b10 L
1O
b101 -
b101 @
b101 C
b11 ,
b11 ?
b11 =
b10 K
1!
#49000
0!
#49500
0:
b0 B
0/
0J
07
0#
b0 H
06
0O
b110 -
b110 @
b110 C
0>
b10 ,
b10 ?
b10 =
b0 G
b11110011100100111010010000110011 "
b11110011100100111010010000110011 +
b11110011100100111010010000110011 2
b11110011100100111010010000110011 F
1!
#50000
0!
#50500
b1 H
1:
b1 B
1/
1J
17
1#
1!
#51000
0!
#51500
0:
b0 B
0/
0J
07
0#
b1 H
b111 -
b111 @
b111 C
b1 ,
b1 ?
b1 =
b1 G
b11100001010010101010000010011100 "
b11100001010010101010000010011100 +
b11100001010010101010000010011100 2
b11100001010010101010000010011100 F
1!
#52000
0!
#52500
1!
#53000
0!
#53500
1!
#54000
0!
#54500
1!
#55000
0!
#55500
b10 H
b11 L
b1 B
1/
1J
1D
b1 A
10
1N
17
19
1#
1'
b100011110101001100101110110 %
b100011110101001100101110110 3
1!
#56000
0!
#56500
b0 A
00
0N
0D
09
0#
0'
b0 %
b0 3
0:
b0 B
0/
0J
07
0$
0*
b10 H
b11 L
1E
b10 G
b111 -
b111 @
b111 C
b1 ,
b1 ?
b1 =
b11 K
b10111100011011011110000100011011 "
b10111100011011011110000100011011 +
b10111100011011011110000100011011 2
b10111100011011011110000100011011 F
1!
#57000
0!
#57500
b11 H
1:
b1 B
1/
1J
17
1#
1$
1*
0E
b100011110101001100101110110 "
b100011110101001100101110110 +
b100011110101001100101110110 2
b100011110101001100101110110 F
1!
#58000
0!
#58500
0#
0:
b0 B
0/
0J
07
0$
0*
b11 H
14
1E
b1000 -
b1000 @
b0 C
1<
b0 ,
b0 ?
b0 =
b11 G
b10010100110100010010110110100 "
b10010100110100010010110110100 +
b10010100110100010010110110100 2
b10010100110100010010110110100 F
1!
#59000
0!
#59500
b100 L
1:
1D
b1 A
10
1N
19
1#
1'
b1001111101100010100111000001101 %
b1001111101100010100111000001101 3
1!
#60000
0!
#60500
0:
b0 A
00
0N
0D
09
0'
b0 %
b0 3
b100 L
04
1O
b111 -
b111 @
b111 C
0<
b1 ,
b1 ?
b1 =
b100 K
1!
#61000
0!
#61500
b101 L
1D
b1 A
10
1N
19
1'
b1010101111010110100100110101 %
b1010101111010110100100110101 3
b100 H
0:
b1 B
1/
1J
17
1$
1*
0E
b1001111101100010100111000001101 "
b1001111101100010100111000001101 +
b1001111101100010100111000001101 2
b1001111101100010100111000001101 F
1!
#62000
0!
#62500
b0 A
00
0N
0D
09
0#
0'
b0 %
b0 3
0:
b0 B
0/
0J
07
0$
0*
b100 H
b101 L
1E
b100 G
b111 -
b111 @
b111 C
b1 ,
b1 ?
b1 =
b101 K
b1110000000000110001000001100101 "
b1110000000000110001000001100101 +
b1110000000000110001000001100101 2
b1110000000000110001000001100101 F
1!
#63000
0!
#63500
1$
1*
0E
b1010101111010110100100110101 "
b1010101111010110100100110101 +
b1010101111010110100100110101 2
b1010101111010110100100110101 F
1!
#64000
0!
#64500
b110 L
1:
1D
b1 A
10
1N
19
1'
b1100001100100111010001110010110 %
b1100001100100111010001110010110 3
1!
#65000
0!
#65500
0:
b0 A
00
0N
0D
09
0'
b0 %
b0 3
b110 L
b110 -
b110 @
b110 C
b10 ,
b10 ?
b10 =
b110 K
1!
#66000
0!
#66500
b101 H
b111 L
b1 B
1/
1J
1D
b1 A
10
1N
17
19
1#
1'
b10110110101001111110111010101110 %
b10110110101001111110111010101110 3
1!
#67000
0!
#67500
b0 B
0/
0J
b0 A
00
0N
0D
07
09
0#
0'
b0 %
b0 3
b101 H
b111 L
08
b101 G
b110 -
b110 @
b110 C
1;
b10 ,
b10 ?
b10 =
b111 K
b1100001100100111010001110010110 "
b1100001100100111010001110010110 +
b1100001100100111010001110010110 2
b1100001100100111010001110010110 F
1!
#68000
0!
#68500
1!
#69000
0!
#69500
1!
#70000
0!
#70500
b110 H
18
b0 L
b1 B
1/
1J
1D
b1 A
10
1N
17
19
1#
1'
b11110110110001110000110010010001 %
b11110110110001110000110010010001 3
1!
#71000
0!
#71500
b0 B
0/
0J
b0 A
00
0N
0D
07
09
0#
0'
b0 %
b0 3
b110 H
b0 L
08
b110 G
b110 -
b110 @
b110 C
0;
b10 ,
b10 ?
b10 =
b0 K
b10110110101001111110111010101110 "
b10110110101001111110111010101110 +
b10110110101001111110111010101110 2
b10110110101001111110111010101110 F
1!
#72000
0!
#72500
b111 H
b1 L
b1 B
1/
1J
1D
b1 A
10
1N
17
19
1#
1'
b1111000100111100111011111010110 %
b1111000100111100111011111010110 3
1!
#73000
0!
#73500
b0 B
0/
0J
b0 A
00
0N
0D
07
09
0#
0'
b0 %
b0 3
b111 H
06
b1 L
1>
b111 G
b110 -
b110 @
b110 C
b10 ,
b10 ?
b10 =
b1 K
b11110110110001110000110010010001 "
b11110110110001110000110010010001 +
b11110110110001110000110010010001 2
b11110110110001110000110010010001 F
1!
#74000
0!
#74500
16
b0 H
1:
b1 B
1/
1J
17
1#
1!
#75000
0!
#75500
0:
b0 B
0/
0J
07
0#
b0 H
06
0O
b111 -
b111 @
b111 C
0>
b1 ,
b1 ?
b1 =
b0 G
b1111000100111100111011111010110 "
b1111000100111100111011111010110 +
b1111000100111100111011111010110 2
b1111000100111100111011111010110 F
1!
#76000
0!
#76500
b10 L
1:
1D
b1 A
10
1N
19
1'
b1000111010000111100111111010111 %
b1000111010000111100111111010111 3
1!
#77000
0!
#77500
b1 H
b1 B
1/
1J
b0 A
00
0N
0D
17
09
1#
0'
b0 %
b0 3
b10 L
1O
b110 -
b110 @
b110 C
b10 ,
b10 ?
b10 =
b10 K
1!
#78000
0!
#78500
0:
b0 B
0/
0J
07
0#
b1 H
0O
b111 -
b111 @
b111 C
b1 ,
b1 ?
b1 =
b1 G
b1000111010000111100111111010111 "
b1000111010000111100111111010111 +
b1000111010000111100111111010111 2
b1000111010000111100111111010111 F
1!
#79000
0!
#79500
b10 H
1:
b1 B
1/
1J
17
1#
1!
#80000
0!
#80500
b11 L
1D
b1 A
10
1N
19
0#
1'
b110110011010111100010011100010 %
b110110011010111100010011100010 3
1:
b0 B
0/
0J
07
0$
0*
b10 H
14
1E
b1000 -
b1000 @
b0 C
1<
b0 ,
b0 ?
b0 =
b10 G
b100011110101001100101110110 "
b100011110101001100101110110 +
b100011110101001100101110110 2
b100011110101001100101110110 F
1!
#81000
0!
#81500
0:
b0 A
00
0N
0D
09
1#
0'
b0 %
b0 3
b11 L
04
1O
b111 -
b111 @
b111 C
0<
b1 ,
b1 ?
b1 =
b11 K
1!
#82000
0!
#82500
b11 H
1:
b1 B
1/
1J
17
1$
1*
0E
b110110011010111100010011100010 "
b110110011010111100010011100010 +
b110110011010111100010011100010 2
b110110011010111100010011100010 F
1!
#83000
0!
#83500
b100 L
1D
b1 A
10
1N
19
0#
1'
b1110111101110011110110110010001 %
b1110111101110011110110110010001 3
1:
b0 B
0/
0J
07
0$
0*
b11 H
14
0O
1E
b1000 -
b1000 @
b0 C
1<
b0 ,
b0 ?
b0 =
b11 G
b1001111101100010100111000001101 "
b1001111101100010100111000001101 +
b1001111101100010100111000001101 2
b1001111101100010100111000001101 F
1!
#84000
0!
#84500
0:
b0 A
00
0N
0D
09
1#
0'
b0 %
b0 3
b100 L
04
1O
b111 -
b111 @
b111 C
0<
b1 ,
b1 ?
b1 =
b100 K
1!
#85000
0!
#85500
b101 L
1D
b1 A
10
1N
19
1'
b11001111110010100001100011110111 %
b11001111110010100001100011110111 3
b100 H
0:
b1 B
1/
1J
17
1$
1*
0E
b1110111101110011110110110010001 "
b1110111101110011110110110010001 +
b1110111101110011110110110010001 2
b1110111101110011110110110010001 F
1!
#86000
0!
#86500
b0 A
00
0N
0D
09
0#
0'
b0 %
b0 3
0:
b0 B
0/
0J
07
0$
0*
b100 H
b101 L
1E
b100 G
b111 -
b111 @
b111 C
b1 ,
b1 ?
b1 =
b101 K
b1010101111010110100100110101 "
b1010101111010110100100110101 +
b1010101111010110100100110101 2
b1010101111010110100100110101 F
1!
#87000
0!
#87500
b101 H
b110 L
b1 B
1/
1J
1D
b1 A
10
1N
17
19
1#
1'
b101100110001011100100000011111 %
b101100110001011100100000011111 3
1$
1*
0E
b11001111110010100001100011110111 "
b11001111110010100001100011110111 +
b11001111110010100001100011110111 2
b11001111110010100001100011110111 F
1!
#88000
0!
#88500
b0 A
00
0N
0D
09
0#
0'
b0 %
b0 3
0:
b0 B
0/
0J
07
0$
0*
b101 H
b110 L
1E
b101 G
b111 -
b111 @
b111 C
b1 ,
b1 ?
b1 =
b110 K
b1100001100100111010001110010110 "
b1100001100100111010001110010110 +
b1100001100100111010001110010110 2
b1100001100100111010001110010110 F
1!
#89000
0!
#89500
1$
1*
0E
b101100110001011100100000011111 "
b101100110001011100100000011111 +
b101100110001011100100000011111 2
b101100110001011100100000011111 F
1!
#90000
0!
#90500
b110 H
1:
b1 B
1/
1J
17
1#
1!
#91000
0!
#91500
0#
0:
b0 B
0/
0J
07
0$
0*
b110 H
14
0O
1E
b1000 -
b1000 @
b0 C
1<
b0 ,
b0 ?
b0 =
b110 G
b10110110101001111110111010101110 "
b10110110101001111110111010101110 +
b10110110101001111110111010101110 2
b10110110101001111110111010101110 F
1!
#92000
0!
#92500
1#
1!
#93000
0!
#93500
b111 L
1:
1D
b1 A
10
1N
19
1'
b10010000010011011010101011100111 %
b10010000010011011010101011100111 3
1!
#94000
0!
#94500
0:
b0 A
00
0N
0D
09
0'
b0 %
b0 3
b111 L
08
04
1O
b111 -
b111 @
b111 C
1;
0<
b1 ,
b1 ?
b1 =
b111 K
1!
#95000
0!
#95500
b111 H
1:
b1 B
1/
1J
17
1$
1*
0E
b10010000010011011010101011100111 "
b10010000010011011010101011100111 +
b10010000010011011010101011100111 2
b10010000010011011010101011100111 F
1!
#96000
0!
#96500
0#
0:
b0 B
0/
0J
07
0$
0*
b111 H
06
14
0O
1E
b1000 -
b1000 @
b0 C
1>
1<
b0 ,
b0 ?
b0 =
b111 G
b11110110110001110000110010010001 "
b11110110110001110000110010010001 +
b11110110110001110000110010010001 2
b11110110110001110000110010010001 F
1!
#97000
0!
#97500
18
b0 L
1:
1D
b1 A
10
1N
19
1#
1'
b1110110011000011000000111000011 %
b1110110011000011000000111000011 3
1!
#98000
0!
