streamTest/streamFIFO/streamFIFOCC/streamFIFOCC.v
// Generator : SpinalHDL v1.7.0a    git head : 150a9b9067020722818dfb17df4a23ac712a7af8
// Component : streamFIFOCC_1
// Git hash  : 3a903e741cbbe310a98c75dc1ebbd289cb1c87a4

`timescale 1ns/1ps

module streamFIFOCC (
  input               io_s_in_valid,
  output              io_s_in_ready,
  input      [31:0]   io_s_in_payload,
  output              io_m_out_valid,
  input               io_m_out_ready,
  output     [31:0]   io_m_out_payload,
  input               io_s_clk,
  input               io_s_rst,
  input               io_m_clk,
  input               io_m_rst
);

  wire                FIFOCC_io_push_ready;
  wire                FIFOCC_io_pop_valid;
  wire       [31:0]   FIFOCC_io_pop_payload;
  wire       [3:0]    FIFOCC_io_pushOccupancy;
  wire       [3:0]    FIFOCC_io_popOccupancy;

  StreamFifoCC FIFOCC (
    .io_push_valid    (io_s_in_valid               ), //i
    .io_push_ready    (FIFOCC_io_push_ready        ), //o
    .io_push_payload  (io_s_in_payload[31:0]       ), //i
    .io_pop_valid     (FIFOCC_io_pop_valid         ), //o
    .io_pop_ready     (io_m_out_ready              ), //i
    .io_pop_payload   (FIFOCC_io_pop_payload[31:0] ), //o
    .io_pushOccupancy (FIFOCC_io_pushOccupancy[3:0]), //o
    .io_popOccupancy  (FIFOCC_io_popOccupancy[3:0] ), //o
    .io_s_clk         (io_s_clk                    ), //i
    .io_s_rst         (io_s_rst                    ), //i
    .io_m_clk         (io_m_clk                    )  //i
  );
  assign io_s_in_ready = FIFOCC_io_push_ready;
  assign io_m_out_valid = FIFOCC_io_pop_valid;
  assign io_m_out_payload = FIFOCC_io_pop_payload;

endmodule

module StreamFifoCC (
  input               io_push_valid,
  output              io_push_ready,
  input      [31:0]   io_push_payload,
  output              io_pop_valid,
  input               io_pop_ready,
  output     [31:0]   io_pop_payload,
  output     [3:0]    io_pushOccupancy,
  output     [3:0]    io_popOccupancy,
  input               io_s_clk,
  input               io_s_rst,
  input               io_m_clk
);

  reg        [31:0]   _zz_ram_port1;
  wire       [3:0]    popToPushGray_buffercc_io_dataOut;
  wire                bufferCC_3_io_dataOut;
  wire       [3:0]    pushToPopGray_buffercc_io_dataOut;
  wire       [3:0]    _zz_pushCC_pushPtrGray;
  wire       [2:0]    _zz_ram_port;
  wire       [3:0]    _zz_popCC_popPtrGray;
  wire       [2:0]    _zz_ram_port_1;
  wire                _zz_ram_port_2;
  wire       [2:0]    _zz_io_pop_payload_1;
  wire                _zz_io_pop_payload_2;
  reg                 _zz_1;
  wire       [3:0]    popToPushGray;
  wire       [3:0]    pushToPopGray;
  reg        [3:0]    pushCC_pushPtr;
  wire       [3:0]    pushCC_pushPtrPlus;
  wire                io_push_fire;
  reg        [3:0]    pushCC_pushPtrGray;
  wire       [3:0]    pushCC_popPtrGray;
  wire                pushCC_full;
  wire                io_push_fire_1;
  wire                _zz_io_pushOccupancy;
  wire                _zz_io_pushOccupancy_1;
  wire                _zz_io_pushOccupancy_2;
  wire                toplevel_io_s_rst_syncronized;
  reg        [3:0]    popCC_popPtr;
  wire       [3:0]    popCC_popPtrPlus;
  wire                io_pop_fire;
  reg        [3:0]    popCC_popPtrGray;
  wire       [3:0]    popCC_pushPtrGray;
  wire                popCC_empty;
  wire                io_pop_fire_1;
  wire       [3:0]    _zz_io_pop_payload;
  wire                io_pop_fire_2;
  wire                _zz_io_popOccupancy;
  wire                _zz_io_popOccupancy_1;
  wire                _zz_io_popOccupancy_2;
  reg [31:0] ram [0:7];

  assign _zz_pushCC_pushPtrGray = (pushCC_pushPtrPlus >>> 1'b1);
  assign _zz_ram_port = pushCC_pushPtr[2:0];
  assign _zz_popCC_popPtrGray = (popCC_popPtrPlus >>> 1'b1);
  assign _zz_io_pop_payload_1 = _zz_io_pop_payload[2:0];
  assign _zz_io_pop_payload_2 = 1'b1;
  always @(posedge io_s_clk) begin
    if(_zz_1) begin
      ram[_zz_ram_port] <= io_push_payload;
    end
  end

  always @(posedge io_m_clk) begin
    if(_zz_io_pop_payload_2) begin
      _zz_ram_port1 <= ram[_zz_io_pop_payload_1];
    end
  end

  BufferCC popToPushGray_buffercc (
    .io_dataIn  (popToPushGray[3:0]                    ), //i
    .io_dataOut (popToPushGray_buffercc_io_dataOut[3:0]), //o
    .io_s_clk   (io_s_clk                              ), //i
    .io_s_rst   (io_s_rst                              )  //i
  );
  BufferCC_1 bufferCC_3 (
    .io_dataIn  (1'b0                 ), //i
    .io_dataOut (bufferCC_3_io_dataOut), //o
    .io_m_clk   (io_m_clk             ), //i
    .io_s_rst   (io_s_rst             )  //i
  );
  BufferCC_2 pushToPopGray_buffercc (
    .io_dataIn                     (pushToPopGray[3:0]                    ), //i
    .io_dataOut                    (pushToPopGray_buffercc_io_dataOut[3:0]), //o
    .io_m_clk                      (io_m_clk                              ), //i
    .toplevel_io_s_rst_syncronized (toplevel_io_s_rst_syncronized         )  //i
  );
  always @(*) begin
    _zz_1 = 1'b0;
    if(io_push_fire_1) begin
      _zz_1 = 1'b1;
    end
  end

  assign pushCC_pushPtrPlus = (pushCC_pushPtr + 4'b0001);
  assign io_push_fire = (io_push_valid && io_push_ready);
  assign pushCC_popPtrGray = popToPushGray_buffercc_io_dataOut;
  assign pushCC_full = ((pushCC_pushPtrGray[3 : 2] == (~ pushCC_popPtrGray[3 : 2])) && (pushCC_pushPtrGray[1 : 0] == pushCC_popPtrGray[1 : 0]));
  assign io_push_ready = (! pushCC_full);
  assign io_push_fire_1 = (io_push_valid && io_push_ready);
  assign _zz_io_pushOccupancy = (pushCC_popPtrGray[1] ^ _zz_io_pushOccupancy_1);
  assign _zz_io_pushOccupancy_1 = (pushCC_popPtrGray[2] ^ _zz_io_pushOccupancy_2);
  assign _zz_io_pushOccupancy_2 = pushCC_popPtrGray[3];
  assign io_pushOccupancy = (pushCC_pushPtr - {_zz_io_pushOccupancy_2,{_zz_io_pushOccupancy_1,{_zz_io_pushOccupancy,(pushCC_popPtrGray[0] ^ _zz_io_pushOccupancy)}}});
  assign toplevel_io_s_rst_syncronized = bufferCC_3_io_dataOut;
  assign popCC_popPtrPlus = (popCC_popPtr + 4'b0001);
  assign io_pop_fire = (io_pop_valid && io_pop_ready);
  assign popCC_pushPtrGray = pushToPopGray_buffercc_io_dataOut;
  assign popCC_empty = (popCC_popPtrGray == popCC_pushPtrGray);
  assign io_pop_valid = (! popCC_empty);
  assign io_pop_fire_1 = (io_pop_valid && io_pop_ready);
  assign _zz_io_pop_payload = (io_pop_fire_1 ? popCC_popPtrPlus : popCC_popPtr);
  assign io_pop_payload = _zz_ram_port1;
  assign io_pop_fire_2 = (io_pop_valid && io_pop_ready);
  assign _zz_io_popOccupancy = (popCC_pushPtrGray[1] ^ _zz_io_popOccupancy_1);
  assign _zz_io_popOccupancy_1 = (popCC_pushPtrGray[2] ^ _zz_io_popOccupancy_2);
  assign _zz_io_popOccupancy_2 = popCC_pushPtrGray[3];
  assign io_popOccupancy = ({_zz_io_popOccupancy_2,{_zz_io_popOccupancy_1,{_zz_io_popOccupancy,(popCC_pushPtrGray[0] ^ _zz_io_popOccupancy)}}} - popCC_popPtr);
  assign pushToPopGray = pushCC_pushPtrGray;
  assign popToPushGray = popCC_popPtrGray;
  always @(posedge io_s_clk or posedge io_s_rst) begin
    if(io_s_rst) begin
      pushCC_pushPtr <= 4'b0000;
      pushCC_pushPtrGray <= 4'b0000;
    end else begin
      if(io_push_fire) begin
        pushCC_pushPtrGray <= (_zz_pushCC_pushPtrGray ^ pushCC_pushPtrPlus);
      end
      if(io_push_fire_1) begin
        pushCC_pushPtr <= pushCC_pushPtrPlus;
      end
    end
  end

  always @(posedge io_m_clk or posedge toplevel_io_s_rst_syncronized) begin
    if(toplevel_io_s_rst_syncronized) begin
      popCC_popPtr <= 4'b0000;
      popCC_popPtrGray <= 4'b0000;
    end else begin
      if(io_pop_fire) begin
        popCC_popPtrGray <= (_zz_popCC_popPtrGray ^ popCC_popPtrPlus);
      end
      if(io_pop_fire_2) begin
        popCC_popPtr <= popCC_popPtrPlus;
      end
    end
  end


endmodule

module BufferCC_2 (
  input      [3:0]    io_dataIn,
  output     [3:0]    io_dataOut,
  input               io_m_clk,
  input               toplevel_io_s_rst_syncronized
);

  (* async_reg = "true" *) reg        [3:0]    buffers_0;
  (* async_reg = "true" *) reg        [3:0]    buffers_1;

  assign io_dataOut = buffers_1;
  always @(posedge io_m_clk or posedge toplevel_io_s_rst_syncronized) begin
    if(toplevel_io_s_rst_syncronized) begin
      buffers_0 <= 4'b0000;
      buffers_1 <= 4'b0000;
    end else begin
      buffers_0 <= io_dataIn;
      buffers_1 <= buffers_0;
    end
  end


endmodule

module BufferCC_1 (
  input               io_dataIn,
  output              io_dataOut,
  input               io_m_clk,
  input               io_s_rst
);

  (* async_reg = "true" *) reg                 buffers_0;
  (* async_reg = "true" *) reg                 buffers_1;

  assign io_dataOut = buffers_1;
  always @(posedge io_m_clk or posedge io_s_rst) begin
    if(io_s_rst) begin
      buffers_0 <= 1'b1;
      buffers_1 <= 1'b1;
    end else begin
      buffers_0 <= io_dataIn;
      buffers_1 <= buffers_0;
    end
  end


endmodule

module BufferCC (
  input      [3:0]    io_dataIn,
  output     [3:0]    io_dataOut,
  input               io_s_clk,
  input               io_s_rst
);

  (* async_reg = "true" *) reg        [3:0]    buffers_0;
  (* async_reg = "true" *) reg        [3:0]    buffers_1;

  assign io_dataOut = buffers_1;
  always @(posedge io_s_clk or posedge io_s_rst) begin
    if(io_s_rst) begin
      buffers_0 <= 4'b0000;
      buffers_1 <= 4'b0000;
    end else begin
      buffers_0 <= io_dataIn;
      buffers_1 <= buffers_0;
    end
  end

  initial begin
    $dumpfile("streamFIFOCC.vcd");
    $dumpvars(0, streamFIFOCC);
  end  

endmodule

streamTest/streamFIFO/streamFIFOCC/streamFIFOCC.vcd
$date
	Fri May 27 06:46:55 2022
$end
$version
	Icarus Verilog
$end
$timescale
	1ps
$end
$scope module streamFIFOCC $end
$var wire 1 ! io_m_clk $end
$var wire 32 " io_m_out_payload [31:0] $end
$var wire 1 # io_m_out_ready $end
$var wire 1 $ io_m_out_valid $end
$var wire 1 % io_m_rst $end
$var wire 1 & io_s_clk $end
$var wire 32 ' io_s_in_payload [31:0] $end
$var wire 1 ( io_s_in_ready $end
$var wire 1 ) io_s_in_valid $end
$var wire 1 * io_s_rst $end
$var wire 1 + FIFOCC_io_push_ready $end
$var wire 4 , FIFOCC_io_pushOccupancy [3:0] $end
$var wire 1 - FIFOCC_io_pop_valid $end
$var wire 32 . FIFOCC_io_pop_payload [31:0] $end
$var wire 4 / FIFOCC_io_popOccupancy [3:0] $end
$scope module FIFOCC $end
$var wire 1 0 _zz_io_popOccupancy $end
$var wire 1 1 _zz_io_popOccupancy_1 $end
$var wire 1 2 _zz_io_pop_payload_2 $end
$var wire 1 3 _zz_io_pushOccupancy $end
$var wire 1 4 _zz_io_pushOccupancy_1 $end
$var wire 1 ! io_m_clk $end
$var wire 1 5 io_pop_fire $end
$var wire 1 6 io_pop_fire_1 $end
$var wire 1 7 io_pop_fire_2 $end
$var wire 32 8 io_pop_payload [31:0] $end
$var wire 1 # io_pop_ready $end
$var wire 1 9 io_push_fire $end
$var wire 1 : io_push_fire_1 $end
$var wire 32 ; io_push_payload [31:0] $end
$var wire 1 ) io_push_valid $end
$var wire 1 & io_s_clk $end
$var wire 1 * io_s_rst $end
$var wire 4 < popCC_pushPtrGray [3:0] $end
$var wire 4 = popToPushGray [3:0] $end
$var wire 1 > pushCC_full $end
$var wire 4 ? pushCC_popPtrGray [3:0] $end
$var wire 4 @ pushToPopGray [3:0] $end
$var wire 1 A toplevel_io_s_rst_syncronized $end
$var wire 4 B pushToPopGray_buffercc_io_dataOut [3:0] $end
$var wire 4 C pushCC_pushPtrPlus [3:0] $end
$var wire 4 D popToPushGray_buffercc_io_dataOut [3:0] $end
$var wire 4 E popCC_popPtrPlus [3:0] $end
$var wire 1 F popCC_empty $end
$var wire 1 + io_push_ready $end
$var wire 4 G io_pushOccupancy [3:0] $end
$var wire 1 - io_pop_valid $end
$var wire 4 H io_popOccupancy [3:0] $end
$var wire 1 I bufferCC_3_io_dataOut $end
$var wire 3 J _zz_ram_port [2:0] $end
$var wire 4 K _zz_pushCC_pushPtrGray [3:0] $end
$var wire 4 L _zz_popCC_popPtrGray [3:0] $end
$var wire 1 M _zz_io_pushOccupancy_2 $end
$var wire 3 N _zz_io_pop_payload_1 [2:0] $end
$var wire 4 O _zz_io_pop_payload [3:0] $end
$var wire 1 P _zz_io_popOccupancy_2 $end
$var reg 1 Q _zz_1 $end
$var reg 32 R _zz_ram_port1 [31:0] $end
$var reg 4 S popCC_popPtr [3:0] $end
$var reg 4 T popCC_popPtrGray [3:0] $end
$var reg 4 U pushCC_pushPtr [3:0] $end
$var reg 4 V pushCC_pushPtrGray [3:0] $end
$scope module bufferCC_3 $end
$var wire 1 W io_dataIn $end
$var wire 1 I io_dataOut $end
$var wire 1 ! io_m_clk $end
$var wire 1 * io_s_rst $end
$var reg 1 X buffers_0 $end
$var reg 1 I buffers_1 $end
$upscope $end
$scope module popToPushGray_buffercc $end
$var wire 4 Y io_dataIn [3:0] $end
$var wire 4 Z io_dataOut [3:0] $end
$var wire 1 & io_s_clk $end
$var wire 1 * io_s_rst $end
$var reg 4 [ buffers_0 [3:0] $end
$var reg 4 \ buffers_1 [3:0] $end
$upscope $end
$scope module pushToPopGray_buffercc $end
$var wire 4 ] io_dataIn [3:0] $end
$var wire 4 ^ io_dataOut [3:0] $end
$var wire 1 ! io_m_clk $end
$var wire 1 A toplevel_io_s_rst_syncronized $end
$var reg 4 _ buffers_0 [3:0] $end
$var reg 4 ` buffers_1 [3:0] $end
$upscope $end
$upscope $end
$upscope $end
$enddefinitions $end
#0
$dumpvars
b0 `
b0 _
b0 ^
b0 ]
b0 \
b0 [
b0 Z
b0 Y
1X
0W
b0 V
b0 U
b0 T
b0 S
bx R
xQ
0P
b0 O
b0 N
0M
b0 L
b0 K
b0 J
1I
b0 H
b0 G
1F
b1 E
b0 D
b1 C
b0 B
1A
b0 @
b0 ?
0>
b0 =
b0 <
bz ;
x:
x9
bx 8
07
06
05
04
03
12
01
00
b0 /
bx .
0-
b0 ,
1+
1*
z)
1(
bz '
0&
1%
0$
z#
bx "
0!
$end
#1000
0Q
09
0:
0)
b0 '
b0 ;
0#
0*
0%
#1500
1&
#1600
0X
1!
#2000
0&
#2200
0!
#2500
1&
#2800
0A
0I
1!
#3000
0&
#3400
0!
#3500
1Q
19
1:
1)
1&
#4000
1#
1!
0&
#4500
b1 J
b1 K
b10 C
b1 ,
b1 G
b1 U
b1 @
b1 ]
b1 V
1&
#4600
0!
#5000
0&
#5200
b1 _
b0 "
b0 .
b0 8
b0 R
1!
#5500
0Q
09
0:
0)
b10 J
b11 C
b10 ,
b10 G
b10 U
b11 @
b11 ]
b11 V
1&
#5800
0!
#6000
0&
#6400
b1 N
b1 O
b1 /
b1 H
17
16
15
1$
1-
0F
b1 <
b1 B
b1 ^
b1 `
b11 _
1!
#6500
1Q
19
1:
1)
b10010100101101011000111000001110 '
b10010100101101011000111000001110 ;
1&
#7000
0!
0&
#7500
0Q
09
0:
0)
b0 '
b0 ;
b11 J
b10 K
b100 C
b11 ,
b11 G
b11 U
b10 @
b10 ]
b10 V
1&
#7600
05
06
07
0#
10
b1 N
b1 O
b1 L
b11 <
b11 B
b11 ^
b11 `
b10 _
b10 E
b1 /
b1 H
b1 S
1$
1-
0F
b1 =
b1 Y
b1 T
1!
#8000
0&
#8200
0!
#8500
b1 [
1&
#8800
b10 /
b10 H
b10 <
b10 B
b10 ^
b10 `
1!
#9000
0&
#9400
0!
#9500
b10 ,
b10 G
b1 ?
b1 D
b1 Z
b1 \
1&
#10000
1!
0&
#10500
1Q
19
1:
1)
b10111000000001011011000011010100 '
b10111000000001011011000011010100 ;
1&
#10600
0!
#11000
0&
#11200
1!
#11500
0Q
09
0:
0)
b0 '
b0 ;
b100 J
b101 C
b11 ,
b11 G
b100 U
b110 @
b110 ]
b110 V
1&
#11800
0!
#12000
0&
#12400
b110 _
1!
#12500
1&
#13000
0!
0&
#13500
1Q
19
1:
1)
b10011010000000010101111111100000 '
b10011010000000010101111111100000 ;
1&
#13600
00
b11 /
b11 H
11
b110 <
b110 B
b110 ^
b110 `
1!
#14000
0&
#14200
0!
#14500
0Q
09
0:
0)
b0 '
b0 ;
b101 J
b11 K
b110 C
b100 ,
b100 G
b101 U
b111 @
b111 ]
b111 V
1&
#14800
b10 N
b10 O
15
16
17
1#
b111 _
1!
#15000
0&
#15400
0!
#15500
1Q
19
1:
1)
b10101010111011000111001000010000 '
b10101010111011000111001000010000 ;
1&
#16000
05
06
07
0#
b10 N
b10 O
b11 E
b11 /
b11 H
b10 S
b11 =
b11 Y
b11 T
b111 <
b111 B
b111 ^
b111 `
b10010100101101011000111000001110 "
b10010100101101011000111000001110 .
b10010100101101011000111000001110 8
b10010100101101011000111000001110 R
1!
0&
#16500
0Q
09
0:
0)
b0 '
b0 ;
b110 J
b11 [
b111 C
b101 ,
b101 G
b110 U
b101 @
b101 ]
b101 V
1&
#16600
0!
#17000
0&
#17200
b101 _
1!
#17500
b100 ,
b100 G
13
b11 ?
b11 D
b11 Z
b11 \
1&
#17800
0!
#18000
0&
#18400
b11 N
b11 O
15
16
17
1#
b100 /
b100 H
10
b101 <
b101 B
b101 ^
b101 `
1!
#18500
1&
#19000
0!
0&
#19500
1&
#19600
05
06
07
0#
b11 N
b11 O
b10 L
b100 E
b11 /
b11 H
b11 S
b10 =
b10 Y
b10 T
b10111000000001011011000011010100 "
b10111000000001011011000011010100 .
b10111000000001011011000011010100 8
b10111000000001011011000011010100 R
1!
#20000
0&
#20200
0!
#20500
1Q
19
1:
1)
b11110111010001011111101010011000 '
b11110111010001011111101010011000 ;
b10 [
1&
#20800
b100 N
b100 O
15
16
17
1#
1!
#21000
0&
#21400
0!
#21500
0Q
09
0:
0)
b0 '
b0 ;
b111 J
b100 K
b1000 C
b100 ,
b100 G
b111 U
b100 @
b100 ]
b100 V
b10 ?
b10 D
b10 Z
b10 \
1&
#22000
05
06
07
0#
b100 N
b100 O
b100 _
b101 E
b10 /
b10 H
b100 S
b110 =
b110 Y
b110 T
b10011010000000010101111111100000 "
b10011010000000010101111111100000 .
b10011010000000010101111111100000 8
b10011010000000010101111111100000 R
1!
0&
#22500
1Q
19
1:
1)
b11010101010011111101000111001110 '
b11010101010011111101000111001110 ;
b110 [
1&
#22600
0!
#23000
0&
#23200
b101 N
b101 O
15
16
17
1#
b11 /
b11 H
b100 <
b100 B
b100 ^
b100 `
1!
#23500
0Q
09
0:
0)
b0 '
b0 ;
03
14
b0 J
b1001 C
b100 ,
b100 G
b1000 U
b1100 @
b1100 ]
b1100 V
b110 ?
b110 D
b110 Z
b110 \
1&
#23800
0!
#24000
0&
#24400
05
06
07
0#
b101 N
b101 O
b11 L
b1100 _
b110 E
b10 /
b10 H
b101 S
b111 =
b111 Y
b111 T
b10101010111011000111001000010000 "
b10101010111011000111001000010000 .
b10101010111011000111001000010000 8
b10101010111011000111001000010000 R
1!
#24500
b111 [
1&
#25000
0!
0&
#25500
b11 ,
b11 G
b111 ?
b111 D
b111 Z
b111 \
1&
#25600
00
01
b11 /
b11 H
1P
b1100 <
b1100 B
b1100 ^
b1100 `
1!
#26000
0&
#26200
0!
#26500
1Q
19
1:
1)
b11010000101011001011111010100110 '
b11010000101011001011111010100110 ;
1&
#26800
1!
#27000
0&
#27400
0!
#27500
0Q
09
0:
0)
b0 '
b0 ;
b1 J
b101 K
b1010 C
b100 ,
b100 G
b1001 U
b1101 @
b1101 ]
b1101 V
1&
#28000
b1101 _
1!
0&
#28500
1Q
19
1:
1)
b1001000110101101011011000111110 '
b1001000110101101011011000111110 ;
1&
#28600
0!
#29000
0&
#29200
b110 N
b110 O
15
16
17
1#
b100 /
b100 H
b1101 <
b1101 B
b1101 ^
b1101 `
1!
#29500
0Q
09
0:
0)
b0 '
b0 ;
b10 J
b1011 C
b101 ,
b101 G
b1010 U
b1111 @
b1111 ]
b1111 V
1&
#29800
0!
#30000
0&
#30400
05
06
07
0#
b110 N
b110 O
b111 E
b11 /
b11 H
b110 S
b101 =
b101 Y
b101 T
b1111 _
b11110111010001011111101010011000 "
b11110111010001011111101010011000 .
b11110111010001011111101010011000 8
b11110111010001011111101010011000 R
1!
#30500
1Q
19
1:
1)
b1000110010111001100010010110 '
b1000110010111001100010010110 ;
b101 [
1&
#31000
0!
0&
#31500
0Q
09
0:
0)
b0 '
b0 ;
13
b11 J
b110 K
b1100 C
b101 ,
b101 G
b1011 U
b1110 @
b1110 ]
b1110 V
b101 ?
b101 D
b101 Z
b101 \
1&
#31600
b100 /
b100 H
10
b1111 <
b1111 B
b1111 ^
b1111 `
b1110 _
1!
#32000
0&
#32200
0!
#32500
1&
#32800
b101 /
b101 H
b1110 <
b1110 B
b1110 ^
b1110 `
1!
#33000
0&
#33400
0!
#33500
1Q
19
1:
1)
b111001011011011110000001001001 '
b111001011011011110000001001001 ;
1&
#34000
1!
0&
#34500
0Q
09
0:
0)
b0 '
b0 ;
b100 J
b1101 C
b110 ,
b110 G
b1100 U
b1010 @
b1010 ]
b1010 V
1&
#34600
0!
#35000
0&
#35200
b111 N
b111 O
15
16
17
1#
b1010 _
1!
#35500
1&
#35800
0!
#36000
0&
#36400
05
06
07
0#
00
11
b111 N
b111 O
b100 L
b1010 <
b1010 B
b1010 ^
b1010 `
b1000 E
b101 /
b101 H
b111 S
b100 =
b100 Y
b100 T
b11010101010011111101000111001110 "
b11010101010011111101000111001110 .
b11010101010011111101000111001110 8
b11010101010011111101000111001110 R
1!
#36500
b100 [
1&
#37000
0!
0&
#37500
b101 ,
b101 G
b100 ?
b100 D
b100 Z
b100 \
1&
#37600
b0 N
b1000 O
15
16
17
1#
1!
#38000
0&
#38200
0!
#38500
1&
#38800
05
06
07
0#
b0 N
b1000 O
b1001 E
b100 /
b100 H
b1000 S
b1100 =
b1100 Y
b1100 T
b11010000101011001011111010100110 "
b11010000101011001011111010100110 .
b11010000101011001011111010100110 8
b11010000101011001011111010100110 R
1!
#39000
0&
#39400
0!
#39500
1Q
19
1:
1)
b101001001010010110001000111110 '
b101001001010010110001000111110 ;
b1100 [
1&
#40000
b1 N
b1001 O
15
16
17
1#
1!
0&
#40500
0Q
09
0:
0)
b0 '
b0 ;
03
04
1M
b101 J
b111 K
b1100 ?
b1100 D
b1100 Z
b1100 \
b1110 C
b101 ,
b101 G
b1101 U
b1011 @
b1011 ]
b1011 V
1&
#40600
0!
#41000
0&
#41200
05
06
07
0#
b1 N
b1001 O
b101 L
b1011 _
b1010 E
b11 /
b11 H
b1001 S
b1101 =
b1101 Y
b1101 T
b1001000110101101011011000111110 "
b1001000110101101011011000111110 .
b1001000110101101011011000111110 8
b1001000110101101011011000111110 R
1!
#41500
1Q
19
1:
1)
b11000100001110011110110101010110 '
b11000100001110011110110101010110 ;
b1101 [
1&
#41800
0!
#42000
0&
#42400
b10 N
b1010 O
15
16
17
1#
b100 /
b100 H
b1011 <
b1011 B
b1011 ^
b1011 `
1!
#42500
0Q
09
0:
0)
b0 '
b0 ;
b110 J
b1101 ?
b1101 D
b1101 Z
b1101 \
b1111 C
b101 ,
b101 G
b1110 U
b1001 @
b1001 ]
b1001 V
1&
#43000
0!
0&
#43500
1&
#43600
05
06
07
0#
b10 N
b1010 O
b1001 _
b1011 E
b11 /
b11 H
b1010 S
b1111 =
b1111 Y
b1111 T
b1000110010111001100010010110 "
b1000110010111001100010010110 .
b1000110010111001100010010110 8
b1000110010111001100010010110 R
1!
#44000
0&
#44200
0!
#44500
1Q
19
1:
1)
b11110101111011110100001101110100 '
b11110101111011110100001101110100 ;
b1111 [
1&
#44800
b11 N
b1011 O
15
16
17
1#
b100 /
b100 H
10
b1001 <
b1001 B
b1001 ^
b1001 `
1!
#45000
0&
#45400
0!
#45500
0Q
09
0:
0)
b0 '
b0 ;
13
b111 J
b0 K
b0 C
b101 ,
b101 G
b1111 U
b1000 @
b1000 ]
b1000 V
b1111 ?
b1111 D
b1111 Z
b1111 \
1&
#46000
05
06
07
0#
b11 N
b1011 O
b110 L
b1000 _
b1100 E
b11 /
b11 H
b1011 S
b1110 =
b1110 Y
b1110 T
b111001011011011110000001001001 "
b111001011011011110000001001001 .
b111001011011011110000001001001 8
b111001011011011110000001001001 R
1!
0&
#46500
1Q
19
1:
1)
b10010001110111110000011011101101 '
b10010001110111110000011011101101 ;
b1110 [
1&
#46600
0!
#47000
0&
#47200
b100 N
b1100 O
15
16
17
1#
b100 /
b100 H
b1000 <
b1000 B
b1000 ^
b1000 `
1!
#47500
0Q
09
0:
0)
b0 '
b0 ;
b0 J
b1 C
b101 ,
b101 G
b0 U
b0 @
b0 ]
b0 V
b1110 ?
b1110 D
b1110 Z
b1110 \
1&
#47800
0!
#48000
0&
#48400
05
06
07
0#
b100 N
b1100 O
b0 _
b1101 E
b11 /
b11 H
b1100 S
b1010 =
b1010 Y
b1010 T
b101001001010010110001000111110 "
b101001001010010110001000111110 .
b101001001010010110001000111110 8
b101001001010010110001000111110 R
1!
#48500
b1010 [
1&
#49000
0!
0&
#49500
03
b100 ,
b100 G
14
b1010 ?
b1010 D
b1010 Z
b1010 \
1&
#49600
00
01
b100 /
b100 H
0P
b0 <
b0 B
b0 ^
b0 `
1!
#50000
0&
#50200
0!
#50500
1Q
19
1:
1)
b100010110111010011010011110000 '
b100010110111010011010011110000 ;
1&
#50800
1!
#51000
0&
#51400
0!
#51500
0Q
09
0:
0)
b0 '
b0 ;
b1 J
b1 K
b10 C
b101 ,
b101 G
b1 U
b1 @
b1 ]
b1 V
1&
#52000
b101 N
b1101 O
15
16
17
1#
b1 _
1!
0&
#52500
1Q
19
1:
1)
b1010001100011101111011010010010 '
b1010001100011101111011010010010 ;
1&
#52600
0!
#53000
0&
#53200
05
06
07
0#
b101 N
b1101 O
b111 L
b1 <
b1 B
b1 ^
b1 `
b1110 E
b100 /
b100 H
b1101 S
b1011 =
b1011 Y
b1011 T
b11000100001110011110110101010110 "
b11000100001110011110110101010110 .
b11000100001110011110110101010110 8
b11000100001110011110110101010110 R
1!
#53500
0Q
09
0:
0)
b0 '
b0 ;
b10 J
b11 C
b110 ,
b110 G
b10 U
b11 @
b11 ]
b11 V
b1011 [
1&
#53800
0!
#54000
0&
#54400
b110 N
b1110 O
15
16
17
1#
b11 _
1!
#54500
b101 ,
b101 G
b1011 ?
b1011 D
b1011 Z
b1011 \
1&
#55000
0!
0&
#55500
1&
#55600
05
06
07
0#
10
b110 N
b1110 O
b11 <
b11 B
b11 ^
b11 `
b1111 E
b100 /
b100 H
b1110 S
b1001 =
b1001 Y
b1001 T
b11110101111011110100001101110100 "
b11110101111011110100001101110100 .
b11110101111011110100001101110100 8
b11110101111011110100001101110100 R
1!
#56000
0&
#56200
0!
#56500
b1001 [
1&
#56800
b111 N
b1111 O
15
16
17
1#
1!
#57000
0&
#57400
0!
#57500
1Q
19
1:
1)
b10100110100000110010100010111110 '
b10100110100000110010100010111110 ;
b100 ,
b100 G
13
b1001 ?
b1001 D
b1001 Z
b1001 \
1&
#58000
05
06
07
0#
b111 N
b1111 O
b0 L
b0 E
b11 /
b11 H
b1111 S
b1000 =
b1000 Y
b1000 T
b10010001110111110000011011101101 "
b10010001110111110000011011101101 .
b10010001110111110000011011101101 8
b10010001110111110000011011101101 R
1!
0&
#58500
0Q
09
0:
0)
b0 '
b0 ;
b11 J
b10 K
b1000 [
b100 C
b101 ,
b101 G
b11 U
b10 @
b10 ]
b10 V
1&
#58600
0!
#59000
0&
#59200
b0 N
b0 O
15
16
17
1#
b10 _
1!
#59500
1Q
19
1:
1)
b1111010001000000101100100101111 '
b1111010001000000101100100101111 ;
b100 ,
b100 G
b1000 ?
b1000 D
b1000 Z
b1000 \
1&
#59800
0!
#60000
0&
#60400
05
06
07
0#
b0 N
b0 O
b10 <
b10 B
b10 ^
b10 `
b1 E
b11 /
b11 H
b0 S
b0 =
b0 Y
b0 T
b100010110111010011010011110000 "
b100010110111010011010011110000 .
b100010110111010011010011110000 8
b100010110111010011010011110000 R
1!
#60500
0Q
09
0:
0)
b0 '
b0 ;
b100 J
b0 [
b101 C
b101 ,
b101 G
b100 U
b110 @
b110 ]
b110 V
1&
#61000
0!
0&
#61500
1Q
19
1:
1)
b110001001100111110000100011010 '
b110001001100111110000100011010 ;
03
04
b100 ,
b100 G
0M
b0 ?
b0 D
b0 Z
b0 \
1&
#61600
b110 _
1!
#62000
0&
#62200
0!
#62500
0Q
09
0:
0)
b0 '
b0 ;
b101 J
b11 K
b110 C
b101 ,
b101 G
b101 U
b111 @
b111 ]
b111 V
1&
#62800
b1 N
b1 O
15
16
17
1#
00
b100 /
b100 H
11
b110 <
b110 B
b110 ^
b110 `
b111 _
1!
#63000
0&
#63400
0!
#63500
1Q
19
1:
1)
b11011111110010111000000101101100 '
b11011111110010111000000101101100 ;
1&
#64000
05
06
07
0#
b1 N
b1 O
b1 L
b10 E
b100 /
b100 H
b1 S
b1 =
b1 Y
b1 T
b111 <
b111 B
b111 ^
b111 `
b1010001100011101111011010010010 "
b1010001100011101111011010010010 .
b1010001100011101111011010010010 8
b1010001100011101111011010010010 R
1!
0&
#64500
0Q
09
0:
0)
b0 '
b0 ;
b110 J
b1 [
b111 C
b110 ,
b110 G
b110 U
b101 @
b101 ]
b101 V
1&
#64600
0!
#65000
0&
#65200
b101 _
1!
#65500
1Q
19
1:
1)
b11010100011101010111010011010000 '
b11010100011101010111010011010000 ;
b101 ,
b101 G
b1 ?
b1 D
b1 Z
b1 \
1&
#65800
0!
#66000
0&
