streamTest/streamArbiter/roundRobin/streamArbiterRoundRobin.v
// Generator : SpinalHDL v1.7.0a    git head : 150a9b9067020722818dfb17df4a23ac712a7af8
// Component : streamArbiterRoundRobin
// Git hash  : 3a903e741cbbe310a98c75dc1ebbd289cb1c87a4

`timescale 1ns/1ps

module streamArbiterRoundRobin (
  input               io_s_in_0_valid,
  output              io_s_in_0_ready,
  input      [31:0]   io_s_in_0_payload,
  input               io_s_in_1_valid,
  output              io_s_in_1_ready,
  input      [31:0]   io_s_in_1_payload,
  input               io_s_in_2_valid,
  output              io_s_in_2_ready,
  input      [31:0]   io_s_in_2_payload,
  input               io_s_in_3_valid,
  output              io_s_in_3_ready,
  input      [31:0]   io_s_in_3_payload,
  output              io_m_out_valid,
  input               io_m_out_ready,
  output     [31:0]   io_m_out_payload,
  input               clk,
  input               reset
);

  wire                streamArbiter_1_io_output_ready;
  wire                streamArbiter_1_io_inputs_0_ready;
  wire                streamArbiter_1_io_inputs_1_ready;
  wire                streamArbiter_1_io_inputs_2_ready;
  wire                streamArbiter_1_io_inputs_3_ready;
  wire                streamArbiter_1_io_output_valid;
  wire       [31:0]   streamArbiter_1_io_output_payload;
  wire       [1:0]    streamArbiter_1_io_chosen;
  wire       [3:0]    streamArbiter_1_io_chosenOH;
  wire                streamArbiter_1_io_output_s2mPipe_valid;
  reg                 streamArbiter_1_io_output_s2mPipe_ready;
  wire       [31:0]   streamArbiter_1_io_output_s2mPipe_payload;
  reg                 streamArbiter_1_io_output_rValid;
  reg        [31:0]   streamArbiter_1_io_output_rData;
  wire                streamArbiter_1_io_output_s2mPipe_m2sPipe_valid;
  wire                streamArbiter_1_io_output_s2mPipe_m2sPipe_ready;
  wire       [31:0]   streamArbiter_1_io_output_s2mPipe_m2sPipe_payload;
  reg                 streamArbiter_1_io_output_s2mPipe_rValid;
  reg        [31:0]   streamArbiter_1_io_output_s2mPipe_rData;
  wire                when_Stream_l368;

  StreamArbiter streamArbiter_1 (
    .io_inputs_0_valid   (io_s_in_0_valid                        ), //i
    .io_inputs_0_ready   (streamArbiter_1_io_inputs_0_ready      ), //o
    .io_inputs_0_payload (io_s_in_0_payload[31:0]                ), //i
    .io_inputs_1_valid   (io_s_in_1_valid                        ), //i
    .io_inputs_1_ready   (streamArbiter_1_io_inputs_1_ready      ), //o
    .io_inputs_1_payload (io_s_in_1_payload[31:0]                ), //i
    .io_inputs_2_valid   (io_s_in_2_valid                        ), //i
    .io_inputs_2_ready   (streamArbiter_1_io_inputs_2_ready      ), //o
    .io_inputs_2_payload (io_s_in_2_payload[31:0]                ), //i
    .io_inputs_3_valid   (io_s_in_3_valid                        ), //i
    .io_inputs_3_ready   (streamArbiter_1_io_inputs_3_ready      ), //o
    .io_inputs_3_payload (io_s_in_3_payload[31:0]                ), //i
    .io_output_valid     (streamArbiter_1_io_output_valid        ), //o
    .io_output_ready     (streamArbiter_1_io_output_ready        ), //i
    .io_output_payload   (streamArbiter_1_io_output_payload[31:0]), //o
    .io_chosen           (streamArbiter_1_io_chosen[1:0]         ), //o
    .io_chosenOH         (streamArbiter_1_io_chosenOH[3:0]       ), //o
    .clk                 (clk                                    ), //i
    .reset               (reset                                  )  //i
  );
  assign io_s_in_0_ready = streamArbiter_1_io_inputs_0_ready;
  assign io_s_in_1_ready = streamArbiter_1_io_inputs_1_ready;
  assign io_s_in_2_ready = streamArbiter_1_io_inputs_2_ready;
  assign io_s_in_3_ready = streamArbiter_1_io_inputs_3_ready;
  assign streamArbiter_1_io_output_ready = (! streamArbiter_1_io_output_rValid);
  assign streamArbiter_1_io_output_s2mPipe_valid = (streamArbiter_1_io_output_valid || streamArbiter_1_io_output_rValid);
  assign streamArbiter_1_io_output_s2mPipe_payload = (streamArbiter_1_io_output_rValid ? streamArbiter_1_io_output_rData : streamArbiter_1_io_output_payload);
  always @(*) begin
    streamArbiter_1_io_output_s2mPipe_ready = streamArbiter_1_io_output_s2mPipe_m2sPipe_ready;
    if(when_Stream_l368) begin
      streamArbiter_1_io_output_s2mPipe_ready = 1'b1;
    end
  end

  assign when_Stream_l368 = (! streamArbiter_1_io_output_s2mPipe_m2sPipe_valid);
  assign streamArbiter_1_io_output_s2mPipe_m2sPipe_valid = streamArbiter_1_io_output_s2mPipe_rValid;
  assign streamArbiter_1_io_output_s2mPipe_m2sPipe_payload = streamArbiter_1_io_output_s2mPipe_rData;
  assign io_m_out_valid = streamArbiter_1_io_output_s2mPipe_m2sPipe_valid;
  assign streamArbiter_1_io_output_s2mPipe_m2sPipe_ready = io_m_out_ready;
  assign io_m_out_payload = streamArbiter_1_io_output_s2mPipe_m2sPipe_payload;
  always @(posedge clk or posedge reset) begin
    if(reset) begin
      streamArbiter_1_io_output_rValid <= 1'b0;
      streamArbiter_1_io_output_s2mPipe_rValid <= 1'b0;
    end else begin
      if(streamArbiter_1_io_output_valid) begin
        streamArbiter_1_io_output_rValid <= 1'b1;
      end
      if(streamArbiter_1_io_output_s2mPipe_ready) begin
        streamArbiter_1_io_output_rValid <= 1'b0;
      end
      if(streamArbiter_1_io_output_s2mPipe_ready) begin
        streamArbiter_1_io_output_s2mPipe_rValid <= streamArbiter_1_io_output_s2mPipe_valid;
      end
    end
  end

  always @(posedge clk) begin
    if(streamArbiter_1_io_output_ready) begin
      streamArbiter_1_io_output_rData <= streamArbiter_1_io_output_payload;
    end
    if(streamArbiter_1_io_output_s2mPipe_ready) begin
      streamArbiter_1_io_output_s2mPipe_rData <= streamArbiter_1_io_output_s2mPipe_payload;
    end
  end


endmodule

module StreamArbiter (
  input               io_inputs_0_valid,
  output              io_inputs_0_ready,
  input      [31:0]   io_inputs_0_payload,
  input               io_inputs_1_valid,
  output              io_inputs_1_ready,
  input      [31:0]   io_inputs_1_payload,
  input               io_inputs_2_valid,
  output              io_inputs_2_ready,
  input      [31:0]   io_inputs_2_payload,
  input               io_inputs_3_valid,
  output              io_inputs_3_ready,
  input      [31:0]   io_inputs_3_payload,
  output              io_output_valid,
  input               io_output_ready,
  output     [31:0]   io_output_payload,
  output     [1:0]    io_chosen,
  output     [3:0]    io_chosenOH,
  input               clk,
  input               reset
);

  wire       [7:0]    _zz__zz_maskProposal_0_2;
  wire       [7:0]    _zz__zz_maskProposal_0_2_1;
  wire       [3:0]    _zz__zz_maskProposal_0_2_2;
  reg        [31:0]   _zz_io_output_payload_2;
  wire       [1:0]    _zz_io_output_payload_3;
  reg                 locked;
  wire                maskProposal_0;
  wire                maskProposal_1;
  wire                maskProposal_2;
  wire                maskProposal_3;
  reg                 maskLocked_0;
  reg                 maskLocked_1;
  reg                 maskLocked_2;
  reg                 maskLocked_3;
  wire                maskRouted_0;
  wire                maskRouted_1;
  wire                maskRouted_2;
  wire                maskRouted_3;
  wire       [3:0]    _zz_maskProposal_0;
  wire       [7:0]    _zz_maskProposal_0_1;
  wire       [7:0]    _zz_maskProposal_0_2;
  wire       [3:0]    _zz_maskProposal_0_3;
  wire                io_output_fire;
  wire                _zz_io_output_payload;
  wire                _zz_io_output_payload_1;
  wire                _zz_io_chosen;
  wire                _zz_io_chosen_1;
  wire                _zz_io_chosen_2;

  assign _zz__zz_maskProposal_0_2 = (_zz_maskProposal_0_1 - _zz__zz_maskProposal_0_2_1);
  assign _zz__zz_maskProposal_0_2_2 = {maskLocked_2,{maskLocked_1,{maskLocked_0,maskLocked_3}}};
  assign _zz__zz_maskProposal_0_2_1 = {4'd0, _zz__zz_maskProposal_0_2_2};
  assign _zz_io_output_payload_3 = {_zz_io_output_payload_1,_zz_io_output_payload};
  always @(*) begin
    case(_zz_io_output_payload_3)
      2'b00 : _zz_io_output_payload_2 = io_inputs_0_payload;
      2'b01 : _zz_io_output_payload_2 = io_inputs_1_payload;
      2'b10 : _zz_io_output_payload_2 = io_inputs_2_payload;
      default : _zz_io_output_payload_2 = io_inputs_3_payload;
    endcase
  end

  assign maskRouted_0 = (locked ? maskLocked_0 : maskProposal_0);
  assign maskRouted_1 = (locked ? maskLocked_1 : maskProposal_1);
  assign maskRouted_2 = (locked ? maskLocked_2 : maskProposal_2);
  assign maskRouted_3 = (locked ? maskLocked_3 : maskProposal_3);
  assign _zz_maskProposal_0 = {io_inputs_3_valid,{io_inputs_2_valid,{io_inputs_1_valid,io_inputs_0_valid}}};
  assign _zz_maskProposal_0_1 = {_zz_maskProposal_0,_zz_maskProposal_0};
  assign _zz_maskProposal_0_2 = (_zz_maskProposal_0_1 & (~ _zz__zz_maskProposal_0_2));
  assign _zz_maskProposal_0_3 = (_zz_maskProposal_0_2[7 : 4] | _zz_maskProposal_0_2[3 : 0]);
  assign maskProposal_0 = _zz_maskProposal_0_3[0];
  assign maskProposal_1 = _zz_maskProposal_0_3[1];
  assign maskProposal_2 = _zz_maskProposal_0_3[2];
  assign maskProposal_3 = _zz_maskProposal_0_3[3];
  assign io_output_fire = (io_output_valid && io_output_ready);
  assign io_output_valid = ((((io_inputs_0_valid && maskRouted_0) || (io_inputs_1_valid && maskRouted_1)) || (io_inputs_2_valid && maskRouted_2)) || (io_inputs_3_valid && maskRouted_3));
  assign _zz_io_output_payload = (maskRouted_1 || maskRouted_3);
  assign _zz_io_output_payload_1 = (maskRouted_2 || maskRouted_3);
  assign io_output_payload = _zz_io_output_payload_2;
  assign io_inputs_0_ready = (maskRouted_0 && io_output_ready);
  assign io_inputs_1_ready = (maskRouted_1 && io_output_ready);
  assign io_inputs_2_ready = (maskRouted_2 && io_output_ready);
  assign io_inputs_3_ready = (maskRouted_3 && io_output_ready);
  assign io_chosenOH = {maskRouted_3,{maskRouted_2,{maskRouted_1,maskRouted_0}}};
  assign _zz_io_chosen = io_chosenOH[3];
  assign _zz_io_chosen_1 = (io_chosenOH[1] || _zz_io_chosen);
  assign _zz_io_chosen_2 = (io_chosenOH[2] || _zz_io_chosen);
  assign io_chosen = {_zz_io_chosen_2,_zz_io_chosen_1};
  always @(posedge clk or posedge reset) begin
    if(reset) begin
      locked <= 1'b0;
      maskLocked_0 <= 1'b0;
      maskLocked_1 <= 1'b0;
      maskLocked_2 <= 1'b0;
      maskLocked_3 <= 1'b1;
    end else begin
      if(io_output_valid) begin
        maskLocked_0 <= maskRouted_0;
        maskLocked_1 <= maskRouted_1;
        maskLocked_2 <= maskRouted_2;
        maskLocked_3 <= maskRouted_3;
      end
      if(io_output_valid) begin
        locked <= 1'b1;
      end
      if(io_output_fire) begin
        locked <= 1'b0;
      end
    end
  end
  
  initial begin
    $dumpfile("streamArbiterRoundRobin_test.vcd");
    $dumpvars(0, streamArbiterRoundRobin);
  end

endmodule

streamTest/streamArbiter/roundRobin/streamArbiterRoundRobin_test.vcd
$date
	Fri May 27 01:28:22 2022
$end
$version
	Icarus Verilog
$end
$timescale
	1ps
$end
$scope module streamArbiterRoundRobin $end
$var wire 1 ! clk $end
$var wire 32 " io_m_out_payload [31:0] $end
$var wire 1 # io_m_out_ready $end
$var wire 1 $ io_m_out_valid $end
$var wire 32 % io_s_in_0_payload [31:0] $end
$var wire 1 & io_s_in_0_ready $end
$var wire 1 ' io_s_in_0_valid $end
$var wire 32 ( io_s_in_1_payload [31:0] $end
$var wire 1 ) io_s_in_1_ready $end
$var wire 1 * io_s_in_1_valid $end
$var wire 32 + io_s_in_2_payload [31:0] $end
$var wire 1 , io_s_in_2_ready $end
$var wire 1 - io_s_in_2_valid $end
$var wire 32 . io_s_in_3_payload [31:0] $end
$var wire 1 / io_s_in_3_ready $end
$var wire 1 0 io_s_in_3_valid $end
$var wire 1 1 reset $end
$var wire 1 2 streamArbiter_1_io_output_s2mPipe_m2sPipe_ready $end
$var wire 1 3 streamArbiter_1_io_output_s2mPipe_valid $end
$var wire 1 4 when_Stream_l368 $end
$var wire 1 5 streamArbiter_1_io_output_valid $end
$var wire 32 6 streamArbiter_1_io_output_s2mPipe_payload [31:0] $end
$var wire 1 7 streamArbiter_1_io_output_s2mPipe_m2sPipe_valid $end
$var wire 32 8 streamArbiter_1_io_output_s2mPipe_m2sPipe_payload [31:0] $end
$var wire 1 9 streamArbiter_1_io_output_ready $end
$var wire 32 : streamArbiter_1_io_output_payload [31:0] $end
$var wire 1 ; streamArbiter_1_io_inputs_3_ready $end
$var wire 1 < streamArbiter_1_io_inputs_2_ready $end
$var wire 1 = streamArbiter_1_io_inputs_1_ready $end
$var wire 1 > streamArbiter_1_io_inputs_0_ready $end
$var wire 4 ? streamArbiter_1_io_chosenOH [3:0] $end
$var wire 2 @ streamArbiter_1_io_chosen [1:0] $end
$var reg 32 A streamArbiter_1_io_output_rData [31:0] $end
$var reg 1 B streamArbiter_1_io_output_rValid $end
$var reg 32 C streamArbiter_1_io_output_s2mPipe_rData [31:0] $end
$var reg 1 7 streamArbiter_1_io_output_s2mPipe_rValid $end
$var reg 1 D streamArbiter_1_io_output_s2mPipe_ready $end
$scope module streamArbiter_1 $end
$var wire 1 E _zz_io_chosen_1 $end
$var wire 1 F _zz_io_chosen_2 $end
$var wire 1 G _zz_io_output_payload $end
$var wire 1 H _zz_io_output_payload_1 $end
$var wire 8 I _zz_maskProposal_0_2 [7:0] $end
$var wire 4 J _zz_maskProposal_0_3 [3:0] $end
$var wire 1 ! clk $end
$var wire 32 K io_inputs_0_payload [31:0] $end
$var wire 1 > io_inputs_0_ready $end
$var wire 1 ' io_inputs_0_valid $end
$var wire 32 L io_inputs_1_payload [31:0] $end
$var wire 1 = io_inputs_1_ready $end
$var wire 1 * io_inputs_1_valid $end
$var wire 32 M io_inputs_2_payload [31:0] $end
$var wire 1 < io_inputs_2_ready $end
$var wire 1 - io_inputs_2_valid $end
$var wire 32 N io_inputs_3_payload [31:0] $end
$var wire 1 ; io_inputs_3_ready $end
$var wire 1 0 io_inputs_3_valid $end
$var wire 1 O io_output_fire $end
$var wire 32 P io_output_payload [31:0] $end
$var wire 1 9 io_output_ready $end
$var wire 1 5 io_output_valid $end
$var wire 1 1 reset $end
$var wire 1 Q maskRouted_3 $end
$var wire 1 R maskRouted_2 $end
$var wire 1 S maskRouted_1 $end
$var wire 1 T maskRouted_0 $end
$var wire 1 U maskProposal_3 $end
$var wire 1 V maskProposal_2 $end
$var wire 1 W maskProposal_1 $end
$var wire 1 X maskProposal_0 $end
$var wire 4 Y io_chosenOH [3:0] $end
$var wire 2 Z io_chosen [1:0] $end
$var wire 8 [ _zz_maskProposal_0_1 [7:0] $end
$var wire 4 \ _zz_maskProposal_0 [3:0] $end
$var wire 2 ] _zz_io_output_payload_3 [1:0] $end
$var wire 1 ^ _zz_io_chosen $end
$var wire 4 _ _zz__zz_maskProposal_0_2_2 [3:0] $end
$var wire 8 ` _zz__zz_maskProposal_0_2_1 [7:0] $end
$var wire 8 a _zz__zz_maskProposal_0_2 [7:0] $end
$var reg 32 b _zz_io_output_payload_2 [31:0] $end
$var reg 1 c locked $end
$var reg 1 d maskLocked_0 $end
$var reg 1 e maskLocked_1 $end
$var reg 1 f maskLocked_2 $end
$var reg 1 g maskLocked_3 $end
$upscope $end
$upscope $end
$enddefinitions $end
#0
$dumpvars
1g
0f
0e
0d
0c
bz b
bx a
b1 `
b1 _
x^
bx ]
bz \
bz [
bx Z
bx Y
xX
xW
xV
xU
xT
xS
xR
xQ
bz P
xO
bz N
bz M
bz L
bz K
bx J
bx I
xH
xG
xF
xE
1D
bx C
0B
bx A
bx @
bx ?
x>
x=
x<
x;
bz :
19
bx 8
07
bz 6
x5
14
x3
z2
11
z0
x/
bz .
z-
x,
bz +
z*
x)
bz (
z'
x&
bz %
0$
z#
bx "
0!
$end
#1000
0F
b0 @
b0 Z
0E
0&
0>
0)
0=
0,
0<
0^
0/
0;
0H
b0 ]
0G
0O
03
0T
0S
0R
b0 ?
b0 Y
0Q
05
0X
0W
0V
0U
b0 J
b0 6
b0 I
b0 :
b0 P
b0 b
1D
b11111111 a
0'
b0 %
b0 K
0*
b0 (
b0 L
0-
b0 +
b0 M
b0 [
b0 \
00
b0 .
b0 N
02
0#
01
#1500
b0 "
b0 8
b0 C
b0 A
1!
#2000
0!
#2500
1!
#3000
0!
#3500
1O
13
15
b1 @
b1 Z
1E
1)
1=
b1 ]
1G
b10 ?
b10 Y
1S
1W
b10 J
b10 I
1*
b10101001 a
b10101010 [
b1010 \
10
1!
#4000
0!
#4500
0&
0>
0T
0X
12
1#
b10111011 [
b1011 \
1'
b11 @
b11 Z
1F
0)
0=
1^
1/
1;
b11 ]
1H
0S
b1000 ?
b1000 Y
1Q
0W
1U
b1000 J
b1000 I
1D
0c
0g
b10110111 a
b100 `
b100 _
1e
04
1$
17
19
0B
1!
#5000
0!
#5500
0D
02
0#
b110011 [
b11 \
00
1O
13
0F
b0 @
b0 Z
0E
15
1&
1>
0^
0/
0;
0H
b0 ]
0G
1T
b1 ?
b1 Y
0Q
1X
0U
b1 J
b1 I
19
0B
0c
1g
b110010 a
b1 `
b1 _
0e
1!
#6000
0!
#6500
0F
0H
0R
0V
1D
12
1#
0'
b1100110 [
b110 \
1-
b1 @
b1 Z
1E
b1 ]
1G
0T
b10 ?
b10 Y
1S
0X
1W
b10 J
b10 I
0O
0&
0>
0c
0g
b1100100 a
b10 `
b10 _
1d
09
1B
1!
#7000
0!
#7500
0U
0D
02
0#
b11101110 [
b1110 \
10
b11101010100000101101000100010100 .
b11101010100000101101000100010100 N
0W
1V
b100 J
b100 I
1O
1)
1=
19
0B
1c
1e
b11101010 a
b100 `
b100 _
0d
1!
#8000
0!
#8500
1D
12
1#
b11001000 a
b11001100 [
b1100 \
0*
0E
b10 @
b10 Z
1F
0G
b10 ]
1H
0S
b100 ?
b100 Y
1R
0O
0)
0=
0c
09
1B
1!
#9000
0!
#9500
0X
0D
02
0#
b11011101 [
b1101 \
1'
b11110111010000010100010011111101 %
b11110111010000010100010011111101 K
0V
1U
b1000 J
b1000 I
1O
1,
1<
19
0B
1c
1f
b11010101 a
b1000 `
b1000 _
0e
1!
#10000
0!
#10500
1D
12
1#
b10010001 a
b10011001 [
b1001 \
0-
b11 @
b11 Z
1E
b11101010100000101101000100010100 :
b11101010100000101101000100010100 P
b11101010100000101101000100010100 b
1^
b11 ]
1G
0R
b1000 ?
b1000 Y
1Q
0O
0,
0<
0c
09
1B
1!
#11000
0!
#11500
0V
0D
02
0#
b11011101 [
b1101 \
1-
b100011000111010101110110000000 +
b100011000111010101110110000000 M
1X
0U
b1 J
b1 I
1O
1/
1;
b11101010100000101101000100010100 6
19
0B
1c
1g
b11011100 a
b1 `
b1 _
0f
1!
#12000
0!
#12500
0S
0W
b1 J
b1 I
1*
b11111101111100111100110001111010 (
b11111101111100111100110001111010 L
b1110110 a
b1110111 [
b111 \
00
b0 .
b0 N
0F
b0 @
b0 Z
0E
b11110111010000010100010011111101 :
b11110111010000010100010011111101 P
b11110111010000010100010011111101 b
15
0^
0H
b0 ]
0G
1T
b1 ?
b1 Y
0Q
0O
0/
0;
0c
09
1B
b11101010100000101101000100010100 A
1!
#13000
0!
#13500
0U
1D
12
1#
b11111111 [
b1111 \
10
b1001010010111100111100111101100 .
b1001010010111100111100111101100 N
0X
1W
b10 J
b10 I
1c
0g
b11111101 a
b10 `
b10 _
1d
1!
#14000
0!
#14500
0D
02
0#
1O
1&
1>
b11110111010000010100010011111101 6
19
0B
b11101010100000101101000100010100 "
b11101010100000101101000100010100 8
b11101010100000101101000100010100 C
1!
#15000
0!
#15500
1D
12
1#
b11101100 a
b11101110 [
b1110 \
0'
b0 %
b0 K
b1 @
b1 Z
1E
b11111101111100111100110001111010 :
b11111101111100111100110001111010 P
b11111101111100111100110001111010 b
b1 ]
1G
0O
0&
0>
0T
b10 ?
b10 Y
1S
09
1B
0c
b11110111010000010100010011111101 A
1!
#16000
0!
#16500
0X
0D
02
0#
b11111111 [
b1111 \
1'
b11100010101110001100000110100110 %
b11100010101110001100000110100110 K
0W
1V
b100 J
b100 I
1O
1)
1=
b11111101111100111100110001111010 6
1c
1e
b11111011 a
b100 `
b100 _
0d
19
0B
b11110111010000010100010011111101 "
b11110111010000010100010011111101 8
b11110111010000010100010011111101 C
1!
#17000
0!
#17500
1D
12
1#
b11011001 a
b11011101 [
b1101 \
0*
b0 (
b0 L
0E
b10 @
b10 Z
1F
b100011000111010101110110000000 :
b100011000111010101110110000000 P
b100011000111010101110110000000 b
0G
b10 ]
1H
0O
0)
0=
0S
b100 ?
b100 Y
1R
09
1B
0c
b11111101111100111100110001111010 A
1!
#18000
0!
#18500
0D
02
0#
0V
1U
b1000 J
b1000 I
1O
1,
1<
b100011000111010101110110000000 6
1c
1f
b11010101 a
b1000 `
b1000 _
0e
19
0B
b11111101111100111100110001111010 "
b11111101111100111100110001111010 8
b11111101111100111100110001111010 C
1!
#19000
0!
#19500
b10010001 a
b10011001 [
b1001 \
0-
b0 +
b0 M
b11 @
b11 Z
1E
b1001010010111100111100111101100 :
b1001010010111100111100111101100 P
b1001010010111100111100111101100 b
1^
b11 ]
1G
0O
0,
0<
0R
b1000 ?
b1000 Y
1Q
09
1B
0c
b100011000111010101110110000000 A
1!
#20000
0!
#20500
1X
0U
b1 J
b1 I
1c
1g
b10011000 a
b1 `
b1 _
0f
1!
#21000
0!
#21500
0V
b1 J
1D
b1 I
12
1#
b11011100 a
b11011101 [
b1101 \
1-
b101000111000000000110100011011 +
b101000111000000000110100011011 M
1!
#22000
0!
#22500
0W
b1 J
0D
b1 I
02
0#
b11111110 a
b11111111 [
b1111 \
1*
b1010011100101111100001001001100 (
b1010011100101111100001001001100 L
1O
1/
1;
b1001010010111100111100111101100 6
19
0B
b100011000111010101110110000000 "
b100011000111010101110110000000 8
b100011000111010101110110000000 C
1!
#23000
0!
#23500
b1110110 a
b1110111 [
b111 \
00
b0 .
b0 N
0F
b0 @
b0 Z
0E
b11100010101110001100000110100110 :
b11100010101110001100000110100110 P
b11100010101110001100000110100110 b
15
0^
0H
b0 ]
0G
0O
0/
0;
1T
b1 ?
b1 Y
0Q
09
1B
0c
b1001010010111100111100111101100 A
1!
#24000
0!
#24500
0X
1W
b10 J
b10 I
1c
0g
b1110101 a
b10 `
b10 _
1d
1!
#25000
0!
#25500
0U
b10 J
b10 I
b11111101 a
b11111111 [
b1111 \
10
b1001110101011101000101011011000 .
b1001110101011101000101011011000 N
1!
#26000
0!
#26500
1!
#27000
0!
#27500
1D
12
1#
1!
#28000
0!
#28500
0D
02
0#
1O
1&
1>
b11100010101110001100000110100110 6
19
0B
b1001010010111100111100111101100 "
b1001010010111100111100111101100 8
b1001010010111100111100111101100 C
1!
#29000
0!
#29500
1D
12
1#
b11101100 a
b11101110 [
b1110 \
0'
b0 %
b0 K
b1 @
b1 Z
1E
b1010011100101111100001001001100 :
b1010011100101111100001001001100 P
b1010011100101111100001001001100 b
b1 ]
1G
0O
0&
0>
0T
b10 ?
b10 Y
1S
09
1B
0c
b11100010101110001100000110100110 A
1!
#30000
0!
#30500
0X
0D
02
0#
b11111111 [
b1111 \
1'
b1110101110100011101100100011111 %
b1110101110100011101100100011111 K
0W
1V
b100 J
b100 I
1O
1)
1=
b1010011100101111100001001001100 6
1c
1e
b11111011 a
b100 `
b100 _
0d
19
0B
b11100010101110001100000110100110 "
b11100010101110001100000110100110 8
b11100010101110001100000110100110 C
1!
#31000
0!
#31500
1D
12
1#
b11011001 a
b11011101 [
b1101 \
0*
b0 (
b0 L
0E
b10 @
b10 Z
1F
b101000111000000000110100011011 :
b101000111000000000110100011011 P
b101000111000000000110100011011 b
0G
b10 ]
1H
0O
0)
0=
0S
b100 ?
b100 Y
1R
09
1B
0c
b1010011100101111100001001001100 A
1!
#32000
0!
#32500
0W
0D
02
0#
b11111111 [
b1111 \
1*
b10110111111100111111001101000011 (
b10110111111100111111001101000011 L
0V
1U
b1000 J
b1000 I
1O
1,
1<
b101000111000000000110100011011 6
1c
1f
b11110111 a
b1000 `
b1000 _
0e
19
0B
b1010011100101111100001001001100 "
b1010011100101111100001001001100 8
b1010011100101111100001001001100 C
1!
#33000
0!
#33500
b10110011 a
b10111011 [
b1011 \
0-
b0 +
b0 M
b11 @
b11 Z
1E
b1001110101011101000101011011000 :
b1001110101011101000101011011000 P
b1001110101011101000101011011000 b
1^
b11 ]
1G
0O
0,
0<
0R
b1000 ?
b1000 Y
1Q
09
1B
0c
b101000111000000000110100011011 A
1!
#34000
0!
#34500
0V
1D
12
1#
b11111111 [
b1111 \
1-
b10011011110110001011110010111111 +
b10011011110110001011110010111111 M
1X
0U
b1 J
b1 I
1c
1g
b11111110 a
b1 `
b1 _
0f
1!
#35000
0!
#35500
0D
02
0#
1O
1/
1;
b1001110101011101000101011011000 6
19
0B
b101000111000000000110100011011 "
b101000111000000000110100011011 8
b101000111000000000110100011011 C
1!
#36000
0!
#36500
1D
12
1#
b1110110 a
b1110111 [
b111 \
00
b0 .
b0 N
0F
b0 @
b0 Z
0E
b1110101110100011101100100011111 :
b1110101110100011101100100011111 P
b1110101110100011101100100011111 b
15
0^
0H
b0 ]
0G
1T
b1 ?
b1 Y
0Q
0O
0/
0;
0c
09
1B
b1001110101011101000101011011000 A
1!
#37000
0!
#37500
0U
0D
02
0#
b11111111 [
b1111 \
10
b1011100111101001011101110000 .
b1011100111101001011101110000 N
0X
1W
b10 J
b10 I
1O
1&
1>
b1110101110100011101100100011111 6
19
0B
1c
0g
b11111101 a
b10 `
b10 _
1d
b1001110101011101000101011011000 "
b1001110101011101000101011011000 8
b1001110101011101000101011011000 C
1!
#38000
0!
#38500
b11101100 a
b11101110 [
b1110 \
0'
b0 %
b0 K
b1 @
b1 Z
1E
b10110111111100111111001101000011 :
b10110111111100111111001101000011 P
b10110111111100111111001101000011 b
b1 ]
1G
0T
b10 ?
b10 Y
1S
0O
0&
0>
0c
09
1B
b1110101110100011101100100011111 A
1!
#39000
0!
#39500
1D
12
1#
0W
1V
b100 J
b100 I
1c
1e
b11101010 a
b100 `
b100 _
0d
1!
#40000
0!
#40500
0X
b100 J
0D
b100 I
02
0#
b11111011 a
b11111111 [
b1111 \
1'
b1000101000100000101010100111111 %
b1000101000100000101010100111111 K
1O
1)
1=
b10110111111100111111001101000011 6
19
0B
b1110101110100011101100100011111 "
b1110101110100011101100100011111 8
b1110101110100011101100100011111 C
1!
#41000
0!
#41500
1D
12
1#
b11011001 a
b11011101 [
b1101 \
0*
b0 (
b0 L
0E
b10 @
b10 Z
1F
b10011011110110001011110010111111 :
b10011011110110001011110010111111 P
b10011011110110001011110010111111 b
0G
b10 ]
1H
0O
0)
0=
0S
b100 ?
b100 Y
1R
09
1B
0c
b10110111111100111111001101000011 A
1!
#42000
0!
#42500
0D
02
0#
0V
1U
b1000 J
b1000 I
1O
1,
1<
b10011011110110001011110010111111 6
1c
1f
b11010101 a
b1000 `
b1000 _
0e
19
0B
b10110111111100111111001101000011 "
b10110111111100111111001101000011 8
b10110111111100111111001101000011 C
1!
#43000
0!
#43500
1D
12
1#
b10010001 a
b10011001 [
b1001 \
0-
b0 +
b0 M
b11 @
b11 Z
1E
b1011100111101001011101110000 :
b1011100111101001011101110000 P
b1011100111101001011101110000 b
1^
b11 ]
1G
0O
0,
0<
0R
b1000 ?
b1000 Y
1Q
09
1B
0c
b10011011110110001011110010111111 A
1!
#44000
0!
#44500
0W
0D
02
0#
b10111011 [
b1011 \
1*
b10010000001111000000100000111110 (
b10010000001111000000100000111110 L
1X
0U
b1 J
b1 I
1O
1/
1;
b1011100111101001011101110000 6
1c
1g
b10111010 a
b1 `
b1 _
0f
19
0B
b10011011110110001011110010111111 "
b10011011110110001011110010111111 8
b10011011110110001011110010111111 C
1!
#45000
0!
#45500
0R
0V
b1 J
b1 I
1-
b10100100101111110101110010100111 +
b10100100101111110101110010100111 M
b1110110 a
b1110111 [
b111 \
00
b0 .
b0 N
0F
b0 @
b0 Z
0E
b1000101000100000101010100111111 :
b1000101000100000101010100111111 P
b1000101000100000101010100111111 b
15
0^
0H
b0 ]
0G
0O
0/
0;
1T
b1 ?
b1 Y
0Q
09
1B
0c
b1011100111101001011101110000 A
1!
#46000
0!
#46500
1D
12
1#
0X
1W
b10 J
b10 I
1c
0g
b1110101 a
b10 `
b10 _
1d
1!
#47000
0!
#47500
0D
02
0#
1O
1&
1>
b1000101000100000101010100111111 6
19
0B
b1011100111101001011101110000 "
b1011100111101001011101110000 8
b1011100111101001011101110000 C
1!
#48000
0!
#48500
0F
0^
0H
0Q
0U
b10 J
1D
b10 I
12
1#
0'
b0 %
b0 K
b11101100 a
b11101110 [
b1110 \
10
b11100011011011100110001100010 .
b11100011011011100110001100010 N
b1 @
b1 Z
1E
b10010000001111000000100000111110 :
b10010000001111000000100000111110 P
b10010000001111000000100000111110 b
b1 ]
1G
0T
b10 ?
b10 Y
1S
0O
0&
0>
0c
09
1B
b1000101000100000101010100111111 A
1!
#49000
0!
#49500
0D
02
0#
0W
1V
b100 J
b100 I
1O
1)
1=
b10010000001111000000100000111110 6
19
0B
1c
1e
b11101010 a
b100 `
b100 _
0d
b1000101000100000101010100111111 "
b1000101000100000101010100111111 8
b1000101000100000101010100111111 C
1!
#50000
0!
#50500
1D
12
1#
b11001000 a
b11001100 [
b1100 \
0*
b0 (
b0 L
0E
b10 @
b10 Z
1F
b10100100101111110101110010100111 :
b10100100101111110101110010100111 P
b10100100101111110101110010100111 b
0G
b10 ]
1H
0S
b100 ?
b100 Y
1R
0O
0)
0=
0c
09
1B
b10010000001111000000100000111110 A
1!
#51000
0!
