counter1/Counter.v
// Generator : SpinalHDL v1.6.4    git head : 598c18959149eb18e5eee5b0aa3eef01ecaa41a1
// Component : Counter
// Git hash  : 89d7543c7219f82d1991c9174f1b313aba4435ca

`timescale 1ns/1ps 

module Counter (
  input               io_clear,
  output     [3:0]    io_value,
  output              io_full,
  input               clk,
  input               reset
);

  wire       [4:0]    _zz_io_full;
  wire       [4:0]    _zz_io_full_1;
  wire       [4:0]    _zz_io_full_2;
  reg        [3:0]    counter_1;

  assign _zz_io_full = {1'd0, counter_1};
  assign _zz_io_full_1 = (_zz_io_full_2 - 5'h01);
  assign _zz_io_full_2 = ({4'd0,1'b1} <<< 4);
  assign io_value = counter_1;
  assign io_full = (_zz_io_full == _zz_io_full_1);
  always @(posedge clk or posedge reset) begin
    if(reset) begin
      counter_1 <= 4'b0000;
    end else begin
      counter_1 <= (counter_1 + 4'b0001);
      if(io_clear) begin
        counter_1 <= 4'b0000;
      end
    end
  end

  initial begin
    $dumpfile("Counter.vcd");
    $dumpvars(0, Counter);
  end


endmodule

counter/Counter.vcd
$date
	Mon May  9 16:40:10 2022
$end
$version
	Icarus Verilog
$end
$timescale
	1ps
$end
$scope module Counter $end
$var wire 5 ! _zz_io_full_2 [4:0] $end
$var wire 1 " clk $end
$var wire 1 # io_clear $end
$var wire 4 $ io_value [3:0] $end
$var wire 1 % reset $end
$var wire 1 & io_full $end
$var wire 5 ' _zz_io_full_1 [4:0] $end
$var wire 5 ( _zz_io_full [4:0] $end
$var reg 4 ) counter_1 [3:0] $end
$upscope $end
$enddefinitions $end
#0
$dumpvars
b0 )
b0 (
b1111 '
0&
1%
b0 $
0#
0"
b10000 !
$end
#1000
b1 (
b1 $
b1 )
0%
1"
#1500
0"
#2000
b10 (
b10 $
b10 )
1"
#2500
0"
#3000
b11 (
b11 $
b11 )
1"
#3500
0"
#4000
b100 (
b100 $
b100 )
1"
#4500
0"
#5000
b101 (
b101 $
b101 )
1"
#5500
0"
#6000
b110 (
b110 $
b110 )
1"
#6500
0"
#7000
b111 (
b111 $
b111 )
1"
#7500
0"
#8000
b1000 (
b1000 $
b1000 )
1"
#8500
0"
#9000
b1001 (
b1001 $
b1001 )
1"
#9500
0"
#10000
b1010 (
b1010 $
b1010 )
1"
