apb3decoder/Apb3Decoder.v
// Generator : SpinalHDL v1.6.4    git head : 598c18959149eb18e5eee5b0aa3eef01ecaa41a1
// Component : Apb3Decoder
// Git hash  : 89d7543c7219f82d1991c9174f1b313aba4435ca

`timescale 1ns/1ps 

module Apb3Decoder (
  input      [15:0]   io_input_PADDR,
  input      [0:0]    io_input_PSEL,
  input               io_input_PENABLE,
  output              io_input_PREADY,
  input               io_input_PWRITE,
  input      [31:0]   io_input_PWDATA,
  output     [31:0]   io_input_PRDATA,
  output              io_input_PSLVERROR,
  output     [15:0]   io_outputs_0_PADDR,
  output     [0:0]    io_outputs_0_PSEL,
  output              io_outputs_0_PENABLE,
  input               io_outputs_0_PREADY,
  output              io_outputs_0_PWRITE,
  output     [31:0]   io_outputs_0_PWDATA,
  input      [31:0]   io_outputs_0_PRDATA,
  input               io_outputs_0_PSLVERROR,
  output     [15:0]   io_outputs_1_PADDR,
  output     [0:0]    io_outputs_1_PSEL,
  output              io_outputs_1_PENABLE,
  input               io_outputs_1_PREADY,
  output              io_outputs_1_PWRITE,
  output     [31:0]   io_outputs_1_PWDATA,
  input      [31:0]   io_outputs_1_PRDATA,
  input               io_outputs_1_PSLVERROR,
  output     [15:0]   io_outputs_2_PADDR,
  output     [0:0]    io_outputs_2_PSEL,
  output              io_outputs_2_PENABLE,
  input               io_outputs_2_PREADY,
  output              io_outputs_2_PWRITE,
  output     [31:0]   io_outputs_2_PWDATA,
  input      [31:0]   io_outputs_2_PRDATA,
  input               io_outputs_2_PSLVERROR,
  output     [15:0]   io_outputs_3_PADDR,
  output     [0:0]    io_outputs_3_PSEL,
  output              io_outputs_3_PENABLE,
  input               io_outputs_3_PREADY,
  output              io_outputs_3_PWRITE,
  output     [31:0]   io_outputs_3_PWDATA,
  input      [31:0]   io_outputs_3_PRDATA,
  input               io_outputs_3_PSLVERROR
);

  reg                 _zz_io_input_PREADY;
  reg        [31:0]   _zz_io_input_PRDATA;
  reg                 _zz_io_input_PSLVERROR;
  wire                mappingHits_0;
  wire                mappingHits_1;
  wire                mappingHits_2;
  wire                mappingHits_3;
  wire                _zz_mappingHitsIndex;
  wire                _zz_mappingHitsIndex_1;
  wire       [1:0]    mappingHitsIndex;

  always @(*) begin
    case(mappingHitsIndex)
      2'b00 : begin
        _zz_io_input_PREADY = io_outputs_0_PREADY;
        _zz_io_input_PRDATA = io_outputs_0_PRDATA;
        _zz_io_input_PSLVERROR = io_outputs_0_PSLVERROR;
      end
      2'b01 : begin
        _zz_io_input_PREADY = io_outputs_1_PREADY;
        _zz_io_input_PRDATA = io_outputs_1_PRDATA;
        _zz_io_input_PSLVERROR = io_outputs_1_PSLVERROR;
      end
      2'b10 : begin
        _zz_io_input_PREADY = io_outputs_2_PREADY;
        _zz_io_input_PRDATA = io_outputs_2_PRDATA;
        _zz_io_input_PSLVERROR = io_outputs_2_PSLVERROR;
      end
      default : begin
        _zz_io_input_PREADY = io_outputs_3_PREADY;
        _zz_io_input_PRDATA = io_outputs_3_PRDATA;
        _zz_io_input_PSLVERROR = io_outputs_3_PSLVERROR;
      end
    endcase
  end

  assign io_outputs_0_PADDR = io_input_PADDR;
  assign io_outputs_0_PENABLE = io_input_PENABLE;
  assign io_outputs_0_PWRITE = io_input_PWRITE;
  assign io_outputs_0_PWDATA = io_input_PWDATA;
  assign io_outputs_1_PADDR = io_input_PADDR;
  assign io_outputs_1_PENABLE = io_input_PENABLE;
  assign io_outputs_1_PWRITE = io_input_PWRITE;
  assign io_outputs_1_PWDATA = io_input_PWDATA;
  assign io_outputs_2_PADDR = io_input_PADDR;
  assign io_outputs_2_PENABLE = io_input_PENABLE;
  assign io_outputs_2_PWRITE = io_input_PWRITE;
  assign io_outputs_2_PWDATA = io_input_PWDATA;
  assign io_outputs_3_PADDR = io_input_PADDR;
  assign io_outputs_3_PENABLE = io_input_PENABLE;
  assign io_outputs_3_PWRITE = io_input_PWRITE;
  assign io_outputs_3_PWDATA = io_input_PWDATA;
  assign mappingHits_0 = ((16'h0 <= io_input_PADDR) && (io_input_PADDR < 16'h1000));
  assign mappingHits_1 = ((16'h1000 <= io_input_PADDR) && (io_input_PADDR < 16'h2000));
  assign mappingHits_2 = ((16'h4000 <= io_input_PADDR) && (io_input_PADDR < 16'h6000));
  assign mappingHits_3 = ((16'h6000 <= io_input_PADDR) && (io_input_PADDR < 16'h9000));
  assign _zz_mappingHitsIndex = (mappingHits_1 || mappingHits_3);
  assign _zz_mappingHitsIndex_1 = (mappingHits_2 || mappingHits_3);
  assign mappingHitsIndex = {_zz_mappingHitsIndex_1,_zz_mappingHitsIndex};
  assign io_outputs_0_PSEL[0] = (mappingHits_0 && io_input_PSEL[0]);
  assign io_outputs_1_PSEL[0] = (mappingHits_1 && io_input_PSEL[0]);
  assign io_outputs_2_PSEL[0] = (mappingHits_2 && io_input_PSEL[0]);
  assign io_outputs_3_PSEL[0] = (mappingHits_3 && io_input_PSEL[0]);
  assign io_input_PREADY = _zz_io_input_PREADY;
  assign io_input_PRDATA = _zz_io_input_PRDATA;
  assign io_input_PSLVERROR = _zz_io_input_PSLVERROR;

  initial begin
    $dumpfile("Apb3Decoder_test.vcd");
    $dumpvars(0, Apb3Decoder);
  end

endmodule

apb3decoder/Apb3Decoder_test.vcd
$date
	Fri Mar 25 19:12:39 2022
$end
$version
	Icarus Verilog
$end
$timescale
	1ps
$end
$scope module Apb3Decoder $end
$var wire 1 ! _zz_mappingHitsIndex $end
$var wire 1 " _zz_mappingHitsIndex_1 $end
$var wire 16 # io_input_PADDR [15:0] $end
$var wire 1 $ io_input_PENABLE $end
$var wire 32 % io_input_PRDATA [31:0] $end
$var wire 1 & io_input_PREADY $end
$var wire 1 ' io_input_PSEL $end
$var wire 1 ( io_input_PSLVERROR $end
$var wire 32 ) io_input_PWDATA [31:0] $end
$var wire 1 * io_input_PWRITE $end
$var wire 16 + io_outputs_0_PADDR [15:0] $end
$var wire 1 , io_outputs_0_PENABLE $end
$var wire 32 - io_outputs_0_PRDATA [31:0] $end
$var wire 1 . io_outputs_0_PREADY $end
$var wire 1 / io_outputs_0_PSEL $end
$var wire 1 0 io_outputs_0_PSLVERROR $end
$var wire 32 1 io_outputs_0_PWDATA [31:0] $end
$var wire 1 2 io_outputs_0_PWRITE $end
$var wire 16 3 io_outputs_1_PADDR [15:0] $end
$var wire 1 4 io_outputs_1_PENABLE $end
$var wire 32 5 io_outputs_1_PRDATA [31:0] $end
$var wire 1 6 io_outputs_1_PREADY $end
$var wire 1 7 io_outputs_1_PSEL $end
$var wire 1 8 io_outputs_1_PSLVERROR $end
$var wire 32 9 io_outputs_1_PWDATA [31:0] $end
$var wire 1 : io_outputs_1_PWRITE $end
$var wire 16 ; io_outputs_2_PADDR [15:0] $end
$var wire 1 < io_outputs_2_PENABLE $end
$var wire 32 = io_outputs_2_PRDATA [31:0] $end
$var wire 1 > io_outputs_2_PREADY $end
$var wire 1 ? io_outputs_2_PSEL $end
$var wire 1 @ io_outputs_2_PSLVERROR $end
$var wire 32 A io_outputs_2_PWDATA [31:0] $end
$var wire 1 B io_outputs_2_PWRITE $end
$var wire 16 C io_outputs_3_PADDR [15:0] $end
$var wire 1 D io_outputs_3_PENABLE $end
$var wire 32 E io_outputs_3_PRDATA [31:0] $end
$var wire 1 F io_outputs_3_PREADY $end
$var wire 1 G io_outputs_3_PSEL $end
$var wire 1 H io_outputs_3_PSLVERROR $end
$var wire 32 I io_outputs_3_PWDATA [31:0] $end
$var wire 1 J io_outputs_3_PWRITE $end
$var wire 1 K mappingHits_0 $end
$var wire 1 L mappingHits_1 $end
$var wire 1 M mappingHits_2 $end
$var wire 1 N mappingHits_3 $end
$var wire 2 O mappingHitsIndex [1:0] $end
$var reg 32 P _zz_io_input_PRDATA [31:0] $end
$var reg 1 Q _zz_io_input_PREADY $end
$var reg 1 R _zz_io_input_PSLVERROR $end
$upscope $end
$enddefinitions $end
#0
$dumpvars
zR
zQ
bz P
b0 O
0N
0M
0L
0K
1J
b1101011101010101001010001010101 I
zH
0G
zF
bz E
1D
b1101100000101100 C
1B
b1101011101010101001010001010101 A
z@
0?
z>
bz =
1<
b1101100000101100 ;
1:
b1101011101010101001010001010101 9
z8
07
z6
bz 5
14
b1101100000101100 3
12
b1101011101010101001010001010101 1
z0
0/
z.
bz -
1,
b1101100000101100 +
1*
b1101011101010101001010001010101 )
z(
0'
z&
bz %
1$
b1101100000101100 #
0"
0!
$end
#1000
b10 O
1"
1?
1M
b101101110101001 +
b101101110101001 3
b101101110101001 ;
b101101110101001 C
b101101110101001 #
1'
b110111111010111101110011011001 1
b110111111010111101110011011001 9
b110111111010111101110011011001 A
b110111111010111101110011011001 I
b110111111010111101110011011001 )
#2000
b0 O
0"
0?
0M
b1111101110010111 +
b1111101110010111 3
b1111101110010111 ;
b1111101110010111 C
b1111101110010111 #
b11100110111101000101100100001011 1
b11100110111101000101100100001011 9
b11100110111101000101100100001011 A
b11100110111101000101100100001011 I
b11100110111101000101100100001011 )
#3000
b10 O
1"
1M
b101101010010010 +
b101101010010010 3
b101101010010010 ;
b101101010010010 C
b101101010010010 #
0'
0,
04
0<
0D
0$
b10100011111100101100100110111111 1
b10100011111100101100100110111111 9
b10100011111100101100100110111111 A
b10100011111100101100100110111111 I
b10100011111100101100100110111111 )
#4000
b11 O
1!
1G
0M
1N
0?
b1000110001110111 +
b1000110001110111 3
b1000110001110111 ;
b1000110001110111 C
b1000110001110111 #
1'
02
0:
0B
0J
0*
b10111000001111101001000011101100 1
b10111000001111101001000011101100 9
b10111000001111101001000011101100 A
b10111000001111101001000011101100 I
b10111000001111101001000011101100 )
#5000
b10 O
0!
1M
0N
0G
b101010101001000 +
b101010101001000 3
b101010101001000 ;
b101010101001000 C
b101010101001000 #
0'
1,
14
1<
1D
1$
b10110100001000011110101011101011 1
b10110100001000011110101011101011 9
b10110100001000011110101011101011 A
b10110100001000011110101011101011 I
b10110100001000011110101011101011 )
#6000
b11 O
1!
0M
1N
b111001010101110 +
b111001010101110 3
b111001010101110 ;
b111001010101110 C
b111001010101110 #
0,
04
0<
0D
0$
12
1:
1B
1J
1*
b1010001111011110001100100100010 1
b1010001111011110001100100100010 9
b1010001111011110001100100100010 A
b1010001111011110001100100100010 I
b1010001111011110001100100100010 )
#7000
1?
b10 O
0!
1M
0N
0G
b101010100101111 +
b101010100101111 3
b101010100101111 ;
b101010100101111 C
b101010100101111 #
1'
1,
14
1<
1D
1$
b110100000001010000100101011100 1
b110100000001010000100101011100 9
b110100000001010000100101011100 A
b110100000001010000100101011100 I
b110100000001010000100101011100 )
#8000
b0 O
0"
0M
0?
b1001001101011101 +
b1001001101011101 3
b1001001101011101 ;
b1001001101011101 C
b1001001101011101 #
0'
0,
04
0<
0D
0$
02
0:
0B
0J
0*
b110000011110111111001100100110 1
b110000011110111111001100100110 9
b110000011110111111001100100110 A
b110000011110111111001100100110 I
b110000011110111111001100100110 )
#9000
b10000101010110 +
b10000101010110 3
b10000101010110 ;
b10000101010110 C
b10000101010110 #
1'
12
1:
1B
1J
1*
b1001111001000110100111100110 1
b1001111001000110100111100110 9
b1001111001000110100111100110 A
b1001111001000110100111100110 I
b1001111001000110100111100110 )
#10000
b10 O
1"
1?
1M
b100011010001111 +
b100011010001111 3
b100011010001111 ;
b100011010001111 C
b100011010001111 #
1,
14
1<
1D
1$
02
0:
0B
0J
0*
b11011001011101111110100110010011 1
b11011001011101111110100110010011 9
b11011001011101111110100110010011 A
b11011001011101111110100110010011 I
b11011001011101111110100110010011 )
#11000
b0 O
0"
0?
0M
b1010010000100101 +
b1010010000100101 3
b1010010000100101 ;
b1010010000100101 C
b1010010000100101 #
12
1:
1B
1J
1*
b11111011100000101000011000001101 1
b11111011100000101000011000001101 9
b11111011100000101000011000001101 A
b11111011100000101000011000001101 I
b11111011100000101000011000001101 )
#12000
b11111000110111 +
b11111000110111 3
b11111000110111 ;
b11111000110111 C
b11111000110111 #
0'
02
0:
0B
0J
0*
b11101111111001000001101010010 1
b11101111111001000001101010010 9
b11101111111001000001101010010 A
b11101111111001000001101010010 I
b11101111111001000001101010010 )
#13000
b1101101011110110 +
b1101101011110110 3
b1101101011110110 ;
b1101101011110110 C
b1101101011110110 #
1'
0,
04
0<
0D
0$
b11010001001011101100101111000100 1
b11010001001011101100101111000100 9
b11010001001011101100101111000100 A
b11010001001011101100101111000100 I
b11010001001011101100101111000100 )
#14000
b1001101100111000 +
b1001101100111000 3
b1001101100111000 ;
b1001101100111000 C
b1001101100111000 #
1,
14
1<
1D
1$
b1100100001001100100110011010101 1
b1100100001001100100110011010101 9
b1100100001001100100110011010101 A
b1100100001001100100110011010101 I
b1100100001001100100110011010101 )
#15000
b1011011111010110 +
b1011011111010110 3
b1011011111010110 ;
b1011011111010110 C
b1011011111010110 #
0'
0,
04
0<
0D
0$
b10111010001001101101100001010001 1
b10111010001001101101100001010001 9
b10111010001001101101100001010001 A
b10111010001001101101100001010001 I
b10111010001001101101100001010001 )
#16000
b11100010001000 +
b11100010001000 3
b11100010001000 ;
b11100010001000 C
b11100010001000 #
1,
14
1<
1D
1$
b1011001101011001101110110011000 1
b1011001101011001101110110011000 9
b1011001101011001101110110011000 A
b1011001101011001101110110011000 I
b1011001101011001101110110011000 )
#17000
b10 O
1"
1M
b100001010011000 +
b100001010011000 3
b100001010011000 ;
b100001010011000 C
b100001010011000 #
12
1:
1B
1J
1*
b1111000011000000001011000000010 1
b1111000011000000001011000000010 9
b1111000011000000001011000000010 A
b1111000011000000001011000000010 I
b1111000011000000001011000000010 )
#18000
b0 O
0"
0M
b1010110100011011 +
b1010110100011011 3
b1010110100011011 ;
b1010110100011011 C
b1010110100011011 #
02
0:
0B
0J
0*
b1010111101000011100101101110001 1
b1010111101000011100101101110001 9
b1010111101000011100101101110001 A
b1010111101000011100101101110001 I
b1010111101000011100101101110001 )
#19000
b1110011001101100 +
b1110011001101100 3
b1110011001101100 ;
b1110011001101100 C
b1110011001101100 #
1'
12
1:
1B
1J
1*
b11101010111000100000001001011110 1
b11101010111000100000001001011110 9
b11101010111000100000001001011110 A
b11101010111000100000001001011110 I
b11101010111000100000001001011110 )
#20000
b1011110111010111 +
b1011110111010111 3
b1011110111010111 ;
b1011110111010111 C
b1011110111010111 #
0'
0,
04
0<
0D
0$
b1011101100101100001111110000 1
b1011101100101100001111110000 9
b1011101100101100001111110000 A
b1011101100101100001111110000 I
b1011101100101100001111110000 )
#21000
b1001011100011100 +
b1001011100011100 3
b1001011100011100 ;
b1001011100011100 C
b1001011100011100 #
1'
1,
14
1<
1D
1$
b11011010100100001111010100110100 1
b11011010100100001111010100110100 9
b11011010100100001111010100110100 A
b11011010100100001111010100110100 I
b11011010100100001111010100110100 )
#22000
b11000100111011 +
b11000100111011 3
b11000100111011 ;
b11000100111011 C
b11000100111011 #
0,
04
0<
0D
0$
02
0:
0B
0J
0*
b111101010010100101110101010001 1
b111101010010100101110101010001 9
b111101010010100101110101010001 A
b111101010010100101110101010001 I
b111101010010100101110101010001 )
#23000
b1101111100100110 +
b1101111100100110 3
b1101111100100110 ;
b1101111100100110 C
b1101111100100110 #
1,
14
1<
1D
1$
b11000101101011011111011010000001 1
b11000101101011011111011010000001 9
b11000101101011011111011010000001 A
b11000101101011011111011010000001 I
b11000101101011011111011010000001 )
#24000
1!
b11 O
1"
1G
1N
b111110010111101 +
b111110010111101 3
b111110010111101 ;
b111110010111101 C
b111110010111101 #
12
1:
1B
1J
1*
b11000001011001110111001100111111 1
b11000001011001110111001100111111 9
b11000001011001110111001100111111 A
b11000001011001110111001100111111 I
b11000001011001110111001100111111 )
#25000
0!
b0 O
0"
0G
0N
b1111100101100011 +
b1111100101100011 3
b1111100101100011 ;
b1111100101100011 C
b1111100101100011 #
0,
04
0<
0D
0$
02
0:
0B
0J
0*
b10001100011011101001000000110111 1
b10001100011011101001000000110111 9
b10001100011011101001000000110111 A
b10001100011011101001000000110111 I
b10001100011011101001000000110111 )
#26000
b1010110110110011 +
b1010110110110011 3
b1010110110110011 ;
b1010110110110011 C
b1010110110110011 #
0'
b110110101010011000110101110100 1
b110110101010011000110101110100 9
b110110101010011000110101110100 A
b110110101010011000110101110100 I
b110110101010011000110101110100 )
#27000
b1001101110111101 +
b1001101110111101 3
b1001101110111101 ;
b1001101110111101 C
b1001101110111101 #
1'
12
1:
1B
1J
1*
b1001101011010110010001101001111 1
b1001101011010110010001101001111 9
b1001101011010110010001101001111 A
b1001101011010110010001101001111 I
b1001101011010110010001101001111 )
#28000
b10 O
1"
1?
1M
b100011001010011 +
b100011001010011 3
b100011001010011 ;
b100011001010011 C
b100011001010011 #
b11001010110101101110010100010100 1
b11001010110101101110010100010100 9
b11001010110101101110010100010100 A
b11001010110101101110010100010100 I
b11001010110101101110010100010100 )
#29000
b0 O
0"
0M
0?
b10011110001001 +
b10011110001001 3
b10011110001001 ;
b10011110001001 C
b10011110001001 #
0'
1,
14
1<
1D
1$
02
0:
0B
0J
0*
b1010110101000000010000010101 1
b1010110101000000010000010101 9
b1010110101000000010000010101 A
b1010110101000000010000010101 I
b1010110101000000010000010101 )
#30000
1/
1K
b101011000000 +
b101011000000 3
b101011000000 ;
b101011000000 C
b101011000000 #
1'
12
1:
1B
1J
1*
b10110011100010100000010111111011 1
b10110011100010100000010111111011 9
b10110011100010100000010111111011 A
b10110011100010100000010111111011 I
b10110011100010100000010111111011 )
#31000
0K
0/
b10110110100100 +
b10110110100100 3
b10110110100100 ;
b10110110100100 C
b10110110100100 #
0'
0,
04
0<
0D
0$
b1001010100000010100110101010011 1
b1001010100000010100110101010011 9
b1001010100000010100110101010011 A
b1001010100000010100110101010011 I
b1001010100000010100110101010011 )
#32000
b1001111011011011 +
b1001111011011011 3
b1001111011011011 ;
b1001111011011011 C
b1001111011011011 #
02
0:
0B
0J
0*
b101001111100101100001111000111 1
b101001111100101100001111000111 9
b101001111100101100001111000111 A
b101001111100101100001111000111 I
b101001111100101100001111000111 )
#33000
b1011101100000011 +
b1011101100000011 3
b1011101100000011 ;
b1011101100000011 C
b1011101100000011 #
1,
14
1<
1D
1$
b1001110110100010011010101010011 1
b1001110110100010011010101010011 9
b1001110110100010011010101010011 A
b1001110110100010011010101010011 I
b1001110110100010011010101010011 )
#34000
b1 O
1!
17
1L
b1100101110010 +
b1100101110010 3
b1100101110010 ;
b1100101110010 C
b1100101110010 #
1'
b1111001010110000101111001101001 1
b1111001010110000101111001101001 9
b1111001010110000101111001101001 A
b1111001010110000101111001101001 I
b1111001010110000101111001101001 )
#35000
b0 O
0!
1K
0L
07
b100110101110 +
b100110101110 3
b100110101110 ;
b100110101110 C
b100110101110 #
0'
0,
04
0<
0D
0$
12
1:
1B
1J
1*
b10101111111001100111100100001010 1
b10101111111001100111100100001010 9
b10101111111001100111100100001010 A
b10101111111001100111100100001010 I
b10101111111001100111100100001010 )
#36000
b1 O
1!
17
0K
1L
0/
b1000011011010 +
b1000011011010 3
b1000011011010 ;
b1000011011010 C
b1000011011010 #
1'
02
0:
0B
0J
0*
b10111111111101110111001111001110 1
b10111111111101110111001111001110 9
b10111111111101110111001111001110 A
b10111111111101110111001111001110 I
b10111111111101110111001111001110 )
#37000
b0 O
0!
07
0L
b1100100111001101 +
b1100100111001101 3
b1100100111001101 ;
b1100100111001101 C
b1100100111001101 #
1,
14
1<
1D
1$
12
1:
1B
1J
1*
b110111100111011110110110100001 1
b110111100111011110110110100001 9
b110111100111011110110110100001 A
b110111100111011110110110100001 I
b110111100111011110110110100001 )
#38000
b10 O
1"
1M
b101101111000111 +
b101101111000111 3
b101101111000111 ;
b101101111000111 C
b101101111000111 #
0'
0,
04
0<
0D
0$
b11011101000100111000001001100110 1
b11011101000100111000001001100110 9
b11011101000100111000001001100110 A
b11011101000100111000001001100110 I
b11011101000100111000001001100110 )
#39000
b100000110101000 +
b100000110101000 3
b100000110101000 ;
b100000110101000 C
b100000110101000 #
1,
14
1<
1D
1$
02
0:
0B
0J
0*
b11111111001111100000101110100001 1
b11111111001111100000101110100001 9
b11111111001111100000101110100001 A
b11111111001111100000101110100001 I
b11111111001111100000101110100001 )
#40000
b0 O
0"
0M
b10011010111101 +
b10011010111101 3
b10011010111101 ;
b10011010111101 C
b10011010111101 #
12
1:
1B
1J
1*
b11111011101001010010111001011001 1
b11111011101001010010111001011001 9
b11111011101001010010111001011001 A
b11111011101001010010111001011001 I
b11111011101001010010111001011001 )
#41000
b1110001101000101 +
b1110001101000101 3
b1110001101000101 ;
b1110001101000101 C
b1110001101000101 #
02
0:
0B
0J
0*
b11111111100010001110110010000010 1
b11111111100010001110110010000010 9
b11111111100010001110110010000010 A
b11111111100010001110110010000010 I
b11111111100010001110110010000010 )
#42000
b1111011001101010 +
b1111011001101010 3
b1111011001101010 ;
b1111011001101010 C
b1111011001101010 #
1'
b11010001011100000011010011001110 1
b11010001011100000011010011001110 9
b11010001011100000011010011001110 A
b11010001011100000011010011001110 I
b11010001011100000011010011001110 )
#43000
b10 O
1"
1?
1M
b100101101011100 +
b100101101011100 3
b100101101011100 ;
b100101101011100 C
b100101101011100 #
12
1:
1B
1J
1*
b1111000011011100011000011101111 1
b1111000011011100011000011101111 9
b1111000011011100011000011101111 A
b1111000011011100011000011101111 I
b1111000011011100011000011101111 )
#44000
1/
b0 O
0"
0?
1K
0M
b1111101001 +
b1111101001 3
b1111101001 ;
b1111101001 C
b1111101001 #
02
0:
0B
0J
0*
b1010100101000011101010100000101 1
b1010100101000011101010100000101 9
b1010100101000011101010100000101 A
b1010100101000011101010100000101 I
b1010100101000011101010100000101 )
#45000
0/
1!
b11 O
1"
1G
0K
1N
b1000011110100001 +
b1000011110100001 3
b1000011110100001 ;
b1000011110100001 C
b1000011110100001 #
0,
04
0<
0D
0$
12
1:
1B
1J
1*
b10111001101001010001001101100 1
b10111001101001010001001101100 9
b10111001101001010001001101100 A
b10111001101001010001001101100 I
b10111001101001010001001101100 )
#46000
0!
b0 O
0"
0N
0G
b11010011000011 +
b11010011000011 3
b11010011000011 ;
b11010011000011 C
b11010011000011 #
0'
1,
14
1<
1D
1$
b10011001001111101100100011000110 1
b10011001001111101100100011000110 9
b10011001001111101100100011000110 A
b10011001001111101100100011000110 I
b10011001001111101100100011000110 )
#47000
b1101110101100010 +
b1101110101100010 3
b1101110101100010 ;
b1101110101100010 C
b1101110101100010 #
1'
0,
04
0<
0D
0$
b11100010101000000001001100110101 1
b11100010101000000001001100110101 9
b11100010101000000001001100110101 A
b11100010101000000001001100110101 I
b11100010101000000001001100110101 )
#48000
b1111000101100100 +
b1111000101100100 3
b1111000101100100 ;
b1111000101100100 C
b1111000101100100 #
b1101000011101110111101110101011 1
b1101000011101110111101110101011 9
b1101000011101110111101110101011 A
b1101000011101110111101110101011 I
b1101000011101110111101110101011 )
#49000
b10 O
1"
1M
b101010110000010 +
b101010110000010 3
b101010110000010 ;
b101010110000010 C
b101010110000010 #
0'
1,
14
1<
1D
1$
02
0:
0B
0J
0*
b1111011001110000111100001011011 1
b1111011001110000111100001011011 9
b1111011001110000111100001011011 A
b1111011001110000111100001011011 I
b1111011001110000111100001011011 )
#50000
b0 O
0"
0M
b1111110010011000 +
b1111110010011000 3
b1111110010011000 ;
b1111110010011000 C
b1111110010011000 #
0,
04
0<
0D
0$
b10011100100111010000001111110011 1
b10011100100111010000001111110011 9
b10011100100111010000001111110011 A
b10011100100111010000001111110011 I
b10011100100111010000001111110011 )
#51000
b10000111111000 +
b10000111111000 3
b10000111111000 ;
b10000111111000 C
b10000111111000 #
1'
b10110011001110000110110000111110 1
b10110011001110000110110000111110 9
b10110011001110000110110000111110 A
b10110011001110000110110000111110 I
b10110011001110000110110000111110 )
#52000
b1001110000110000 +
b1001110000110000 3
b1001110000110000 ;
b1001110000110000 C
b1001110000110000 #
12
1:
1B
1J
1*
b10100001110111110011110110100111 1
b10100001110111110011110110100111 9
b10100001110111110011110110100111 A
b10100001110111110011110110100111 I
b10100001110111110011110110100111 )
#53000
b1111010101011110 +
b1111010101011110 3
b1111010101011110 ;
b1111010101011110 C
b1111010101011110 #
b1001011001101101011010101000101 1
b1001011001101101011010101000101 9
b1001011001101101011010101000101 A
b1001011001101101011010101000101 I
b1001011001101101011010101000101 )
#54000
b11000001101010 +
b11000001101010 3
b11000001101010 ;
b11000001101010 C
b11000001101010 #
0'
1,
14
1<
1D
1$
02
0:
0B
0J
0*
b1110001110011111111100000010100 1
b1110001110011111111100000010100 9
b1110001110011111111100000010100 A
b1110001110011111111100000010100 I
b1110001110011111111100000010100 )
#55000
1K
b101000111100 +
b101000111100 3
b101000111100 ;
b101000111100 C
b101000111100 #
0,
04
0<
0D
0$
12
1:
1B
1J
1*
b110110100101110110101111100 1
b110110100101110110101111100 9
b110110100101110110101111100 A
b110110100101110110101111100 I
b110110100101110110101111100 )
#56000
0K
0/
b1110001110000110 +
b1110001110000110 3
b1110001110000110 ;
b1110001110000110 C
b1110001110000110 #
1'
1,
14
1<
1D
1$
b10110010110100010000111000111101 1
b10110010110100010000111000111101 9
b10110010110100010000111000111101 A
b10110010110100010000111000111101 I
b10110010110100010000111000111101 )
#57000
b1 O
1!
17
1L
b1010110000011 +
b1010110000011 3
b1010110000011 ;
b1010110000011 C
b1010110000011 #
0,
04
0<
0D
0$
02
0:
0B
0J
0*
b10000000110111011010111111010 1
b10000000110111011010111111010 9
b10000000110111011010111111010 A
b10000000110111011010111111010 I
b10000000110111011010111111010 )
#58000
b0 O
0!
1K
0L
07
b11110110110 +
b11110110110 3
b11110110110 ;
b11110110110 C
b11110110110 #
0'
1,
14
1<
1D
1$
12
1:
1B
1J
1*
b11110110010101011000011000001011 1
b11110110010101011000011000001011 9
b11110110010101011000011000001011 A
b11110110010101011000011000001011 I
b11110110010101011000011000001011 )
#59000
0K
b10110110001011 +
b10110110001011 3
b10110110001011 ;
b10110110001011 C
b10110110001011 #
b111011000000011001111111001011 1
b111011000000011001111111001011 9
b111011000000011001111111001011 A
b111011000000011001111111001011 I
b111011000000011001111111001011 )
#60000
b1111000000110001 +
b1111000000110001 3
b1111000000110001 ;
b1111000000110001 C
b1111000000110001 #
1'
0,
04
0<
0D
0$
b1110101101101100100000011 1
b1110101101101100100000011 9
b1110101101101100100000011 A
b1110101101101100100000011 I
b1110101101101100100000011 )
#61000
1!
b11 O
1"
1N
b111101000001000 +
b111101000001000 3
b111101000001000 ;
b111101000001000 C
b111101000001000 #
0'
1,
14
1<
1D
1$
b1000010000110101010000101011110 1
b1000010000110101010000101011110 9
b1000010000110101010000101011110 A
b1000010000110101010000101011110 I
b1000010000110101010000101011110 )
#62000
0!
b0 O
0"
0N
0G
b1111010101001001 +
b1111010101001001 3
b1111010101001001 ;
b1111010101001001 C
b1111010101001001 #
1'
02
0:
0B
0J
0*
b101111000111011001101111101111 1
b101111000111011001101111101111 9
b101111000111011001101111101111 A
b101111000111011001101111101111 I
b101111000111011001101111101111 )
#63000
b10000000001111 +
b10000000001111 3
b10000000001111 ;
b10000000001111 C
b10000000001111 #
0,
04
0<
0D
0$
b10000010001000100001001101000101 1
b10000010001000100001001101000101 9
b10000010001000100001001101000101 A
b10000010001000100001001101000101 I
b10000010001000100001001101000101 )
#64000
1K
b10101000010 +
b10101000010 3
b10101000010 ;
b10101000010 C
b10101000010 #
0'
12
1:
1B
1J
1*
b10010101111011111011101011111 1
b10010101111011111011101011111 9
b10010101111011111011101011111 A
b10010101111011111011101011111 I
b10010101111011111011101011111 )
#65000
b10 O
1"
0K
1M
b101101011000100 +
b101101011000100 3
b101101011000100 ;
b101101011000100 C
b101101011000100 #
02
0:
0B
0J
0*
b10100001111111011100110111110001 1
b10100001111111011100110111110001 9
b10100001111111011100110111110001 A
b10100001111111011100110111110001 I
b10100001111111011100110111110001 )
#66000
b101001000010111 +
b101001000010111 3
b101001000010111 ;
b101001000010111 C
b101001000010111 #
b1001011000101100111100011100100 1
b1001011000101100111100011100100 9
b1001011000101100111100011100100 A
b1001011000101100111100011100100 I
b1001011000101100111100011100100 )
#67000
b0 O
0"
0M
0?
b10011101100100 +
b10011101100100 3
b10011101100100 ;
b10011101100100 C
b10011101100100 #
1'
1,
14
1<
1D
1$
b11101101101000101111110001001100 1
b11101101101000101111110001001100 9
b11101101101000101111110001001100 A
b11101101101000101111110001001100 I
b11101101101000101111110001001100 )
#68000
b10010001111111 +
b10010001111111 3
b10010001111111 ;
b10010001111111 C
b10010001111111 #
0'
0,
04
0<
0D
0$
12
1:
1B
1J
1*
b10100011001001100101001011101000 1
b10100011001001100101001011101000 9
b10100011001001100101001011101000 A
b10100011001001100101001011101000 I
b10100011001001100101001011101000 )
#69000
b11011111111110 +
b11011111111110 3
b11011111111110 ;
b11011111111110 C
b11011111111110 #
b11111010100100101100110100101000 1
b11111010100100101100110100101000 9
b11111010100100101100110100101000 A
b11111010100100101100110100101000 I
b11111010100100101100110100101000 )
#70000
b1100001010010101 +
b1100001010010101 3
b1100001010010101 ;
b1100001010010101 C
b1100001010010101 #
1'
b11000011000100100001101011110110 1
b11000011000100100001101011110110 9
b11000011000100100001101011110110 A
b11000011000100100001101011110110 I
b11000011000100100001101011110110 )
#71000
1!
b11 O
1"
1G
1N
b110010111111111 +
b110010111111111 3
b110010111111111 ;
b110010111111111 C
b110010111111111 #
1,
14
1<
1D
1$
b10110101110000000011111101101111 1
b10110101110000000011111101101111 9
b10110101110000000011111101101111 A
b10110101110000000011111101101111 I
b10110101110000000011111101101111 )
