streamTest/stream_Reg/streamReg/streamReg.v
// Generator : SpinalHDL v1.7.0a    git head : 150a9b9067020722818dfb17df4a23ac712a7af8
// Component : streamReg
// Git hash  : 3a903e741cbbe310a98c75dc1ebbd289cb1c87a4

`timescale 1ns/1ps

module streamReg (
  input               io_s_in_valid,
  output              io_s_in_ready,
  input      [31:0]   io_s_in_payload,
  output              io_m_out_valid,
  input               io_m_out_ready,
  output     [31:0]   io_m_out_payload,
  input               clk,
  input               reset
);

  wire                io_s_in_s2mPipe_valid;
  reg                 io_s_in_s2mPipe_ready;
  wire       [31:0]   io_s_in_s2mPipe_payload;
  reg                 io_s_in_rValid;
  reg        [31:0]   io_s_in_rData;
  wire                io_s_in_s2mPipe_m2sPipe_valid;
  wire                io_s_in_s2mPipe_m2sPipe_ready;
  wire       [31:0]   io_s_in_s2mPipe_m2sPipe_payload;
  reg                 io_s_in_s2mPipe_rValid;
  reg        [31:0]   io_s_in_s2mPipe_rData;
  wire                when_Stream_l368;

  assign io_s_in_ready = (! io_s_in_rValid);
  assign io_s_in_s2mPipe_valid = (io_s_in_valid || io_s_in_rValid);
  assign io_s_in_s2mPipe_payload = (io_s_in_rValid ? io_s_in_rData : io_s_in_payload);
  always @(*) begin
    io_s_in_s2mPipe_ready = io_s_in_s2mPipe_m2sPipe_ready;
    if(when_Stream_l368) begin
      io_s_in_s2mPipe_ready = 1'b1;
    end
  end

  assign when_Stream_l368 = (! io_s_in_s2mPipe_m2sPipe_valid);
  assign io_s_in_s2mPipe_m2sPipe_valid = io_s_in_s2mPipe_rValid;
  assign io_s_in_s2mPipe_m2sPipe_payload = io_s_in_s2mPipe_rData;
  assign io_m_out_valid = io_s_in_s2mPipe_m2sPipe_valid;
  assign io_s_in_s2mPipe_m2sPipe_ready = io_m_out_ready;
  assign io_m_out_payload = io_s_in_s2mPipe_m2sPipe_payload;
  always @(posedge clk or posedge reset) begin
    if(reset) begin
      io_s_in_rValid <= 1'b0;
      io_s_in_s2mPipe_rValid <= 1'b0;
    end else begin
      if(io_s_in_valid) begin
        io_s_in_rValid <= 1'b1;
      end
      if(io_s_in_s2mPipe_ready) begin
        io_s_in_rValid <= 1'b0;
      end
      if(io_s_in_s2mPipe_ready) begin
        io_s_in_s2mPipe_rValid <= io_s_in_s2mPipe_valid;
      end
    end
  end

  always @(posedge clk) begin
    if(io_s_in_ready) begin
      io_s_in_rData <= io_s_in_payload;
    end
    if(io_s_in_s2mPipe_ready) begin
      io_s_in_s2mPipe_rData <= io_s_in_s2mPipe_payload;
    end
  end

  initial begin
    $dumpfile("streamReg_test.vcd");
    $dumpvars(0, streamReg);
  end


endmodule

streamTest/stream_Reg/streamReg/streamReg_test.vcd
$date
	Mon May 30 13:32:43 2022
$end
$version
	Icarus Verilog
$end
$timescale
	1ps
$end
$scope module streamReg $end
$var wire 1 ! clk $end
$var wire 32 " io_m_out_payload [31:0] $end
$var wire 1 # io_m_out_ready $end
$var wire 1 $ io_m_out_valid $end
$var wire 32 % io_s_in_payload [31:0] $end
$var wire 1 & io_s_in_s2mPipe_m2sPipe_ready $end
$var wire 1 ' io_s_in_s2mPipe_valid $end
$var wire 1 ( io_s_in_valid $end
$var wire 1 ) reset $end
$var wire 1 * when_Stream_l368 $end
$var wire 32 + io_s_in_s2mPipe_payload [31:0] $end
$var wire 1 , io_s_in_s2mPipe_m2sPipe_valid $end
$var wire 32 - io_s_in_s2mPipe_m2sPipe_payload [31:0] $end
$var wire 1 . io_s_in_ready $end
$var reg 32 / io_s_in_rData [31:0] $end
$var reg 1 0 io_s_in_rValid $end
$var reg 32 1 io_s_in_s2mPipe_rData [31:0] $end
$var reg 1 , io_s_in_s2mPipe_rValid $end
$var reg 1 2 io_s_in_s2mPipe_ready $end
$upscope $end
$enddefinitions $end
#0
$dumpvars
12
bx 1
00
bx /
1.
bx -
0,
bz +
1*
1)
z(
x'
z&
bz %
0$
z#
bx "
0!
$end
#1000
0'
b0 +
12
0(
b0 %
0&
0#
0)
#1500
b0 "
b0 -
b0 1
b0 /
1!
#2000
0!
#2500
1!
#3000
0!
#3500
1!
#4000
0!
#4500
1&
1#
1!
#5000
0!
#5500
1'
1(
1!
#6000
0!
#6500
0*
1$
1,
1.
00
1!
#7000
0!
#7500
0'
02
0(
0&
0#
1.
00
1!
#8000
0!
#8500
1'
b11111001101111010100011100011001 +
1(
b11111001101111010100011100011001 %
1!
#9000
0!
#9500
12
0(
b0 %
1&
1#
b11111001101111010100011100011001 /
0.
10
1!
#10000
0!
#10500
02
0&
0#
b0 +
0'
b11111001101111010100011100011001 "
b11111001101111010100011100011001 -
b11111001101111010100011100011001 1
1.
00
1!
#11000
0!
#11500
12
1&
1#
b0 /
1!
#12000
0!
#12500
12
0&
0#
b0 "
b0 -
b0 1
1*
0$
0,
1!
#13000
0!
#13500
1'
b11101011010011111001111111011010 +
1(
b11101011010011111001111111011010 %
1&
1#
1!
#14000
0!
#14500
0'
b0 +
0(
b0 %
b11101011010011111001111111011010 "
b11101011010011111001111111011010 -
b11101011010011111001111111011010 1
b11101011010011111001111111011010 /
0*
1$
1,
1.
00
1!
#15000
0!
#15500
12
0&
0#
b0 "
b0 -
b0 1
b0 /
1*
0$
0,
1!
#16000
0!
#16500
1'
b11000000111100111001110101000101 +
1(
b11000000111100111001110101000101 %
1&
1#
1!
#17000
0!
#17500
0'
b0 +
0(
b0 %
b11000000111100111001110101000101 "
b11000000111100111001110101000101 -
b11000000111100111001110101000101 1
b11000000111100111001110101000101 /
0*
1$
1,
1.
00
1!
#18000
0!
#18500
1'
b11010111010100111111100001000101 +
12
1(
b11010111010100111111100001000101 %
0&
0#
b0 "
b0 -
b0 1
b0 /
1*
0$
0,
1!
#19000
0!
#19500
0'
b0 +
0(
b0 %
02
b11010111010100111111100001000101 "
b11010111010100111111100001000101 -
b11010111010100111111100001000101 1
b11010111010100111111100001000101 /
0*
1$
1,
1.
00
1!
#20000
0!
#20500
1'
b10101101011101001111010110111010 +
1(
b10101101011101001111010110111010 %
b0 /
1!
#21000
0!
#21500
0(
b0 %
b10101101011101001111010110111010 /
0.
10
1!
#22000
0!
#22500
1(
b11110101100000100000101111110010 %
1!
#23000
0!
#23500
12
1&
1#
1!
#24000
0!
#24500
02
0&
0#
b11110101100000100000101111110010 +
b10101101011101001111010110111010 "
b10101101011101001111010110111010 -
b10101101011101001111010110111010 1
1.
00
1!
#25000
0!
#25500
12
0(
b0 %
1&
1#
b11110101100000100000101111110010 /
0.
10
1!
#26000
0!
#26500
02
0&
0#
b0 +
0'
b11110101100000100000101111110010 "
b11110101100000100000101111110010 -
b11110101100000100000101111110010 1
1.
00
1!
#27000
0!
#27500
b0 /
1!
#28000
0!
#28500
1'
b10100010001011100011001100001111 +
1(
b10100010001011100011001100001111 %
1!
#29000
0!
#29500
12
0(
b0 %
1&
1#
b10100010001011100011001100001111 /
0.
10
1!
#30000
0!
#30500
02
0&
0#
b0 +
0'
b10100010001011100011001100001111 "
b10100010001011100011001100001111 -
b10100010001011100011001100001111 1
1.
00
1!
#31000
0!
#31500
b0 /
1!
#32000
0!
#32500
1'
b11101111101111100011100101010110 +
1(
b11101111101111100011100101010110 %
1!
#33000
0!
#33500
12
0(
b0 %
1&
1#
b11101111101111100011100101010110 /
0.
10
1!
#34000
0!
#34500
02
0&
0#
b0 +
0'
b11101111101111100011100101010110 "
b11101111101111100011100101010110 -
b11101111101111100011100101010110 1
1.
00
1!
#35000
0!
#35500
1'
b11011111010010001000000101110110 +
1(
b11011111010010001000000101110110 %
b0 /
1!
#36000
0!
#36500
12
0(
b0 %
1&
1#
b11011111010010001000000101110110 /
0.
10
1!
#37000
0!
#37500
02
0&
0#
b0 +
0'
b11011111010010001000000101110110 "
b11011111010010001000000101110110 -
b11011111010010001000000101110110 1
1.
00
1!
#38000
0!
#38500
1'
b1000101001101001001101101111101 +
1(
b1000101001101001001101101111101 %
b0 /
1!
#39000
0!
#39500
12
0(
b0 %
1&
1#
b1000101001101001001101101111101 /
0.
10
1!
#40000
0!
#40500
02
0&
0#
b0 +
0'
b1000101001101001001101101111101 "
b1000101001101001001101101111101 -
b1000101001101001001101101111101 1
1.
00
1!
#41000
0!
#41500
b0 /
1!
#42000
0!
#42500
1'
b10011110000100100101000011110110 +
1(
b10011110000100100101000011110110 %
1!
#43000
0!
#43500
12
0(
b0 %
1&
1#
b10011110000100100101000011110110 /
0.
10
1!
#44000
0!
#44500
02
1(
b1111001001010011010011011100010 %
0&
0#
b1111001001010011010011011100010 +
1'
b10011110000100100101000011110110 "
b10011110000100100101000011110110 -
b10011110000100100101000011110110 1
1.
00
1!
#45000
0!
#45500
12
0(
b0 %
1&
1#
b1111001001010011010011011100010 /
0.
10
1!
#46000
0!
#46500
02
1(
b11100010000001101100101001010000 %
0&
0#
b11100010000001101100101001010000 +
1'
b1111001001010011010011011100010 "
b1111001001010011010011011100010 -
b1111001001010011010011011100010 1
1.
00
1!
#47000
0!
#47500
12
0(
b0 %
1&
1#
b11100010000001101100101001010000 /
0.
10
1!
#48000
0!
#48500
02
1(
b1111101010111100001011000101000 %
0&
0#
b1111101010111100001011000101000 +
1'
b11100010000001101100101001010000 "
b11100010000001101100101001010000 -
b11100010000001101100101001010000 1
1.
00
1!
#49000
0!
#49500
12
0(
b0 %
1&
1#
b1111101010111100001011000101000 /
0.
10
1!
#50000
0!
#50500
02
1(
b10010100100111001110101101100110 %
0&
0#
b10010100100111001110101101100110 +
1'
b1111101010111100001011000101000 "
b1111101010111100001011000101000 -
b1111101010111100001011000101000 1
1.
00
1!
#51000
0!
#51500
0(
b0 %
b10010100100111001110101101100110 /
0.
10
1!
#52000
0!
#52500
1(
b1110111000000001100111010010000 %
1!
#53000
0!
#53500
1!
#54000
0!
#54500
12
1&
1#
1!
#55000
0!
#55500
02
0&
0#
b1110111000000001100111010010000 +
b10010100100111001110101101100110 "
b10010100100111001110101101100110 -
b10010100100111001110101101100110 1
1.
00
1!
#56000
0!
#56500
0(
b0 %
b1110111000000001100111010010000 /
0.
10
1!
#57000
0!
#57500
12
1&
1#
1!
#58000
0!
#58500
02
0&
0#
b0 +
0'
b1110111000000001100111010010000 "
b1110111000000001100111010010000 -
b1110111000000001100111010010000 1
1.
00
1!
#59000
0!
#59500
b0 /
1!
#60000
0!
#60500
12
1&
1#
1!
#61000
0!
#61500
1'
b10110101111011101101111100101011 +
12
1(
b10110101111011101101111100101011 %
0&
0#
b0 "
b0 -
b0 1
1*
0$
0,
1!
#62000
0!
#62500
0'
b0 +
0(
b0 %
1&
1#
12
b10110101111011101101111100101011 "
b10110101111011101101111100101011 -
b10110101111011101101111100101011 1
b10110101111011101101111100101011 /
0*
1$
1,
1.
00
1!
#63000
0!
#63500
12
0&
0#
b0 "
b0 -
b0 1
b0 /
1*
0$
0,
1!
#64000
0!
#64500
1'
b11110110010010100010001010100110 +
1(
b11110110010010100010001010100110 %
1&
1#
1!
#65000
0!
#65500
0'
b0 +
0(
b0 %
b11110110010010100010001010100110 "
b11110110010010100010001010100110 -
b11110110010010100010001010100110 1
b11110110010010100010001010100110 /
0*
1$
1,
1.
00
1!
#66000
0!
#66500
1'
b110010000010111100111111111100 +
12
1(
b110010000010111100111111111100 %
0&
0#
b0 "
b0 -
b0 1
b0 /
1*
0$
0,
1!
#67000
0!
#67500
0'
b0 +
0(
b0 %
1&
1#
12
b110010000010111100111111111100 "
b110010000010111100111111111100 -
b110010000010111100111111111100 1
b110010000010111100111111111100 /
0*
1$
1,
1.
00
1!
#68000
0!
#68500
1'
b100111001000101101000111000000 +
12
1(
b100111001000101101000111000000 %
0&
0#
b0 "
b0 -
b0 1
b0 /
1*
0$
0,
1!
#69000
0!
#69500
0'
b0 +
0(
b0 %
1&
1#
12
b100111001000101101000111000000 "
b100111001000101101000111000000 -
b100111001000101101000111000000 1
b100111001000101101000111000000 /
0*
1$
1,
1.
00
1!
#70000
0!
#70500
1'
b11000111000110111111111111001111 +
12
1(
b11000111000110111111111111001111 %
0&
0#
b0 "
b0 -
b0 1
b0 /
1*
0$
0,
1!
#71000
0!
#71500
0'
b0 +
0(
b0 %
02
b11000111000110111111111111001111 "
b11000111000110111111111111001111 -
b11000111000110111111111111001111 1
b11000111000110111111111111001111 /
0*
1$
1,
1.
00
1!
#72000
0!
#72500
1'
b11110110100011111111100010100110 +
12
1(
b11110110100011111111100010100110 %
1&
1#
b0 /
1!
#73000
0!
#73500
0'
b0 +
02
0(
b0 %
0&
0#
b11110110100011111111100010100110 "
b11110110100011111111100010100110 -
b11110110100011111111100010100110 1
b11110110100011111111100010100110 /
1.
00
1!
#74000
0!
#74500
1'
b10001000000000011100100011111110 +
1(
b10001000000000011100100011111110 %
b0 /
1!
#75000
0!
#75500
12
0(
b0 %
1&
1#
b10001000000000011100100011111110 /
0.
10
1!
#76000
0!
#76500
02
1(
b11111111001000000111000111001101 %
0&
0#
b11111111001000000111000111001101 +
1'
b10001000000000011100100011111110 "
b10001000000000011100100011111110 -
b10001000000000011100100011111110 1
1.
00
1!
#77000
0!
#77500
12
0(
b0 %
1&
1#
b11111111001000000111000111001101 /
0.
10
1!
#78000
0!
#78500
02
1(
b11110010111101010010001011010001 %
0&
0#
b11110010111101010010001011010001 +
1'
b11111111001000000111000111001101 "
b11111111001000000111000111001101 -
b11111111001000000111000111001101 1
1.
00
1!
#79000
0!
#79500
12
0(
b0 %
1&
1#
b11110010111101010010001011010001 /
0.
10
1!
#80000
0!
#80500
02
1(
b10000111000111011001100001111101 %
0&
0#
b10000111000111011001100001111101 +
1'
b11110010111101010010001011010001 "
b11110010111101010010001011010001 -
b11110010111101010010001011010001 1
1.
00
1!
#81000
0!
#81500
12
0(
b0 %
1&
1#
b10000111000111011001100001111101 /
0.
10
1!
#82000
0!
#82500
02
0&
0#
b0 +
0'
b10000111000111011001100001111101 "
b10000111000111011001100001111101 -
b10000111000111011001100001111101 1
1.
00
1!
#83000
0!
#83500
1'
b1111011000111111000000101110111 +
12
1(
b1111011000111111000000101110111 %
1&
1#
b0 /
1!
#84000
0!
#84500
0'
b0 +
02
0(
b0 %
0&
0#
b1111011000111111000000101110111 "
b1111011000111111000000101110111 -
b1111011000111111000000101110111 1
b1111011000111111000000101110111 /
1.
00
1!
#85000
0!
#85500
1'
b11111001010110110100000110110100 +
12
1(
b11111001010110110100000110110100 %
1&
1#
b0 /
1!
#86000
0!
#86500
0'
b0 +
02
0(
b0 %
0&
0#
b11111001010110110100000110110100 "
b11111001010110110100000110110100 -
b11111001010110110100000110110100 1
b11111001010110110100000110110100 /
1.
00
1!
#87000
0!
#87500
12
1&
1#
b0 /
1!
#88000
0!
#88500
12
0&
0#
b0 "
b0 -
b0 1
1*
0$
0,
1!
#89000
0!
#89500
1'
b11111010111000011001101000100010 +
1(
b11111010111000011001101000100010 %
1&
1#
1!
#90000
0!
#90500
0'
b0 +
0(
b0 %
b11111010111000011001101000100010 "
b11111010111000011001101000100010 -
b11111010111000011001101000100010 1
b11111010111000011001101000100010 /
0*
1$
1,
1.
00
1!
#91000
0!
#91500
1'
b10011100101001110011000101111110 +
12
1(
b10011100101001110011000101111110 %
0&
0#
b0 "
b0 -
b0 1
b0 /
1*
0$
0,
1!
#92000
0!
#92500
0'
b0 +
0(
b0 %
02
b10011100101001110011000101111110 "
b10011100101001110011000101111110 -
b10011100101001110011000101111110 1
b10011100101001110011000101111110 /
0*
1$
1,
1.
00
1!
#93000
0!
#93500
1'
b10101101110100111111011000011 +
1(
b10101101110100111111011000011 %
b0 /
1!
#94000
0!
#94500
0(
b0 %
b10101101110100111111011000011 /
0.
10
1!
#95000
0!
#95500
1(
b1001000111010101110001100100100 %
1!
#96000
0!
#96500
12
1&
1#
1!
#97000
0!
#97500
02
0&
0#
b1001000111010101110001100100100 +
b10101101110100111111011000011 "
b10101101110100111111011000011 -
b10101101110100111111011000011 1
1.
00
1!
#98000
0!
#98500
12
0(
b0 %
1&
1#
b1001000111010101110001100100100 /
0.
10
1!
#99000
0!
#99500
02
1(
b10001110011100111000100110000000 %
0&
0#
b10001110011100111000100110000000 +
1'
b1001000111010101110001100100100 "
b1001000111010101110001100100100 -
b1001000111010101110001100100100 1
1.
00
1!
#100000
0!
#100500
12
0(
b0 %
1&
1#
b10001110011100111000100110000000 /
0.
10
1!
#101000
0!
#101500
02
1(
b10000011000000101111110001111111 %
0&
0#
b10000011000000101111110001111111 +
1'
b10001110011100111000100110000000 "
b10001110011100111000100110000000 -
b10001110011100111000100110000000 1
1.
00
1!
#102000
0!
#102500
0(
b0 %
b10000011000000101111110001111111 /
0.
10
1!
#103000
0!
#103500
12
1(
b10111000011110111000100001100100 %
1&
1#
1!
#104000
0!
#104500
02
0&
0#
b10111000011110111000100001100100 +
b10000011000000101111110001111111 "
b10000011000000101111110001111111 -
b10000011000000101111110001111111 1
1.
00
1!
#105000
0!
#105500
0(
b0 %
b10111000011110111000100001100100 /
0.
10
1!
#106000
0!
#106500
12
1&
1#
1!
#107000
0!
#107500
02
0&
0#
b0 +
0'
b10111000011110111000100001100100 "
b10111000011110111000100001100100 -
b10111000011110111000100001100100 1
1.
00
1!
#108000
0!
#108500
12
1&
1#
b0 /
1!
#109000
0!
#109500
12
0&
0#
b0 "
b0 -
b0 1
1*
0$
0,
1!
#110000
0!
#110500
1&
1#
1!
#111000
0!
#111500
1!
#112000
0!
#112500
1'
b1100000001001001010000101111011 +
1(
b1100000001001001010000101111011 %
1!
#113000
0!
#113500
0'
b0 +
0(
b0 %
b1100000001001001010000101111011 "
b1100000001001001010000101111011 -
b1100000001001001010000101111011 1
b1100000001001001010000101111011 /
0*
1$
1,
1.
00
1!
#114000
0!
#114500
12
0&
0#
b0 "
b0 -
b0 1
b0 /
1*
0$
0,
1!
#115000
0!
#115500
1'
b11011010110001010011100100010 +
1(
b11011010110001010011100100010 %
1&
1#
1!
#116000
0!
#116500
0'
b0 +
0(
b0 %
b11011010110001010011100100010 "
b11011010110001010011100100010 -
b11011010110001010011100100010 1
b11011010110001010011100100010 /
0*
1$
1,
1.
00
1!
#117000
0!
#117500
12
0&
0#
b0 "
b0 -
b0 1
b0 /
1*
0$
0,
1!
#118000
0!
#118500
1'
b10111000011111010010001000010011 +
1(
b10111000011111010010001000010011 %
1!
#119000
0!
#119500
0'
b0 +
0(
b0 %
02
b10111000011111010010001000010011 "
b10111000011111010010001000010011 -
b10111000011111010010001000010011 1
b10111000011111010010001000010011 /
0*
1$
1,
1.
00
1!
#120000
0!
#120500
b0 /
1!
#121000
0!
#121500
12
1&
1#
1!
#122000
0!
#122500
12
0&
0#
b0 "
b0 -
b0 1
1*
0$
0,
1!
#123000
0!
#123500
1'
b1010101111001101011101001111000 +
1(
b1010101111001101011101001111000 %
1!
#124000
0!
#124500
0'
b0 +
0(
b0 %
02
b1010101111001101011101001111000 "
b1010101111001101011101001111000 -
b1010101111001101011101001111000 1
b1010101111001101011101001111000 /
0*
1$
1,
1.
00
1!
#125000
0!
#125500
1'
b10011100010011100110011111000000 +
12
1(
b10011100010011100110011111000000 %
1&
1#
b0 /
1!
#126000
0!
#126500
0'
b0 +
02
0(
b0 %
0&
0#
b10011100010011100110011111000000 "
b10011100010011100110011111000000 -
b10011100010011100110011111000000 1
b10011100010011100110011111000000 /
1.
00
1!
#127000
0!
#127500
1'
b10100011111000001000101010110100 +
12
1(
b10100011111000001000101010110100 %
1&
1#
b0 /
1!
#128000
0!
#128500
0'
b0 +
02
0(
b0 %
0&
0#
b10100011111000001000101010110100 "
b10100011111000001000101010110100 -
b10100011111000001000101010110100 1
b10100011111000001000101010110100 /
1.
00
1!
#129000
0!
#129500
1'
b10100001100011000101101111100111 +
1(
b10100001100011000101101111100111 %
b0 /
1!
#130000
0!
#130500
0(
b0 %
b10100001100011000101101111100111 /
0.
10
1!
#131000
0!
#131500
1!
#132000
0!
#132500
1!
#133000
0!
#133500
12
1(
b11111111000111100100011000011010 %
1&
1#
1!
#134000
0!
#134500
02
0&
0#
b11111111000111100100011000011010 +
b10100001100011000101101111100111 "
b10100001100011000101101111100111 -
b10100001100011000101101111100111 1
1.
00
1!
#135000
0!
#135500
0(
b0 %
b11111111000111100100011000011010 /
0.
10
1!
#136000
0!
#136500
1!
#137000
0!
#137500
1!
#138000
0!
#138500
1!
#139000
0!
#139500
12
1(
b110011001000110011001101111111 %
1&
1#
1!
#140000
0!
#140500
02
0&
0#
b110011001000110011001101111111 +
b11111111000111100100011000011010 "
b11111111000111100100011000011010 -
b11111111000111100100011000011010 1
1.
00
1!
#141000
0!
#141500
0(
b0 %
b110011001000110011001101111111 /
0.
10
1!
#142000
0!
#142500
1!
#143000
0!
#143500
12
1&
1#
1!
#144000
0!
#144500
02
1(
b10011010011111110010011101010011 %
0&
0#
b10011010011111110010011101010011 +
1'
b110011001000110011001101111111 "
b110011001000110011001101111111 -
b110011001000110011001101111111 1
1.
00
1!
#145000
0!
#145500
0(
b0 %
b10011010011111110010011101010011 /
0.
10
1!
#146000
0!
#146500
12
1(
b1110110010001110011011111110 %
1&
1#
1!
#147000
0!
#147500
02
0&
0#
b1110110010001110011011111110 +
b10011010011111110010011101010011 "
b10011010011111110010011101010011 -
b10011010011111110010011101010011 1
1.
00
1!
#148000
0!
#148500
0(
b0 %
b1110110010001110011011111110 /
0.
10
1!
#149000
0!
#149500
12
1(
b1011110111010010000000011000100 %
1&
1#
1!
#150000
0!
#150500
02
0&
0#
b1011110111010010000000011000100 +
b1110110010001110011011111110 "
b1110110010001110011011111110 -
b1110110010001110011011111110 1
1.
00
1!
#151000
0!
#151500
0(
b0 %
b1011110111010010000000011000100 /
0.
10
1!
#152000
0!
#152500
12
1&
1#
1!
#153000
0!
#153500
02
1(
b11001101101100101111101010001001 %
0&
0#
b11001101101100101111101010001001 +
1'
b1011110111010010000000011000100 "
b1011110111010010000000011000100 -
b1011110111010010000000011000100 1
1.
00
1!
#154000
0!
#154500
12
0(
b0 %
1&
1#
b11001101101100101111101010001001 /
0.
10
1!
#155000
0!
#155500
02
1(
b1011001110010000000100111001100 %
0&
0#
b1011001110010000000100111001100 +
1'
b11001101101100101111101010001001 "
b11001101101100101111101010001001 -
b11001101101100101111101010001001 1
1.
00
1!
#156000
0!
#156500
12
0(
b0 %
1&
1#
b1011001110010000000100111001100 /
0.
10
1!
#157000
0!
#157500
02
1(
b10101100111110010000011001110000 %
0&
0#
b10101100111110010000011001110000 +
1'
b1011001110010000000100111001100 "
b1011001110010000000100111001100 -
b1011001110010000000100111001100 1
1.
00
1!
#158000
0!
#158500
0(
b0 %
b10101100111110010000011001110000 /
0.
10
1!
#159000
0!
#159500
1(
b11111010111100101101010000100101 %
1!
#160000
0!
#160500
12
1&
1#
1!
#161000
0!
#161500
02
0&
0#
b11111010111100101101010000100101 +
b10101100111110010000011001110000 "
b10101100111110010000011001110000 -
b10101100111110010000011001110000 1
1.
00
1!
#162000
0!
#162500
12
0(
b0 %
1&
1#
b11111010111100101101010000100101 /
0.
10
1!
#163000
0!
#163500
02
0&
0#
b0 +
0'
b11111010111100101101010000100101 "
b11111010111100101101010000100101 -
b11111010111100101101010000100101 1
1.
00
1!
#164000
0!
#164500
12
1&
1#
b0 /
1!
#165000
0!
#165500
12
0&
0#
b0 "
b0 -
b0 1
1*
0$
0,
1!
#166000
0!
#166500
1&
1#
1!
#167000
0!
#167500
1'
b10010110111111100101001100000 +
1(
b10010110111111100101001100000 %
1!
#168000
0!
#168500
0'
b0 +
0(
b0 %
b10010110111111100101001100000 "
b10010110111111100101001100000 -
b10010110111111100101001100000 1
b10010110111111100101001100000 /
0*
1$
1,
1.
00
1!
#169000
0!
#169500
1'
b11001000000001010001100000100000 +
12
1(
b11001000000001010001100000100000 %
0&
0#
b0 "
b0 -
b0 1
b0 /
1*
0$
0,
1!
#170000
0!
#170500
0'
b0 +
0(
b0 %
1&
1#
12
b11001000000001010001100000100000 "
b11001000000001010001100000100000 -
b11001000000001010001100000100000 1
b11001000000001010001100000100000 /
0*
1$
1,
1.
00
1!
#171000
0!
#171500
12
0&
0#
b0 "
b0 -
b0 1
b0 /
1*
0$
0,
1!
#172000
0!
#172500
1'
b100101111011111111110101011100 +
1(
b100101111011111111110101011100 %
1&
1#
1!
#173000
0!
#173500
0'
b0 +
0(
b0 %
b100101111011111111110101011100 "
b100101111011111111110101011100 -
b100101111011111111110101011100 1
b100101111011111111110101011100 /
0*
1$
1,
1.
00
1!
#174000
0!
#174500
1'
b1000100011011000000100011101011 +
12
1(
b1000100011011000000100011101011 %
0&
0#
b0 "
b0 -
b0 1
b0 /
1*
0$
0,
1!
#175000
0!
#175500
0'
b0 +
0(
b0 %
1&
1#
12
b1000100011011000000100011101011 "
b1000100011011000000100011101011 -
b1000100011011000000100011101011 1
b1000100011011000000100011101011 /
0*
1$
1,
1.
00
1!
#176000
0!
#176500
1'
b11110011010101110110100111000 +
12
1(
b11110011010101110110100111000 %
0&
0#
b0 "
b0 -
b0 1
b0 /
1*
0$
0,
1!
#177000
0!
#177500
0'
b0 +
0(
b0 %
1&
1#
12
b11110011010101110110100111000 "
b11110011010101110110100111000 -
b11110011010101110110100111000 1
b11110011010101110110100111000 /
0*
1$
1,
1.
00
1!
#178000
0!
#178500
12
0&
0#
b0 "
b0 -
b0 1
b0 /
1*
0$
0,
1!
#179000
0!
#179500
1!
#180000
0!
#180500
1'
b11001111101110001101011001101100 +
1(
b11001111101110001101011001101100 %
1&
1#
1!
#181000
0!
#181500
0'
b0 +
0(
b0 %
b11001111101110001101011001101100 "
b11001111101110001101011001101100 -
b11001111101110001101011001101100 1
b11001111101110001101011001101100 /
0*
1$
1,
1.
00
1!
#182000
0!
#182500
12
0&
0#
b0 "
b0 -
b0 1
b0 /
1*
0$
0,
1!
#183000
0!
#183500
1'
b1100011100100000001011011001101 +
1(
b1100011100100000001011011001101 %
1&
1#
1!
#184000
0!
#184500
0'
b0 +
0(
b0 %
b1100011100100000001011011001101 "
b1100011100100000001011011001101 -
b1100011100100000001011011001101 1
b1100011100100000001011011001101 /
0*
1$
1,
1.
00
1!
#185000
0!
#185500
12
0&
0#
b0 "
b0 -
b0 1
b0 /
1*
0$
0,
1!
#186000
0!
#186500
1!
#187000
0!
#187500
1&
1#
1!
#188000
0!
#188500
1!
#189000
0!
#189500
1'
b10110101010000001100110111111001 +
1(
b10110101010000001100110111111001 %
1!
#190000
0!
#190500
0'
b0 +
0(
b0 %
b10110101010000001100110111111001 "
b10110101010000001100110111111001 -
b10110101010000001100110111111001 1
b10110101010000001100110111111001 /
0*
1$
1,
1.
00
1!
#191000
0!
#191500
1'
b1111010101011111111101101 +
12
1(
b1111010101011111111101101 %
0&
0#
b0 "
b0 -
b0 1
b0 /
1*
0$
0,
1!
#192000
0!
#192500
0'
b0 +
0(
b0 %
1&
1#
12
b1111010101011111111101101 "
b1111010101011111111101101 -
b1111010101011111111101101 1
b1111010101011111111101101 /
0*
1$
1,
1.
00
1!
#193000
0!
#193500
12
0&
0#
b0 "
b0 -
b0 1
b0 /
1*
0$
0,
1!
#194000
0!
#194500
1'
b111010000110101100100101100101 +
1(
b111010000110101100100101100101 %
1&
1#
1!
#195000
0!
#195500
0'
b0 +
0(
b0 %
b111010000110101100100101100101 "
b111010000110101100100101100101 -
b111010000110101100100101100101 1
b111010000110101100100101100101 /
0*
1$
1,
1.
00
1!
#196000
0!
#196500
12
0&
0#
b0 "
b0 -
b0 1
b0 /
1*
0$
0,
1!
#197000
0!
#197500
1!
#198000
0!
#198500
1'
b10100011011101111000001111101000 +
1(
b10100011011101111000001111101000 %
1&
1#
1!
#199000
0!
#199500
0'
b0 +
0(
b0 %
b10100011011101111000001111101000 "
b10100011011101111000001111101000 -
b10100011011101111000001111101000 1
b10100011011101111000001111101000 /
0*
1$
1,
1.
00
1!
#200000
0!
#200500
1'
b11110110100101001110011001 +
12
1(
b11110110100101001110011001 %
0&
0#
b0 "
b0 -
b0 1
b0 /
1*
0$
0,
1!
#201000
0!
#201500
0'
b0 +
0(
b0 %
1&
1#
12
b11110110100101001110011001 "
b11110110100101001110011001 -
b11110110100101001110011001 1
b11110110100101001110011001 /
0*
1$
1,
1.
00
1!
#202000
0!
#202500
12
0&
0#
b0 "
b0 -
b0 1
b0 /
1*
0$
0,
1!
#203000
0!
#203500
1'
b11101101001101000111101100111001 +
1(
b11101101001101000111101100111001 %
1!
#204000
0!
#204500
0'
b0 +
0(
b0 %
02
b11101101001101000111101100111001 "
b11101101001101000111101100111001 -
b11101101001101000111101100111001 1
b11101101001101000111101100111001 /
0*
1$
1,
1.
00
1!
#205000
0!
#205500
12
1&
1#
b0 /
1!
#206000
0!
#206500
12
0&
0#
b0 "
b0 -
b0 1
1*
0$
0,
1!
#207000
0!
#207500
1'
b10000001111110011101000101011101 +
1(
b10000001111110011101000101011101 %
1!
#208000
0!
#208500
0'
b0 +
0(
b0 %
02
b10000001111110011101000101011101 "
b10000001111110011101000101011101 -
b10000001111110011101000101011101 1
b10000001111110011101000101011101 /
0*
1$
1,
1.
00
1!
#209000
0!
#209500
b0 /
1!
#210000
0!
#210500
12
1&
1#
1!
#211000
0!
#211500
12
0&
0#
b0 "
b0 -
b0 1
1*
0$
0,
1!
#212000
0!
#212500
1'
b10011111010110110000111111000101 +
1(
b10011111010110110000111111000101 %
1!
#213000
0!
#213500
0'
b0 +
0(
b0 %
02
b10011111010110110000111111000101 "
b10011111010110110000111111000101 -
b10011111010110110000111111000101 1
b10011111010110110000111111000101 /
0*
1$
1,
1.
00
1!
#214000
0!
#214500
b0 /
1!
#215000
0!
#215500
1'
b11101011100011010111101001111 +
1(
b11101011100011010111101001111 %
1!
#216000
0!
#216500
12
0(
b0 %
1&
1#
b11101011100011010111101001111 /
0.
10
1!
#217000
0!
