uart/UartCtrlRx.v
// Generator : SpinalHDL v1.6.4    git head : 598c18959149eb18e5eee5b0aa3eef01ecaa41a1
// Component : UartCtrlRx
// Git hash  : 89d7543c7219f82d1991c9174f1b313aba4435ca

`timescale 1ns/1ps 

module UartCtrlRx (
  input               io_rxd,
  input               io_samplingTick,
  output reg          io_read_valid,
  output     [7:0]    io_read_payload,
  input               clk,
  input               reset
);
  localparam UartCtrlRxState_IDLE = 2'd0;
  localparam UartCtrlRxState_START = 2'd1;
  localparam UartCtrlRxState_DATA = 2'd2;
  localparam UartCtrlRxState_STOP = 2'd3;

  wire                _zz_sampler_value;
  wire                _zz_sampler_value_1;
  wire                _zz_sampler_value_2;
  wire                _zz_sampler_value_3;
  wire                _zz_sampler_value_4;
  wire                _zz_sampler_value_5;
  wire                _zz_sampler_value_6;
  wire                sampler_samples_0;
  wire                sampler_samples_1;
  wire                sampler_samples_2;
  wire                sampler_samples_3;
  wire                sampler_samples_4;
  reg                 _zz_sampler_samples_0;
  reg                 _zz_sampler_samples_0_1;
  reg                 _zz_sampler_samples_1;
  reg                 _zz_sampler_samples_2;
  reg                 _zz_sampler_samples_3;
  reg                 _zz_sampler_samples_4;
  reg                 sampler_value;
  reg                 sampler_tick;
  reg        [2:0]    bitTimer_counter;
  reg                 bitTimer_recenter;
  reg                 bitTimer_tick;
  wire                when_UartCtrlRx_l49;
  reg        [2:0]    bitCounter_value;
  reg                 bitCounter_clear;
  reg        [1:0]    stateMachine_state;
  reg        [7:0]    stateMachine_buffer;
  wire                when_UartCtrlRx_l84;
  wire                when_UartCtrlRx_l98;
  `ifndef SYNTHESIS
  reg [39:0] stateMachine_state_string;
  `endif


  assign _zz_sampler_value = ((((1'b0 || ((_zz_sampler_value_1 && sampler_samples_1) && sampler_samples_2)) || (((_zz_sampler_value_2 && sampler_samples_0) && sampler_samples_1) && sampler_samples_3)) || (((1'b1 && sampler_samples_0) && sampler_samples_2) && sampler_samples_3)) || (((1'b1 && sampler_samples_1) && sampler_samples_2) && sampler_samples_3));
  assign _zz_sampler_value_3 = (((1'b1 && sampler_samples_0) && sampler_samples_1) && sampler_samples_4);
  assign _zz_sampler_value_4 = ((1'b1 && sampler_samples_0) && sampler_samples_2);
  assign _zz_sampler_value_5 = (1'b1 && sampler_samples_1);
  assign _zz_sampler_value_6 = 1'b1;
  assign _zz_sampler_value_1 = (1'b1 && sampler_samples_0);
  assign _zz_sampler_value_2 = 1'b1;
  `ifndef SYNTHESIS
  always @(*) begin
    case(stateMachine_state)
      UartCtrlRxState_IDLE : stateMachine_state_string = "IDLE ";
      UartCtrlRxState_START : stateMachine_state_string = "START";
      UartCtrlRxState_DATA : stateMachine_state_string = "DATA ";
      UartCtrlRxState_STOP : stateMachine_state_string = "STOP ";
      default : stateMachine_state_string = "?????";
    endcase
  end
  `endif

  assign sampler_samples_0 = _zz_sampler_samples_0_1;
  assign sampler_samples_1 = _zz_sampler_samples_1;
  assign sampler_samples_2 = _zz_sampler_samples_2;
  assign sampler_samples_3 = _zz_sampler_samples_3;
  assign sampler_samples_4 = _zz_sampler_samples_4;
  always @(*) begin
    bitTimer_recenter = 1'b0;
    case(stateMachine_state)
      UartCtrlRxState_IDLE : begin
        if(when_UartCtrlRx_l84) begin
          bitTimer_recenter = 1'b1;
        end
      end
      UartCtrlRxState_START : begin
      end
      UartCtrlRxState_DATA : begin
      end
      default : begin
      end
    endcase
  end

  always @(*) begin
    bitTimer_tick = 1'b0;
    if(sampler_tick) begin
      if(when_UartCtrlRx_l49) begin
        bitTimer_tick = 1'b1;
      end
    end
  end

  assign when_UartCtrlRx_l49 = (bitTimer_counter == 3'b000);
  always @(*) begin
    bitCounter_clear = 1'b0;
    case(stateMachine_state)
      UartCtrlRxState_IDLE : begin
      end
      UartCtrlRxState_START : begin
        if(bitTimer_tick) begin
          bitCounter_clear = 1'b1;
        end
      end
      UartCtrlRxState_DATA : begin
      end
      default : begin
      end
    endcase
  end

  always @(*) begin
    io_read_valid = 1'b0;
    case(stateMachine_state)
      UartCtrlRxState_IDLE : begin
      end
      UartCtrlRxState_START : begin
      end
      UartCtrlRxState_DATA : begin
      end
      default : begin
        if(bitTimer_tick) begin
          io_read_valid = 1'b1;
        end
      end
    endcase
  end

  assign when_UartCtrlRx_l84 = (sampler_tick && (! sampler_value));
  assign when_UartCtrlRx_l98 = (bitCounter_value == 3'b111);
  assign io_read_payload = stateMachine_buffer;
  always @(posedge clk or posedge reset) begin
    if(reset) begin
      _zz_sampler_samples_0 <= 1'b1;
      _zz_sampler_samples_0_1 <= 1'b1;
      _zz_sampler_samples_1 <= 1'b1;
      _zz_sampler_samples_2 <= 1'b1;
      _zz_sampler_samples_3 <= 1'b1;
      _zz_sampler_samples_4 <= 1'b1;
      sampler_value <= 1'b1;
      sampler_tick <= 1'b0;
      stateMachine_state <= UartCtrlRxState_IDLE;
    end else begin
      if(io_samplingTick) begin
        _zz_sampler_samples_0 <= io_rxd;
      end
      if(io_samplingTick) begin
        _zz_sampler_samples_0_1 <= _zz_sampler_samples_0;
      end
      if(io_samplingTick) begin
        _zz_sampler_samples_1 <= _zz_sampler_samples_0_1;
      end
      if(io_samplingTick) begin
        _zz_sampler_samples_2 <= _zz_sampler_samples_1;
      end
      if(io_samplingTick) begin
        _zz_sampler_samples_3 <= _zz_sampler_samples_2;
      end
      if(io_samplingTick) begin
        _zz_sampler_samples_4 <= _zz_sampler_samples_3;
      end
      sampler_value <= ((((((_zz_sampler_value || _zz_sampler_value_3) || (_zz_sampler_value_4 && sampler_samples_4)) || ((_zz_sampler_value_5 && sampler_samples_2) && sampler_samples_4)) || (((_zz_sampler_value_6 && sampler_samples_0) && sampler_samples_3) && sampler_samples_4)) || (((1'b1 && sampler_samples_1) && sampler_samples_3) && sampler_samples_4)) || (((1'b1 && sampler_samples_2) && sampler_samples_3) && sampler_samples_4));
      sampler_tick <= io_samplingTick;
      case(stateMachine_state)
        UartCtrlRxState_IDLE : begin
          if(when_UartCtrlRx_l84) begin
            stateMachine_state <= UartCtrlRxState_START;
          end
        end
        UartCtrlRxState_START : begin
          if(bitTimer_tick) begin
            stateMachine_state <= UartCtrlRxState_DATA;
          end
        end
        UartCtrlRxState_DATA : begin
          if(bitTimer_tick) begin
            if(when_UartCtrlRx_l98) begin
              stateMachine_state <= UartCtrlRxState_STOP;
            end
          end
        end
        default : begin
          if(bitTimer_tick) begin
            stateMachine_state <= UartCtrlRxState_IDLE;
          end
        end
      endcase
    end
  end

  always @(posedge clk) begin
    if(sampler_tick) begin
      bitTimer_counter <= (bitTimer_counter - 3'b001);
    end
    if(bitTimer_recenter) begin
      bitTimer_counter <= 3'b010;
    end
    if(bitTimer_tick) begin
      bitCounter_value <= (bitCounter_value + 3'b001);
    end
    if(bitCounter_clear) begin
      bitCounter_value <= 3'b000;
    end
    case(stateMachine_state)
      UartCtrlRxState_IDLE : begin
      end
      UartCtrlRxState_START : begin
      end
      UartCtrlRxState_DATA : begin
        if(bitTimer_tick) begin
          stateMachine_buffer[bitCounter_value] <= sampler_value;
        end
      end
      default : begin
      end
    endcase
  end

  `ifdef COCOTB_SIM
  initial begin
    $dumpfile("UartCtrlRX_test.vcd");
    $dumpvars(0,UartCtrlRx);
  end
  `endif


endmodule

uart/UartCtrlRX_test.vcd
$date
	Mon Mar 28 17:24:23 2022
$end
$version
	Icarus Verilog
$end
$timescale
	1ps
$end
$scope module UartCtrlRx $end
$var wire 1 ! _zz_sampler_value $end
$var wire 1 " _zz_sampler_value_1 $end
$var wire 1 # _zz_sampler_value_2 $end
$var wire 1 $ _zz_sampler_value_3 $end
$var wire 1 % _zz_sampler_value_4 $end
$var wire 1 & _zz_sampler_value_5 $end
$var wire 1 ' _zz_sampler_value_6 $end
$var wire 1 ( clk $end
$var wire 8 ) io_read_payload [7:0] $end
$var wire 1 * io_rxd $end
$var wire 1 + io_samplingTick $end
$var wire 1 , reset $end
$var wire 1 - sampler_samples_0 $end
$var wire 1 . sampler_samples_1 $end
$var wire 1 / sampler_samples_2 $end
$var wire 1 0 sampler_samples_3 $end
$var wire 1 1 sampler_samples_4 $end
$var wire 1 2 when_UartCtrlRx_l84 $end
$var wire 1 3 when_UartCtrlRx_l98 $end
$var wire 1 4 when_UartCtrlRx_l49 $end
$var reg 1 5 _zz_sampler_samples_0 $end
$var reg 1 - _zz_sampler_samples_0_1 $end
$var reg 1 . _zz_sampler_samples_1 $end
$var reg 1 / _zz_sampler_samples_2 $end
$var reg 1 0 _zz_sampler_samples_3 $end
$var reg 1 1 _zz_sampler_samples_4 $end
$var reg 1 6 bitCounter_clear $end
$var reg 3 7 bitCounter_value [2:0] $end
$var reg 3 8 bitTimer_counter [2:0] $end
$var reg 1 9 bitTimer_recenter $end
$var reg 1 : bitTimer_tick $end
$var reg 1 ; io_read_valid $end
$var reg 1 < sampler_tick $end
$var reg 1 = sampler_value $end
$var reg 8 > stateMachine_buffer [7:0] $end
$var reg 2 ? stateMachine_state [1:0] $end
$var reg 40 @ stateMachine_state_string [39:0] $end
$upscope $end
$enddefinitions $end
#0
$dumpvars
b100100101000100010011000100010100100000 @
b0 ?
bx >
1=
0<
0;
0:
09
bx 8
bx 7
06
15
x4
x3
02
11
10
1/
1.
1-
1,
1+
1*
bx )
0(
1'
1&
1%
1$
1#
1"
1!
$end
#500
1(
0+
#1000
0,
1+
#1500
0(
0+
#2000
1<
1(
1+
#2500
0(
0+
#3000
1(
1+
#3500
0(
0+
#4000
1(
1+
#4500
0(
0+
#5000
1(
1+
#5500
0(
0+
#6000
1(
1+
#6500
0(
0+
#7000
1(
1+
#7500
0(
0+
#8000
1(
1+
#8500
0(
0+
#9000
0*
1(
1+
#9500
0(
0+
#10000
05
1(
1+
#10500
0(
0+
#11000
0$
0%
0"
0-
1(
1+
#11500
0(
0+
#12000
0!
0&
0.
1(
1+
#12500
0(
0+
#13000
0/
1(
1+
#13500
0(
0+
#14000
19
12
0=
00
1(
1+
#14500
0(
0+
#15000
09
b101001101010100010000010101001001010100 @
04
b10 8
b1 ?
01
1(
1+
#15500
0(
0+
#16000
b1 8
1(
1+
#16500
0(
0+
#17000
16
1:
14
b0 8
1(
1+
#17500
0(
0+
#18000
0:
06
b100010001000001010101000100000100100000 @
03
b0 7
04
b111 8
b10 ?
1(
1+
#18500
0(
0+
#19000
b110 8
1(
1+
#19500
0(
0+
#20000
b101 8
1(
1+
#20500
0(
0+
#21000
b100 8
1(
1+
#21500
0(
0+
#22000
b11 8
1(
1+
#22500
0(
0+
#23000
b10 8
1(
1+
#23500
0(
0+
#24000
b1 8
1(
1+
#24500
0(
0+
#25000
1:
14
b0 8
1(
1+
#25500
0(
0+
#26000
0:
bx0 )
bx0 >
b1 7
04
b111 8
1(
1+
#26500
0(
0+
#27000
b110 8
1(
1+
#27500
0(
0+
#28000
b101 8
1(
1+
#28500
0(
0+
#29000
b100 8
1(
1+
#29500
0(
0+
#30000
b11 8
1(
1+
#30500
0(
0+
#31000
b10 8
1(
1+
#31500
0(
0+
#32000
b1 8
1(
1+
#32500
0(
0+
#33000
1:
14
b0 8
15
1*
1(
1+
#33500
0(
0+
#34000
0:
1"
bx00 )
bx00 >
b10 7
04
b111 8
1-
1(
1+
#34500
0(
0+
#35000
1&
b110 8
1.
1(
1+
#35500
0(
0+
#36000
1!
1%
b101 8
1/
1(
1+
#36500
0(
0+
#37000
02
b100 8
1=
10
1(
1+
#37500
0(
0+
#38000
1$
b11 8
11
1(
1+
#38500
0(
0+
#39000
b10 8
1(
1+
#39500
0(
0+
#40000
b1 8
1(
1+
#40500
0(
0+
#41000
1:
14
b0 8
05
0*
1(
1+
#41500
0(
0+
#42000
0$
0%
0:
0"
bx100 )
bx100 >
b11 7
04
b111 8
0-
1(
1+
#42500
0(
0+
#43000
0!
0&
b110 8
0.
1(
1+
#43500
0(
0+
#44000
b101 8
0/
1(
1+
#44500
0(
0+
#45000
12
b100 8
0=
00
1(
1+
#45500
0(
0+
#46000
b11 8
01
1(
1+
#46500
0(
0+
#47000
b10 8
1(
1+
#47500
0(
0+
#48000
b1 8
1(
1+
#48500
0(
0+
#49000
1:
14
b0 8
15
1*
1(
1+
#49500
0(
0+
#50000
0:
1"
bx0100 )
bx0100 >
b100 7
04
b111 8
1-
1(
1+
#50500
0(
0+
#51000
1&
b110 8
1.
1(
1+
#51500
0(
0+
#52000
1!
1%
b101 8
1/
1(
1+
#52500
0(
0+
#53000
02
b100 8
1=
10
1(
1+
#53500
0(
0+
#54000
1$
b11 8
11
1(
1+
#54500
0(
0+
#55000
b10 8
1(
1+
#55500
0(
0+
#56000
b1 8
1(
1+
#56500
0(
0+
#57000
1:
14
b0 8
1(
1+
#57500
0(
0+
#58000
0:
bx10100 )
bx10100 >
b101 7
04
b111 8
1(
1+
#58500
0(
0+
#59000
b110 8
1(
1+
#59500
0(
0+
#60000
b101 8
1(
1+
#60500
0(
0+
#61000
b100 8
1(
1+
#61500
0(
0+
#62000
b11 8
1(
1+
#62500
0(
0+
#63000
b10 8
1(
1+
#63500
0(
0+
#64000
b1 8
1(
1+
#64500
0(
0+
#65000
1:
14
b0 8
1(
1+
#65500
0(
0+
#66000
0:
bx110100 )
bx110100 >
b110 7
04
b111 8
1(
1+
#66500
0(
0+
#67000
b110 8
1(
1+
#67500
0(
0+
#68000
b101 8
1(
1+
#68500
0(
0+
#69000
b100 8
1(
1+
#69500
0(
0+
#70000
b11 8
1(
1+
#70500
0(
0+
#71000
b10 8
1(
1+
#71500
0(
0+
#72000
b1 8
1(
1+
#72500
0(
0+
#73000
1:
14
b0 8
1(
1+
#73500
0(
0+
#74000
0:
bx1110100 )
bx1110100 >
13
b111 7
04
b111 8
1(
1+
#74500
0(
0+
#75000
b110 8
1(
1+
#75500
0(
0+
#76000
b101 8
1(
1+
#76500
0(
0+
#77000
b100 8
1(
1+
#77500
0(
0+
#78000
b11 8
1(
1+
#78500
0(
0+
#79000
b10 8
1(
1+
#79500
0(
0+
#80000
b1 8
1(
1+
#80500
0(
0+
#81000
1:
14
b0 8
1(
1+
#81500
0(
0+
#82000
0:
0;
b101001101010100010011110101000000100000 @
b11110100 )
b11110100 >
03
b0 7
04
b111 8
b11 ?
1(
1+
#82500
0(
0+
#83000
b110 8
1(
1+
#83500
0(
0+
#84000
b101 8
1(
1+
#84500
0(
0+
#85000
b100 8
1(
1+
#85500
0(
0+
#86000
b11 8
1(
1+
#86500
0(
0+
#87000
b10 8
1(
1+
#87500
0(
0+
#88000
b1 8
1(
1+
#88500
0(
0+
#89000
1;
1:
14
b0 8
1(
1+
#89500
0(
0+
#90000
0:
0;
b100100101000100010011000100010100100000 @
b1 7
04
b111 8
b0 ?
1(
1+
#90500
0(
0+
#91000
b110 8
1(
1+
#91500
0(
0+
#92000
b101 8
1(
1+
#92500
0(
0+
#93000
b100 8
1(
1+
#93500
0(
0+
#94000
b11 8
1(
1+
#94500
0(
0+
#95000
b10 8
1(
1+
#95500
0(
0+
#96000
b1 8
1(
1+
#96500
0(
0+
#97000
1:
14
b0 8
1(
1+
#97500
0(
0+
#98000
0:
b10 7
04
b111 8
1(
1+
#98500
0(
0+
#99000
0*
b110 8
1(
1+
#99500
0(
0+
#100000
b101 8
05
1(
1+
#100500
0(
0+
#101000
0$
0%
0"
b100 8
0-
1(
1+
#101500
0(
0+
#102000
0!
0&
b11 8
0.
1(
1+
#102500
0(
0+
#103000
b10 8
0/
1(
1+
#103500
0(
0+
#104000
19
12
b1 8
0=
00
1(
1+
#104500
0(
0+
#105000
09
b101001101010100010000010101001001010100 @
04
b10 8
b1 ?
01
1(
1+
#105500
0(
0+
#106000
b1 8
1(
1+
#106500
0(
0+
#107000
16
1:
14
b0 8
15
1*
1(
1+
#107500
0(
0+
#108000
0:
06
b100010001000001010101000100000100100000 @
1"
b0 7
04
b111 8
b10 ?
1-
1(
1+
#108500
0(
0+
#109000
1&
b110 8
1.
1(
1+
#109500
0(
0+
#110000
1!
1%
b101 8
1/
1(
1+
#110500
0(
0+
#111000
02
b100 8
1=
10
1(
1+
#111500
0(
0+
#112000
1$
b11 8
11
1(
1+
#112500
0(
0+
#113000
b10 8
1(
1+
#113500
0(
0+
#114000
b1 8
1(
1+
#114500
0(
0+
#115000
1:
14
b0 8
05
0*
1(
1+
#115500
0(
0+
#116000
0$
0%
0:
0"
b11110101 )
b11110101 >
b1 7
04
b111 8
0-
1(
1+
#116500
0(
0+
#117000
0!
0&
b110 8
0.
1(
1+
#117500
0(
0+
#118000
b101 8
0/
1(
1+
#118500
0(
0+
#119000
12
b100 8
0=
00
1(
1+
#119500
0(
0+
#120000
b11 8
01
1(
1+
#120500
0(
0+
#121000
b10 8
1(
1+
#121500
0(
0+
#122000
b1 8
1(
1+
#122500
0(
0+
#123000
1:
14
b0 8
1(
1+
#123500
0(
0+
#124000
0:
b10 7
04
b111 8
1(
1+
#124500
0(
0+
#125000
b110 8
1(
1+
#125500
0(
0+
#126000
b101 8
1(
1+
#126500
0(
0+
#127000
b100 8
1(
1+
#127500
0(
0+
#128000
b11 8
1(
1+
#128500
0(
0+
#129000
b10 8
1(
1+
#129500
0(
0+
#130000
b1 8
1(
1+
#130500
0(
0+
#131000
1:
14
b0 8
15
1*
1(
1+
#131500
0(
0+
#132000
0:
1"
b11110001 )
b11110001 >
b11 7
04
b111 8
1-
1(
1+
#132500
0(
0+
#133000
1&
b110 8
1.
1(
1+
#133500
0(
0+
#134000
1!
1%
b101 8
1/
1(
1+
#134500
0(
0+
#135000
02
b100 8
1=
10
1(
1+
#135500
0(
0+
#136000
1$
b11 8
11
1(
1+
#136500
0(
0+
#137000
b10 8
1(
1+
#137500
0(
0+
#138000
b1 8
1(
1+
#138500
0(
0+
#139000
1:
14
b0 8
1(
1+
#139500
0(
0+
#140000
0:
b11111001 )
b11111001 >
b100 7
04
b111 8
1(
1+
#140500
0(
0+
#141000
b110 8
1(
1+
#141500
0(
0+
#142000
b101 8
1(
1+
#142500
0(
0+
#143000
b100 8
1(
1+
#143500
0(
0+
#144000
b11 8
1(
1+
#144500
0(
0+
#145000
b10 8
1(
1+
#145500
0(
0+
#146000
b1 8
1(
1+
#146500
0(
0+
#147000
1:
14
b0 8
1(
1+
#147500
0(
0+
#148000
0:
b101 7
04
b111 8
1(
1+
#148500
0(
0+
#149000
b110 8
1(
1+
#149500
0(
0+
#150000
b101 8
1(
1+
#150500
0(
0+
#151000
b100 8
1(
1+
#151500
0(
0+
#152000
b11 8
1(
1+
#152500
0(
0+
#153000
b10 8
1(
1+
#153500
0(
0+
#154000
b1 8
1(
1+
#154500
0(
0+
#155000
1:
14
b0 8
05
0*
1(
1+
#155500
0(
0+
#156000
0$
0%
0:
0"
b110 7
04
b111 8
0-
1(
1+
#156500
0(
0+
#157000
0!
0&
b110 8
0.
1(
1+
#157500
0(
0+
#158000
b101 8
0/
1(
1+
#158500
0(
0+
#159000
12
b100 8
0=
00
1(
1+
#159500
0(
0+
#160000
b11 8
01
1(
1+
#160500
0(
0+
#161000
b10 8
1(
1+
#161500
0(
0+
#162000
b1 8
1(
1+
#162500
0(
0+
#163000
1:
14
b0 8
15
1*
1(
1+
#163500
0(
0+
#164000
0:
1"
b10111001 )
b10111001 >
13
b111 7
04
b111 8
1-
1(
1+
#164500
0(
0+
#165000
1&
b110 8
1.
1(
1+
#165500
0(
0+
#166000
1!
1%
b101 8
1/
1(
1+
#166500
0(
0+
#167000
02
b100 8
1=
10
1(
1+
#167500
0(
0+
#168000
1$
b11 8
11
1(
1+
#168500
0(
0+
#169000
b10 8
1(
1+
#169500
0(
0+
#170000
b1 8
1(
1+
#170500
0(
0+
#171000
1:
14
b0 8
1(
1+
#171500
0(
0+
#172000
0:
0;
b101001101010100010011110101000000100000 @
03
b0 7
04
b111 8
b11 ?
1(
1+
#172500
0(
0+
#173000
b110 8
1(
1+
#173500
0(
0+
#174000
b101 8
1(
1+
#174500
0(
0+
#175000
b100 8
1(
1+
#175500
0(
0+
#176000
b11 8
1(
1+
#176500
0(
0+
#177000
b10 8
1(
1+
#177500
0(
0+
#178000
b1 8
1(
1+
#178500
0(
0+
#179000
1;
1:
14
b0 8
1(
1+
#179500
0(
0+
#180000
0:
0;
b100100101000100010011000100010100100000 @
b1 7
04
b111 8
b0 ?
1(
1+
#180500
0(
0+
#181000
b110 8
1(
1+
#181500
0(
0+
#182000
b101 8
1(
1+
#182500
0(
0+
#183000
b100 8
1(
1+
#183500
0(
0+
#184000
b11 8
1(
1+
#184500
0(
0+
#185000
b10 8
1(
1+
#185500
0(
0+
#186000
b1 8
1(
1+
#186500
0(
0+
#187000
1:
14
b0 8
1(
1+
#187500
0(
0+
#188000
0:
b10 7
04
b111 8
1(
1+
#188500
0(
0+
#189000
0*
b110 8
1(
1+
#189500
0(
0+
#190000
b101 8
05
1(
1+
#190500
0(
0+
#191000
0$
0%
0"
b100 8
0-
1(
1+
#191500
0(
0+
#192000
0!
0&
b11 8
0.
1(
1+
#192500
0(
0+
#193000
b10 8
0/
1(
1+
#193500
0(
0+
#194000
19
12
b1 8
0=
00
1(
1+
#194500
0(
0+
#195000
09
b101001101010100010000010101001001010100 @
04
b10 8
b1 ?
01
1(
1+
#195500
0(
0+
#196000
b1 8
1(
1+
#196500
0(
0+
#197000
16
1:
14
b0 8
1(
1+
#197500
0(
0+
#198000
0:
06
b100010001000001010101000100000100100000 @
b0 7
04
b111 8
b10 ?
1(
1+
#198500
0(
0+
#199000
b110 8
1(
1+
#199500
0(
0+
#200000
b101 8
1(
1+
#200500
0(
0+
#201000
b100 8
1(
1+
#201500
0(
0+
#202000
b11 8
1(
1+
#202500
0(
0+
#203000
b10 8
1(
1+
#203500
0(
0+
#204000
b1 8
1(
1+
#204500
0(
0+
#205000
1:
14
b0 8
15
1*
1(
1+
#205500
0(
0+
#206000
0:
1"
b10111000 )
b10111000 >
b1 7
04
b111 8
1-
1(
1+
#206500
0(
0+
#207000
1&
b110 8
1.
1(
1+
#207500
0(
0+
#208000
1!
1%
b101 8
1/
1(
1+
#208500
0(
0+
#209000
02
b100 8
1=
10
1(
1+
#209500
0(
0+
#210000
1$
b11 8
11
1(
1+
#210500
0(
0+
#211000
b10 8
1(
1+
#211500
0(
0+
#212000
b1 8
1(
1+
#212500
0(
0+
#213000
1:
14
b0 8
1(
1+
#213500
0(
0+
#214000
0:
b10111010 )
b10111010 >
b10 7
04
b111 8
1(
1+
#214500
0(
0+
#215000
b110 8
1(
1+
#215500
0(
0+
#216000
b101 8
1(
1+
#216500
0(
0+
#217000
b100 8
1(
1+
#217500
0(
0+
#218000
b11 8
1(
1+
#218500
0(
0+
#219000
b10 8
1(
1+
#219500
0(
0+
#220000
b1 8
1(
1+
#220500
0(
0+
#221000
1:
14
b0 8
05
0*
1(
1+
#221500
0(
0+
#222000
0$
0%
0:
0"
b10111110 )
b10111110 >
b11 7
04
b111 8
0-
1(
1+
#222500
0(
0+
#223000
0!
0&
b110 8
0.
1(
1+
#223500
0(
0+
#224000
b101 8
0/
1(
1+
#224500
0(
0+
#225000
12
b100 8
0=
00
1(
1+
#225500
0(
0+
#226000
b11 8
01
1(
1+
#226500
0(
0+
#227000
b10 8
1(
1+
#227500
0(
0+
#228000
b1 8
1(
1+
#228500
0(
0+
#229000
1:
14
b0 8
15
1*
1(
1+
#229500
0(
0+
#230000
0:
1"
b10110110 )
b10110110 >
b100 7
04
b111 8
1-
1(
1+
#230500
0(
0+
#231000
1&
b110 8
1.
1(
1+
#231500
0(
0+
#232000
1!
1%
b101 8
1/
1(
1+
#232500
0(
0+
#233000
02
b100 8
1=
10
1(
1+
#233500
0(
0+
#234000
1$
b11 8
11
1(
1+
#234500
0(
0+
#235000
b10 8
1(
1+
#235500
0(
0+
#236000
b1 8
1(
1+
#236500
0(
0+
#237000
1:
14
b0 8
1(
1+
#237500
0(
0+
#238000
0:
b101 7
04
b111 8
1(
1+
#238500
0(
0+
#239000
b110 8
1(
1+
#239500
0(
0+
#240000
b101 8
1(
1+
#240500
0(
0+
#241000
b100 8
1(
1+
#241500
0(
0+
#242000
b11 8
1(
1+
#242500
0(
0+
#243000
b10 8
1(
1+
#243500
0(
0+
#244000
b1 8
1(
1+
#244500
0(
0+
#245000
1:
14
b0 8
05
0*
1(
1+
#245500
0(
0+
#246000
0$
0%
0:
0"
b110 7
04
b111 8
0-
1(
1+
#246500
0(
0+
#247000
0!
0&
b110 8
0.
1(
1+
#247500
0(
0+
#248000
b101 8
0/
1(
1+
#248500
0(
0+
#249000
12
b100 8
0=
00
1(
1+
#249500
0(
0+
#250000
b11 8
01
1(
1+
#250500
0(
0+
#251000
b10 8
1(
1+
#251500
0(
0+
#252000
b1 8
1(
1+
#252500
0(
0+
#253000
1:
14
b0 8
15
1*
1(
1+
#253500
0(
0+
#254000
0:
1"
13
b111 7
04
b111 8
1-
1(
1+
#254500
0(
0+
#255000
1&
b110 8
1.
1(
1+
#255500
0(
0+
#256000
1!
1%
b101 8
1/
1(
1+
#256500
0(
0+
#257000
02
b100 8
1=
10
1(
1+
#257500
0(
0+
#258000
1$
b11 8
11
1(
1+
#258500
0(
0+
#259000
b10 8
1(
1+
#259500
0(
0+
#260000
b1 8
1(
1+
#260500
0(
0+
#261000
1:
14
b0 8
1(
1+
#261500
0(
0+
#262000
0:
0;
b101001101010100010011110101000000100000 @
03
b0 7
04
b111 8
b11 ?
1(
1+
#262500
0(
0+
#263000
b110 8
1(
1+
#263500
0(
0+
#264000
b101 8
1(
1+
#264500
0(
0+
#265000
b100 8
1(
1+
#265500
0(
0+
#266000
b11 8
1(
1+
#266500
0(
0+
#267000
b10 8
1(
1+
#267500
0(
0+
#268000
b1 8
1(
1+
#268500
0(
0+
#269000
1;
1:
14
b0 8
1(
1+
#269500
0(
0+
#270000
0:
0;
b100100101000100010011000100010100100000 @
b1 7
04
b111 8
b0 ?
1(
1+
#270500
0(
0+
#271000
b110 8
1(
1+
#271500
0(
0+
#272000
b101 8
1(
1+
#272500
0(
0+
#273000
b100 8
1(
1+
#273500
0(
0+
#274000
b11 8
1(
1+
#274500
0(
0+
#275000
b10 8
1(
1+
#275500
0(
0+
#276000
b1 8
1(
1+
#276500
0(
0+
#277000
1:
14
b0 8
1(
1+
#277500
0(
0+
#278000
0:
b10 7
04
b111 8
1(
1+
#278500
0(
0+
#279000
0*
b110 8
1(
1+
#279500
0(
0+
#280000
b101 8
05
1(
1+
#280500
0(
0+
#281000
0$
0%
0"
b100 8
0-
1(
1+
#281500
0(
0+
#282000
0!
0&
b11 8
0.
1(
1+
#282500
0(
0+
#283000
b10 8
0/
1(
1+
#283500
0(
0+
#284000
19
12
b1 8
0=
00
1(
1+
#284500
0(
0+
#285000
09
b101001101010100010000010101001001010100 @
04
b10 8
b1 ?
01
1(
1+
#285500
0(
0+
#286000
b1 8
1(
1+
#286500
0(
0+
#287000
16
1:
14
b0 8
1(
1+
#287500
0(
0+
#288000
0:
06
b100010001000001010101000100000100100000 @
b0 7
04
b111 8
b10 ?
1(
1+
#288500
0(
0+
#289000
b110 8
1(
1+
#289500
0(
0+
#290000
b101 8
1(
1+
#290500
0(
0+
#291000
b100 8
1(
1+
#291500
0(
0+
#292000
b11 8
1(
1+
#292500
0(
0+
#293000
b10 8
1(
1+
#293500
0(
0+
#294000
b1 8
1(
1+
#294500
0(
0+
#295000
1:
14
b0 8
15
1*
1(
1+
#295500
0(
0+
#296000
0:
1"
b1 7
04
b111 8
1-
1(
1+
#296500
0(
0+
#297000
1&
b110 8
1.
1(
1+
#297500
0(
0+
#298000
1!
1%
b101 8
1/
1(
1+
#298500
0(
0+
#299000
02
b100 8
1=
10
1(
1+
#299500
0(
0+
#300000
1$
b11 8
11
1(
1+
#300500
0(
0+
#301000
b10 8
1(
1+
#301500
0(
0+
#302000
b1 8
1(
1+
#302500
0(
0+
#303000
1:
14
b0 8
1(
1+
#303500
0(
0+
#304000
0:
b10 7
04
b111 8
1(
1+
#304500
0(
0+
#305000
b110 8
1(
1+
#305500
0(
0+
#306000
b101 8
1(
1+
#306500
0(
0+
#307000
b100 8
1(
1+
#307500
0(
0+
#308000
b11 8
1(
1+
#308500
0(
0+
#309000
b10 8
1(
1+
#309500
0(
0+
#310000
b1 8
1(
1+
#310500
0(
0+
#311000
1:
14
b0 8
05
0*
1(
1+
#311500
0(
0+
#312000
0$
0%
0:
0"
b11 7
04
b111 8
0-
1(
1+
#312500
0(
0+
#313000
0!
0&
b110 8
0.
1(
1+
#313500
0(
0+
#314000
b101 8
0/
1(
1+
#314500
0(
0+
#315000
12
b100 8
0=
00
1(
1+
#315500
0(
0+
#316000
b11 8
01
1(
1+
#316500
0(
0+
#317000
b10 8
1(
1+
#317500
0(
0+
#318000
b1 8
1(
1+
#318500
0(
0+
#319000
1:
14
b0 8
1(
1+
#319500
0(
0+
#320000
0:
b100 7
04
b111 8
1(
1+
#320500
0(
0+
#321000
b110 8
1(
1+
#321500
0(
0+
#322000
b101 8
1(
1+
#322500
0(
0+
#323000
b100 8
1(
1+
#323500
0(
0+
#324000
b11 8
1(
1+
#324500
0(
0+
#325000
b10 8
1(
1+
#325500
0(
0+
#326000
b1 8
1(
1+
#326500
0(
0+
#327000
1:
14
b0 8
15
1*
1(
1+
#327500
0(
0+
#328000
0:
1"
b10100110 )
b10100110 >
b101 7
04
b111 8
1-
1(
1+
#328500
0(
0+
#329000
1&
b110 8
1.
1(
1+
#329500
0(
0+
#330000
1!
1%
b101 8
1/
1(
1+
#330500
0(
0+
#331000
02
b100 8
1=
10
1(
1+
#331500
0(
0+
#332000
1$
b11 8
11
1(
1+
#332500
0(
0+
#333000
b10 8
1(
1+
#333500
0(
0+
#334000
b1 8
1(
1+
#334500
0(
0+
