streamTest/basicStream/basicStream.v
// Generator : SpinalHDL v1.7.0a    git head : 150a9b9067020722818dfb17df4a23ac712a7af8
// Component : basicStream
// Git hash  : 3a903e741cbbe310a98c75dc1ebbd289cb1c87a4

`timescale 1ns/1ps

module basicStream (
  input               io_s_in_valid,
  output              io_s_in_ready,
  input      [31:0]   io_s_in_payload,
  output              io_m_out_valid,
  input               io_m_out_ready,
  output     [31:0]   io_m_out_payload
);


  assign io_m_out_valid = io_s_in_valid;
  assign io_s_in_ready = io_m_out_ready;
  assign io_m_out_payload = io_s_in_payload;
  
  initial begin
    $dumpfile("basicStream_test.vcd");
    $dumpvars(0, basicStream);
  end

endmodule

streamTest/basicStream/basicStream_test.vcd
$date
	Thu May 26 08:54:16 2022
$end
$version
	Icarus Verilog
$end
$timescale
	1ps
$end
$scope module basicStream $end
$var wire 32 ! io_m_out_payload [31:0] $end
$var wire 1 " io_m_out_ready $end
$var wire 1 # io_m_out_valid $end
$var wire 32 $ io_s_in_payload [31:0] $end
$var wire 1 % io_s_in_ready $end
$var wire 1 & io_s_in_valid $end
$upscope $end
$enddefinitions $end
#0
$dumpvars
0&
0%
b0 $
0#
0"
b0 !
$end
#1000
1#
1&
#1500
1%
1"
#2000
0#
0&
0%
0"
#3000
1%
1"
#4000
1#
1&
b10000000100111011010110110010100 !
b10000000100111011010110110010100 $
#4500
0#
0&
b0 !
b0 $
0%
0"
#5000
1%
1"
#5500
1#
1&
b1101100101100110110111100110000 !
b1101100101100110110111100110000 $
#6000
0#
0&
b0 !
b0 $
0%
0"
#6500
1%
1"
#7000
1#
1&
b10101001100110111111111010001011 !
b10101001100110111111111010001011 $
#7500
0#
0&
b0 !
b0 $
0%
0"
#8500
1#
1&
b1110110001011011100100011111010 !
b1110110001011011100100011111010 $
#9500
1%
1"
#10000
0#
0&
b0 !
b0 $
0%
0"
#10500
1#
1&
b11101100101010111101011101111000 !
b11101100101010111101011101111000 $
1%
1"
#11000
0#
0&
b0 !
b0 $
0%
0"
#11500
1%
1"
#13000
1#
1&
b10111000110111011011011010011101 !
b10111000110111011011011010011101 $
#13500
0#
0&
b0 !
b0 $
0%
0"
#14000
1#
1&
b11111110001111110101100100010 !
b11111110001111110101100100010 $
1%
1"
#14500
0#
0&
b0 !
b0 $
0%
0"
#15000
1%
1"
#16000
1#
1&
b110100011001010000011000111011 !
b110100011001010000011000111011 $
#16500
0#
0&
b0 !
b0 $
0%
0"
#17500
1%
1"
#18000
1#
1&
b10100000101000111000100010110 !
b10100000101000111000100010110 $
#18500
0#
0&
b0 !
b0 $
0%
0"
#19000
1#
1&
b1010101110101001011101011001100 !
b1010101110101001011101011001100 $
#19500
1%
1"
#20000
0#
0&
b0 !
b0 $
0%
0"
#21000
1#
1&
b11101011111100011010110101111 !
b11101011111100011010110101111 $
1%
1"
#21500
0#
0&
b0 !
b0 $
0%
0"
#22000
1#
1&
b1000011111110110100111011011 !
b1000011111110110100111011011 $
1%
1"
#22500
0#
0&
b0 !
b0 $
0%
0"
#23000
1#
1&
b1000110011111100011110010010101 !
b1000110011111100011110010010101 $
1%
1"
#23500
0#
0&
b0 !
b0 $
0%
0"
#24500
1%
1"
#25000
1#
1&
b101001100000101101111111101001 !
b101001100000101101111111101001 $
#25500
0#
0&
b0 !
b0 $
0%
0"
#26000
1#
1&
b1000101111001111010110010010001 !
b1000101111001111010110010010001 $
1%
1"
#26500
0#
0&
b0 !
b0 $
0%
0"
#27500
1%
1"
#28500
1#
1&
b1000110011111001000101100101 !
b1000110011111001000101100101 $
#29000
0#
0&
b0 !
b0 $
0%
0"
#29500
1#
1&
b10000100011010011011010000110011 !
b10000100011010011011010000110011 $
1%
1"
#30000
0#
0&
b0 !
b0 $
0%
0"
#30500
1%
1"
#32000
1#
1&
b11010010101110011010111111000 !
b11010010101110011010111111000 $
#32500
0#
0&
b0 !
b0 $
0%
0"
#34000
1#
1&
b1111010011011010101101100000110 !
b1111010011011010101101100000110 $
#37500
1%
1"
#38000
0#
0&
b0 !
b0 $
0%
0"
#38500
1#
1&
b111110111001010111100000111110 !
b111110111001010111100000111110 $
#39500
1%
1"
#40000
0#
0&
b0 !
b0 $
0%
0"
#40500
1#
1&
b11011011011101101000001010101110 !
b11011011011101101000001010101110 $
1%
1"
#41000
0#
0&
b0 !
b0 $
0%
0"
#41500
1#
1&
b10001000000111011111100000001101 !
b10001000000111011111100000001101 $
#42500
1%
1"
#43000
0#
0&
b0 !
b0 $
0%
0"
#44000
1#
1&
b11010001010110001111101111010011 !
b11010001010110001111101111010011 $
#46000
1%
1"
#46500
0#
0&
b0 !
b0 $
0%
0"
#47000
1#
1&
b11111000111100010011001100000111 !
b11111000111100010011001100000111 $
#47500
1%
1"
#48000
0#
0&
b0 !
b0 $
0%
0"
#48500
1#
1&
b10111101010000100001010110010110 !
b10111101010000100001010110010110 $
1%
1"
#49000
0#
0&
b0 !
b0 $
0%
0"
#50000
1#
1&
b11011000011111100110110001111011 !
b11011000011111100110110001111011 $
1%
1"
#50500
0#
0&
b0 !
b0 $
0%
0"
#51000
1#
1&
b10111010000011101110111011011111 !
b10111010000011101110111011011111 $
1%
1"
#51500
0#
0&
b0 !
b0 $
0%
0"
#52000
1#
1&
b11110101110100111001110010001111 !
b11110101110100111001110010001111 $
#52500
1%
1"
#53000
0#
0&
b0 !
b0 $
0%
0"
#53500
1#
1&
b11101100111011000000101101011111 !
b11101100111011000000101101011111 $
#54000
1%
1"
#54500
0#
0&
b0 !
b0 $
0%
0"
#55000
1#
1&
b110000101100110000001100010100 !
b110000101100110000001100010100 $
#57000
1%
1"
#57500
0#
0&
b0 !
b0 $
0%
0"
#58000
1%
1"
#60000
1#
1&
b1000111010111100000011111110101 !
b1000111010111100000011111110101 $
#60500
0#
0&
b0 !
b0 $
0%
0"
#61000
1#
1&
b111111100110100100011010111 !
b111111100110100100011010111 $
1%
1"
#61500
0#
0&
b0 !
b0 $
0%
0"
#62000
1#
1&
b10110010010000101010111111111010 !
b10110010010000101010111111111010 $
1%
1"
#62500
0#
0&
b0 !
b0 $
0%
0"
#63000
1#
1&
b10010101010100101100011000001100 !
b10010101010100101100011000001100 $
#63500
1%
1"
#64000
0#
0&
b0 !
b0 $
0%
0"
#64500
1#
1&
b101110001010110100010001011001 !
b101110001010110100010001011001 $
1%
1"
#65000
0#
0&
b0 !
b0 $
0%
0"
#65500
1#
1&
b10101001011111010001101001101111 !
b10101001011111010001101001101111 $
1%
1"
#66000
0#
0&
b0 !
b0 $
0%
0"
#67500
1#
1&
b101001111110100100001110011 !
b101001111110100100001110011 $
1%
1"
#68000
0#
0&
b0 !
b0 $
0%
0"
#69000
1%
1"
#70000
1#
1&
b10000001100001100110110000001 !
b10000001100001100110110000001 $
#70500
0#
0&
b0 !
b0 $
0%
0"
#71000
1%
1"
#72000
1#
1&
b11100111110000101000101010010000 !
b11100111110000101000101010010000 $
#72500
0#
0&
b0 !
b0 $
0%
0"
#73000
1%
1"
#75000
1#
1&
b11011100000100011111110000111000 !
b11011100000100011111110000111000 $
#75500
0#
0&
b0 !
b0 $
0%
0"
#76000
1#
1&
b110101010000011110011010010010 !
b110101010000011110011010010010 $
1%
1"
#76500
0#
0&
b0 !
b0 $
0%
0"
#77000
1#
1&
b1110001111001001110111010101001 !
b1110001111001001110111010101001 $
#78500
1%
1"
#79000
0#
0&
b0 !
b0 $
0%
0"
#79500
1#
1&
b11110100110011010110010011110000 !
b11110100110011010110010011110000 $
#82000
1%
1"
#82500
0#
0&
b0 !
b0 $
0%
0"
#83000
1%
1"
#84000
1#
1&
b110110001010111010010011001100 !
b110110001010111010010011001100 $
#84500
0#
0&
b0 !
b0 $
0%
0"
#85000
1#
1&
b11000011111010100101000110011000 !
b11000011111010100101000110011000 $
1%
1"
#85500
0#
0&
b0 !
b0 $
0%
0"
#86000
1#
1&
b11100001110001111100001010111111 !
b11100001110001111100001010111111 $
1%
1"
#86500
0#
0&
b0 !
b0 $
0%
0"
#87000
1%
1"
#88000
1#
1&
b10010011001011111001000001000110 !
b10010011001011111001000001000110 $
#88500
0#
0&
b0 !
b0 $
0%
0"
#89000
1#
1&
b1110000111001110101101001110110 !
b1110000111001110101101001110110 $
#90000
1%
1"
#90500
0#
0&
b0 !
b0 $
0%
0"
#91000
1%
1"
#93500
1#
1&
b10011010000110111110001111001011 !
b10011010000110111110001111001011 $
#94000
0#
0&
b0 !
b0 $
0%
0"
#95000
1#
1&
b1011111011011110100111010111101 !
b1011111011011110100111010111101 $
1%
1"
#95500
0#
0&
b0 !
b0 $
0%
0"
#96000
1#
1&
b1101011101011001001000010010 !
b1101011101011001001000010010 $
#98000
1%
1"
#98500
0#
0&
b0 !
b0 $
0%
0"
#99000
1%
1"
#99500
1#
1&
b1100101101101011001001011001 !
b1100101101101011001001011001 $
#100000
0#
0&
b0 !
b0 $
0%
0"
#101000
1#
1&
b11100000111010100010111101001001 !
b11100000111010100010111101001001 $
1%
1"
#101500
0#
0&
b0 !
b0 $
0%
0"
#102500
1%
1"
#103500
1#
1&
b11101110101111001010110011011100 !
b11101110101111001010110011011100 $
#104000
0#
0&
b0 !
b0 $
0%
0"
#104500
1%
1"
#105000
1#
1&
b10101010011111011011011011110000 !
b10101010011111011011011011110000 $
#105500
0#
0&
b0 !
b0 $
0%
0"
#106000
1#
1&
b1110010011000111101010100111110 !
b1110010011000111101010100111110 $
#108500
1%
1"
#109000
0#
0&
b0 !
b0 $
0%
0"
#109500
1%
1"
#112500
1#
1&
b10001100111101010001001101110001 !
b10001100111101010001001101110001 $
#113000
0#
0&
b0 !
b0 $
0%
0"
#114500
1#
1&
b11111010111010000110101001100 !
b11111010111010000110101001100 $
1%
1"
#115000
0#
0&
b0 !
b0 $
0%
0"
#115500
1#
1&
b11011110111110111001001101101110 !
b11011110111110111001001101101110 $
#116000
1%
1"
#116500
0#
0&
b0 !
b0 $
0%
0"
#117500
1%
1"
#119000
1#
1&
b1000101000110110110000000000111 !
b1000101000110110110000000000111 $
#119500
0#
0&
b0 !
b0 $
0%
0"
#120500
1#
1&
b11000101010000101101101101100100 !
b11000101010000101101101101100100 $
#121000
1%
1"
#121500
0#
0&
b0 !
b0 $
0%
0"
#122500
1#
1&
b11110010000001111111100000110010 !
b11110010000001111111100000110010 $
1%
1"
#123000
0#
0&
b0 !
b0 $
0%
0"
#124000
1%
1"
#124500
1#
1&
b1011100001101011011010011010011 !
b1011100001101011011010011010011 $
#125000
0#
0&
b0 !
b0 $
0%
0"
#125500
1%
1"
#126000
1#
1&
b11000010111111110000001001101101 !
b11000010111111110000001001101101 $
#126500
0#
0&
b0 !
b0 $
0%
0"
#127000
1#
1&
b10000110000000000101000111111100 !
b10000110000000000101000111111100 $
#127500
1%
1"
#128000
0#
0&
b0 !
b0 $
0%
0"
#128500
1#
1&
b1010000011011011110011001110 !
b1010000011011011110011001110 $
1%
1"
#129000
0#
0&
b0 !
b0 $
0%
0"
#129500
1%
1"
#130000
1#
1&
b11110010110010000001010000001000 !
b11110010110010000001010000001000 $
#130500
0#
0&
b0 !
b0 $
0%
0"
#131000
1#
1&
b10110100011000101101001101100000 !
b10110100011000101101001101100000 $
1%
1"
#131500
0#
0&
b0 !
b0 $
0%
0"
#132000
1%
1"
#133500
1#
1&
b11011100000110010111101010100111 !
b11011100000110010111101010100111 $
#134000
0#
0&
b0 !
b0 $
0%
0"
#135000
1#
1&
b11010011111101100100100001101110 !
b11010011111101100100100001101110 $
1%
1"
#135500
0#
0&
b0 !
b0 $
0%
0"
#136000
1#
1&
b11001110101010010101101000010011 !
b11001110101010010101101000010011 $
1%
1"
#136500
0#
0&
b0 !
b0 $
0%
0"
#137500
1%
1"
#138000
1#
1&
b101010010001011111110101001110 !
b101010010001011111110101001110 $
#138500
0#
0&
b0 !
b0 $
0%
0"
#139000
1#
1&
b10010111011010000001110010100 !
b10010111011010000001110010100 $
#140000
1%
1"
#140500
0#
0&
b0 !
b0 $
0%
0"
#141000
1#
1&
b10111111101100101001110010111100 !
b10111111101100101001110010111100 $
1%
1"
#141500
0#
0&
b0 !
b0 $
0%
0"
#142000
1#
1&
b11001000100000011101111101001000 !
b11001000100000011101111101001000 $
#143500
1%
1"
#144000
0#
0&
b0 !
b0 $
0%
0"
#145000
1%
1"
#147500
1#
1&
b1100001011111110011100101101110 !
b1100001011111110011100101101110 $
#148000
0#
0&
b0 !
b0 $
0%
0"
#148500
1#
1&
b111000001000000111001011110010 !
b111000001000000111001011110010 $
#149000
1%
1"
#149500
0#
0&
b0 !
b0 $
0%
0"
#150000
1%
1"
#151000
1#
1&
b10110001011001001011000000110100 !
b10110001011001001011000000110100 $
#151500
0#
0&
b0 !
b0 $
0%
0"
#152500
1#
1&
b1001010100000100101110010101 !
b1001010100000100101110010101 $
1%
1"
#153000
0#
0&
b0 !
b0 $
0%
0"
#153500
1#
1&
b10100100100010011010110000010110 !
b10100100100010011010110000010110 $
#154000
1%
1"
#154500
0#
0&
b0 !
b0 $
0%
0"
#155000
1#
1&
b100010110011101001001010010101 !
b100010110011101001001010010101 $
#157000
1%
1"
#157500
0#
0&
b0 !
b0 $
0%
0"
#158500
1#
1&
b10000111100001100011100110111101 !
b10000111100001100011100110111101 $
#159000
1%
1"
#159500
0#
0&
b0 !
b0 $
0%
0"
#160000
1%
1"
#160500
1#
1&
b101010001110101110011111101010 !
b101010001110101110011111101010 $
#161000
0#
0&
b0 !
b0 $
0%
0"
#161500
1#
1&
b1100010101110111011111000110000 !
b1100010101110111011111000110000 $
1%
1"
#162000
0#
0&
b0 !
b0 $
0%
0"
#162500
1#
1&
b100100100001000111001111101100 !
b100100100001000111001111101100 $
#163000
1%
1"
#163500
0#
0&
b0 !
b0 $
0%
0"
#164000
1#
1&
b10110001010100001110011101101110 !
b10110001010100001110011101101110 $
1%
1"
#164500
0#
0&
b0 !
b0 $
0%
0"
#165000
1#
1&
b1110100011100011010000001100110 !
b1110100011100011010000001100110 $
1%
1"
#165500
0#
0&
b0 !
b0 $
0%
0"
#166000
1#
1&
b1110101010010100000100111110011 !
b1110101010010100000100111110011 $
1%
1"
#166500
0#
0&
b0 !
b0 $
0%
0"
#167000
1#
1&
b1111111000000010011110111010101 !
b1111111000000010011110111010101 $
#169500
1%
1"
#170000
0#
0&
b0 !
b0 $
0%
0"
#171000
1#
1&
b11111000010100001100010010110011 !
b11111000010100001100010010110011 $
#172000
1%
1"
#172500
0#
0&
b0 !
b0 $
0%
0"
#173000
1#
1&
b11100110010000101011001010010101 !
b11100110010000101011001010010101 $
#173500
1%
1"
#174000
0#
0&
b0 !
b0 $
0%
0"
#175000
1%
1"
#178000
1#
1&
b1010110010110000110100101001011 !
b1010110010110000110100101001011 $
#178500
0#
0&
b0 !
b0 $
0%
0"
#179500
1%
1"
#180500
1#
1&
b11000011101111111010000011100001 !
b11000011101111111010000011100001 $
#181000
0#
0&
b0 !
b0 $
0%
0"
#181500
1#
1&
b11000110000010110110010100011101 !
b11000110000010110110010100011101 $
#182500
1%
1"
#183000
0#
0&
b0 !
b0 $
0%
0"
#184000
1%
1"
#187000
1#
1&
b11010000010100000101011110011111 !
b11010000010100000101011110011111 $
#187500
0#
0&
b0 !
b0 $
0%
0"
#188000
1#
1&
b1111000110111111110110010011 !
b1111000110111111110110010011 $
#188500
1%
1"
#189000
0#
0&
b0 !
b0 $
0%
0"
#189500
1%
1"
#190000
1#
1&
b111111110000100001000010101110 !
b111111110000100001000010101110 $
#190500
0#
0&
b0 !
b0 $
0%
0"
#191000
1#
1&
b10101111000110011000110111101100 !
b10101111000110011000110111101100 $
#191500
1%
1"
#192000
0#
0&
b0 !
b0 $
0%
0"
#192500
1#
1&
b11000000000111101001001101100000 !
b11000000000111101001001101100000 $
#193500
1%
1"
#194000
0#
0&
b0 !
b0 $
0%
0"
#194500
1%
1"
#196000
1#
1&
b1010110111111110110110001100011 !
b1010110111111110110110001100011 $
#196500
0#
0&
b0 !
b0 $
0%
0"
#197000
1%
1"
#198000
1#
1&
b11101101011001001110011011111010 !
b11101101011001001110011011111010 $
#198500
0#
0&
b0 !
b0 $
0%
0"
#199000
1#
1&
b11111010001101111100101111101101 !
b11111010001101111100101111101101 $
1%
1"
#199500
0#
0&
b0 !
b0 $
0%
0"
#200000
1%
1"
#204000
1#
1&
b1001010000001101110110000101010 !
b1001010000001101110110000101010 $
#204500
0#
0&
b0 !
b0 $
0%
0"
#205000
1#
1&
b101111110001000001111110001010 !
b101111110001000001111110001010 $
1%
1"
#205500
0#
0&
b0 !
b0 $
0%
0"
#206000
1#
1&
b10111110001010000010111111101111 !
b10111110001010000010111111101111 $
#206500
1%
1"
#207000
0#
0&
b0 !
b0 $
0%
0"
#207500
1#
1&
b110111011100111011100100001010 !
b110111011100111011100100001010 $
1%
1"
#208000
0#
0&
b0 !
b0 $
0%
0"
#209000
1#
1&
b10110100010111100101100010001111 !
b10110100010111100101100010001111 $
#209500
1%
1"
#210000
0#
0&
b0 !
b0 $
0%
0"
#210500
1#
1&
b1101001010011111111101100011 !
b1101001010011111111101100011 $
1%
1"
#211000
0#
0&
b0 !
b0 $
0%
0"
#212000
1#
1&
b100010100101110101100101000000 !
b100010100101110101100101000000 $
#212500
1%
1"
#213000
0#
0&
b0 !
b0 $
0%
0"
#214000
1#
1&
b10101111001000011011110001110100 !
b10101111001000011011110001110100 $
1%
1"
#214500
0#
0&
b0 !
b0 $
0%
0"
#215500
1#
1&
b11110111101001101010110010010011 !
b11110111101001101010110010010011 $
#216000
1%
1"
#216500
0#
0&
b0 !
b0 $
0%
0"
#217000
1#
1&
b100011111010110010101100111011 !
b100011111010110010101100111011 $
#218000
1%
1"
#218500
0#
0&
b0 !
b0 $
0%
0"
#219000
1#
1&
b1010010111011001011010111100000 !
b1010010111011001011010111100000 $
1%
1"
#219500
0#
0&
b0 !
b0 $
0%
0"
#220500
1#
1&
b1100100011101101001111000010101 !
b1100100011101101001111000010101 $
#224000
1%
1"
#224500
0#
0&
b0 !
b0 $
0%
0"
#225000
1#
1&
b1000111011001100001010001110111 !
b1000111011001100001010001110111 $
1%
1"
#225500
0#
0&
b0 !
b0 $
0%
0"
#226000
1%
1"
#228000
1#
1&
b10111000110100010011110111101001 !
b10111000110100010011110111101001 $
#228500
0#
0&
b0 !
b0 $
0%
0"
#229000
1#
1&
b10011100001101101101001101000010 !
b10011100001101101101001101000010 $
#229500
1%
1"
#230000
0#
0&
b0 !
b0 $
0%
0"
#230500
1#
1&
b1101000010100111100010100110101 !
b1101000010100111100010100110101 $
#231500
1%
1"
#232000
0#
0&
b0 !
b0 $
0%
0"
#232500
1#
1&
b100011010001001010100110111101 !
b100011010001001010100110111101 $
1%
1"
#233000
0#
0&
b0 !
b0 $
0%
0"
#233500
1%
1"
#235000
1#
1&
b1100110110011010101001111110010 !
b1100110110011010101001111110010 $
#235500
0#
0&
b0 !
b0 $
0%
0"
#236000
1#
1&
b11110101010000001001010011010110 !
b11110101010000001001010011010110 $
1%
1"
#236500
0#
0&
b0 !
b0 $
0%
0"
#239000
1%
1"
#239500
1#
1&
b10010111011000110010111001111000 !
b10010111011000110010111001111000 $
#240000
0#
0&
b0 !
b0 $
0%
0"
#240500
1#
1&
b11011011100000010100101111111011 !
b11011011100000010100101111111011 $
1%
1"
#241000
0#
0&
b0 !
b0 $
0%
0"
#241500
1#
1&
b10111011101000110011101110110100 !
b10111011101000110011101110110100 $
#242000
1%
1"
#242500
0#
0&
b0 !
b0 $
0%
0"
#243000
1#
1&
b11001001011010101100111010100001 !
b11001001011010101100111010100001 $
#243500
1%
1"
#244000
0#
0&
b0 !
b0 $
0%
0"
#244500
1#
1&
b101000001010110110110001011111 !
b101000001010110110110001011111 $
#245500
1%
1"
#246000
0#
0&
b0 !
b0 $
0%
0"
#246500
1#
1&
b1111100000000011001111111011011 !
b1111100000000011001111111011011 $
#247500
1%
1"
#248000
0#
0&
b0 !
b0 $
0%
0"
#248500
1%
1"
#249000
1#
1&
b101100011101011000101001100101 !
b101100011101011000101001100101 $
#249500
0#
0&
b0 !
b0 $
0%
0"
#250500
1%
1"
#251000
1#
1&
b10101011100110001010001010101100 !
b10101011100110001010001010101100 $
#251500
0#
0&
b0 !
b0 $
0%
0"
#252000
1#
1&
b11000101001100110110011000101 !
b11000101001100110110011000101 $
#252500
1%
1"
#253000
0#
0&
b0 !
b0 $
0%
0"
#253500
1%
1"
#255500
1#
1&
b101111010110111110000011000100 !
b101111010110111110000011000100 $
#256000
0#
0&
b0 !
b0 $
0%
0"
#256500
1%
1"
#257500
1#
1&
b111011100110010001001100001101 !
b111011100110010001001100001101 $
#258000
0#
0&
b0 !
b0 $
0%
0"
#258500
1%
1"
#259000
1#
1&
b11010001011110001000110000110000 !
b11010001011110001000110000110000 $
#259500
0#
0&
b0 !
b0 $
0%
0"
#260000
1%
1"
#261500
1#
1&
b10111110100010010110011111100011 !
b10111110100010010110011111100011 $
#262000
0#
0&
b0 !
b0 $
0%
0"
#262500
1%
1"
#263000
1#
1&
b1011111100101011010110010011101 !
b1011111100101011010110010011101 $
#263500
0#
0&
b0 !
b0 $
0%
0"
#264000
1%
1"
#264500
1#
1&
b1100010010000110110001101100010 !
b1100010010000110110001101100010 $
#265000
0#
0&
b0 !
b0 $
0%
0"
#265500
1#
1&
b11111101001110000011011000011 !
b11111101001110000011011000011 $
#267000
1%
1"
#267500
0#
0&
b0 !
b0 $
0%
0"
#268500
1#
1&
b10110010001100100001111100110101 !
b10110010001100100001111100110101 $
1%
1"
#269000
0#
0&
b0 !
b0 $
0%
0"
#270000
1%
1"
#270500
1#
1&
b10100100001101011001011010100101 !
b10100100001101011001011010100101 $
#271000
0#
0&
b0 !
b0 $
0%
0"
#271500
1#
1&
b110011010110110001011001000 !
b110011010110110001011001000 $
#273500
1%
1"
#274000
0#
0&
b0 !
b0 $
0%
0"
#274500
1#
1&
b10000100001011001010100011011001 !
b10000100001011001010100011011001 $
#276000
1%
1"
#276500
0#
0&
b0 !
b0 $
0%
0"
#277000
1%
1"
#277500
1#
1&
b10001000101101110000000000001000 !
b10001000101101110000000000001000 $
#278000
0#
0&
b0 !
b0 $
0%
0"
#278500
1%
1"
#280000
1#
1&
b1011010101100110110110111000000 !
b1011010101100110110110111000000 $
#280500
0#
0&
b0 !
b0 $
0%
0"
#282000
1#
1&
b1001100011111001100110011001111 !
b1001100011111001100110011001111 $
1%
1"
#282500
0#
0&
b0 !
b0 $
0%
0"
#283000
1#
1&
b110111100111010001111101101011 !
b110111100111010001111101101011 $
#283500
1%
1"
#284000
0#
0&
b0 !
b0 $
0%
0"
#284500
1#
1&
b1011010000100011110110100111110 !
b1011010000100011110110100111110 $
#285000
1%
1"
#285500
0#
0&
b0 !
b0 $
0%
0"
#286000
1#
1&
b111101101101111111011011000 !
b111101101101111111011011000 $
#286500
1%
1"
#287000
0#
0&
b0 !
b0 $
0%
0"
#287500
1#
1&
b10101001110011000111101010001100 !
b10101001110011000111101010001100 $
1%
1"
#288000
0#
0&
b0 !
b0 $
0%
0"
#288500
1#
1&
b11111001101100101011111110010001 !
b11111001101100101011111110010001 $
1%
1"
#289000
0#
0&
b0 !
b0 $
0%
0"
#289500
1#
1&
b1111111100100101010110111110011 !
b1111111100100101010110111110011 $
#290500
1%
1"
#291000
0#
0&
b0 !
b0 $
0%
0"
#291500
1#
1&
b10010101100110100100101101001010 !
b10010101100110100100101101001010 $
#292000
1%
1"
#292500
0#
0&
b0 !
b0 $
0%
0"
#293000
1#
1&
b11000011011110001101100111001011 !
b11000011011110001101100111001011 $
1%
1"
#293500
0#
0&
b0 !
b0 $
0%
0"
#294000
1#
1&
b10110111000011011101010101110000 !
b10110111000011011101010101110000 $
#295000
1%
1"
#295500
0#
0&
b0 !
b0 $
0%
0"
#296000
1#
1&
b1110010100001111010011011100100 !
b1110010100001111010011011100100 $
1%
1"
#296500
0#
0&
b0 !
b0 $
0%
0"
#297500
1%
1"
#298500
1#
1&
b1110110010110111011100010001000 !
b1110110010110111011100010001000 $
#299000
0#
0&
b0 !
b0 $
0%
0"
#299500
1#
1&
b110011111100000010010000100011 !
b110011111100000010010000100011 $
1%
1"
#300000
0#
0&
b0 !
b0 $
0%
0"
#300500
1#
1&
b11000110100001100001110111111000 !
b11000110100001100001110111111000 $
#301000
1%
1"
#301500
0#
0&
b0 !
b0 $
0%
0"
#302000
1#
1&
b10000010111111001010111000001000 !
b10000010111111001010111000001000 $
1%
1"
#302500
0#
0&
b0 !
b0 $
0%
0"
#303500
1#
1&
b11100011101100111101101011001101 !
b11100011101100111101101011001101 $
#304000
1%
1"
#304500
0#
0&
b0 !
b0 $
0%
0"
#305500
1%
1"
#306000
1#
1&
b111111110110101100000101011000 !
b111111110110101100000101011000 $
#306500
0#
0&
b0 !
b0 $
0%
0"
#307500
1#
1&
b1100101011111110101011011100110 !
b1100101011111110101011011100110 $
#308000
1%
1"
#308500
0#
0&
b0 !
b0 $
0%
0"
#309500
1%
1"
#310500
1#
1&
b1011110000010110101010011001010 !
b1011110000010110101010011001010 $
#311000
0#
0&
b0 !
b0 $
0%
0"
#311500
1%
1"
#313500
1#
1&
b111110111000110001101000100110 !
b111110111000110001101000100110 $
#314000
0#
0&
b0 !
b0 $
0%
0"
#314500
1#
1&
b1010011101000100010110000000000 !
b1010011101000100010110000000000 $
#318000
1%
1"
#318500
0#
0&
b0 !
b0 $
0%
0"
#319500
1#
1&
b10101110010101101011010010101001 !
b10101110010101101011010010101001 $
1%
1"
#320000
0#
0&
b0 !
b0 $
0%
0"
#320500
1#
1&
b111010101101101000000110001110 !
b111010101101101000000110001110 $
#321000
1%
1"
#321500
0#
0&
b0 !
b0 $
0%
0"
#322500
1#
1&
b10100110101000100101010100001100 !
b10100110101000100101010100001100 $
#323500
1%
1"
#324000
0#
0&
b0 !
b0 $
0%
0"
#324500
1%
1"
#325500
1#
1&
b10000110001010010010100001101110 !
b10000110001010010010100001101110 $
#326000
0#
0&
b0 !
b0 $
0%
0"
#326500
1#
1&
b1100001011011100010010110000011 !
b1100001011011100010010110000011 $
1%
1"
#327000
0#
0&
b0 !
b0 $
0%
0"
#327500
1#
1&
b1101001000110010001110100111010 !
b1101001000110010001110100111010 $
#328000
1%
1"
#328500
0#
0&
b0 !
b0 $
0%
0"
#329000
1#
1&
b1001001100110101011011100111010 !
b1001001100110101011011100111010 $
#330000
1%
1"
#330500
0#
0&
b0 !
b0 $
0%
0"
#331000
1#
1&
b10011000001110101000111101100101 !
b10011000001110101000111101100101 $
1%
1"
#331500
0#
0&
b0 !
b0 $
0%
0"
#332000
1#
1&
b10010001010010000011100001100000 !
b10010001010010000011100001100000 $
#332500
1%
1"
#333000
0#
0&
b0 !
b0 $
0%
0"
#333500
1#
1&
b11010101110100010000000010001010 !
b11010101110100010000000010001010 $
#334000
1%
1"
#334500
0#
0&
b0 !
b0 $
0%
0"
#335000
1#
1&
b1101010011110011100110101001011 !
b1101010011110011100110101001011 $
#335500
1%
1"
#336000
0#
0&
b0 !
b0 $
0%
0"
#336500
1%
1"
#338500
1#
1&
b11011100011100001001111010010001 !
b11011100011100001001111010010001 $
#339000
0#
0&
b0 !
b0 $
0%
0"
#339500
1#
1&
b11111101010111110110110001010001 !
b11111101010111110110110001010001 $
1%
1"
#340000
0#
0&
b0 !
b0 $
0%
0"
#341000
1#
1&
b1001010110111100101110001111100 !
b1001010110111100101110001111100 $
#342500
1%
1"
#343000
0#
0&
b0 !
b0 $
0%
0"
#343500
1#
1&
b10100111101111001111100110000010 !
b10100111101111001111100110000010 $
#344000
1%
1"
#344500
0#
0&
b0 !
b0 $
0%
0"
#345000
1#
1&
b1111001000011010000010100111010 !
b1111001000011010000010100111010 $
#346500
1%
1"
#347000
0#
0&
b0 !
b0 $
0%
0"
#347500
1#
1&
b11101001110000011100100101111100 !
b11101001110000011100100101111100 $
1%
1"
#348000
0#
0&
b0 !
b0 $
0%
0"
#349000
1#
1&
b11011001111110000110110011010 !
b11011001111110000110110011010 $
1%
1"
#349500
0#
0&
b0 !
b0 $
0%
0"
#350000
1%
1"
#351000
1#
1&
b10001101001011000011000101111101 !
b10001101001011000011000101111101 $
#351500
0#
0&
b0 !
b0 $
0%
0"
#352000
1#
1&
b11000100110010010100100010101000 !
b11000100110010010100100010101000 $
1%
1"
#352500
0#
0&
b0 !
b0 $
0%
0"
#353500
1#
1&
b11110000000011110100001110111 !
b11110000000011110100001110111 $
1%
1"
#354000
0#
0&
b0 !
b0 $
0%
0"
#354500
1#
1&
b11010001100110010000100111 !
b11010001100110010000100111 $
#355000
1%
1"
#355500
0#
0&
b0 !
b0 $
0%
0"
#356000
1#
1&
b1010110000011001011000000001011 !
b1010110000011001011000000001011 $
1%
1"
#356500
0#
0&
b0 !
b0 $
0%
0"
#357000
1%
1"
#357500
1#
1&
b11110110100101111001100111111011 !
b11110110100101111001100111111011 $
#358000
0#
0&
b0 !
b0 $
0%
0"
#358500
1#
1&
b10101001011110101000111100010111 !
b10101001011110101000111100010111 $
#361000
1%
1"
#361500
0#
0&
b0 !
b0 $
0%
0"
#362000
1%
1"
#363000
1#
1&
b11101001011001111001100111001 !
b11101001011001111001100111001 $
#363500
0#
0&
b0 !
b0 $
0%
0"
#364500
1#
1&
b10110001000111100110101111111100 !
b10110001000111100110101111111100 $
1%
1"
#365000
0#
0&
b0 !
b0 $
0%
0"
#365500
1%
1"
#366000
1#
1&
b11110110010111011001110001010100 !
b11110110010111011001110001010100 $
#366500
0#
0&
b0 !
b0 $
0%
0"
#367000
1%
1"
#368500
1#
1&
b10001100101000010000000111011011 !
b10001100101000010000000111011011 $
#369000
0#
0&
b0 !
b0 $
0%
0"
#370500
1%
1"
#371500
1#
1&
b11100011110110010010010011011010 !
b11100011110110010010010011011010 $
